Workbook
Name a: #REF!
Name AUGUST: #REF!
Name CAPSTOCK: #REF!
Name CASHREC: #REF!
Name check1: #REF!
Name CHECKLIST: #REF!
Name cklst: [3]Chklst!$A$1:$C$26
Name CLASSEXP: #REF!
Name COST: #REF!
Name COST2: #REF!
Name Days: '[4]Cost Rollforward - PTO'!$C$45
Name Days_2: '[5]Cost Roll'!$C$52
Name DERIVATIVE: #REF!
Name DETAIL: #REF!
Name DISTREC: #REF!
Name DISTRIBUTION: #REF!
Name DVD: #REF!
Name DVDII: #REF!
Name EntityNames: [6]EntityLookup!$A$3:$A$5
Name EXPENSES: #REF!
Name Facility_Name: '[7]PAR Settled'!$B:$B
Name fadfs: '[8]Cost Roll'!$C$24
Name FAX: #REF!
Name foursixtythree: #REF!
Name GAIN: #REF!
Name Gain_Loss_01: #REF!
Name Gain_Loss_02: #REF!
Name Gain_Loss_03: #REF!
Name Gain_Loss_04: #REF!
Name Gain_Loss_05: #REF!
Name Gain_Loss_06: #REF!
Name Gain_Loss_07: #REF!
Name Gain_Loss_08: #REF!
Name Gain_Loss_09: #REF!
Name Gain_Loss_10: #REF!
Name Gain_Loss_11: #REF!
Name Gain_Loss_12: #REF!
Name GAINLOSS: #REF!
Name INT: #REF!
Name INTEREST: #REF!
Name INTEREST2: #REF!
Name IO_14: '[9]501773CG8sold'!$A$59:$L$80
Name IO_15: '[9]23322BFC7soldoff'!$A$45:$L$67
Name IO_16: '[9]3133TKAB6Sold Off'!$A$42:$L$63
Name IO_17: '[9]3133TGQG7 paid off'!$A$40:$L$61
Name IO_18: '[9]3133TKT91Sold Off'!$A$40:$L$61
Name IO_19: '[9]3133t2wf3- paid off'!$A$37:$L$58
Name IO_20: '[9]3133TKYZ7PaidOff'!$A$39:$L$60
Name IO_6: '[9]312915gc9paidoff'!$A$298:$T$320
Name Issuer_Name: '[7]PAR Settled'!$A:$A
Name JULY: #REF!
Name JUNE: #REF!
Name LOAN: #REF!
Name Marketing_Explanation: '[6]Sponsor Due Dillig Explan'!$A$3:$A$110
Name MgmtDealLIst: '[6]Deal_Expense Lookup'!$A$1:$A$106
Name MISCADJ: #REF!
Name MISCADJ2: #REF!
Name MKTVALUE: #REF!
Name MKTVALUE2: #REF!
Name MMINT: #REF!

Sheet Borrowing Base
A1: SAMPLE FLOATING RATE FUNDING I, LLC
A2: BORROWING BASE CERTIFICATE
A3: Amounts are pro forma for proposed borrowing and related use of proceeds
A4: DETERMINATION DATE | J4: 45869
A5: CONCENTRATION TEST AMOUNT | J5: ='Loan List'!DH6 | O5: Cash and Credit Facility Balance Projections
A8: BORROWING BASE - (A) minus (B) minus (A)(iv) | J8: =J10-J18-J14 | K8: ='Loan List'!GA6-J14 | O8: AUD
K9: Check | O9: 0 | P9: Current Credit Facility Balance
B10: (A) | C10: Aggregate Collateral Balance (without duplication) sum of (i)-(vi) | J10: =SUM(J11:J16) | K10: =J10='Loan List'!DG6 | O10: =+O71 | P10: Borrowing
C11: (i) Aggregate Principal Balance of all Collateral Loans (other than Defaulted, Restructured, Haircut Ineligible, and Discount) | J11: ='Loan List'!HV8 | O11: =SUM(O9:O10) | P11: Projected Credit Facility Balance
C12: (ii) Defaulted Collateral Loan Balance | J12: ='Loan List'!IA8 | O12: USD
C13: (iii) The aggregate purchase price of all Discount Loans that are Eligible Collateral Loans and not Defaulted, Haircut or Restructured | J13: ='Loan List'!HZ8 | O13: =325500000-20800000+23000000+3000000-12000000+1200000+6000000+9500000+7500000-3000000-17000000+5000000+15000000+4000000+35500000-13000000+19000000+5000000+6000000+3500000-27000000+18000000+10000000+5000000+5000000-10000000+17000000+19000000+13000000-200000000-6000000+4000000+4000000-10000000+8000000+18000000+10000000+16000000+5000000+21000000+27000000+40000000+5000000+15000000+16000000-27000000+15000000+8000000+15000000+18000000-54000000+20000000-58000000-23000000-43000000-15000000-46000000+10000000+10000000+7500000-6500000-115000000+32000000+46000000-81000000+8000000+50000000+12000000+69000000+11000000-80000000-50000000-25500000+11000000+20000000+10000000+10000000+20000000+20000000-5000000-65000000+20000000+60000000+30000000+20000000-35000000-7000000+10000000-40000000-50000000+30000000-48000000+20000000-45000000-35000000+15000000-35000000-55000000+15000000+160000000+75000000+50000000+30000000-130000000-42000000+50000000+55000000+40000000+50000000+80000000+20000000+100000000+20000000+25000000+50000000-320000000-30000000+20000000-55000000+25000000+20000000+75000000 | P13: Current Credit Facility Balance
C14: (iv) The aggregate Unfunded Commitments of all Delayed Drawdown and Revolvers that are Eligible Loans | J14: ='Loan List'!HU8 | O14: =+O33 | P14: Borrowing
C15: (v) The Credit Improved Loan Balance | J15: ='Loan List'!HY8 | O15: =SUM(O13:O14) | P15: Projected Credit Facility Balance
C16: (vi) The Haircut Collateral Loan Balance | J16: ='Loan List'!HX8 | O16: CAD
O17: 2000000 | P17: Current Credit Facility Balance
B18: (B) | C18: Excess Concentration Amount | J18: =SUM('Loan List'!HG10:HG117) | O18: 0 | P18: Borrowing
O19: =SUM(O17:O18) | P19: Projected Credit Facility Balance
A20: MAXIMUM AVAILABLE AMOUNT - Least of (A), (B) and (C) | J20: =MIN(J27,J35,J40) | O20: EUR
O21: 0 | P21: Current Credit Facility Balance
C22: Least of: | O22: 0 | P22: Borrowing
O23: =SUM(O21:O22) | P23: Projected Credit Facility Balance
B24: (A) | D24: Facility Amount, less | J24: 718000000
D25: Revolving Exposure, plus | J25: ='Loan List'!$DF$6 | O25: 393842760
D26: Amount on deposit in the Revolving Reserve Account | J26: 0 | O26: =+J46-O25 | P26: Check
J27: =J24-J25+J26
O28: =+J53 | P28: Equity/Cushion
B29: (B) | C29: (i) | D29: (x) Borrowing Base, multipled by | J29: ='Borrowing Base'!J8 | O29: =+J18 | P29: Net Penalty
D30: (y) Weighted Average Advance Rate, minus | J30: ='Loan List'!AZ2
C31: (ii) | D31: Foreign Currency Variability Reserve, minus | J31: ='Loan List'!DL6 | O31: USD
C32: (iii) | D32: Revolving Exposure, plus | J32: ='Loan List'!$DF$6 | O32: 36200325 | P32: Cash - Current & PreBorrowing
C33: (iv) | D33: Cash on deposit in Principal Collection Subaccount | J33: 36362717
C34: (v) | D34: Amount on deposit in the Revolving Reserve Account | J34: =J26 | O34: =SUM(O32:O33) | P34: Cash - Budgeted & PostBorrowing
J35: =(J29*J30)-J31-J32+J33+J34
B37: (C) | C37: (A) | D37: Aggregate Collateral Balance, minus | J37: =J10-J14
C38: (B) | D38: Minimum Equity Amount, plus | J38: 1.1655229e+08
C39: (C) | D39: Cash on deposit in Principal Collection Subaccount | J39: =J33
J40: =J37-J38+J39
A42: ADVANCES OUTSTANDING
A44: Advances Outstanding at beginning of the Interest Accrual Period | J44: 393842760
A45: Advances/(Repayments) during the period through and including 07/31/2025 | J45: 0
A46: Advances Outstanding as of 7/31/25 | J46: =J44+J45
A48: MAXIMUM AVAILABILITY
B50: (a) | C50: Maximum Available Amount | J50: =$J$20
B51: (b) | C51: Advances | J51: =J46 | O51: =SUM(O34:O50) | P51: Cash - Net of UnSettled Trades
A53: AVAILABILITY - (a) minus (b) | J53: =J50-J51 | O53: CAD
O54: 225112.54 | P54: Cash - Current & PreBorrowing
P55: Borrowing
A56: EVENTS OF DEFAULT | J56: PASS
A57: COVERAGE TESTS | J57: PASS | O57: =SUM(O54:O56) | P57: Cash - Budgeted & PostBorrowing
A58: PORTFOLIO QUALITY TESTS | J58: PASS
B59: If not satisfied, improving: | J59: Yes | O59: =SUM(O57:O58) | P59: Cash - Net of UnSettled Trades
B61: IN WITNESS WHEREOF, the undersigned has duly executed this Report. | O61: EUR
B62: By: | O62: 0 | P62: Cash - Current & PreBorrowing
P63: Borrowing
C65: Signature | O65: =SUM(O62:O64) | P65: Cash - Budgeted & PostBorrowing
C67: Andrew Jordan | O67: =SUM(O65:O66) | P67: Cash - Net of UnSettled Trades
C68: (Print Name)
O69: AUD
C70: Managing Director | O70: 0 | P70: Cash - Current & PreBorrowing
C71: Title | P71: Borrowing
C73: =TODAY() | O73: =SUM(O70:O72) | P73: Cash - Budgeted & PostBorrowing
C74: Date
O75: =SUM(O73:O74) | P75: Cash - Net of UnSettled Trades

Sheet Loan List
B1: ='Borrowing Base'!A1 | AG1: 20% Conc. Limit | AJ1: Level 1 - 10% Haircut | AM1: Level 2 - 20% Haircut | AP1: Level 3 - 35% Haircut | AS1: Level 4 - Max Eligibility - 50% Haircut | GH1: No of Industry | GI1: Limit | GJ1: Limit $ | GQ1: No of Obligor | GR1: Limit % | GS1: Limit $ | GZ1: No of Obligor | HA1: Limit % | HB1: Limit $ | HC1: Total Excess
B2: Loan List | AG2: Tier 1 Obligor | AH2: Tier 2 Obligor | AI2: Tier 3 Obligor | AJ2: Tier 1 Obligor | AK2: Tier 2 Obligor | AL2: Tier 3 Obligor | AM2: Tier 1 Obligor | AN2: Tier 2 Obligor | AO2: Tier 3 Obligor | AP2: Tier 1 Obligor | AQ2: Tier 2 Obligor | AR2: Tier 3 Obligor | AS2: Tier 1 Obligor | AT2: Tier 2 Obligor | AU2: Tier 3 Obligor | AY2: Weighted Average Advance Rate: | AZ2: =SUMPRODUCT(($GB10:$GB406>0)*$GB10:$GB406*$V10:$V406)/SUMPRODUCT(($GB10:$GB406>0)*$GB10:$GB406) | DM2: Limit % | DN2: 0.15 | DQ2: 0.1 | DT2: 0.05 | DW2: 0.15 | DZ2: 0.1 | EC2: 0.15 | EF2: 0.1 | EI2: 0.25 | EL2: 0.1 | EO2: 0.03 | ER2: 0.15 | EU2: 0.05 | EX2: 0.15 | FA2: 0.1 | FD2: 0.15 | FP2: 0.05 | FS2: 0.2 | FV2: 0.2 | GH2: 1 | GI2: 0.25 | GJ2: ='Borrowing Base'!J5*GI2 | GQ2: 3 | GR2: 0.06666666 | GS2: ='Borrowing Base'!J5*GR2 | GZ2: 5 | HA2: 0.3 | HB2: =HA2*'Borrowing Base'!J5 | HC2: =MAX(0,SUM(HA10:HA11)-HB2)
B3: Loan Portfolio as of: July 31, 2025 | AF3: SD/EBITDA | AG3: 5 | AH3: 4.25 | AI3: 3.75 | AJ3: 5.5 | AK3: 4.75 | AL3: 4.25 | AM3: 6 | AN3: 5.25 | AO3: 4.75 | AP3: 6.5 | AQ3: 5.75 | AR3: 5.25 | AS3: 7 | AT3: 6.25 | AU3: 5.75 | AY3: Weighted Average Coupon: | AZ3: =IFERROR(SUMPRODUCT((AS10:AS406>0)*DG10:DG406*AS10:AS406)/SUMPRODUCT((AS10:AS406>0)*DG10:DG406),"N/A") | DM3: Limit | DN3: =DN2*'Borrowing Base'!$J$5 | DQ3: =DQ2*'Borrowing Base'!$J$5 | DT3: =DT2*'Borrowing Base'!$J$5 | DW3: =DW2*'Borrowing Base'!$J$5 | DZ3: =DZ2*'Borrowing Base'!$J$5 | EC3: =EC2*'Borrowing Base'!$J$5 | EF3: =EF2*'Borrowing Base'!$J$5 | EI3: =EI2*'Borrowing Base'!$J$5 | EL3: =EL2*'Borrowing Base'!$J$5 | EO3: =EO2*'Borrowing Base'!$J$5 | ER3: =ER2*'Borrowing Base'!$J$5 | EU3: =EU2*'Borrowing Base'!$J$5 | EX3: =EX2*'Borrowing Base'!$J$5 | FA3: =FA2*'Borrowing Base'!$J$5 | FD3: =FD2*'Borrowing Base'!$J$5 | FP3: =FP2*'Borrowing Base'!$J$5 | FS3: =FS2*'Borrowing Base'!$J$5 | FV3: =FV2*'Borrowing Base'!$J$5 | GH3: 2 and 3 | GI3: 0.15 | GJ3: ='Borrowing Base'!J5*GI3 | GQ3: 5 | GR3: 0.06 | GS3: ='Borrowing Base'!J5*GR3
AF4: TD/EBITDA | AG4: 7 | AH4: 6 | AI4: 5 | AJ4: 7.5 | AK4: 6.5 | AL4: 5.5 | AM4: 8 | AN4: 7 | AO4: 6 | AP4: 8.5 | AQ4: 7.5 | AR4: 6.5 | AS4: 9 | AT4: 8 | AU4: 7 | AY4: Specified Term SOFR: | AZ4: 0.0432224 | DM4: Total | DN4: =SUM(DN10:DN406) | DQ4: =SUM(DQ10:DQ406) | DT4: =SUM(DT10:DT406) | DW4: =SUM(DW10:DW406) | DZ4: =SUM(DZ10:DZ406) | EC4: =SUM(EC10:EC406) | EF4: =SUM(EF10:EF406) | EI4: =SUM(EI10:EI406) | EL4: =SUM(EL10:EL406) | EO4: =SUM(EO10:EO406) | ER4: =SUM(ER10:ER406) | EU4: =SUM(EU10:EU406) | EX4: =SUM(EX10:EX406) | FA4: =SUM(FA10:FA406) | FD4: =SUM(FD10:FD406) | FP4: =SUM(FP10:FP406) | FS4: =SUM(FS10:FS406) | FV4: =SUM(FY10:FY406) | FW4: =SUM(FW10:FW406) | FX4: =SUM(FX10:FX406) | FY4: =SUM(FY10:FY406) | GH4: Other | GI4: 0.15 | GJ4: ='Borrowing Base'!J5*GI4 | GQ4: All others | GR4: 0.05 | GS4: ='Borrowing Base'!J5*GR4
AF5: UD/EBITDA | AG5: 6 | AH5: 5.25 | AI5: 4.5 | AJ5: 6.5 | AK5: 5.75 | AL5: 5 | AM5: 7 | AN5: 6.25 | AO5: 5.5 | AP5: 7.5 | AQ5: 6.75 | AR5: 6 | AS5: 8 | AT5: 7.25 | AU5: 6.5 | AV5: Weighted Average Life: | AW5: =SUMPRODUCT(AQ10:AQ406,$DG$10:$DG$406)/SUM($DG$10:$DG$406) | AY5: Weighted Average Spread: | AZ5: =SUM($CB$10:$CC$406)/SUMIF($AR$10:$AR$406,"No",$DE$10:$DE$406) | CX5: =SUM(CX10:CX406) | CY5: =SUM(CY10:CY406) | CZ5: =SUM(CZ10:CZ406) | DA5: =SUM(DA10:DA406) | DB5: =SUM(DB10:DB406) | DC5: =SUM(DC10:DC406) | DM5: Excess | DN5: =MAX(0,DN4-DN3) | DQ5: =MAX(0,DQ4-DQ3) | DT5: =MAX(0,DT4-DT3) | DW5: =MAX(0,DW4-DW3) | DZ5: =MAX(0,DZ4-DZ3) | EC5: =MAX(0,EC4-EC3) | EF5: =MAX(0,EF4-EF3) | EI5: =MAX(0,EI4-EI3) | EL5: =MAX(0,EL4-EL3) | EO5: =MAX(0,EO4-EO3) | ER5: =MAX(0,ER4-ER3) | EU5: =MAX(0,EU4-EU3) | EX5: =MAX(0,EX4-EX3) | FA5: =MAX(0,FA4-FA3) | FD5: =MAX(0,FD4-FD3) | FP5: =MAX(0,FP4-FP3) | FQ5: Haircut Excess | FS5: =MAX(0,FS4-FS3) | FT5: Haircut Excess | FV5: =MAX(0,SUM(FY4:FY4)-FV3) | FZ5: Haircut Excess | GG5: =COUNTIF(GF10:GF406,">"&0) | GP5: =COUNTIF(GP10:GP406,">"&0) | GY5: =COUNTIF(GY10:GY406,">"&0)
DE6: =SUM(DE10:DE406) | DF6: =SUM(DF10:DF406) | DG6: =SUM(DG10:DG406) | DH6: =SUM(DH10:DH406) | DI6: =SUM(DI10:DI406) | DL6: =SUM(DL10:DL406) | DM6: Haircut | DN6: =IF(DN4<0.01,0,DN5/DN4) | DO6: =SUM(DO10:DO406) | DP6: =SUM(DP10:DP406) | DQ6: =IF(DQ4<0.01,0,DQ5/DQ4) | DR6: =SUM(DR10:DR406) | DS6: =SUM(DS10:DS406) | DT6: =IF(DT4<0.01,0,DT5/DT4) | DU6: =SUM(DU10:DU117) | DV6: =SUM(DV10:DV117) | DW6: =IF(DW4<0.01,0,DW5/DW4) | DX6: =SUM(DX10:DX406) | DY6: =SUM(DY10:DY406) | DZ6: =IF(DZ4<0.01,0,DZ5/DZ4) | EA6: =SUM(EA10:EA406) | EB6: =SUM(EB10:EB406) | EC6: =IF(EC4<0.01,0,EC5/EC4) | ED6: =SUM(ED10:ED406) | EE6: =SUM(EE10:EE406) | EF6: =IF(EF4<0.01,0,EF5/EF4) | EG6: =SUM(EG10:EG406) | EH6: =SUM(EH10:EH406) | EI6: =IF(EI4<0.01,0,EI5/EI4) | EJ6: =SUM(EJ10:EJ406) | EK6: =SUM(EK10:EK406) | EL6: =IF(EL4<0.01,0,EL5/EL4) | EM6: =SUM(EM10:EM406) | EN6: =SUM(EN10:EN406) | EO6: =IF(EO4<0.01,0,EO5/EO4) | EP6: =SUM(EP10:EP406) | EQ6: =SUM(EQ10:EQ406) | ER6: =IF(ER4<0.01,0,ER5/ER4) | ES6: =SUM(ES10:ES406) | ET6: =SUM(ET10:ET406) | EU6: =IF(EU4<0.01,0,EU5/EU4) | EV6: =SUM(EV10:EV406) | EW6: =SUM(EW10:EW406) | EX6: =IF(EX4<0.01,0,EX5/EX4) | EY6: =SUM(EY10:EY406) | EZ6: =SUM(EZ10:EZ406) | FA6: =IF(FA4<0.01,0,FA5/FA4) | FB6: =SUM(FB10:FB406) | FC6: =SUM(FC10:FC406) | FD6: =IF(FD4<0.01,0,FD5/FD4) | FE6: =SUM(FE10:FE406) | FF6: =SUM(FF10:FF406) | FH6: =SUM(FH10:FH406) | FI6: =SUM(FI10:FI406) | FJ6: =SUM(FJ10:FJ406) | FK6: =SUM(FK10:FK406) | FL6: =SUM(FL10:FL406) | FN6: =SUM(FN10:FN406) | FO6: =SUM(FO10:FO406) | FP6: =IF(FP4<0.01,0,FP5/FP4) | FQ6: =SUM(FQ10:FQ406) | FR6: =SUM(FR10:FR406) | FS6: =IF(FS4<0.01,0,FS5/FS4) | FT6: =SUM(FT10:FT406) | FU6: =SUM(FU10:FU406) | FV6: =IF(SUM(FV4:FY4)<0.01,0,FV5/SUM(FY4:FY4)) | FZ6: =SUM(FZ10:FZ406) | GA6: =SUM(GA10:GA406) | GB6: =SUM(GB10:GB406) | GC6: =SUM(GC10:GC406) | GG6: =SUM(GG10:GG406) | GH6: =GG5 | GI6: =SUM(GI10:GI406) | GK6: =SUM(GK10:GK406) | GP6: =SUM(GP10:GP406) | GQ6: =GP5 | GR6: =SUM(GR10:GR406) | GT6: =SUM(GT10:GT406) | GY6: =SUM(GY10:GY406) | GZ6: =GY5 | HA6: =SUM(HA10:HA406) | HC6: =SUM(HC10:HC406) | HG6: =SUM(HG10:HG406) | HH6: =SUM(HH10:HH117) | HU6: Eligible Unfunded
G7: =SUM(G10:G406) | H7: =SUM(H10:H406) | J7: =SUM(J10:J406) | K7: =SUM(K10:K406) | L7: =SUM(L10:L406) | M7: =SUM(M10:M406) | O7: =SUMIF(N10:N406,"Yes",K10:K406) | W7: =SUM(W10:W406) | HS7: =SUM(HS10:HS406)
L8: Eligible Balances | N8: Loan Value Criteria | AA8: Credit/Performance Metrics | AR8: Interest Metrics | BE8: Other Loan Characteristics | BN8: Eligibility Criteria | CE8: Eligibility Criteria | DN8: Excess Concentrations | HN8: =SUM(HN10:HN406) | HO8: =SUM(HO10:HO406) | HU8: =SUMIF($HT$10:$HT$117,"",$HU$10:$HU$117) | HV8: =SUMIF(HV10:HV406,"> 0",HO10:HO406) | HW8: =SUM(HW10:HW406) | HX8: =SUM(HX10:HX406) | HY8: =SUM(HY10:HY406) | HZ8: =SUM(HZ10:HZ406) | IA8: =SUM(IA10:IA406)
B9: Loan Number | C9: Obligor | D9: Obligor Name | E9: Security Name | F9: Purchase Date (Date Loan contributed to the facility) | G9: Total Commitment (Issue Currency) | H9: Outstanding Principal Balance (Issue Currency) | I9: Exchange Rate | J9: Total Commitment (USD) | K9: Outstanding Principal Balance (USD) | L9: Eligible Commitment (USD) | M9: Eligible Outstanding Principal Balance (USD) | N9: Defaulted Collateral Loan / Material Mod (Y/N) | O9: Date of Default | P9: Months Since Default | Q9: Credit Improved Loan (Y/N) | R9: Purchase Price | S9: Discount Collateral Loan (Y/N) | T9: Market Value | U9: Applicable Recovery Rate | V9: Advance Rate | W9: Aggregate Collateral Balance (Pre-Eligibility; Excluding Unfunded; Excluding Principal Acct) | X9: Stretch Senior Loan (Y/N) | Y9: Lien Type (First Lien / Split First Lien / Split Lien / Second Lien) | Z9: Loan Type (Term / Delayed Draw / Revolver) | AA9: Current Moody's Rating | AB9: Current S&P Rating | AC9: Initial Fixed Charge Coverage Ratio | AD9: Current Fixed Charge Coverage Ratio | AE9: Current Interest Coverage Ratio | AF9: Initial Debt to Capitalization Ratio | AG9: Initial Senior Debt/ EBITDA | AH9: Initial Total Debt/ EBITDA | AI9: Current Senior Debt/ EBITDA | AJ9: Current Total Debt/ EBITDA | AK9: Initial TTM EBITDA | AL9: Current TTM EBITDA | AM9: Current As of Date For Leverage and EBITDA | AN9: Tier 1 / Tier 2 Obligor | AO9: Maturity Date | AP9: Rem. Term to Maturity | AQ9: Avg Life | AR9: Fixed Rate (Y/N) | AS9: Coupon incl. PIK and PIK'able (if Fixed) | AT9: Floor Obligation (Y/N) | AU9: Floor | AV9: Spread incl. PIK and PIK'able | AW9: Base Rate | AX9: Greater of Base Rate and Floor | AY9: For Revolvers/Delayed Draw, commitment or other unused fee | AZ9: PIK / PIK'able For Floating Rate Loans | BA9: PIK / PIK'able For Fixed Rate Loans | BB9: Cash Spread On Floating Rate Loans | BC9: Cash Spread On Fixed Rate Loans | BD9: Interest Paid | BE9: Obligor Industry | BF9: Currency (USD / CAD / GBP / AUD / EUR) | BG9: Obligor Country | BH9: DIP Loan (Y/N) | BI9: Partial PIK Loan (Y/N) | BJ9: Non-Cash PIK Loan (Y/N) | BK9: Warrants to Purchase Equity (Y/N) | BL9: LBO Loan (Y/N) | BM9: Parti-cipation (Y/N) | BN9: Convertible to Equity (Y/N) | BO9: Equity Security (Y/N) | BP9: At Acquisition - Subject to offer or called for redemption (Y/N) | BQ9: Margin Stock (Y/N) | BR9: Subject to withholding tax (Y/N) | BS9: At Acquisition - Defaulted Collateral Loan | BT9: Zero Coupon Obligation(Y/N) | BU9: Covenant Lite (Y/N) | BV9: Eligible Covenant Lite (Y/N) | BW9: Structured Finance Obligation, finance lease or chattel paper (Y/N) | BX9: Material Non-Credit Related Risk (Y/N) | BY9: Primarily Secured by Real Estate, Construction Loan or Project Finance Loan (Y/N) | BZ9: Interest Only Security (Y/N) | CA9: Satisfies all Other Eligibility Criteria (Y/N) | CB9: Aggregate Funded Spread | CC9: Aggregate Unfunded Spread | CE9: Purchased Below 85% of Par | CF9: Eligible Currency | CG9: Eligible Country | CH9: Convertible to Equity | CI9: Equity Security | CJ9: Subject to offer or called for redemption | CK9: Margin Stock | CL9: Subject to withholding tax | CM9: At Acquisition - Defaulted Collateral Loan | CN9: Non-cash PIK | CO9: Zero Coupon Obligation | CP9: Covenant Lite | CQ9: Structured Finance Obligation | CR9: Remaining term > 7 yrs | CS9: Interest Paid At Least Semi Annually | CT9: Material Non-Credit Related Risk | CU9: Real Estate, Construction or Project Finance Loan | CV9: Interest Only Security | CW9: Satisfies all Other Eligibility Criteria | CX9: EBITDA Requirement at Acquisition | CY9: EBITDA Requirement Ongoing | CZ9: Leverage 10% Haircut | DA9: Leverage 20% Haircut | DB9: Leverage 35% Haircut | DC9: Leverage - Final Haircut - 50% | DD9: Total Ineligible (excl. EBITDA and Leverage Ongoing) | DE9: Aggregate Collateral Balance (Post Eligibility; Including Haircut Ineligible; Excluding Unfunded) | DF9: Eligible Unfunded | DG9: Aggregate Collateral Balance (Post Eligibility; Including Eligible Unfunded) | DH9: Concentration Test Balance - OPB + Eligible Unfunded | DI9: Revolving Exposure | DJ9: Foreign Currency Loan OC Balance | DK9: Foreign Currency Variability Factor | DL9: Foreign Currency Variability Reserve | DN9: Second Lien and Split Lien | DO9: Excess | DP9: Net Loan Balance | DQ9: Second Lien | DR9: Excess | DS9: Net Loan Balance | DT9: DIP Collateral Loans | DU9: Excess | DV9: Net Loan Balance | DW9: Eligible Foreign Country | DX9: Excess | DY9: Net Loan Balance | DZ9: Partial PIK Loan | EA9: Excess | EB9: Net Loan Balance | EC9: Revolving / Delayed Drawdown | ED9: Excess | EE9: Net Loan Balance | EF9: Discount Loans | EG9: Excess | EH9: Net Loan Balance | EI9: Credit Improved Loans | EJ9: Excess | EK9: Net Loan Balance | EL9: Less than Quarterly Pay | EM9: Excess | EN9: Net Loan Balance | EO9: Warrants to Purchase Equity Securities | EP9: Excess | EQ9: Net Loan Balance | ER9: LBO Loan with Equity to Cap <25% | ES9: Excess | ET9: Net Loan Balance | EU9: Participation Interests | EV9: Excess | EW9: Net Loan Balance | EX9: Eligible Covenant Lite Loans | EY9: Excess | EZ9: Net Loan Balance | FA9: Fixed Rate Loan | FB9: Excess | FC9: Net Loan Balance | FD9: Agreed Foreign Currency | FE9: Excess | FF9: Net Loan Balance | FG9: Obligor | FH9: Excess | FI9: Net Loan Balance | FJ9: Obligor Industry | FK9: Excess | FL9: Net Loan Balance | FM9: Top 5 Obligors | FN9: Excess | FO9: Net Loan Balance | FP9: LTM EBITDA >= 5,000,000 but < 7,500,000 | FQ9: Excess; Haircut to 1-Recovery Rate | FR9: Net Loan Balance | FS9: LTM EBITDA < 15,000,000 | FT9: Excess; Haircut to 1-Recovery Rate | FU9: Net Loan Balance | FV9: LTM Snr Debt / EBITDA | FW9: LTM Total Debt / EBITDA | FX9: Stretch Senior LTM Total Debt / EBITDA | FY9: Exceeds Leverage Limitation | FZ9: Excess; Haircut to 1-Min(90% and Market Value) | GA9: Excess Concentration Test | GB9: Net Loan Balance | GC9: Borrowing Base | GE9: Industry No | GF9: Lookups'!F2:F3 Loan Balance | GG9: Industry Loan Balance | GH9: Industry Order | GI9: Outstanding Loan Balance | GJ9: Limit | GK9: Excess | GL9: Industry No (Matched) | GM9: Haircut | GO9: Obligor No | GP9: Obligor Loan Balance | GQ9: Obligor Order | GR9: Obligor Loan Balance | GS9: Limit | GT9: Excess | GU9: Obligor No | GV9: Haircut | GX9: Obligor No | GY9: Obligor Loan Balance | GZ9: Obligor Order | HA9: Obligor Loan Balance | HB9: Limit | HC9: Excess | HD9: Obligor No | HE9: Haircut | HG9: Excess Concentration Amount (Dynamic) | HH9: Excess Concentration Amount (HARD CODE on Last Day of Reinvestment Period) | HI9: Applicable Excess Concentration Amount (Last Day of Reinvestment Period) | HK9: Obligor No | HL9: Obligor Loan Balance | HN9: Aggregate Collateral Balance (Pre-Eligibility; Excluding Unfunded; Excluding Principal Acct) | HO9: Outstanding Principal Balance | HP9: Defaulted Collateral Loan Balance | HQ9: Discount Loan Balance | HR9: Credit Improved Balance | HS9: Haircut Ineligible | HT9: Ineligibles | HU9: Total Unfunded | HV9: APB (Other Than Def, Inelib, Restructured, Haircut) | HW9: Ineligibles Test | HX9: Haircut Test | HY9: Credit Improved Test | HZ9: Discount Test | IA9: Defaulted Test | IB9: Lookups'!F2:F3 No | IE9: Initial Haircut Level
A10: =D10 | B10: 1 | C10: 1 | D10: Northgate Holdings, LLC | E10: Northgate (TL) | G10: 18406747 | H10: 18406747 | I10: 1 | J10: =IF(B10="","",G10*I10) | K10: =IF(B10="","",H10*I10) | L10: =IF(B10="","",IF(COUNTIF($CE10:$CX10,1)>0,0,J10)) | M10: =IF(B10="","",IF(COUNTIF($CE10:$CX10,1)>0,0,K10)) | N10: No | O10: N/A | P10: =IF(B10="","",IF(OR(O10="N/A",O10=""),0,YEARFRAC('Borrowing Base'!$J$4,'Loan List'!O10)*12)) | Q10: No | R10: 0.9975 | S10: =IF(B10="","",IF(R10<95%,"Yes","No")) | T10: 0.99 | U10: =IF(B10="","",IF(OR(Y10="First Lien",Y10="Split First Lien",Y10="Tier 1 Split Lien",Y10="Tier 2 Split Lien"),50%,30%)) | V10: =IF(B10="",0,IF(AND(Y10="First Lien",AN10="Tier 1"),IF(AND(X10="Yes",MIN(AH10,$AJ$5)>4.5),(((4.5/MIN(AH10,$AJ$5))*72.5%)+(((MIN(AH10,$AJ$5)-4.5)/MIN(AH10,$AJ$5))*35%)),72.5%),IF(AND(Y10="First Lien",AN10="Tier 2"),IF(AND(X10="Yes",MIN(AH10,$AK$5)>4.5),(((4.5/MIN(AH10,$AK$5))*72.5%)+(((MIN(AH10,$AK$5)-4.5)/MIN(AH10,$AK$5))*35%)),72.5%),IF(AND(X10="Yes",MIN(AH10,$AL$5)>4),(((4/MIN(AH10,$AL$5))*72.5%)+(((MIN(AH10,$AL$5)-4)/MIN(AH10,$AL$5))*35%)),IF(OR(Y10="First Lien",Y10="Split First Lien"),72.5%,IF(Y10="Split Lien", 53%,35%)))))) | W10: =IF($C10="","",MIN($HO10:$HS10)) | X10: Yes | Y10: First Lien | Z10: Term | AA10: NR | AB10: NR | AC10: 1.1174448 | AD10: 5.1870295 | AE10: 4.6060902 | AF10: 0.4590766 | AG10: 5.1870295 | AH10: 5.1870295 | AI10: 4.6060902 | AJ10: 4.6060902 | AK10: 33738000 | AL10: 77650021 | AM10: 45747 | AN10: =IF(C10="","",(IF(AK10>=50000000,"Tier 1",(IF(OR(AK10>=20000000,AND(AK10>5000000,AC10>=1.25,AF10<=0.65)),"Tier 2","Tier 3"))))) | AO10: 47393 | AP10: 4.1722222 | AQ10: =IF(C10="","",AP10) | AR10: No | AS10: 0 | AT10: Yes | AU10: 0.01 | AV10: 0.0475 | AW10: 0.042906 | AX10: =IF(C10="","",MAX(AU10,AW10)) | AY10: 0 | AZ10: 0 | BA10: 0 | BB10: =IF(B10="","",IF(AR10="No",AV10-AZ10,"")) | BC10: =IF(B10="","",IF(AR10="Yes",AS10-BA10,"")) | BD10: Quarterly | BE10: IT Services | BF10: USD | BG10: United States | BH10: No | BI10: =IF(B10="","",IF(OR(AND(AZ10>0,BB10>=2.5%,BB10<4%),AND(BA10>0,BC10>=6%,BC10<8%)),"Yes","No")) | BJ10: =IF(B10="","",IF(OR(AND(AZ10>0,BB10<2.5%),AND(BA10>0,BC10<6%)),"Yes","No")) | BK10: No | BL10: No | BM10: No | BN10: No | BO10: No | BP10: No | BQ10: No | BR10: No | BS10: No | BT10: No | BU10: No | BV10: No | BW10: No | BX10: No | BY10: No | BZ10: No | CA10: Yes | CB10: =IF(B10="","",IF(AT10="No",((BB10+AW10)-$AZ$4),((BB10+AX10)-$AZ$4))*IF(DD10>0,0,M10)) | CC10: =IF(B10="","",AY10*(L10-M10)*IF(DD10>0,0,1)) | CE10: =IF(AND(B10<>"",R10<=85%),1,0) | CF10: =IF(B10="",0,(IF(OR(BF10="USD",BF10="CAD",BF10="GBP",BF10="AUD",BF10="EUR"),0,1))) | CG10: =IF(B10="",0,(IF(OR(BG10="United States",BG10="Canada",BG10="United Kingdom",BG10="Australia",BG10="Netherlands Antilles",BG10="Bermuda",BG10="Cayman Islands",BG10="British Virgin Islands",BG10="Channel Islands",BG10="Isle of Man",BG10="Australia",BG10="Netherlands",BG10="Germany",BG10="Sweden",BG10="Switzerland",BG10="Austria",BG10="Belgium",BG10="Denmark",BG10="Finland",BG10="Iceland",BG10="Ireland",BG10="Lichtenstein",BG10="Luxemborg",BG10="Norway"),0,1))) | CH10: =IF(BN10="Yes",1,0) | CI10: =IF(BO10="Yes",1,0) | CJ10: =IF(BP10="Yes",1,0) | CK10: =IF(BQ10="Yes",1,0) | CL10: =IF(BR10="Yes",1,0) | CM10: =IF(BS10="Yes",1,0) | CN10: =IF(OR(AND(BJ10="Yes",N10="No"),AND(BJ10="Yes",N10="Yes",P10>=6)),1,0) | CO10: =IF(BT10="Yes",1,0) | CP10: =IF(AND(BU10="Yes",BV10="No"),1,0) | CQ10: =IF(BW10="Yes",1,0) | CR10: =IF(AP10="",0,IF(AP10>7,1,0)) | CS10: =IF(OR(BD10<>"Monthly",BD10<>"Quarterly",BD10<>"Semi-Annually"),0,1) | CT10: =IF(BX10="Yes",1,0) | CU10: =IF(BY10="Yes",1,0) | CV10: =IF(BZ10="Yes",1,0) | CW10: =IF(CA10="No",1,0) | CX10: =IF(B10="",0,IF(AK10>=5000000,0,1)) | CY10: =IF(B10="",0,IF(AL10>=5000000,0,1)) | CZ10: =IF(OR(DA10=1,DB10=1,DC10=1),0,IF(B10="",0,IF(OR(AND(AN10="Tier 1",X10="No",OR(AI10>$AJ$3,AJ10>$AJ$4)),(AND(AN10="Tier 1",X10="Yes",AJ10>$AJ$5)),(AND(AN10="Tier 2",X10="No",OR(AI10>$AK$3,AJ10>$AK$4))),(AND(AN10="Tier 2",X10="Yes",AJ10>$AK$5)),(AND(AN10="Tier 3",X10="No",OR(AI10>$AL$3,AJ10>$AL$4))),(AND(AN10="Tier 3",X10="Yes",AJ10>$AL$5))),1,0))) | DA10: =IF(OR(DB10=1,DC10=1),0,IF(B10="",0,IF(OR(AND(AN10="Tier 1",X10="No",OR(AI10>$AM$3,AJ10>$AM$4)),(AND(AN10="Tier 1",X10="Yes",AJ10>$AM$5)),(AND(AN10="Tier 2",X10="No",OR(AI10>$AN$3,AJ10>$AN$4))),(AND(AN10="Tier 2",X10="Yes",AJ10>$AN$5)),(AND(AN10="Tier 3",X10="No",OR(AI10>$AO$3,AJ10>$AO$4))),(AND(AN10="Tier 3",X10="Yes",AJ10>$AO$5))),1,0))) | DB10: =IF(DC10=1,0,IF(B10="",0,IF(OR(AND(AN10="Tier 1",X10="No",OR(AI10>$AP$3,AJ10>$AP$4)),(AND(AN10="Tier 1",X10="Yes",AJ10>$AP$5)),(AND(AN10="Tier 2",X10="No",OR(AI10>$AQ$3,AJ10>$AQ$4))),(AND(AN10="Tier 2",X10="Yes",AJ10>$AQ$5)),(AND(AN10="Tier 3",X10="No",OR(AI10>$AR$3,AJ10>$AR$4))),(AND(AN10="Tier 3",X10="Yes",AJ10>$AR$5))),1,0))) | DC10: =IF(B10="",0,IF(OR(AND(AN10="Tier 1",X10="No",OR(AI10>$AS$3,AJ10>$AS$4)),(AND(AN10="Tier 1",X10="Yes",AJ10>$AS$5)),(AND(AN10="Tier 2",X10="No",OR(AI10>$AT$3,AJ10>$AT$4))),(AND(AN10="Tier 2",X10="Yes",AJ10>$AT$5)),(AND(AN10="Tier 3",X10="No",OR(AI10>$AU$3,AJ10>$AU$4))),(AND(AN10="Tier 3",X10="Yes",AJ10>$AU$5))),1,0)) | DD10: =IF((SUM(CE10:CX10)=0),0,W10) | DE10: =IF(OR(B10="",DD10>0),0,W10) | DF10: =IF(B10="",0,IF(COUNTIF(CE10:CX10,1)>0,0,L10-M10)) | DG10: =DE10+IF(DD10>0,0,DF10) | DH10: =IF(B10="","",M10+DF10) | DI10: =IF(B10="",0,J10-K10) | DJ10: =IF(OR(BF10="EUR",BF10="CAD",BF10="GBP",BF10="AUD"),(GA10*(1-V10))+(HG10)+IF(HX10="",0,HX10*(1-U10)),0) | DK10: =IF(BF10="EUR",33%,IF(BF10="CAD",38%,IF(BF10="GBP",51%,IF(BF10="AUD",61%,0)))) | DL10: =DJ10*DK10 | DN10: =IF(OR(Y10="Second Lien",Y10="Tier 1 Split Lien",Y10="Tier 2 Split Lien"),DG10,0) | DO10: =DN10*DN$6 | DP10: =DG10-DO10 | DQ10: =IF(Y10="Second Lien",DP10,0) | DR10: =DQ10*DQ$6 | DS10: =DP10-DR10 | DT10: =IF(BH10="Yes",DS10,0) | DU10: =DT10*DT$6 | DV10: =DS10-DU10 | DW10: =IF(OR(BG10="Canada",BG10="United Kingdom",BG10="Australia",BG10="Netherlands Antilles",BG10="Bermuda",BG10="Cayman Islands",BG10="British Virgin Islands",BG10="Channel Islands",BG10="Isle of Man",BG10="Australia",BG10="Netherlands",BG10="Germany",BG10="Sweden",BG10="Switzerland",BG10="Austria",BG10="Belgium",BG10="Denmark",BG10="Finland",BG10="Iceland",BG10="Ireland",BG10="Lichtenstein",BG10="Luxemborg",BG10="Norway"),DV10,0) | DX10: =DW10*DW$6 | DY10: =DV10-DX10 | DZ10: =IF(BI10="Yes",DY10,0) | EA10: =DZ10*DZ$6 | EB10: =DY10-EA10 | EC10: =IF(OR(Z10="Delayed Draw",Z10="Revolver"),EB10,0) | ED10: =EC10*EC$6 | EE10: =EB10-ED10 | EF10: =IF(S10="Yes",EE10,0) | EG10: =EF10*EF$6 | EH10: =EE10-EG10 | EI10: =IF(Q10="Yes",EH10,0) | EJ10: =EI10*EI$6 | EK10: =EH10-EJ10 | EL10: =IF(BD10="Semi-Annually",EK10,0) | EM10: =EL10*EL$6 | EN10: =EK10-EM10 | EO10: =IF(BK10="Yes",EN10,0) | EP10: =EO10*EO$6 | EQ10: =EN10-EP10 | ER10: =IF(BL10="Yes",EQ10,0) | ES10: =ER10*ER$6 | ET10: =EQ10-ES10 | EU10: =IF(BM10="Yes",ET10,0) | EV10: =EU10*EU$6 | EW10: =ET10-EV10 | EX10: =IF(BV10="Yes",EW10,0) | EY10: =EX10*EX$6 | EZ10: =EW10-EY10 | FA10: =IF(AR10="Yes",EZ10,0) | FB10: =FA10*FA$6 | FC10: =EZ10-FB10 | FD10: =IF(OR(BF10="EUR",BF10="AUD",BF10="CAD",BF10="GBP"),FC10,0) | FE10: =FD10*FD$6 | FF10: =FC10-FE10 | FG10: =FF10 | FH10: =IF(FF10=0,0,VLOOKUP(C10,$GU$10:$GV$406,2,FALSE)*FF10) | FI10: =FF10-FH10 | FJ10: =FI10 | FK10: =IF(OR(IB10="",FI10<0.01),,VLOOKUP(IB10,$GL$10:$GM$406,2,FALSE)*FI10) | FL10: =FI10-FK10 | FM10: =FL10 | FN10: =IF(FL10=0,0,VLOOKUP(C10,$HD$10:$HE$406,2,FALSE)*FL10) | FO10: =FL10-FN10 | FP10: =IF(SUM(CY10:DC10)>0,0,IF(AND(AL10>=5000000,AL10<7500000),FO10,0)) | FQ10: =IF(B10="",0,FP10*FP$6*(1-$U10)) | FR10: =FO10-FQ10 | FS10: =IF(SUM(CY10:DC10)>0,0,IF(AL10<15000000,FR10,0)) | FT10: =IF(B10="",0,FS10*FS$6*(1-$U10)) | FU10: =FR10-FT10 | FV10: =IF(SUM(CY10:DC10)>0,0,IF(OR(AND(X10="No",AN10="Tier 1",AI10>$AG$3),AND(X10="No",AN10="Tier 2",AI10>$AH$3),AND(X10="No",AN10="Tier 3",AI10>$AI$3)),FU10,0)) | FW10: =IF(SUM(CY10:DC10)>0,0,IF(OR(AND(X10="No",AN10="Tier 1",AJ10>$AG$4),AND(X10="No",AN10="Tier 2",AJ10>$AH$4),AND(X10="No",AN10="Tier 3",AJ10>$AI$4)),FU10,0)) | FX10: =IF(SUM(CY10:DC10)>0,0,IF(OR(AND(X10="Yes",AN10="Tier 1",AJ10>$AG$5),AND(X10="Yes",AN10="Tier 2",AJ10>$AH$5),AND(X10="Yes",AN10="Tier 3",AJ10>$AI$5)),FU10,0)) | FY10: =IF(SUM(FV10:FX10)>0,FU10,0) | FZ10: =IF(B10="",0,FY10*FV$6*(1-MIN(90%,T10))) | GA10: =FU10-FZ10 | GB10: =IF(AND(N10="No",DI10=0),GA10,IF(AND(N10="No",DI10<>0,K10=0),0,IF(AND(N10="No",DI10<>0,K10>0,J10<>K10),MAX(0,M10-(DH10-GA10)),DG10))) | GC10: =+GB10*V10 | GD10: =IFERROR(GC10/K10,"") | GE10: =IF(IB10="","",IB10) | GF10: {=IF(SUM(IF(IB$9:IB9=IB10,1,0))>0,0,SUMIF($IB$10:$IB$406,IB10,$FI$10:$FI$406))} | GG10: =GF10 | GH10: 1 | GI10: =LARGE($GG$10:$GG$406,GH10) | GJ10: =IF(GH10>GH$6,0,IF(GH10=$GH$2,$GJ$2,IF(GH10<4,$GJ$3,$GJ$4))) | GK10: =MAX(0,GI10-GJ10) | GL10: {=IF(GI10=0,0,LARGE(IF($GF$10:$GF$406=GI10,$GE$10:$GE$406,0),COUNTIF($GI$10:$GI$406,GI10)-COUNTIF(GI$9:GI9,GI10)))} | GM10: =IF(GI10=0,0,GK10/GI10) | GO10: 1 | GP10: =IF(COUNTIF($A$10:A10,A10)<=1,SUMIF($A$10:$A$406,A10,$FG$10:$FG$406),0) | GQ10: 1 | GR10: =LARGE($GP$10:$GP$406,GQ10) | GS10: =IF(GQ10>GQ$6,0,IF(GQ10<=GQ$2,GS$2,IF(AND(GQ10<=$GQ$3,GQ10>$GQ$2),GS$3,GS$4))) | GT10: =MAX(0,GR10-GS10) | GU10: {=IF(GR10=0,0,LARGE(IF($GP$10:$GP$406=GR10,$GO$10:$GO$406,0),COUNTIF($GR$10:$GR$406,GR10)-COUNTIF(GR$9:GR9,GR10)))} | GV10: =IF(GR10=0,0,GT10/GR10) | GX10: 1 | GY10: =IF(COUNTIF($A$10:A10,A10)<=1,SUMIF($A$10:$A$406,A10,$FG$10:$FG$406),0) | GZ10: 1 | HA10: =LARGE($GY$10:$GY$406,GZ10) | HB10: - | HC10: =IF(GZ10<6,MAX(0,$HC$2/5),0) | HD10: {=IF(HA10=0,0,LARGE(IF($GY$10:$GY$406=HA10,$GX$10:$GX$406,0),COUNTIF($HA$10:$HA$406,HA10)-COUNTIF(HA$9:HA9,HA10)))} | HE10: =IF(HA10=0,0,HC10/HA10) | HG10: =DG10-GA10 | HH10: 0 | HI10: =MIN(HH10,DE10) | HK10: 1 | HL10: =SUMIF($C$10:$C$406,HK10,$DG$10:$DG$406) | HN10: =MIN(HO10:HS10) | HO10: =IF(B10="","",$M10) | HP10: =IF($N10="Yes",IF(P10>=6,0,MIN($T10*$M10,$U10*$M10)),"") | HQ10: =IF(AND(N10="Yes",P10>=6),"",IF($S10="Yes",$R10*$M10,"")) | HR10: =IF($Q10="Yes",MIN($M10,$T10*$M10),"") | HS10: =IF(AND($N10="Yes",$P10>=6),"",IF(OR(CY10=1,DC10=1,),MIN($T10*$M10,$U10*$M10),IF(OR(CZ10=1,DA10=1,DB10=1),IF(AK10>=5000000,MIN($T10*$M10,$IE10*$M10),MIN($T10*$M10,$U10*$M10)),""))) | HT10: =IF(DD10>0,DD10,"") | HU10: =IF(B10="",0,$L10-$M10) | HV10: =IF(OR(SUM(HP10:HT10)>0,P10>=6),"",IF($B10="","",1)) | HW10: =IF(AND($HT10<>0,OR(HT10<=MIN(HP10:HS10),SUM(HP10:HS10)=0)),$HT10,0) | HX10: =IF(AND($HS10<>0,OR(AND($HS10<>$HT10,$HS10<>$HR10,$HS10<>$HQ10,$HS10<>$HP10,$HS10<MIN($HP10:$HR10),$HS10<HT10),SUM($HP10:$HR10)+SUM(HT10)=0),IA10<=0),$HS10,0) | HY10: =IF(AND($HR10<>0,OR(AND($HR10<>$HT10,$HR10<>$HS10,$HR10<>$HQ10,$HR10<>$HP10),$HR10<MIN($HP10:$HQ10),$HR10<MIN($HS10:$HT10),SUM($HP10:$HQ10)+SUM($HS10:$HT10)=0)),$HR10,0) | HZ10: =IF(AND($HQ10<>0,OR(AND($HQ10<>$HT10,HQ10<>HS10,HQ10<>HR10,HQ10<>HP10,HQ10<MIN(HR10:HT10)),SUM(HP10)+SUM(HR10:HT10)=0)),$HQ10,0) | IA10: =IF(AND($HP10<>0,OR(HP10<=MIN(HQ10:HT10),SUM(HQ10:HT10)=0)),$HP10,0) | IB10: 41 | IC10: =HU10=DF10 | IE10: =IF(B10="","",IF(AND(Y10="Second Lien",OR(CZ10=1,DA10=1,DB10=1)),50%,IF(CZ10=1,90%,IF(DA10=1,80%,IF(DB10=1,65%,"No Initial Haircut")))))
A11: =D11 | B11: =IF(D11="","",B10+1) | C11: =IF(COUNTIF($A$10:A10,A11)>0,C10,C10+1) | D11: Cedar Ridge Holdings, LLC | E11: Cedar Ridge (Term Loan) | G11: 6009486.5 | H11: 6009486.5 | I11: 1 | J11: =IF(B11="","",G11*I11) | K11: =IF(B11="","",H11*I11) | L11: =IF(B11="","",IF(COUNTIF($CE11:$CX11,1)>0,0,J11)) | M11: =IF(B11="","",IF(COUNTIF($CE11:$CX11,1)>0,0,K11)) | N11: No | O11: N/A | P11: =IF(B11="","",IF(OR(O11="N/A",O11=""),0,YEARFRAC('Borrowing Base'!$J$4,'Loan List'!O11)*12)) | Q11: No | R11: 0.9975 | S11: =IF(B11="","",IF(R11<95%,"Yes","No")) | T11: 0.995 | U11: =IF(B11="","",IF(OR(Y11="First Lien",Y11="Split First Lien",Y11="Tier 1 Split Lien",Y11="Tier 2 Split Lien"),50%,30%)) | V11: =IF(B11="",0,IF(AND(Y11="First Lien",AN11="Tier 1"),IF(AND(X11="Yes",MIN(AH11,$AJ$5)>4.5),(((4.5/MIN(AH11,$AJ$5))*72.5%)+(((MIN(AH11,$AJ$5)-4.5)/MIN(AH11,$AJ$5))*35%)),72.5%),IF(AND(Y11="First Lien",AN11="Tier 2"),IF(AND(X11="Yes",MIN(AH11,$AK$5)>4.5),(((4.5/MIN(AH11,$AK$5))*72.5%)+(((MIN(AH11,$AK$5)-4.5)/MIN(AH11,$AK$5))*35%)),72.5%),IF(AND(X11="Yes",MIN(AH11,$AL$5)>4),(((4/MIN(AH11,$AL$5))*72.5%)+(((MIN(AH11,$AL$5)-4)/MIN(AH11,$AL$5))*35%)),IF(OR(Y11="First Lien",Y11="Split First Lien"),72.5%,IF(Y11="Split Lien", 53%,35%)))))) | W11: =IF($C11="","",MIN($HO11:$HS11)) | X11: Yes | Y11: First Lien | Z11: Term | AA11: NR | AB11: NR | AC11: 2.68 | AD11: 3.76 | AE11: 4.3704657 | AF11: 0.42754938 | AG11: 3.76 | AH11: 3.76 | AI11: 4.3704657 | AJ11: 4.3704657 | AK11: 35900000 | AL11: 61779000 | AM11: 45747 | AN11: =IF(C11="","",(IF(AK11>=50000000,"Tier 1",(IF(OR(AK11>=20000000,AND(AK11>5000000,AC11>=1.25,AF11<=0.65)),"Tier 2","Tier 3"))))) | AO11: 48149 | AP11: 6.2444444 | AQ11: =IF(C11="","",AP11) | AR11: No | AS11: 0 | AT11: Yes | AU11: 0.01 | AV11: 0.05 | AW11: 0.043079 | AX11: =IF(C11="","",MAX(AU11,AW11)) | AY11: 0 | AZ11: 0 | BA11: 0 | BB11: =IF(B11="","",IF(AR11="No",AV11-AZ11,"")) | BC11: =IF(B11="","",IF(AR11="Yes",AS11-BA11,"")) | BD11: Quarterly | BE11: Aerospace & Defense | BF11: USD | BG11: United States | BH11: No | BI11: =IF(B11="","",IF(OR(AND(AZ11>0,BB11>=2.5%,BB11<4%),AND(BA11>0,BC11>=6%,BC11<8%)),"Yes","No")) | BJ11: =IF(B11="","",IF(OR(AND(AZ11>0,BB11<2.5%),AND(BA11>0,BC11<6%)),"Yes","No")) | BK11: No | BL11: No | BM11: No | BN11: No | BO11: No | BP11: No | BQ11: No | BR11: No | BS11: No | BT11: No | BU11: No | BV11: No | BW11: No | BX11: No | BY11: No | BZ11: No | CA11: Yes | CB11: =IF(B11="","",IF(AT11="No",((BB11+AW11)-$AZ$4),((BB11+AX11)-$AZ$4))*IF(DD11>0,0,M11)) | CC11: =IF(B11="","",AY11*(L11-M11)*IF(DD11>0,0,1)) | CE11: =IF(AND(B11<>"",R11<=85%),1,0) | CF11: =IF(B11="",0,(IF(OR(BF11="USD",BF11="CAD",BF11="GBP",BF11="AUD",BF11="EUR"),0,1))) | CG11: =IF(B11="",0,(IF(OR(BG11="United States",BG11="Canada",BG11="United Kingdom",BG11="Australia",BG11="Netherlands Antilles",BG11="Bermuda",BG11="Cayman Islands",BG11="British Virgin Islands",BG11="Channel Islands",BG11="Isle of Man",BG11="Australia",BG11="Netherlands",BG11="Germany",BG11="Sweden",BG11="Switzerland",BG11="Austria",BG11="Belgium",BG11="Denmark",BG11="Finland",BG11="Iceland",BG11="Ireland",BG11="Lichtenstein",BG11="Luxemborg",BG11="Norway"),0,1))) | CH11: =IF(BN11="Yes",1,0) | CI11: =IF(BO11="Yes",1,0) | CJ11: =IF(BP11="Yes",1,0) | CK11: =IF(BQ11="Yes",1,0) | CL11: =IF(BR11="Yes",1,0) | CM11: =IF(BS11="Yes",1,0) | CN11: =IF(OR(AND(BJ11="Yes",N11="No"),AND(BJ11="Yes",N11="Yes",P11>=6)),1,0) | CO11: =IF(BT11="Yes",1,0) | CP11: =IF(AND(BU11="Yes",BV11="No"),1,0) | CQ11: =IF(BW11="Yes",1,0) | CR11: =IF(AP11="",0,IF(AP11>7,1,0)) | CS11: =IF(OR(BD11<>"Monthly",BD11<>"Quarterly",BD11<>"Semi-Annually"),0,1) | CT11: =IF(BX11="Yes",1,0) | CU11: =IF(BY11="Yes",1,0) | CV11: =IF(BZ11="Yes",1,0) | CW11: =IF(CA11="No",1,0) | CX11: =IF(B11="",0,IF(AK11>=5000000,0,1)) | CY11: =IF(B11="",0,IF(AL11>=5000000,0,1)) | CZ11: =IF(OR(DA11=1,DB11=1,DC11=1),0,IF(B11="",0,IF(OR(AND(AN11="Tier 1",X11="No",OR(AI11>$AJ$3,AJ11>$AJ$4)),(AND(AN11="Tier 1",X11="Yes",AJ11>$AJ$5)),(AND(AN11="Tier 2",X11="No",OR(AI11>$AK$3,AJ11>$AK$4))),(AND(AN11="Tier 2",X11="Yes",AJ11>$AK$5)),(AND(AN11="Tier 3",X11="No",OR(AI11>$AL$3,AJ11>$AL$4))),(AND(AN11="Tier 3",X11="Yes",AJ11>$AL$5))),1,0))) | DA11: =IF(OR(DB11=1,DC11=1),0,IF(B11="",0,IF(OR(AND(AN11="Tier 1",X11="No",OR(AI11>$AM$3,AJ11>$AM$4)),(AND(AN11="Tier 1",X11="Yes",AJ11>$AM$5)),(AND(AN11="Tier 2",X11="No",OR(AI11>$AN$3,AJ11>$AN$4))),(AND(AN11="Tier 2",X11="Yes",AJ11>$AN$5)),(AND(AN11="Tier 3",X11="No",OR(AI11>$AO$3,AJ11>$AO$4))),(AND(AN11="Tier 3",X11="Yes",AJ11>$AO$5))),1,0))) | DB11: =IF(DC11=1,0,IF(B11="",0,IF(OR(AND(AN11="Tier 1",X11="No",OR(AI11>$AP$3,AJ11>$AP$4)),(AND(AN11="Tier 1",X11="Yes",AJ11>$AP$5)),(AND(AN11="Tier 2",X11="No",OR(AI11>$AQ$3,AJ11>$AQ$4))),(AND(AN11="Tier 2",X11="Yes",AJ11>$AQ$5)),(AND(AN11="Tier 3",X11="No",OR(AI11>$AR$3,AJ11>$AR$4))),(AND(AN11="Tier 3",X11="Yes",AJ11>$AR$5))),1,0))) | DC11: =IF(B11="",0,IF(OR(AND(AN11="Tier 1",X11="No",OR(AI11>$AS$3,AJ11>$AS$4)),(AND(AN11="Tier 1",X11="Yes",AJ11>$AS$5)),(AND(AN11="Tier 2",X11="No",OR(AI11>$AT$3,AJ11>$AT$4))),(AND(AN11="Tier 2",X11="Yes",AJ11>$AT$5)),(AND(AN11="Tier 3",X11="No",OR(AI11>$AU$3,AJ11>$AU$4))),(AND(AN11="Tier 3",X11="Yes",AJ11>$AU$5))),1,0)) | DD11: =IF((SUM(CE11:CX11)=0),0,W11) | DE11: =IF(OR(B11="",DD11>0),0,W11) | DF11: =IF(B11="",0,IF(COUNTIF(CE11:CX11,1)>0,0,L11-M11)) | DG11: =DE11+IF(DD11>0,0,DF11) | DH11: =IF(B11="","",M11+DF11) | DI11: =IF(B11="",0,J11-K11) | DJ11: =IF(OR(BF11="EUR",BF11="CAD",BF11="GBP",BF11="AUD"),(GA11*(1-V11))+(HG11)+IF(HX11="",0,HX11*(1-U11)),0) | DK11: =IF(BF11="EUR",33%,IF(BF11="CAD",38%,IF(BF11="GBP",51%,IF(BF11="AUD",61%,0)))) | DL11: =DJ11*DK11 | DN11: =IF(OR(Y11="Second Lien",Y11="Tier 1 Split Lien",Y11="Tier 2 Split Lien"),DG11,0) | DO11: =DN11*DN$6 | DP11: =DG11-DO11 | DQ11: =IF(Y11="Second Lien",DP11,0) | DR11: =DQ11*DQ$6 | DS11: =DP11-DR11 | DT11: =IF(BH11="Yes",DS11,0) | DU11: =DT11*DT$6 | DV11: =DS11-DU11 | DW11: =IF(OR(BG11="Canada",BG11="United Kingdom",BG11="Australia",BG11="Netherlands Antilles",BG11="Bermuda",BG11="Cayman Islands",BG11="British Virgin Islands",BG11="Channel Islands",BG11="Isle of Man",BG11="Australia",BG11="Netherlands",BG11="Germany",BG11="Sweden",BG11="Switzerland",BG11="Austria",BG11="Belgium",BG11="Denmark",BG11="Finland",BG11="Iceland",BG11="Ireland",BG11="Lichtenstein",BG11="Luxemborg",BG11="Norway"),DV11,0) | DX11: =DW11*DW$6 | DY11: =DV11-DX11 | DZ11: =IF(BI11="Yes",DY11,0) | EA11: =DZ11*DZ$6 | EB11: =DY11-EA11 | EC11: =IF(OR(Z11="Delayed Draw",Z11="Revolver"),EB11,0) | ED11: =EC11*EC$6 | EE11: =EB11-ED11 | EF11: =IF(S11="Yes",EE11,0) | EG11: =EF11*EF$6 | EH11: =EE11-EG11 | EI11: =IF(Q11="Yes",EH11,0) | EJ11: =EI11*EI$6 | EK11: =EH11-EJ11 | EL11: =IF(BD11="Semi-Annually",EK11,0) | EM11: =EL11*EL$6 | EN11: =EK11-EM11 | EO11: =IF(BK11="Yes",EN11,0) | EP11: =EO11*EO$6 | EQ11: =EN11-EP11 | ER11: =IF(BL11="Yes",EQ11,0) | ES11: =ER11*ER$6 | ET11: =EQ11-ES11 | EU11: =IF(BM11="Yes",ET11,0) | EV11: =EU11*EU$6 | EW11: =ET11-EV11 | EX11: =IF(BV11="Yes",EW11,0) | EY11: =EX11*EX$6 | EZ11: =EW11-EY11 | FA11: =IF(AR11="Yes",EZ11,0) | FB11: =FA11*FA$6 | FC11: =EZ11-FB11 | FD11: =IF(OR(BF11="EUR",BF11="AUD",BF11="CAD",BF11="GBP"),FC11,0) | FE11: =FD11*FD$6 | FF11: =FC11-FE11 | FG11: =FF11 | FH11: =IF(FF11=0,0,VLOOKUP(C11,$GU$10:$GV$406,2,FALSE)*FF11) | FI11: =FF11-FH11 | FJ11: =FI11 | FK11: =IF(OR(IB11="",FI11<0.01),,VLOOKUP(IB11,$GL$10:$GM$406,2,FALSE)*FI11) | FL11: =FI11-FK11 | FM11: =FL11 | FN11: =IF(FL11=0,0,VLOOKUP(C11,$HD$10:$HE$406,2,FALSE)*FL11) | FO11: =FL11-FN11 | FP11: =IF(SUM(CY11:DC11)>0,0,IF(AND(AL11>=5000000,AL11<7500000),FO11,0)) | FQ11: =IF(B11="",0,FP11*FP$6*(1-$U11)) | FR11: =FO11-FQ11 | FS11: =IF(SUM(CY11:DC11)>0,0,IF(AL11<15000000,FR11,0)) | FT11: =IF(B11="",0,FS11*FS$6*(1-$U11)) | FU11: =FR11-FT11 | FV11: =IF(SUM(CY11:DC11)>0,0,IF(OR(AND(X11="No",AN11="Tier 1",AI11>$AG$3),AND(X11="No",AN11="Tier 2",AI11>$AH$3),AND(X11="No",AN11="Tier 3",AI11>$AI$3)),FU11,0)) | FW11: =IF(SUM(CY11:DC11)>0,0,IF(OR(AND(X11="No",AN11="Tier 1",AJ11>$AG$4),AND(X11="No",AN11="Tier 2",AJ11>$AH$4),AND(X11="No",AN11="Tier 3",AJ11>$AI$4)),FU11,0)) | FX11: =IF(SUM(CY11:DC11)>0,0,IF(OR(AND(X11="Yes",AN11="Tier 1",AJ11>$AG$5),AND(X11="Yes",AN11="Tier 2",AJ11>$AH$5),AND(X11="Yes",AN11="Tier 3",AJ11>$AI$5)),FU11,0)) | FY11: =IF(SUM(FV11:FX11)>0,FU11,0) | FZ11: =IF(B11="",0,FY11*FV$6*(1-MIN(90%,T11))) | GA11: =FU11-FZ11 | GB11: =IF(AND(N11="No",DI11=0),GA11,IF(AND(N11="No",DI11<>0,K11=0),0,IF(AND(N11="No",DI11<>0,K11>0,J11<>K11),MAX(0,M11-(DH11-GA11)),DG11))) | GC11: =+GB11*V11 | GD11: =IFERROR(GC11/K11,"") | GE11: =IF(IB11="","",IB11) | GF11: {=IF(SUM(IF(IB$9:IB10=IB11,1,0))>0,0,SUMIF($IB$10:$IB$406,IB11,$FI$10:$FI$406))} | GG11: =GF11 | GH11: =GH10+1 | GI11: =LARGE($GG$10:$GG$406,GH11) | GJ11: =IF(GH11>GH$6,0,IF(GH11=$GH$2,$GJ$2,IF(GH11<4,$GJ$3,$GJ$4))) | GK11: =MAX(0,GI11-GJ11) | GL11: {=IF(GI11=0,0,LARGE(IF($GF$10:$GF$406=GI11,$GE$10:$GE$406,0),COUNTIF($GI$10:$GI$406,GI11)-COUNTIF(GI$9:GI10,GI11)))} | GM11: =IF(GI11=0,0,GK11/GI11) | GO11: =IF(C11="","",IF(ISERROR(MATCH(C11,C10:C$10,0)),MAX(GO10:GO$10)+1,INDEX(GO10:GO$10,MATCH(C11,C10:C$10,0)))) | GP11: =IF(COUNTIF($A$10:A11,A11)<=1,SUMIF($A$10:$A$406,A11,$FG$10:$FG$406),0) | GQ11: =GQ10+1 | GR11: =LARGE($GP$10:$GP$406,GQ11) | GS11: =IF(GQ11>GQ$6,0,IF(GQ11<=GQ$2,GS$2,IF(AND(GQ11<=$GQ$3,GQ11>$GQ$2),GS$3,GS$4))) | GT11: =MAX(0,GR11-GS11) | GU11: {=IF(GR11=0,0,LARGE(IF($GP$10:$GP$406=GR11,$GO$10:$GO$406,0),COUNTIF($GR$10:$GR$406,GR11)-COUNTIF(GR$9:GR10,GR11)))} | GV11: =IF(GR11=0,0,GT11/GR11) | GX11: =IF(C11="","",IF(ISERROR(MATCH(C11,C10:C$10,0)),MAX(GO10:GO$10)+1,INDEX(GO10:GO$10,MATCH(C11,C10:C$10,0)))) | GY11: =IF(COUNTIF($A$10:A11,A11)<=1,SUMIF($A$10:$A$406,A11,$FG$10:$FG$406),0) | GZ11: =GZ10+1 | HA11: =LARGE($GY$10:$GY$406,GZ11) | HB11: - | HC11: =IF(GZ11<6,MAX(0,$HC$2/5),0) | HD11: {=IF(HA11=0,0,LARGE(IF($GY$10:$GY$406=HA11,$GX$10:$GX$406,0),COUNTIF($HA$10:$HA$406,HA11)-COUNTIF(HA$9:HA10,HA11)))} | HE11: =IF(HA11=0,0,HC11/HA11) | HG11: =DG11-GA11 | HH11: 0 | HI11: =MIN(HH11,DE11) | HK11: =IF(COUNTIF($C$10:$C$406,HK10+1),HK10+1,"") | HL11: =SUMIF($C$10:$C$406,HK11,$DG$10:$DG$406) | HN11: =MIN(HO11:HS11) | HO11: =IF(B11="","",$M11) | HP11: =IF($N11="Yes",IF(P11>=6,0,MIN($T11*$M11,$U11*$M11)),"") | HQ11: =IF(AND(N11="Yes",P11>=6),"",IF($S11="Yes",$R11*$M11,"")) | HR11: =IF($Q11="Yes",MIN($M11,$T11*$M11),"") | HS11: =IF(AND($N11="Yes",$P11>=6),"",IF(OR(CY11=1,DC11=1,),MIN($T11*$M11,$U11*$M11),IF(OR(CZ11=1,DA11=1,DB11=1),IF(AK11>=5000000,MIN($T11*$M11,$IE11*$M11),MIN($T11*$M11,$U11*$M11)),""))) | HT11: =IF(DD11>0,DD11,"") | HU11: =IF(B11="",0,$L11-$M11) | HV11: =IF(OR(SUM(HP11:HT11)>0,P11>=6),"",IF($B11="","",1)) | HW11: =IF(AND($HT11<>0,OR(HT11<=MIN(HP11:HS11),SUM(HP11:HS11)=0)),$HT11,0) | HX11: =IF(AND($HS11<>0,OR(AND($HS11<>$HT11,$HS11<>$HR11,$HS11<>$HQ11,$HS11<>$HP11,$HS11<MIN($HP11:$HR11),$HS11<HT11),SUM($HP11:$HR11)+SUM(HT11)=0),IA11<=0),$HS11,0) | HY11: =IF(AND($HR11<>0,OR(AND($HR11<>$HT11,$HR11<>$HS11,$HR11<>$HQ11,$HR11<>$HP11),$HR11<MIN($HP11:$HQ11),$HR11<MIN($HS11:$HT11),SUM($HP11:$HQ11)+SUM($HS11:$HT11)=0)),$HR11,0) | HZ11: =IF(AND($HQ11<>0,OR(AND($HQ11<>$HT11,HQ11<>HS11,HQ11<>HR11,HQ11<>HP11,HQ11<MIN(HR11:HT11)),SUM(HP11)+SUM(HR11:HT11)=0)),$HQ11,0) | IA11: =IF(AND($HP11<>0,OR(HP11<=MIN(HQ11:HT11),SUM(HQ11:HT11)=0)),$HP11,0) | IB11: 1 | IC11: =HU11=DF11 | IE11: =IF(B11="","",IF(AND(Y11="Second Lien",OR(CZ11=1,DA11=1,DB11=1)),50%,IF(CZ11=1,90%,IF(DA11=1,80%,IF(DB11=1,65%,"No Initial Haircut")))))
A12: =D12 | B12: =IF(D12="","",B11+1) | C12: =IF(COUNTIF($A$10:A11,A12)>0,C11,C11+1) | D12: Bluewater Holdings, LLC | E12: Bluewater (Term Loan) | G12: 5271860.2 | H12: 5271860.2 | I12: 1 | J12: =IF(B12="","",G12*I12) | K12: =IF(B12="","",H12*I12) | L12: =IF(B12="","",IF(COUNTIF($CE12:$CX12,1)>0,0,J12)) | M12: =IF(B12="","",IF(COUNTIF($CE12:$CX12,1)>0,0,K12)) | N12: No | O12: N/A | P12: =IF(B12="","",IF(OR(O12="N/A",O12=""),0,YEARFRAC('Borrowing Base'!$J$4,'Loan List'!O12)*12)) | Q12: No | R12: 0.99000524 | S12: =IF(B12="","",IF(R12<95%,"Yes","No")) | T12: 1 | U12: =IF(B12="","",IF(OR(Y12="First Lien",Y12="Split First Lien",Y12="Tier 1 Split Lien",Y12="Tier 2 Split Lien"),50%,30%)) | V12: =IF(B12="",0,IF(AND(Y12="First Lien",AN12="Tier 1"),IF(AND(X12="Yes",MIN(AH12,$AJ$5)>4.5),(((4.5/MIN(AH12,$AJ$5))*72.5%)+(((MIN(AH12,$AJ$5)-4.5)/MIN(AH12,$AJ$5))*35%)),72.5%),IF(AND(Y12="First Lien",AN12="Tier 2"),IF(AND(X12="Yes",MIN(AH12,$AK$5)>4.5),(((4.5/MIN(AH12,$AK$5))*72.5%)+(((MIN(AH12,$AK$5)-4.5)/MIN(AH12,$AK$5))*35%)),72.5%),IF(AND(X12="Yes",MIN(AH12,$AL$5)>4),(((4/MIN(AH12,$AL$5))*72.5%)+(((MIN(AH12,$AL$5)-4)/MIN(AH12,$AL$5))*35%)),IF(OR(Y12="First Lien",Y12="Split First Lien"),72.5%,IF(Y12="Split Lien", 53%,35%)))))) | W12: =IF($C12="","",MIN($HO12:$HS12)) | X12: No | Y12: First Lien | Z12: Term | AA12: NR | AB12: NR | AC12: 1.633068 | AD12: 3.4364287 | AE12: 3.5785077 | AF12: 0.48220859 | AG12: 3.4364287 | AH12: 3.4364287 | AI12: 3.8376355 | AJ12: 3.8376355 | AK12: 11436291 | AL12: 15496061 | AM12: 45838 | AN12: =IF(C12="","",(IF(AK12>=50000000,"Tier 1",(IF(OR(AK12>=20000000,AND(AK12>5000000,AC12>=1.25,AF12<=0.65)),"Tier 2","Tier 3"))))) | AO12: 47358 | AP12: 4.0777778 | AQ12: =IF(C12="","",AP12) | AR12: No | AS12: 0 | AT12: Yes | AU12: 0.01 | AV12: 0.0575 | AW12: 0.042956 | AX12: =IF(C12="","",MAX(AU12,AW12)) | AY12: 0 | AZ12: 0 | BA12: 0 | BB12: =IF(B12="","",IF(AR12="No",AV12-AZ12,"")) | BC12: =IF(B12="","",IF(AR12="Yes",AS12-BA12,"")) | BD12: Quarterly | BE12: Diversified Financial Services | BF12: USD | BG12: United States | BH12: No | BI12: =IF(B12="","",IF(OR(AND(AZ12>0,BB12>=2.5%,BB12<4%),AND(BA12>0,BC12>=6%,BC12<8%)),"Yes","No")) | BJ12: =IF(B12="","",IF(OR(AND(AZ12>0,BB12<2.5%),AND(BA12>0,BC12<6%)),"Yes","No")) | BK12: No | BL12: No | BM12: No | BN12: No | BO12: No | BP12: No | BQ12: No | BR12: No | BS12: No | BT12: No | BU12: No | BV12: No | BW12: No | BX12: No | BY12: No | BZ12: No | CA12: Yes | CB12: =IF(B12="","",IF(AT12="No",((BB12+AW12)-$AZ$4),((BB12+AX12)-$AZ$4))*IF(DD12>0,0,M12)) | CC12: =IF(B12="","",AY12*(L12-M12)*IF(DD12>0,0,1)) | CE12: =IF(AND(B12<>"",R12<=85%),1,0) | CF12: =IF(B12="",0,(IF(OR(BF12="USD",BF12="CAD",BF12="GBP",BF12="AUD",BF12="EUR"),0,1))) | CG12: =IF(B12="",0,(IF(OR(BG12="United States",BG12="Canada",BG12="United Kingdom",BG12="Australia",BG12="Netherlands Antilles",BG12="Bermuda",BG12="Cayman Islands",BG12="British Virgin Islands",BG12="Channel Islands",BG12="Isle of Man",BG12="Australia",BG12="Netherlands",BG12="Germany",BG12="Sweden",BG12="Switzerland",BG12="Austria",BG12="Belgium",BG12="Denmark",BG12="Finland",BG12="Iceland",BG12="Ireland",BG12="Lichtenstein",BG12="Luxemborg",BG12="Norway"),0,1))) | CH12: =IF(BN12="Yes",1,0) | CI12: =IF(BO12="Yes",1,0) | CJ12: =IF(BP12="Yes",1,0) | CK12: =IF(BQ12="Yes",1,0) | CL12: =IF(BR12="Yes",1,0) | CM12: =IF(BS12="Yes",1,0) | CN12: =IF(OR(AND(BJ12="Yes",N12="No"),AND(BJ12="Yes",N12="Yes",P12>=6)),1,0) | CO12: =IF(BT12="Yes",1,0) | CP12: =IF(AND(BU12="Yes",BV12="No"),1,0) | CQ12: =IF(BW12="Yes",1,0) | CR12: =IF(AP12="",0,IF(AP12>7,1,0)) | CS12: =IF(OR(BD12<>"Monthly",BD12<>"Quarterly",BD12<>"Semi-Annually"),0,1) | CT12: =IF(BX12="Yes",1,0) | CU12: =IF(BY12="Yes",1,0) | CV12: =IF(BZ12="Yes",1,0) | CW12: =IF(CA12="No",1,0) | CX12: =IF(B12="",0,IF(AK12>=5000000,0,1)) | CY12: =IF(B12="",0,IF(AL12>=5000000,0,1)) | CZ12: =IF(OR(DA12=1,DB12=1,DC12=1),0,IF(B12="",0,IF(OR(AND(AN12="Tier 1",X12="No",OR(AI12>$AJ$3,AJ12>$AJ$4)),(AND(AN12="Tier 1",X12="Yes",AJ12>$AJ$5)),(AND(AN12="Tier 2",X12="No",OR(AI12>$AK$3,AJ12>$AK$4))),(AND(AN12="Tier 2",X12="Yes",AJ12>$AK$5)),(AND(AN12="Tier 3",X12="No",OR(AI12>$AL$3,AJ12>$AL$4))),(AND(AN12="Tier 3",X12="Yes",AJ12>$AL$5))),1,0))) | DA12: =IF(OR(DB12=1,DC12=1),0,IF(B12="",0,IF(OR(AND(AN12="Tier 1",X12="No",OR(AI12>$AM$3,AJ12>$AM$4)),(AND(AN12="Tier 1",X12="Yes",AJ12>$AM$5)),(AND(AN12="Tier 2",X12="No",OR(AI12>$AN$3,AJ12>$AN$4))),(AND(AN12="Tier 2",X12="Yes",AJ12>$AN$5)),(AND(AN12="Tier 3",X12="No",OR(AI12>$AO$3,AJ12>$AO$4))),(AND(AN12="Tier 3",X12="Yes",AJ12>$AO$5))),1,0))) | DB12: =IF(DC12=1,0,IF(B12="",0,IF(OR(AND(AN12="Tier 1",X12="No",OR(AI12>$AP$3,AJ12>$AP$4)),(AND(AN12="Tier 1",X12="Yes",AJ12>$AP$5)),(AND(AN12="Tier 2",X12="No",OR(AI12>$AQ$3,AJ12>$AQ$4))),(AND(AN12="Tier 2",X12="Yes",AJ12>$AQ$5)),(AND(AN12="Tier 3",X12="No",OR(AI12>$AR$3,AJ12>$AR$4))),(AND(AN12="Tier 3",X12="Yes",AJ12>$AR$5))),1,0))) | DC12: =IF(B12="",0,IF(OR(AND(AN12="Tier 1",X12="No",OR(AI12>$AS$3,AJ12>$AS$4)),(AND(AN12="Tier 1",X12="Yes",AJ12>$AS$5)),(AND(AN12="Tier 2",X12="No",OR(AI12>$AT$3,AJ12>$AT$4))),(AND(AN12="Tier 2",X12="Yes",AJ12>$AT$5)),(AND(AN12="Tier 3",X12="No",OR(AI12>$AU$3,AJ12>$AU$4))),(AND(AN12="Tier 3",X12="Yes",AJ12>$AU$5))),1,0)) | DD12: =IF((SUM(CE12:CX12)=0),0,W12) | DE12: =IF(OR(B12="",DD12>0),0,W12) | DF12: =IF(B12="",0,IF(COUNTIF(CE12:CX12,1)>0,0,L12-M12)) | DG12: =DE12+IF(DD12>0,0,DF12) | DH12: =IF(B12="","",M12+DF12) | DI12: =IF(B12="",0,J12-K12) | DJ12: =IF(OR(BF12="EUR",BF12="CAD",BF12="GBP",BF12="AUD"),(GA12*(1-V12))+(HG12)+IF(HX12="",0,HX12*(1-U12)),0) | DK12: =IF(BF12="EUR",33%,IF(BF12="CAD",38%,IF(BF12="GBP",51%,IF(BF12="AUD",61%,0)))) | DL12: =DJ12*DK12 | DN12: =IF(OR(Y12="Second Lien",Y12="Tier 1 Split Lien",Y12="Tier 2 Split Lien"),DG12,0) | DO12: =DN12*DN$6 | DP12: =DG12-DO12 | DQ12: =IF(Y12="Second Lien",DP12,0) | DR12: =DQ12*DQ$6 | DS12: =DP12-DR12 | DT12: =IF(BH12="Yes",DS12,0) | DU12: =DT12*DT$6 | DV12: =DS12-DU12 | DW12: =IF(OR(BG12="Canada",BG12="United Kingdom",BG12="Australia",BG12="Netherlands Antilles",BG12="Bermuda",BG12="Cayman Islands",BG12="British Virgin Islands",BG12="Channel Islands",BG12="Isle of Man",BG12="Australia",BG12="Netherlands",BG12="Germany",BG12="Sweden",BG12="Switzerland",BG12="Austria",BG12="Belgium",BG12="Denmark",BG12="Finland",BG12="Iceland",BG12="Ireland",BG12="Lichtenstein",BG12="Luxemborg",BG12="Norway"),DV12,0) | DX12: =DW12*DW$6 | DY12: =DV12-DX12 | DZ12: =IF(BI12="Yes",DY12,0) | EA12: =DZ12*DZ$6 | EB12: =DY12-EA12 | EC12: =IF(OR(Z12="Delayed Draw",Z12="Revolver"),EB12,0) | ED12: =EC12*EC$6 | EE12: =EB12-ED12 | EF12: =IF(S12="Yes",EE12,0) | EG12: =EF12*EF$6 | EH12: =EE12-EG12 | EI12: =IF(Q12="Yes",EH12,0) | EJ12: =EI12*EI$6 | EK12: =EH12-EJ12 | EL12: =IF(BD12="Semi-Annually",EK12,0) | EM12: =EL12*EL$6 | EN12: =EK12-EM12 | EO12: =IF(BK12="Yes",EN12,0) | EP12: =EO12*EO$6 | EQ12: =EN12-EP12 | ER12: =IF(BL12="Yes",EQ12,0) | ES12: =ER12*ER$6 | ET12: =EQ12-ES12 | EU12: =IF(BM12="Yes",ET12,0) | EV12: =EU12*EU$6 | EW12: =ET12-EV12 | EX12: =IF(BV12="Yes",EW12,0) | EY12: =EX12*EX$6 | EZ12: =EW12-EY12 | FA12: =IF(AR12="Yes",EZ12,0) | FB12: =FA12*FA$6 | FC12: =EZ12-FB12 | FD12: =IF(OR(BF12="EUR",BF12="AUD",BF12="CAD",BF12="GBP"),FC12,0) | FE12: =FD12*FD$6 | FF12: =FC12-FE12 | FG12: =FF12 | FH12: =IF(FF12=0,0,VLOOKUP(C12,$GU$10:$GV$406,2,FALSE)*FF12) | FI12: =FF12-FH12 | FJ12: =FI12 | FK12: =IF(OR(IB12="",FI12<0.01),,VLOOKUP(IB12,$GL$10:$GM$406,2,FALSE)*FI12) | FL12: =FI12-FK12 | FM12: =FL12 | FN12: =IF(FL12=0,0,VLOOKUP(C12,$HD$10:$HE$406,2,FALSE)*FL12) | FO12: =FL12-FN12 | FP12: =IF(SUM(CY12:DC12)>0,0,IF(AND(AL12>=5000000,AL12<7500000),FO12,0)) | FQ12: =IF(B12="",0,FP12*FP$6*(1-$U12)) | FR12: =FO12-FQ12 | FS12: =IF(SUM(CY12:DC12)>0,0,IF(AL12<15000000,FR12,0)) | FT12: =IF(B12="",0,FS12*FS$6*(1-$U12)) | FU12: =FR12-FT12 | FV12: =IF(SUM(CY12:DC12)>0,0,IF(OR(AND(X12="No",AN12="Tier 1",AI12>$AG$3),AND(X12="No",AN12="Tier 2",AI12>$AH$3),AND(X12="No",AN12="Tier 3",AI12>$AI$3)),FU12,0)) | FW12: =IF(SUM(CY12:DC12)>0,0,IF(OR(AND(X12="No",AN12="Tier 1",AJ12>$AG$4),AND(X12="No",AN12="Tier 2",AJ12>$AH$4),AND(X12="No",AN12="Tier 3",AJ12>$AI$4)),FU12,0)) | FX12: =IF(SUM(CY12:DC12)>0,0,IF(OR(AND(X12="Yes",AN12="Tier 1",AJ12>$AG$5),AND(X12="Yes",AN12="Tier 2",AJ12>$AH$5),AND(X12="Yes",AN12="Tier 3",AJ12>$AI$5)),FU12,0)) | FY12: =IF(SUM(FV12:FX12)>0,FU12,0) | FZ12: =IF(B12="",0,FY12*FV$6*(1-MIN(90%,T12))) | GA12: =FU12-FZ12 | GB12: =IF(AND(N12="No",DI12=0),GA12,IF(AND(N12="No",DI12<>0,K12=0),0,IF(AND(N12="No",DI12<>0,K12>0,J12<>K12),MAX(0,M12-(DH12-GA12)),DG12))) | GC12: =+GB12*V12 | GD12: =IFERROR(GC12/K12,"") | GE12: =IF(IB12="","",IB12) | GF12: {=IF(SUM(IF(IB$9:IB11=IB12,1,0))>0,0,SUMIF($IB$10:$IB$406,IB12,$FI$10:$FI$406))} | GG12: =GF12 | GH12: =GH11+1 | GI12: =LARGE($GG$10:$GG$406,GH12) | GJ12: =IF(GH12>GH$6,0,IF(GH12=$GH$2,$GJ$2,IF(GH12<4,$GJ$3,$GJ$4))) | GK12: =MAX(0,GI12-GJ12) | GL12: {=IF(GI12=0,0,LARGE(IF($GF$10:$GF$406=GI12,$GE$10:$GE$406,0),COUNTIF($GI$10:$GI$406,GI12)-COUNTIF(GI$9:GI11,GI12)))} | GM12: =IF(GI12=0,0,GK12/GI12) | GO12: =IF(C12="","",IF(ISERROR(MATCH(C12,C$10:C11,0)),MAX(GO$10:GO11)+1,INDEX(GO$10:GO11,MATCH(C12,C$10:C11,0)))) | GP12: =IF(COUNTIF($A$10:A12,A12)<=1,SUMIF($A$10:$A$406,A12,$FG$10:$FG$406),0) | GQ12: =GQ11+1 | GR12: =LARGE($GP$10:$GP$406,GQ12) | GS12: =IF(GQ12>GQ$6,0,IF(GQ12<=GQ$2,GS$2,IF(AND(GQ12<=$GQ$3,GQ12>$GQ$2),GS$3,GS$4))) | GT12: =MAX(0,GR12-GS12) | GU12: {=IF(GR12=0,0,LARGE(IF($GP$10:$GP$406=GR12,$GO$10:$GO$406,0),COUNTIF($GR$10:$GR$406,GR12)-COUNTIF(GR$9:GR11,GR12)))} | GV12: =IF(GR12=0,0,GT12/GR12) | GX12: =IF(C12="","",IF(ISERROR(MATCH(C12,C$10:C11,0)),MAX(GO$10:GO11)+1,INDEX(GO$10:GO11,MATCH(C12,C$10:C11,0)))) | GY12: =IF(COUNTIF($A$10:A12,A12)<=1,SUMIF($A$10:$A$406,A12,$FG$10:$FG$406),0) | GZ12: =GZ11+1 | HA12: =LARGE($GY$10:$GY$406,GZ12) | HB12: - | HC12: =IF(GZ12<6,MAX(0,$HC$2/5),0) | HD12: {=IF(HA12=0,0,LARGE(IF($GY$10:$GY$406=HA12,$GX$10:$GX$406,0),COUNTIF($HA$10:$HA$406,HA12)-COUNTIF(HA$9:HA11,HA12)))} | HE12: =IF(HA12=0,0,HC12/HA12) | HG12: =DG12-GA12 | HH12: 0 | HI12: =MIN(HH12,DE12) | HK12: =IF(COUNTIF($C$10:$C$406,HK11+1),HK11+1,"") | HL12: =SUMIF($C$10:$C$406,HK12,$DG$10:$DG$406) | HN12: =MIN(HO12:HS12) | HO12: =IF(B12="","",$M12) | HP12: =IF($N12="Yes",IF(P12>=6,0,MIN($T12*$M12,$U12*$M12)),"") | HQ12: =IF(AND(N12="Yes",P12>=6),"",IF($S12="Yes",$R12*$M12,"")) | HR12: =IF($Q12="Yes",MIN($M12,$T12*$M12),"") | HS12: =IF(AND($N12="Yes",$P12>=6),"",IF(OR(CY12=1,DC12=1,),MIN($T12*$M12,$U12*$M12),IF(OR(CZ12=1,DA12=1,DB12=1),IF(AK12>=5000000,MIN($T12*$M12,$IE12*$M12),MIN($T12*$M12,$U12*$M12)),""))) | HT12: =IF(DD12>0,DD12,"") | HU12: =IF(B12="",0,$L12-$M12) | HV12: =IF(OR(SUM(HP12:HT12)>0,P12>=6),"",IF($B12="","",1)) | HW12: =IF(AND($HT12<>0,OR(HT12<=MIN(HP12:HS12),SUM(HP12:HS12)=0)),$HT12,0) | HX12: =IF(AND($HS12<>0,OR(AND($HS12<>$HT12,$HS12<>$HR12,$HS12<>$HQ12,$HS12<>$HP12,$HS12<MIN($HP12:$HR12),$HS12<HT12),SUM($HP12:$HR12)+SUM(HT12)=0),IA12<=0),$HS12,0) | HY12: =IF(AND($HR12<>0,OR(AND($HR12<>$HT12,$HR12<>$HS12,$HR12<>$HQ12,$HR12<>$HP12),$HR12<MIN($HP12:$HQ12),$HR12<MIN($HS12:$HT12),SUM($HP12:$HQ12)+SUM($HS12:$HT12)=0)),$HR12,0) | HZ12: =IF(AND($HQ12<>0,OR(AND($HQ12<>$HT12,HQ12<>HS12,HQ12<>HR12,HQ12<>HP12,HQ12<MIN(HR12:HT12)),SUM(HP12)+SUM(HR12:HT12)=0)),$HQ12,0) | IA12: =IF(AND($HP12<>0,OR(HP12<=MIN(HQ12:HT12),SUM(HQ12:HT12)=0)),$HP12,0) | IB12: 20 | IC12: =HU12=DF12 | IE12: =IF(B12="","",IF(AND(Y12="Second Lien",OR(CZ12=1,DA12=1,DB12=1)),50%,IF(CZ12=1,90%,IF(DA12=1,80%,IF(DB12=1,65%,"No Initial Haircut")))))
A13: =D13 | B13: =IF(D13="","",B12+1) | C13: =IF(COUNTIF($A$10:A12,A13)>0,C12,C12+1) | D13: Ironwood Holdings, LLC | E13: Ironwood (Term Loan) | G13: 34673920 | H13: 34673920 | I13: 1 | J13: =IF(B13="","",G13*I13) | K13: =IF(B13="","",H13*I13) | L13: =IF(B13="","",IF(COUNTIF($CE13:$CX13,1)>0,0,J13)) | M13: =IF(B13="","",IF(COUNTIF($CE13:$CX13,1)>0,0,K13)) | N13: No | O13: N/A | P13: =IF(B13="","",IF(OR(O13="N/A",O13=""),0,YEARFRAC('Borrowing Base'!$J$4,'Loan List'!O13)*12)) | Q13: No | R13: 0.99010093 | S13: =IF(B13="","",IF(R13<95%,"Yes","No")) | T13: 0.991 | U13: =IF(B13="","",IF(OR(Y13="First Lien",Y13="Split First Lien",Y13="Tier 1 Split Lien",Y13="Tier 2 Split Lien"),50%,30%)) | V13: =IF(B13="",0,IF(AND(Y13="First Lien",AN13="Tier 1"),IF(AND(X13="Yes",MIN(AH13,$AJ$5)>4.5),(((4.5/MIN(AH13,$AJ$5))*72.5%)+(((MIN(AH13,$AJ$5)-4.5)/MIN(AH13,$AJ$5))*35%)),72.5%),IF(AND(Y13="First Lien",AN13="Tier 2"),IF(AND(X13="Yes",MIN(AH13,$AK$5)>4.5),(((4.5/MIN(AH13,$AK$5))*72.5%)+(((MIN(AH13,$AK$5)-4.5)/MIN(AH13,$AK$5))*35%)),72.5%),IF(AND(X13="Yes",MIN(AH13,$AL$5)>4),(((4/MIN(AH13,$AL$5))*72.5%)+(((MIN(AH13,$AL$5)-4)/MIN(AH13,$AL$5))*35%)),IF(OR(Y13="First Lien",Y13="Split First Lien"),72.5%,IF(Y13="Split Lien", 53%,35%)))))) | W13: =IF($C13="","",MIN($HO13:$HS13)) | X13: No | Y13: First Lien | Z13: Term | AA13: NR | AB13: NR | AC13: 1.8301481 | AD13: 3.5191248 | AE13: 4.791559 | AF13: 0.34427481 | AG13: 3.5191248 | AH13: 3.5191248 | AI13: 5.1371733 | AJ13: 6.9590511 | AK13: 64078433 | AL13: 82332636 | AM13: 45838 | AN13: =IF(C13="","",(IF(AK13>=50000000,"Tier 1",(IF(OR(AK13>=20000000,AND(AK13>5000000,AC13>=1.25,AF13<=0.65)),"Tier 2","Tier 3"))))) | AO13: 47374 | AP13: 4.1194444 | AQ13: =IF(C13="","",AP13) | AR13: No | AS13: 0 | AT13: Yes | AU13: 0.01 | AV13: 0.0575 | AW13: 0.043507 | AX13: =IF(C13="","",MAX(AU13,AW13)) | AY13: 0 | AZ13: 0 | BA13: 0 | BB13: =IF(B13="","",IF(AR13="No",AV13-AZ13,"")) | BC13: =IF(B13="","",IF(AR13="Yes",AS13-BA13,"")) | BD13: Quarterly | BE13: IT Services | BF13: USD | BG13: United States | BH13: No | BI13: =IF(B13="","",IF(OR(AND(AZ13>0,BB13>=2.5%,BB13<4%),AND(BA13>0,BC13>=6%,BC13<8%)),"Yes","No")) | BJ13: =IF(B13="","",IF(OR(AND(AZ13>0,BB13<2.5%),AND(BA13>0,BC13<6%)),"Yes","No")) | BK13: No | BL13: No | BM13: No | BN13: No | BO13: No | BP13: No | BQ13: No | BR13: No | BS13: No | BT13: No | BU13: No | BV13: No | BW13: No | BX13: No | BY13: No | BZ13: No | CA13: Yes | CB13: =IF(B13="","",IF(AT13="No",((BB13+AW13)-$AZ$4),((BB13+AX13)-$AZ$4))*IF(DD13>0,0,M13)) | CC13: =IF(B13="","",AY13*(L13-M13)*IF(DD13>0,0,1)) | CE13: =IF(AND(B13<>"",R13<=85%),1,0) | CF13: =IF(B13="",0,(IF(OR(BF13="USD",BF13="CAD",BF13="GBP",BF13="AUD",BF13="EUR"),0,1))) | CG13: =IF(B13="",0,(IF(OR(BG13="United States",BG13="Canada",BG13="United Kingdom",BG13="Australia",BG13="Netherlands Antilles",BG13="Bermuda",BG13="Cayman Islands",BG13="British Virgin Islands",BG13="Channel Islands",BG13="Isle of Man",BG13="Australia",BG13="Netherlands",BG13="Germany",BG13="Sweden",BG13="Switzerland",BG13="Austria",BG13="Belgium",BG13="Denmark",BG13="Finland",BG13="Iceland",BG13="Ireland",BG13="Lichtenstein",BG13="Luxemborg",BG13="Norway"),0,1))) | CH13: =IF(BN13="Yes",1,0) | CI13: =IF(BO13="Yes",1,0) | CJ13: =IF(BP13="Yes",1,0) | CK13: =IF(BQ13="Yes",1,0) | CL13: =IF(BR13="Yes",1,0) | CM13: =IF(BS13="Yes",1,0) | CN13: =IF(OR(AND(BJ13="Yes",N13="No"),AND(BJ13="Yes",N13="Yes",P13>=6)),1,0) | CO13: =IF(BT13="Yes",1,0) | CP13: =IF(AND(BU13="Yes",BV13="No"),1,0) | CQ13: =IF(BW13="Yes",1,0) | CR13: =IF(AP13="",0,IF(AP13>7,1,0)) | CS13: =IF(OR(BD13<>"Monthly",BD13<>"Quarterly",BD13<>"Semi-Annually"),0,1) | CT13: =IF(BX13="Yes",1,0) | CU13: =IF(BY13="Yes",1,0) | CV13: =IF(BZ13="Yes",1,0) | CW13: =IF(CA13="No",1,0) | CX13: =IF(B13="",0,IF(AK13>=5000000,0,1)) | CY13: =IF(B13="",0,IF(AL13>=5000000,0,1)) | CZ13: =IF(OR(DA13=1,DB13=1,DC13=1),0,IF(B13="",0,IF(OR(AND(AN13="Tier 1",X13="No",OR(AI13>$AJ$3,AJ13>$AJ$4)),(AND(AN13="Tier 1",X13="Yes",AJ13>$AJ$5)),(AND(AN13="Tier 2",X13="No",OR(AI13>$AK$3,AJ13>$AK$4))),(AND(AN13="Tier 2",X13="Yes",AJ13>$AK$5)),(AND(AN13="Tier 3",X13="No",OR(AI13>$AL$3,AJ13>$AL$4))),(AND(AN13="Tier 3",X13="Yes",AJ13>$AL$5))),1,0))) | DA13: =IF(OR(DB13=1,DC13=1),0,IF(B13="",0,IF(OR(AND(AN13="Tier 1",X13="No",OR(AI13>$AM$3,AJ13>$AM$4)),(AND(AN13="Tier 1",X13="Yes",AJ13>$AM$5)),(AND(AN13="Tier 2",X13="No",OR(AI13>$AN$3,AJ13>$AN$4))),(AND(AN13="Tier 2",X13="Yes",AJ13>$AN$5)),(AND(AN13="Tier 3",X13="No",OR(AI13>$AO$3,AJ13>$AO$4))),(AND(AN13="Tier 3",X13="Yes",AJ13>$AO$5))),1,0))) | DB13: =IF(DC13=1,0,IF(B13="",0,IF(OR(AND(AN13="Tier 1",X13="No",OR(AI13>$AP$3,AJ13>$AP$4)),(AND(AN13="Tier 1",X13="Yes",AJ13>$AP$5)),(AND(AN13="Tier 2",X13="No",OR(AI13>$AQ$3,AJ13>$AQ$4))),(AND(AN13="Tier 2",X13="Yes",AJ13>$AQ$5)),(AND(AN13="Tier 3",X13="No",OR(AI13>$AR$3,AJ13>$AR$4))),(AND(AN13="Tier 3",X13="Yes",AJ13>$AR$5))),1,0))) | DC13: =IF(B13="",0,IF(OR(AND(AN13="Tier 1",X13="No",OR(AI13>$AS$3,AJ13>$AS$4)),(AND(AN13="Tier 1",X13="Yes",AJ13>$AS$5)),(AND(AN13="Tier 2",X13="No",OR(AI13>$AT$3,AJ13>$AT$4))),(AND(AN13="Tier 2",X13="Yes",AJ13>$AT$5)),(AND(AN13="Tier 3",X13="No",OR(AI13>$AU$3,AJ13>$AU$4))),(AND(AN13="Tier 3",X13="Yes",AJ13>$AU$5))),1,0)) | DD13: =IF((SUM(CE13:CX13)=0),0,W13) | DE13: =IF(OR(B13="",DD13>0),0,W13) | DF13: =IF(B13="",0,IF(COUNTIF(CE13:CX13,1)>0,0,L13-M13)) | DG13: =DE13+IF(DD13>0,0,DF13) | DH13: =IF(B13="","",M13+DF13) | DI13: =IF(B13="",0,J13-K13) | DJ13: =IF(OR(BF13="EUR",BF13="CAD",BF13="GBP",BF13="AUD"),(GA13*(1-V13))+(HG13)+IF(HX13="",0,HX13*(1-U13)),0) | DK13: =IF(BF13="EUR",33%,IF(BF13="CAD",38%,IF(BF13="GBP",51%,IF(BF13="AUD",61%,0)))) | DL13: =DJ13*DK13 | DN13: =IF(OR(Y13="Second Lien",Y13="Tier 1 Split Lien",Y13="Tier 2 Split Lien"),DG13,0) | DO13: =DN13*DN$6 | DP13: =DG13-DO13 | DQ13: =IF(Y13="Second Lien",DP13,0) | DR13: =DQ13*DQ$6 | DS13: =DP13-DR13 | DT13: =IF(BH13="Yes",DS13,0) | DU13: =DT13*DT$6 | DV13: =DS13-DU13 | DW13: =IF(OR(BG13="Canada",BG13="United Kingdom",BG13="Australia",BG13="Netherlands Antilles",BG13="Bermuda",BG13="Cayman Islands",BG13="British Virgin Islands",BG13="Channel Islands",BG13="Isle of Man",BG13="Australia",BG13="Netherlands",BG13="Germany",BG13="Sweden",BG13="Switzerland",BG13="Austria",BG13="Belgium",BG13="Denmark",BG13="Finland",BG13="Iceland",BG13="Ireland",BG13="Lichtenstein",BG13="Luxemborg",BG13="Norway"),DV13,0) | DX13: =DW13*DW$6 | DY13: =DV13-DX13 | DZ13: =IF(BI13="Yes",DY13,0) | EA13: =DZ13*DZ$6 | EB13: =DY13-EA13 | EC13: =IF(OR(Z13="Delayed Draw",Z13="Revolver"),EB13,0) | ED13: =EC13*EC$6 | EE13: =EB13-ED13 | EF13: =IF(S13="Yes",EE13,0) | EG13: =EF13*EF$6 | EH13: =EE13-EG13 | EI13: =IF(Q13="Yes",EH13,0) | EJ13: =EI13*EI$6 | EK13: =EH13-EJ13 | EL13: =IF(BD13="Semi-Annually",EK13,0) | EM13: =EL13*EL$6 | EN13: =EK13-EM13 | EO13: =IF(BK13="Yes",EN13,0) | EP13: =EO13*EO$6 | EQ13: =EN13-EP13 | ER13: =IF(BL13="Yes",EQ13,0) | ES13: =ER13*ER$6 | ET13: =EQ13-ES13 | EU13: =IF(BM13="Yes",ET13,0) | EV13: =EU13*EU$6 | EW13: =ET13-EV13 | EX13: =IF(BV13="Yes",EW13,0) | EY13: =EX13*EX$6 | EZ13: =EW13-EY13 | FA13: =IF(AR13="Yes",EZ13,0) | FB13: =FA13*FA$6 | FC13: =EZ13-FB13 | FD13: =IF(OR(BF13="EUR",BF13="AUD",BF13="CAD",BF13="GBP"),FC13,0) | FE13: =FD13*FD$6 | FF13: =FC13-FE13 | FG13: =FF13 | FH13: =IF(FF13=0,0,VLOOKUP(C13,$GU$10:$GV$406,2,FALSE)*FF13) | FI13: =FF13-FH13 | FJ13: =FI13 | FK13: =IF(OR(IB13="",FI13<0.01),,VLOOKUP(IB13,$GL$10:$GM$406,2,FALSE)*FI13) | FL13: =FI13-FK13 | FM13: =FL13 | FN13: =IF(FL13=0,0,VLOOKUP(C13,$HD$10:$HE$406,2,FALSE)*FL13) | FO13: =FL13-FN13 | FP13: =IF(SUM(CY13:DC13)>0,0,IF(AND(AL13>=5000000,AL13<7500000),FO13,0)) | FQ13: =IF(B13="",0,FP13*FP$6*(1-$U13)) | FR13: =FO13-FQ13 | FS13: =IF(SUM(CY13:DC13)>0,0,IF(AL13<15000000,FR13,0)) | FT13: =IF(B13="",0,FS13*FS$6*(1-$U13)) | FU13: =FR13-FT13 | FV13: =IF(SUM(CY13:DC13)>0,0,IF(OR(AND(X13="No",AN13="Tier 1",AI13>$AG$3),AND(X13="No",AN13="Tier 2",AI13>$AH$3),AND(X13="No",AN13="Tier 3",AI13>$AI$3)),FU13,0)) | FW13: =IF(SUM(CY13:DC13)>0,0,IF(OR(AND(X13="No",AN13="Tier 1",AJ13>$AG$4),AND(X13="No",AN13="Tier 2",AJ13>$AH$4),AND(X13="No",AN13="Tier 3",AJ13>$AI$4)),FU13,0)) | FX13: =IF(SUM(CY13:DC13)>0,0,IF(OR(AND(X13="Yes",AN13="Tier 1",AJ13>$AG$5),AND(X13="Yes",AN13="Tier 2",AJ13>$AH$5),AND(X13="Yes",AN13="Tier 3",AJ13>$AI$5)),FU13,0)) | FY13: =IF(SUM(FV13:FX13)>0,FU13,0) | FZ13: =IF(B13="",0,FY13*FV$6*(1-MIN(90%,T13))) | GA13: =FU13-FZ13 | GB13: =IF(AND(N13="No",DI13=0),GA13,IF(AND(N13="No",DI13<>0,K13=0),0,IF(AND(N13="No",DI13<>0,K13>0,J13<>K13),MAX(0,M13-(DH13-GA13)),DG13))) | GC13: =+GB13*V13 | GD13: =IFERROR(GC13/K13,"") | GE13: =IF(IB13="","",IB13) | GF13: {=IF(SUM(IF(IB$9:IB12=IB13,1,0))>0,0,SUMIF($IB$10:$IB$406,IB13,$FI$10:$FI$406))} | GG13: =GF13 | GH13: =GH12+1 | GI13: =LARGE($GG$10:$GG$406,GH13) | GJ13: =IF(GH13>GH$6,0,IF(GH13=$GH$2,$GJ$2,IF(GH13<4,$GJ$3,$GJ$4))) | GK13: =MAX(0,GI13-GJ13) | GL13: {=IF(GI13=0,0,LARGE(IF($GF$10:$GF$406=GI13,$GE$10:$GE$406,0),COUNTIF($GI$10:$GI$406,GI13)-COUNTIF(GI$9:GI12,GI13)))} | GM13: =IF(GI13=0,0,GK13/GI13) | GO13: =IF(C13="","",IF(ISERROR(MATCH(C13,C$10:C12,0)),MAX(GO$10:GO12)+1,INDEX(GO$10:GO12,MATCH(C13,C$10:C12,0)))) | GP13: =IF(COUNTIF($A$10:A13,A13)<=1,SUMIF($A$10:$A$406,A13,$FG$10:$FG$406),0) | GQ13: =GQ12+1 | GR13: =LARGE($GP$10:$GP$406,GQ13) | GS13: =IF(GQ13>GQ$6,0,IF(GQ13<=GQ$2,GS$2,IF(AND(GQ13<=$GQ$3,GQ13>$GQ$2),GS$3,GS$4))) | GT13: =MAX(0,GR13-GS13) | GU13: {=IF(GR13=0,0,LARGE(IF($GP$10:$GP$406=GR13,$GO$10:$GO$406,0),COUNTIF($GR$10:$GR$406,GR13)-COUNTIF(GR$9:GR12,GR13)))} | GV13: =IF(GR13=0,0,GT13/GR13) | GX13: =IF(C13="","",IF(ISERROR(MATCH(C13,C$10:C12,0)),MAX(GO$10:GO12)+1,INDEX(GO$10:GO12,MATCH(C13,C$10:C12,0)))) | GY13: =IF(COUNTIF($A$10:A13,A13)<=1,SUMIF($A$10:$A$406,A13,$FG$10:$FG$406),0) | GZ13: =GZ12+1 | HA13: =LARGE($GY$10:$GY$406,GZ13) | HB13: - | HC13: =IF(GZ13<6,MAX(0,$HC$2/5),0) | HD13: {=IF(HA13=0,0,LARGE(IF($GY$10:$GY$406=HA13,$GX$10:$GX$406,0),COUNTIF($HA$10:$HA$406,HA13)-COUNTIF(HA$9:HA12,HA13)))} | HE13: =IF(HA13=0,0,HC13/HA13) | HG13: =DG13-GA13 | HH13: 0 | HI13: =MIN(HH13,DE13) | HK13: =IF(COUNTIF($C$10:$C$406,HK12+1),HK12+1,"") | HL13: =SUMIF($C$10:$C$406,HK13,$DG$10:$DG$406) | HN13: =MIN(HO13:HS13) | HO13: =IF(B13="","",$M13) | HP13: =IF($N13="Yes",IF(P13>=6,0,MIN($T13*$M13,$U13*$M13)),"") | HQ13: =IF(AND(N13="Yes",P13>=6),"",IF($S13="Yes",$R13*$M13,"")) | HR13: =IF($Q13="Yes",MIN($M13,$T13*$M13),"") | HS13: =IF(AND($N13="Yes",$P13>=6),"",IF(OR(CY13=1,DC13=1,),MIN($T13*$M13,$U13*$M13),IF(OR(CZ13=1,DA13=1,DB13=1),IF(AK13>=5000000,MIN($T13*$M13,$IE13*$M13),MIN($T13*$M13,$U13*$M13)),""))) | HT13: =IF(DD13>0,DD13,"") | HU13: =IF(B13="",0,$L13-$M13) | HV13: =IF(OR(SUM(HP13:HT13)>0,P13>=6),"",IF($B13="","",1)) | HW13: =IF(AND($HT13<>0,OR(HT13<=MIN(HP13:HS13),SUM(HP13:HS13)=0)),$HT13,0) | HX13: =IF(AND($HS13<>0,OR(AND($HS13<>$HT13,$HS13<>$HR13,$HS13<>$HQ13,$HS13<>$HP13,$HS13<MIN($HP13:$HR13),$HS13<HT13),SUM($HP13:$HR13)+SUM(HT13)=0),IA13<=0),$HS13,0) | HY13: =IF(AND($HR13<>0,OR(AND($HR13<>$HT13,$HR13<>$HS13,$HR13<>$HQ13,$HR13<>$HP13),$HR13<MIN($HP13:$HQ13),$HR13<MIN($HS13:$HT13),SUM($HP13:$HQ13)+SUM($HS13:$HT13)=0)),$HR13,0) | HZ13: =IF(AND($HQ13<>0,OR(AND($HQ13<>$HT13,HQ13<>HS13,HQ13<>HR13,HQ13<>HP13,HQ13<MIN(HR13:HT13)),SUM(HP13)+SUM(HR13:HT13)=0)),$HQ13,0) | IA13: =IF(AND($HP13<>0,OR(HP13<=MIN(HQ13:HT13),SUM(HQ13:HT13)=0)),$HP13,0) | IB13: 41 | IC13: =HU13=DF13 | IE13: =IF(B13="","",IF(AND(Y13="Second Lien",OR(CZ13=1,DA13=1,DB13=1)),50%,IF(CZ13=1,90%,IF(DA13=1,80%,IF(DB13=1,65%,"No Initial Haircut")))))
A14: =D14 | B14: =IF(D14="","",B13+1) | C14: =IF(COUNTIF($A$10:A13,A14)>0,C13,C13+1) | D14: Silverline Holdings, LLC | E14: Silverline (Term Loan) | G14: 26250412 | H14: 26250412 | I14: 1 | J14: =IF(B14="","",G14*I14) | K14: =IF(B14="","",H14*I14) | L14: =IF(B14="","",IF(COUNTIF($CE14:$CX14,1)>0,0,J14)) | M14: =IF(B14="","",IF(COUNTIF($CE14:$CX14,1)>0,0,K14)) | N14: No | O14: N/A | P14: =IF(B14="","",IF(OR(O14="N/A",O14=""),0,YEARFRAC('Borrowing Base'!$J$4,'Loan List'!O14)*12)) | Q14: No | R14: 0.99181993 | S14: =IF(B14="","",IF(R14<95%,"Yes","No")) | T14: 0.99178565 | U14: =IF(B14="","",IF(OR(Y14="First Lien",Y14="Split First Lien",Y14="Tier 1 Split Lien",Y14="Tier 2 Split Lien"),50%,30%)) | V14: =IF(B14="",0,IF(AND(Y14="First Lien",AN14="Tier 1"),IF(AND(X14="Yes",MIN(AH14,$AJ$5)>4.5),(((4.5/MIN(AH14,$AJ$5))*72.5%)+(((MIN(AH14,$AJ$5)-4.5)/MIN(AH14,$AJ$5))*35%)),72.5%),IF(AND(Y14="First Lien",AN14="Tier 2"),IF(AND(X14="Yes",MIN(AH14,$AK$5)>4.5),(((4.5/MIN(AH14,$AK$5))*72.5%)+(((MIN(AH14,$AK$5)-4.5)/MIN(AH14,$AK$5))*35%)),72.5%),IF(AND(X14="Yes",MIN(AH14,$AL$5)>4),(((4/MIN(AH14,$AL$5))*72.5%)+(((MIN(AH14,$AL$5)-4)/MIN(AH14,$AL$5))*35%)),IF(OR(Y14="First Lien",Y14="Split First Lien"),72.5%,IF(Y14="Split Lien", 53%,35%)))))) | W14: =IF($C14="","",MIN($HO14:$HS14)) | X14: No | Y14: First Lien | Z14: Term | AA14: NR | AB14: NR | AC14: 1.5400113 | AD14: 1.35 | AE14: 1.9 | AF14: 0.36153846 | AG14: 4.4470089 | AH14: 4.4470089 | AI14: 4.4470089 | AJ14: 4.4470089 | AK14: 10568902 | AL14: 10568902 | AM14: 45777 | AN14: =IF(C14="","",(IF(AK14>=50000000,"Tier 1",(IF(OR(AK14>=20000000,AND(AK14>5000000,AC14>=1.25,AF14<=0.65)),"Tier 2","Tier 3"))))) | AO14: 48046 | AP14: 5.9638889 | AQ14: =IF(C14="","",AP14) | AR14: No | AS14: 0 | AT14: Yes | AU14: 0.01 | AV14: 0.055 | AW14: 0.035931 | AX14: =IF(C14="","",MAX(AU14,AW14)) | AY14: 0 | AZ14: 0 | BA14: 0 | BB14: =IF(B14="","",IF(AR14="No",AV14-AZ14,"")) | BC14: =IF(B14="","",IF(AR14="Yes",AS14-BA14,"")) | BD14: Quarterly | BE14: Commercial Services & Supplies | BF14: USD | BG14: United States | BH14: No | BI14: =IF(B14="","",IF(OR(AND(AZ14>0,BB14>=2.5%,BB14<4%),AND(BA14>0,BC14>=6%,BC14<8%)),"Yes","No")) | BJ14: =IF(B14="","",IF(OR(AND(AZ14>0,BB14<2.5%),AND(BA14>0,BC14<6%)),"Yes","No")) | BK14: No | BL14: No | BM14: No | BN14: No | BO14: No | BP14: No | BQ14: No | BR14: No | BS14: No | BT14: No | BU14: No | BV14: No | BW14: No | BX14: No | BY14: No | BZ14: No | CA14: Yes | CB14: =IF(B14="","",IF(AT14="No",((BB14+AW14)-$AZ$4),((BB14+AX14)-$AZ$4))*IF(DD14>0,0,M14)) | CC14: =IF(B14="","",AY14*(L14-M14)*IF(DD14>0,0,1)) | CE14: =IF(AND(B14<>"",R14<=85%),1,0) | CF14: =IF(B14="",0,(IF(OR(BF14="USD",BF14="CAD",BF14="GBP",BF14="AUD",BF14="EUR"),0,1))) | CG14: =IF(B14="",0,(IF(OR(BG14="United States",BG14="Canada",BG14="United Kingdom",BG14="Australia",BG14="Netherlands Antilles",BG14="Bermuda",BG14="Cayman Islands",BG14="British Virgin Islands",BG14="Channel Islands",BG14="Isle of Man",BG14="Australia",BG14="Netherlands",BG14="Germany",BG14="Sweden",BG14="Switzerland",BG14="Austria",BG14="Belgium",BG14="Denmark",BG14="Finland",BG14="Iceland",BG14="Ireland",BG14="Lichtenstein",BG14="Luxemborg",BG14="Norway"),0,1))) | CH14: =IF(BN14="Yes",1,0) | CI14: =IF(BO14="Yes",1,0) | CJ14: =IF(BP14="Yes",1,0) | CK14: =IF(BQ14="Yes",1,0) | CL14: =IF(BR14="Yes",1,0) | CM14: =IF(BS14="Yes",1,0) | CN14: =IF(OR(AND(BJ14="Yes",N14="No"),AND(BJ14="Yes",N14="Yes",P14>=6)),1,0) | CO14: =IF(BT14="Yes",1,0) | CP14: =IF(AND(BU14="Yes",BV14="No"),1,0) | CQ14: =IF(BW14="Yes",1,0) | CR14: =IF(AP14="",0,IF(AP14>7,1,0)) | CS14: =IF(OR(BD14<>"Monthly",BD14<>"Quarterly",BD14<>"Semi-Annually"),0,1) | CT14: =IF(BX14="Yes",1,0) | CU14: =IF(BY14="Yes",1,0) | CV14: =IF(BZ14="Yes",1,0) | CW14: =IF(CA14="No",1,0) | CX14: =IF(B14="",0,IF(AK14>=5000000,0,1)) | CY14: =IF(B14="",0,IF(AL14>=5000000,0,1)) | CZ14: =IF(OR(DA14=1,DB14=1,DC14=1),0,IF(B14="",0,IF(OR(AND(AN14="Tier 1",X14="No",OR(AI14>$AJ$3,AJ14>$AJ$4)),(AND(AN14="Tier 1",X14="Yes",AJ14>$AJ$5)),(AND(AN14="Tier 2",X14="No",OR(AI14>$AK$3,AJ14>$AK$4))),(AND(AN14="Tier 2",X14="Yes",AJ14>$AK$5)),(AND(AN14="Tier 3",X14="No",OR(AI14>$AL$3,AJ14>$AL$4))),(AND(AN14="Tier 3",X14="Yes",AJ14>$AL$5))),1,0))) | DA14: =IF(OR(DB14=1,DC14=1),0,IF(B14="",0,IF(OR(AND(AN14="Tier 1",X14="No",OR(AI14>$AM$3,AJ14>$AM$4)),(AND(AN14="Tier 1",X14="Yes",AJ14>$AM$5)),(AND(AN14="Tier 2",X14="No",OR(AI14>$AN$3,AJ14>$AN$4))),(AND(AN14="Tier 2",X14="Yes",AJ14>$AN$5)),(AND(AN14="Tier 3",X14="No",OR(AI14>$AO$3,AJ14>$AO$4))),(AND(AN14="Tier 3",X14="Yes",AJ14>$AO$5))),1,0))) | DB14: =IF(DC14=1,0,IF(B14="",0,IF(OR(AND(AN14="Tier 1",X14="No",OR(AI14>$AP$3,AJ14>$AP$4)),(AND(AN14="Tier 1",X14="Yes",AJ14>$AP$5)),(AND(AN14="Tier 2",X14="No",OR(AI14>$AQ$3,AJ14>$AQ$4))),(AND(AN14="Tier 2",X14="Yes",AJ14>$AQ$5)),(AND(AN14="Tier 3",X14="No",OR(AI14>$AR$3,AJ14>$AR$4))),(AND(AN14="Tier 3",X14="Yes",AJ14>$AR$5))),1,0))) | DC14: =IF(B14="",0,IF(OR(AND(AN14="Tier 1",X14="No",OR(AI14>$AS$3,AJ14>$AS$4)),(AND(AN14="Tier 1",X14="Yes",AJ14>$AS$5)),(AND(AN14="Tier 2",X14="No",OR(AI14>$AT$3,AJ14>$AT$4))),(AND(AN14="Tier 2",X14="Yes",AJ14>$AT$5)),(AND(AN14="Tier 3",X14="No",OR(AI14>$AU$3,AJ14>$AU$4))),(AND(AN14="Tier 3",X14="Yes",AJ14>$AU$5))),1,0)) | DD14: =IF((SUM(CE14:CX14)=0),0,W14) | DE14: =IF(OR(B14="",DD14>0),0,W14) | DF14: =IF(B14="",0,IF(COUNTIF(CE14:CX14,1)>0,0,L14-M14)) | DG14: =DE14+IF(DD14>0,0,DF14) | DH14: =IF(B14="","",M14+DF14) | DI14: =IF(B14="",0,J14-K14) | DJ14: =IF(OR(BF14="EUR",BF14="CAD",BF14="GBP",BF14="AUD"),(GA14*(1-V14))+(HG14)+IF(HX14="",0,HX14*(1-U14)),0) | DK14: =IF(BF14="EUR",33%,IF(BF14="CAD",38%,IF(BF14="GBP",51%,IF(BF14="AUD",61%,0)))) | DL14: =DJ14*DK14 | DN14: =IF(OR(Y14="Second Lien",Y14="Tier 1 Split Lien",Y14="Tier 2 Split Lien"),DG14,0) | DO14: =DN14*DN$6 | DP14: =DG14-DO14 | DQ14: =IF(Y14="Second Lien",DP14,0) | DR14: =DQ14*DQ$6 | DS14: =DP14-DR14 | DT14: =IF(BH14="Yes",DS14,0) | DU14: =DT14*DT$6 | DV14: =DS14-DU14 | DW14: =IF(OR(BG14="Canada",BG14="United Kingdom",BG14="Australia",BG14="Netherlands Antilles",BG14="Bermuda",BG14="Cayman Islands",BG14="British Virgin Islands",BG14="Channel Islands",BG14="Isle of Man",BG14="Australia",BG14="Netherlands",BG14="Germany",BG14="Sweden",BG14="Switzerland",BG14="Austria",BG14="Belgium",BG14="Denmark",BG14="Finland",BG14="Iceland",BG14="Ireland",BG14="Lichtenstein",BG14="Luxemborg",BG14="Norway"),DV14,0) | DX14: =DW14*DW$6 | DY14: =DV14-DX14 | DZ14: =IF(BI14="Yes",DY14,0) | EA14: =DZ14*DZ$6 | EB14: =DY14-EA14 | EC14: =IF(OR(Z14="Delayed Draw",Z14="Revolver"),EB14,0) | ED14: =EC14*EC$6 | EE14: =EB14-ED14 | EF14: =IF(S14="Yes",EE14,0) | EG14: =EF14*EF$6 | EH14: =EE14-EG14 | EI14: =IF(Q14="Yes",EH14,0) | EJ14: =EI14*EI$6 | EK14: =EH14-EJ14 | EL14: =IF(BD14="Semi-Annually",EK14,0) | EM14: =EL14*EL$6 | EN14: =EK14-EM14 | EO14: =IF(BK14="Yes",EN14,0) | EP14: =EO14*EO$6 | EQ14: =EN14-EP14 | ER14: =IF(BL14="Yes",EQ14,0) | ES14: =ER14*ER$6 | ET14: =EQ14-ES14 | EU14: =IF(BM14="Yes",ET14,0) | EV14: =EU14*EU$6 | EW14: =ET14-EV14 | EX14: =IF(BV14="Yes",EW14,0) | EY14: =EX14*EX$6 | EZ14: =EW14-EY14 | FA14: =IF(AR14="Yes",EZ14,0) | FB14: =FA14*FA$6 | FC14: =EZ14-FB14 | FD14: =IF(OR(BF14="EUR",BF14="AUD",BF14="CAD",BF14="GBP"),FC14,0) | FE14: =FD14*FD$6 | FF14: =FC14-FE14 | FG14: =FF14 | FH14: =IF(FF14=0,0,VLOOKUP(C14,$GU$10:$GV$406,2,FALSE)*FF14) | FI14: =FF14-FH14 | FJ14: =FI14 | FK14: =IF(OR(IB14="",FI14<0.01),,VLOOKUP(IB14,$GL$10:$GM$406,2,FALSE)*FI14) | FL14: =FI14-FK14 | FM14: =FL14 | FN14: =IF(FL14=0,0,VLOOKUP(C14,$HD$10:$HE$406,2,FALSE)*FL14) | FO14: =FL14-FN14 | FP14: =IF(SUM(CY14:DC14)>0,0,IF(AND(AL14>=5000000,AL14<7500000),FO14,0)) | FQ14: =IF(B14="",0,FP14*FP$6*(1-$U14)) | FR14: =FO14-FQ14 | FS14: =IF(SUM(CY14:DC14)>0,0,IF(AL14<15000000,FR14,0)) | FT14: =IF(B14="",0,FS14*FS$6*(1-$U14)) | FU14: =FR14-FT14 | FV14: =IF(SUM(CY14:DC14)>0,0,IF(OR(AND(X14="No",AN14="Tier 1",AI14>$AG$3),AND(X14="No",AN14="Tier 2",AI14>$AH$3),AND(X14="No",AN14="Tier 3",AI14>$AI$3)),FU14,0)) | FW14: =IF(SUM(CY14:DC14)>0,0,IF(OR(AND(X14="No",AN14="Tier 1",AJ14>$AG$4),AND(X14="No",AN14="Tier 2",AJ14>$AH$4),AND(X14="No",AN14="Tier 3",AJ14>$AI$4)),FU14,0)) | FX14: =IF(SUM(CY14:DC14)>0,0,IF(OR(AND(X14="Yes",AN14="Tier 1",AJ14>$AG$5),AND(X14="Yes",AN14="Tier 2",AJ14>$AH$5),AND(X14="Yes",AN14="Tier 3",AJ14>$AI$5)),FU14,0)) | FY14: =IF(SUM(FV14:FX14)>0,FU14,0) | FZ14: =IF(B14="",0,FY14*FV$6*(1-MIN(90%,T14))) | GA14: =FU14-FZ14 | GB14: =IF(AND(N14="No",DI14=0),GA14,IF(AND(N14="No",DI14<>0,K14=0),0,IF(AND(N14="No",DI14<>0,K14>0,J14<>K14),MAX(0,M14-(DH14-GA14)),DG14))) | GC14: =+GB14*V14 | GD14: =IFERROR(GC14/K14,"") | GE14: =IF(IB14="","",IB14) | GF14: {=IF(SUM(IF(IB$9:IB13=IB14,1,0))>0,0,SUMIF($IB$10:$IB$406,IB14,$FI$10:$FI$406))} | GG14: =GF14 | GH14: =GH13+1 | GI14: =LARGE($GG$10:$GG$406,GH14) | GJ14: =IF(GH14>GH$6,0,IF(GH14=$GH$2,$GJ$2,IF(GH14<4,$GJ$3,$GJ$4))) | GK14: =MAX(0,GI14-GJ14) | GL14: {=IF(GI14=0,0,LARGE(IF($GF$10:$GF$406=GI14,$GE$10:$GE$406,0),COUNTIF($GI$10:$GI$406,GI14)-COUNTIF(GI$9:GI13,GI14)))} | GM14: =IF(GI14=0,0,GK14/GI14) | GO14: =IF(C14="","",IF(ISERROR(MATCH(C14,C$10:C13,0)),MAX(GO$10:GO13)+1,INDEX(GO$10:GO13,MATCH(C14,C$10:C13,0)))) | GP14: =IF(COUNTIF($A$10:A14,A14)<=1,SUMIF($A$10:$A$406,A14,$FG$10:$FG$406),0) | GQ14: =GQ13+1 | GR14: =LARGE($GP$10:$GP$406,GQ14) | GS14: =IF(GQ14>GQ$6,0,IF(GQ14<=GQ$2,GS$2,IF(AND(GQ14<=$GQ$3,GQ14>$GQ$2),GS$3,GS$4))) | GT14: =MAX(0,GR14-GS14) | GU14: {=IF(GR14=0,0,LARGE(IF($GP$10:$GP$406=GR14,$GO$10:$GO$406,0),COUNTIF($GR$10:$GR$406,GR14)-COUNTIF(GR$9:GR13,GR14)))} | GV14: =IF(GR14=0,0,GT14/GR14) | GX14: =IF(C14="","",IF(ISERROR(MATCH(C14,C$10:C13,0)),MAX(GO$10:GO13)+1,INDEX(GO$10:GO13,MATCH(C14,C$10:C13,0)))) | GY14: =IF(COUNTIF($A$10:A14,A14)<=1,SUMIF($A$10:$A$406,A14,$FG$10:$FG$406),0) | GZ14: =GZ13+1 | HA14: =LARGE($GY$10:$GY$406,GZ14) | HB14: - | HC14: =IF(GZ14<6,MAX(0,$HC$2/5),0) | HD14: {=IF(HA14=0,0,LARGE(IF($GY$10:$GY$406=HA14,$GX$10:$GX$406,0),COUNTIF($HA$10:$HA$406,HA14)-COUNTIF(HA$9:HA13,HA14)))} | HE14: =IF(HA14=0,0,HC14/HA14) | HG14: =DG14-GA14 | HH14: 0 | HI14: =MIN(HH14,DE14) | HK14: =IF(COUNTIF($C$10:$C$406,HK13+1),HK13+1,"") | HL14: =SUMIF($C$10:$C$406,HK14,$DG$10:$DG$406) | HN14: =MIN(HO14:HS14) | HO14: =IF(B14="","",$M14) | HP14: =IF($N14="Yes",IF(P14>=6,0,MIN($T14*$M14,$U14*$M14)),"") | HQ14: =IF(AND(N14="Yes",P14>=6),"",IF($S14="Yes",$R14*$M14,"")) | HR14: =IF($Q14="Yes",MIN($M14,$T14*$M14),"") | HS14: =IF(AND($N14="Yes",$P14>=6),"",IF(OR(CY14=1,DC14=1,),MIN($T14*$M14,$U14*$M14),IF(OR(CZ14=1,DA14=1,DB14=1),IF(AK14>=5000000,MIN($T14*$M14,$IE14*$M14),MIN($T14*$M14,$U14*$M14)),""))) | HT14: =IF(DD14>0,DD14,"") | HU14: =IF(B14="",0,$L14-$M14) | HV14: =IF(OR(SUM(HP14:HT14)>0,P14>=6),"",IF($B14="","",1)) | HW14: =IF(AND($HT14<>0,OR(HT14<=MIN(HP14:HS14),SUM(HP14:HS14)=0)),$HT14,0) | HX14: =IF(AND($HS14<>0,OR(AND($HS14<>$HT14,$HS14<>$HR14,$HS14<>$HQ14,$HS14<>$HP14,$HS14<MIN($HP14:$HR14),$HS14<HT14),SUM($HP14:$HR14)+SUM(HT14)=0),IA14<=0),$HS14,0) | HY14: =IF(AND($HR14<>0,OR(AND($HR14<>$HT14,$HR14<>$HS14,$HR14<>$HQ14,$HR14<>$HP14),$HR14<MIN($HP14:$HQ14),$HR14<MIN($HS14:$HT14),SUM($HP14:$HQ14)+SUM($HS14:$HT14)=0)),$HR14,0) | HZ14: =IF(AND($HQ14<>0,OR(AND($HQ14<>$HT14,HQ14<>HS14,HQ14<>HR14,HQ14<>HP14,HQ14<MIN(HR14:HT14)),SUM(HP14)+SUM(HR14:HT14)=0)),$HQ14,0) | IA14: =IF(AND($HP14<>0,OR(HP14<=MIN(HQ14:HT14),SUM(HQ14:HT14)=0)),$HP14,0) | IB14: 12 | IC14: =HU14=DF14
A15: =D15 | B15: =IF(D15="","",B14+1) | C15: =IF(COUNTIF($A$10:A14,A15)>0,C14,C14+1) | D15: Harborview Holdings, LLC | E15: Harborview (Term Loan) | G15: 4247877.1 | H15: 4247877.1 | I15: 1 | J15: =IF(B15="","",G15*I15) | K15: =IF(B15="","",H15*I15) | L15: =IF(B15="","",IF(COUNTIF($CE15:$CX15,1)>0,0,J15)) | M15: =IF(B15="","",IF(COUNTIF($CE15:$CX15,1)>0,0,K15)) | N15: No | O15: N/A | P15: =IF(B15="","",IF(OR(O15="N/A",O15=""),0,YEARFRAC('Borrowing Base'!$J$4,'Loan List'!O15)*12)) | Q15: No | R15: 0.9901553 | S15: =IF(B15="","",IF(R15<95%,"Yes","No")) | T15: 0.977 | U15: =IF(B15="","",IF(OR(Y15="First Lien",Y15="Split First Lien",Y15="Tier 1 Split Lien",Y15="Tier 2 Split Lien"),50%,30%)) | V15: =IF(B15="",0,IF(AND(Y15="First Lien",AN15="Tier 1"),IF(AND(X15="Yes",MIN(AH15,$AJ$5)>4.5),(((4.5/MIN(AH15,$AJ$5))*72.5%)+(((MIN(AH15,$AJ$5)-4.5)/MIN(AH15,$AJ$5))*35%)),72.5%),IF(AND(Y15="First Lien",AN15="Tier 2"),IF(AND(X15="Yes",MIN(AH15,$AK$5)>4.5),(((4.5/MIN(AH15,$AK$5))*72.5%)+(((MIN(AH15,$AK$5)-4.5)/MIN(AH15,$AK$5))*35%)),72.5%),IF(AND(X15="Yes",MIN(AH15,$AL$5)>4),(((4/MIN(AH15,$AL$5))*72.5%)+(((MIN(AH15,$AL$5)-4)/MIN(AH15,$AL$5))*35%)),IF(OR(Y15="First Lien",Y15="Split First Lien"),72.5%,IF(Y15="Split Lien", 53%,35%)))))) | W15: =IF($C15="","",MIN($HO15:$HS15)) | X15: No | Y15: First Lien | Z15: Term | AA15: NR | AB15: NR | AC15: 2.0309022 | AD15: 2.3080215 | AE15: 3.2384246 | AF15: 0.32838249 | AG15: 2.3080215 | AH15: 2.3080215 | AI15: 3.2384246 | AJ15: 3.2384246 | AK15: 7235634.7 | AL15: 13442171 | AM15: 45838 | AN15: =IF(C15="","",(IF(AK15>=50000000,"Tier 1",(IF(OR(AK15>=20000000,AND(AK15>5000000,AC15>=1.25,AF15<=0.65)),"Tier 2","Tier 3"))))) | AO15: 47295 | AP15: 3.9055556 | AQ15: =IF(C15="","",AP15) | AR15: No | AS15: 0 | AT15: Yes | AU15: 0.01 | AV15: 0.0575 | AW15: 0.043507 | AX15: =IF(C15="","",MAX(AU15,AW15)) | AY15: 0 | AZ15: 0 | BA15: 0 | BB15: =IF(B15="","",IF(AR15="No",AV15-AZ15,"")) | BC15: =IF(B15="","",IF(AR15="Yes",AS15-BA15,"")) | BD15: Quarterly | BE15: Diversified Consumer Services | BF15: USD | BG15: United States | BH15: No | BI15: =IF(B15="","",IF(OR(AND(AZ15>0,BB15>=2.5%,BB15<4%),AND(BA15>0,BC15>=6%,BC15<8%)),"Yes","No")) | BJ15: =IF(B15="","",IF(OR(AND(AZ15>0,BB15<2.5%),AND(BA15>0,BC15<6%)),"Yes","No")) | BK15: No | BL15: No | BM15: No | BN15: No | BO15: No | BP15: No | BQ15: No | BR15: No | BS15: No | BT15: No | BU15: No | BV15: No | BW15: No | BX15: No | BY15: No | BZ15: No | CA15: Yes | CB15: =IF(B15="","",IF(AT15="No",((BB15+AW15)-$AZ$4),((BB15+AX15)-$AZ$4))*IF(DD15>0,0,M15)) | CC15: =IF(B15="","",AY15*(L15-M15)*IF(DD15>0,0,1)) | CE15: =IF(AND(B15<>"",R15<=85%),1,0) | CF15: =IF(B15="",0,(IF(OR(BF15="USD",BF15="CAD",BF15="GBP",BF15="AUD",BF15="EUR"),0,1))) | CG15: =IF(B15="",0,(IF(OR(BG15="United States",BG15="Canada",BG15="United Kingdom",BG15="Australia",BG15="Netherlands Antilles",BG15="Bermuda",BG15="Cayman Islands",BG15="British Virgin Islands",BG15="Channel Islands",BG15="Isle of Man",BG15="Australia",BG15="Netherlands",BG15="Germany",BG15="Sweden",BG15="Switzerland",BG15="Austria",BG15="Belgium",BG15="Denmark",BG15="Finland",BG15="Iceland",BG15="Ireland",BG15="Lichtenstein",BG15="Luxemborg",BG15="Norway"),0,1))) | CH15: =IF(BN15="Yes",1,0) | CI15: =IF(BO15="Yes",1,0) | CJ15: =IF(BP15="Yes",1,0) | CK15: =IF(BQ15="Yes",1,0) | CL15: =IF(BR15="Yes",1,0) | CM15: =IF(BS15="Yes",1,0) | CN15: =IF(OR(AND(BJ15="Yes",N15="No"),AND(BJ15="Yes",N15="Yes",P15>=6)),1,0) | CO15: =IF(BT15="Yes",1,0) | CP15: =IF(AND(BU15="Yes",BV15="No"),1,0) | CQ15: =IF(BW15="Yes",1,0) | CR15: =IF(AP15="",0,IF(AP15>7,1,0)) | CS15: =IF(OR(BD15<>"Monthly",BD15<>"Quarterly",BD15<>"Semi-Annually"),0,1) | CT15: =IF(BX15="Yes",1,0) | CU15: =IF(BY15="Yes",1,0) | CV15: =IF(BZ15="Yes",1,0) | CW15: =IF(CA15="No",1,0) | CX15: =IF(B15="",0,IF(AK15>=5000000,0,1)) | CY15: =IF(B15="",0,IF(AL15>=5000000,0,1)) | CZ15: =IF(OR(DA15=1,DB15=1,DC15=1),0,IF(B15="",0,IF(OR(AND(AN15="Tier 1",X15="No",OR(AI15>$AJ$3,AJ15>$AJ$4)),(AND(AN15="Tier 1",X15="Yes",AJ15>$AJ$5)),(AND(AN15="Tier 2",X15="No",OR(AI15>$AK$3,AJ15>$AK$4))),(AND(AN15="Tier 2",X15="Yes",AJ15>$AK$5)),(AND(AN15="Tier 3",X15="No",OR(AI15>$AL$3,AJ15>$AL$4))),(AND(AN15="Tier 3",X15="Yes",AJ15>$AL$5))),1,0))) | DA15: =IF(OR(DB15=1,DC15=1),0,IF(B15="",0,IF(OR(AND(AN15="Tier 1",X15="No",OR(AI15>$AM$3,AJ15>$AM$4)),(AND(AN15="Tier 1",X15="Yes",AJ15>$AM$5)),(AND(AN15="Tier 2",X15="No",OR(AI15>$AN$3,AJ15>$AN$4))),(AND(AN15="Tier 2",X15="Yes",AJ15>$AN$5)),(AND(AN15="Tier 3",X15="No",OR(AI15>$AO$3,AJ15>$AO$4))),(AND(AN15="Tier 3",X15="Yes",AJ15>$AO$5))),1,0))) | DB15: =IF(DC15=1,0,IF(B15="",0,IF(OR(AND(AN15="Tier 1",X15="No",OR(AI15>$AP$3,AJ15>$AP$4)),(AND(AN15="Tier 1",X15="Yes",AJ15>$AP$5)),(AND(AN15="Tier 2",X15="No",OR(AI15>$AQ$3,AJ15>$AQ$4))),(AND(AN15="Tier 2",X15="Yes",AJ15>$AQ$5)),(AND(AN15="Tier 3",X15="No",OR(AI15>$AR$3,AJ15>$AR$4))),(AND(AN15="Tier 3",X15="Yes",AJ15>$AR$5))),1,0))) | DC15: =IF(B15="",0,IF(OR(AND(AN15="Tier 1",X15="No",OR(AI15>$AS$3,AJ15>$AS$4)),(AND(AN15="Tier 1",X15="Yes",AJ15>$AS$5)),(AND(AN15="Tier 2",X15="No",OR(AI15>$AT$3,AJ15>$AT$4))),(AND(AN15="Tier 2",X15="Yes",AJ15>$AT$5)),(AND(AN15="Tier 3",X15="No",OR(AI15>$AU$3,AJ15>$AU$4))),(AND(AN15="Tier 3",X15="Yes",AJ15>$AU$5))),1,0)) | DD15: =IF((SUM(CE15:CX15)=0),0,W15) | DE15: =IF(OR(B15="",DD15>0),0,W15) | DF15: =IF(B15="",0,IF(COUNTIF(CE15:CX15,1)>0,0,L15-M15)) | DG15: =DE15+IF(DD15>0,0,DF15) | DH15: =IF(B15="","",M15+DF15) | DI15: =IF(B15="",0,J15-K15) | DJ15: =IF(OR(BF15="EUR",BF15="CAD",BF15="GBP",BF15="AUD"),(GA15*(1-V15))+(HG15)+IF(HX15="",0,HX15*(1-U15)),0) | DK15: =IF(BF15="EUR",33%,IF(BF15="CAD",38%,IF(BF15="GBP",51%,IF(BF15="AUD",61%,0)))) | DL15: =DJ15*DK15 | DN15: =IF(OR(Y15="Second Lien",Y15="Tier 1 Split Lien",Y15="Tier 2 Split Lien"),DG15,0) | DO15: =DN15*DN$6 | DP15: =DG15-DO15 | DQ15: =IF(Y15="Second Lien",DP15,0) | DR15: =DQ15*DQ$6 | DS15: =DP15-DR15 | DT15: =IF(BH15="Yes",DS15,0) | DU15: =DT15*DT$6 | DV15: =DS15-DU15 | DW15: =IF(OR(BG15="Canada",BG15="United Kingdom",BG15="Australia",BG15="Netherlands Antilles",BG15="Bermuda",BG15="Cayman Islands",BG15="British Virgin Islands",BG15="Channel Islands",BG15="Isle of Man",BG15="Australia",BG15="Netherlands",BG15="Germany",BG15="Sweden",BG15="Switzerland",BG15="Austria",BG15="Belgium",BG15="Denmark",BG15="Finland",BG15="Iceland",BG15="Ireland",BG15="Lichtenstein",BG15="Luxemborg",BG15="Norway"),DV15,0) | DX15: =DW15*DW$6 | DY15: =DV15-DX15 | DZ15: =IF(BI15="Yes",DY15,0) | EA15: =DZ15*DZ$6 | EB15: =DY15-EA15 | EC15: =IF(OR(Z15="Delayed Draw",Z15="Revolver"),EB15,0) | ED15: =EC15*EC$6 | EE15: =EB15-ED15 | EF15: =IF(S15="Yes",EE15,0) | EG15: =EF15*EF$6 | EH15: =EE15-EG15 | EI15: =IF(Q15="Yes",EH15,0) | EJ15: =EI15*EI$6 | EK15: =EH15-EJ15 | EL15: =IF(BD15="Semi-Annually",EK15,0) | EM15: =EL15*EL$6 | EN15: =EK15-EM15 | EO15: =IF(BK15="Yes",EN15,0) | EP15: =EO15*EO$6 | EQ15: =EN15-EP15 | ER15: =IF(BL15="Yes",EQ15,0) | ES15: =ER15*ER$6 | ET15: =EQ15-ES15 | EU15: =IF(BM15="Yes",ET15,0) | EV15: =EU15*EU$6 | EW15: =ET15-EV15 | EX15: =IF(BV15="Yes",EW15,0) | EY15: =EX15*EX$6 | EZ15: =EW15-EY15 | FA15: =IF(AR15="Yes",EZ15,0) | FB15: =FA15*FA$6 | FC15: =EZ15-FB15 | FD15: =IF(OR(BF15="EUR",BF15="AUD",BF15="CAD",BF15="GBP"),FC15,0) | FE15: =FD15*FD$6 | FF15: =FC15-FE15 | FG15: =FF15 | FH15: =IF(FF15=0,0,VLOOKUP(C15,$GU$10:$GV$406,2,FALSE)*FF15) | FI15: =FF15-FH15 | FJ15: =FI15 | FK15: =IF(OR(IB15="",FI15<0.01),,VLOOKUP(IB15,$GL$10:$GM$406,2,FALSE)*FI15) | FL15: =FI15-FK15 | FM15: =FL15 | FN15: =IF(FL15=0,0,VLOOKUP(C15,$HD$10:$HE$406,2,FALSE)*FL15) | FO15: =FL15-FN15 | FP15: =IF(SUM(CY15:DC15)>0,0,IF(AND(AL15>=5000000,AL15<7500000),FO15,0)) | FQ15: =IF(B15="",0,FP15*FP$6*(1-$U15)) | FR15: =FO15-FQ15 | FS15: =IF(SUM(CY15:DC15)>0,0,IF(AL15<15000000,FR15,0)) | FT15: =IF(B15="",0,FS15*FS$6*(1-$U15)) | FU15: =FR15-FT15 | FV15: =IF(SUM(CY15:DC15)>0,0,IF(OR(AND(X15="No",AN15="Tier 1",AI15>$AG$3),AND(X15="No",AN15="Tier 2",AI15>$AH$3),AND(X15="No",AN15="Tier 3",AI15>$AI$3)),FU15,0)) | FW15: =IF(SUM(CY15:DC15)>0,0,IF(OR(AND(X15="No",AN15="Tier 1",AJ15>$AG$4),AND(X15="No",AN15="Tier 2",AJ15>$AH$4),AND(X15="No",AN15="Tier 3",AJ15>$AI$4)),FU15,0)) | FX15: =IF(SUM(CY15:DC15)>0,0,IF(OR(AND(X15="Yes",AN15="Tier 1",AJ15>$AG$5),AND(X15="Yes",AN15="Tier 2",AJ15>$AH$5),AND(X15="Yes",AN15="Tier 3",AJ15>$AI$5)),FU15,0)) | FY15: =IF(SUM(FV15:FX15)>0,FU15,0) | FZ15: =IF(B15="",0,FY15*FV$6*(1-MIN(90%,T15))) | GA15: =FU15-FZ15 | GB15: =IF(AND(N15="No",DI15=0),GA15,IF(AND(N15="No",DI15<>0,K15=0),0,IF(AND(N15="No",DI15<>0,K15>0,J15<>K15),MAX(0,M15-(DH15-GA15)),DG15))) | GC15: =+GB15*V15 | GD15: =IFERROR(GC15/K15,"") | GE15: =IF(IB15="","",IB15) | GF15: {=IF(SUM(IF(IB$9:IB14=IB15,1,0))>0,0,SUMIF($IB$10:$IB$406,IB15,$FI$10:$FI$406))} | GG15: =GF15 | GH15: =GH14+1 | GI15: =LARGE($GG$10:$GG$406,GH15) | GJ15: =IF(GH15>GH$6,0,IF(GH15=$GH$2,$GJ$2,IF(GH15<4,$GJ$3,$GJ$4))) | GK15: =MAX(0,GI15-GJ15) | GL15: {=IF(GI15=0,0,LARGE(IF($GF$10:$GF$406=GI15,$GE$10:$GE$406,0),COUNTIF($GI$10:$GI$406,GI15)-COUNTIF(GI$9:GI14,GI15)))} | GM15: =IF(GI15=0,0,GK15/GI15) | GO15: =IF(C15="","",IF(ISERROR(MATCH(C15,C$10:C14,0)),MAX(GO$10:GO14)+1,INDEX(GO$10:GO14,MATCH(C15,C$10:C14,0)))) | GP15: =IF(COUNTIF($A$10:A15,A15)<=1,SUMIF($A$10:$A$406,A15,$FG$10:$FG$406),0) | GQ15: =GQ14+1 | GR15: =LARGE($GP$10:$GP$406,GQ15) | GS15: =IF(GQ15>GQ$6,0,IF(GQ15<=GQ$2,GS$2,IF(AND(GQ15<=$GQ$3,GQ15>$GQ$2),GS$3,GS$4))) | GT15: =MAX(0,GR15-GS15) | GU15: {=IF(GR15=0,0,LARGE(IF($GP$10:$GP$406=GR15,$GO$10:$GO$406,0),COUNTIF($GR$10:$GR$406,GR15)-COUNTIF(GR$9:GR14,GR15)))} | GV15: =IF(GR15=0,0,GT15/GR15) | GX15: =IF(C15="","",IF(ISERROR(MATCH(C15,C$10:C14,0)),MAX(GO$10:GO14)+1,INDEX(GO$10:GO14,MATCH(C15,C$10:C14,0)))) | GY15: =IF(COUNTIF($A$10:A15,A15)<=1,SUMIF($A$10:$A$406,A15,$FG$10:$FG$406),0) | GZ15: =GZ14+1 | HA15: =LARGE($GY$10:$GY$406,GZ15) | HB15: - | HC15: =IF(GZ15<6,MAX(0,$HC$2/5),0) | HD15: {=IF(HA15=0,0,LARGE(IF($GY$10:$GY$406=HA15,$GX$10:$GX$406,0),COUNTIF($HA$10:$HA$406,HA15)-COUNTIF(HA$9:HA14,HA15)))} | HE15: =IF(HA15=0,0,HC15/HA15) | HG15: =DG15-GA15 | HH15: 0 | HI15: =MIN(HH15,DE15) | HK15: =IF(COUNTIF($C$10:$C$406,HK14+1),HK14+1,"") | HL15: =SUMIF($C$10:$C$406,HK15,$DG$10:$DG$406) | HN15: =MIN(HO15:HS15) | HO15: =IF(B15="","",$M15) | HP15: =IF($N15="Yes",IF(P15>=6,0,MIN($T15*$M15,$U15*$M15)),"") | HQ15: =IF(AND(N15="Yes",P15>=6),"",IF($S15="Yes",$R15*$M15,"")) | HR15: =IF($Q15="Yes",MIN($M15,$T15*$M15),"") | HS15: =IF(AND($N15="Yes",$P15>=6),"",IF(OR(CY15=1,DC15=1,),MIN($T15*$M15,$U15*$M15),IF(OR(CZ15=1,DA15=1,DB15=1),IF(AK15>=5000000,MIN($T15*$M15,$IE15*$M15),MIN($T15*$M15,$U15*$M15)),""))) | HT15: =IF(DD15>0,DD15,"") | HU15: =IF(B15="",0,$L15-$M15) | HV15: =IF(OR(SUM(HP15:HT15)>0,P15>=6),"",IF($B15="","",1)) | HW15: =IF(AND($HT15<>0,OR(HT15<=MIN(HP15:HS15),SUM(HP15:HS15)=0)),$HT15,0) | HX15: =IF(AND($HS15<>0,OR(AND($HS15<>$HT15,$HS15<>$HR15,$HS15<>$HQ15,$HS15<>$HP15,$HS15<MIN($HP15:$HR15),$HS15<HT15),SUM($HP15:$HR15)+SUM(HT15)=0),IA15<=0),$HS15,0) | HY15: =IF(AND($HR15<>0,OR(AND($HR15<>$HT15,$HR15<>$HS15,$HR15<>$HQ15,$HR15<>$HP15),$HR15<MIN($HP15:$HQ15),$HR15<MIN($HS15:$HT15),SUM($HP15:$HQ15)+SUM($HS15:$HT15)=0)),$HR15,0) | HZ15: =IF(AND($HQ15<>0,OR(AND($HQ15<>$HT15,HQ15<>HS15,HQ15<>HR15,HQ15<>HP15,HQ15<MIN(HR15:HT15)),SUM(HP15)+SUM(HR15:HT15)=0)),$HQ15,0) | IA15: =IF(AND($HP15<>0,OR(HP15<=MIN(HQ15:HT15),SUM(HQ15:HT15)=0)),$HP15,0) | IB15: 19 | IC15: =HU15=DF15 | IE15: =IF(B15="","",IF(AND(Y15="Second Lien",OR(CZ15=1,DA15=1,DB15=1)),50%,IF(CZ15=1,90%,IF(DA15=1,80%,IF(DB15=1,65%,"No Initial Haircut")))))
A16: =D16 | B16: =IF(D16="","",B15+1) | C16: =IF(COUNTIF($A$10:A15,A16)>0,C15,C15+1) | D16: Meridian Holdings, LLC | E16: Meridian (Term Loan) | G16: 17387196 | H16: 17387196 | I16: 1 | J16: =IF(B16="","",G16*I16) | K16: =IF(B16="","",H16*I16) | L16: =IF(B16="","",IF(COUNTIF($CE16:$CX16,1)>0,0,J16)) | M16: =IF(B16="","",IF(COUNTIF($CE16:$CX16,1)>0,0,K16)) | N16: No | O16: N/A | P16: =IF(B16="","",IF(OR(O16="N/A",O16=""),0,YEARFRAC('Borrowing Base'!$J$4,'Loan List'!O16)*12)) | Q16: No | R16: 0.98881144 | S16: =IF(B16="","",IF(R16<95%,"Yes","No")) | T16: 0.99 | U16: =IF(B16="","",IF(OR(Y16="First Lien",Y16="Split First Lien",Y16="Tier 1 Split Lien",Y16="Tier 2 Split Lien"),50%,30%)) | V16: =IF(B16="",0,IF(AND(Y16="First Lien",AN16="Tier 1"),IF(AND(X16="Yes",MIN(AH16,$AJ$5)>4.5),(((4.5/MIN(AH16,$AJ$5))*72.5%)+(((MIN(AH16,$AJ$5)-4.5)/MIN(AH16,$AJ$5))*35%)),72.5%),IF(AND(Y16="First Lien",AN16="Tier 2"),IF(AND(X16="Yes",MIN(AH16,$AK$5)>4.5),(((4.5/MIN(AH16,$AK$5))*72.5%)+(((MIN(AH16,$AK$5)-4.5)/MIN(AH16,$AK$5))*35%)),72.5%),IF(AND(X16="Yes",MIN(AH16,$AL$5)>4),(((4/MIN(AH16,$AL$5))*72.5%)+(((MIN(AH16,$AL$5)-4)/MIN(AH16,$AL$5))*35%)),IF(OR(Y16="First Lien",Y16="Split First Lien"),72.5%,IF(Y16="Split Lien", 53%,35%)))))) | W16: =IF($C16="","",MIN($HO16:$HS16)) | X16: No | Y16: First Lien | Z16: Term | AA16: NR | AB16: NR | AC16: 1.8043488 | AD16: 4.4244732 | AE16: 5.8163704 | AF16: 0.43180748 | AG16: 3.8076241 | AH16: 3.8076241 | AI16: 5.1840024 | AJ16: 5.1855655 | AK16: 16872358 | AL16: 21286315 | AM16: 45838 | AN16: =IF(C16="","",(IF(AK16>=50000000,"Tier 1",(IF(OR(AK16>=20000000,AND(AK16>5000000,AC16>=1.25,AF16<=0.65)),"Tier 2","Tier 3"))))) | AO16: 47290 | AP16: 3.8916667 | AQ16: =IF(C16="","",AP16) | AR16: No | AS16: 0 | AT16: Yes | AU16: 0.01 | AV16: 0.055 | AW16: 0.042956 | AX16: =IF(C16="","",MAX(AU16,AW16)) | AY16: 0 | AZ16: 0 | BA16: 0 | BB16: =IF(B16="","",IF(AR16="No",AV16-AZ16,"")) | BC16: =IF(B16="","",IF(AR16="Yes",AS16-BA16,"")) | BD16: Quarterly | BE16: Health Care Providers & Services | BF16: USD | BG16: United States | BH16: No | BI16: =IF(B16="","",IF(OR(AND(AZ16>0,BB16>=2.5%,BB16<4%),AND(BA16>0,BC16>=6%,BC16<8%)),"Yes","No")) | BJ16: =IF(B16="","",IF(OR(AND(AZ16>0,BB16<2.5%),AND(BA16>0,BC16<6%)),"Yes","No")) | BK16: No | BL16: No | BM16: No | BN16: No | BO16: No | BP16: No | BQ16: No | BR16: No | BS16: No | BT16: No | BU16: No | BV16: No | BW16: No | BX16: No | BY16: No | BZ16: No | CA16: Yes | CB16: =IF(B16="","",IF(AT16="No",((BB16+AW16)-$AZ$4),((BB16+AX16)-$AZ$4))*IF(DD16>0,0,M16)) | CC16: =IF(B16="","",AY16*(L16-M16)*IF(DD16>0,0,1)) | CE16: =IF(AND(B16<>"",R16<=85%),1,0) | CF16: =IF(B16="",0,(IF(OR(BF16="USD",BF16="CAD",BF16="GBP",BF16="AUD",BF16="EUR"),0,1))) | CG16: =IF(B16="",0,(IF(OR(BG16="United States",BG16="Canada",BG16="United Kingdom",BG16="Australia",BG16="Netherlands Antilles",BG16="Bermuda",BG16="Cayman Islands",BG16="British Virgin Islands",BG16="Channel Islands",BG16="Isle of Man",BG16="Australia",BG16="Netherlands",BG16="Germany",BG16="Sweden",BG16="Switzerland",BG16="Austria",BG16="Belgium",BG16="Denmark",BG16="Finland",BG16="Iceland",BG16="Ireland",BG16="Lichtenstein",BG16="Luxemborg",BG16="Norway"),0,1))) | CH16: =IF(BN16="Yes",1,0) | CI16: =IF(BO16="Yes",1,0) | CJ16: =IF(BP16="Yes",1,0) | CK16: =IF(BQ16="Yes",1,0) | CL16: =IF(BR16="Yes",1,0) | CM16: =IF(BS16="Yes",1,0) | CN16: =IF(OR(AND(BJ16="Yes",N16="No"),AND(BJ16="Yes",N16="Yes",P16>=6)),1,0) | CO16: =IF(BT16="Yes",1,0) | CP16: =IF(AND(BU16="Yes",BV16="No"),1,0) | CQ16: =IF(BW16="Yes",1,0) | CR16: =IF(AP16="",0,IF(AP16>7,1,0)) | CS16: =IF(OR(BD16<>"Monthly",BD16<>"Quarterly",BD16<>"Semi-Annually"),0,1) | CT16: =IF(BX16="Yes",1,0) | CU16: =IF(BY16="Yes",1,0) | CV16: =IF(BZ16="Yes",1,0) | CW16: =IF(CA16="No",1,0) | CX16: =IF(B16="",0,IF(AK16>=5000000,0,1)) | CY16: =IF(B16="",0,IF(AL16>=5000000,0,1)) | CZ16: =IF(OR(DA16=1,DB16=1,DC16=1),0,IF(B16="",0,IF(OR(AND(AN16="Tier 1",X16="No",OR(AI16>$AJ$3,AJ16>$AJ$4)),(AND(AN16="Tier 1",X16="Yes",AJ16>$AJ$5)),(AND(AN16="Tier 2",X16="No",OR(AI16>$AK$3,AJ16>$AK$4))),(AND(AN16="Tier 2",X16="Yes",AJ16>$AK$5)),(AND(AN16="Tier 3",X16="No",OR(AI16>$AL$3,AJ16>$AL$4))),(AND(AN16="Tier 3",X16="Yes",AJ16>$AL$5))),1,0))) | DA16: =IF(OR(DB16=1,DC16=1),0,IF(B16="",0,IF(OR(AND(AN16="Tier 1",X16="No",OR(AI16>$AM$3,AJ16>$AM$4)),(AND(AN16="Tier 1",X16="Yes",AJ16>$AM$5)),(AND(AN16="Tier 2",X16="No",OR(AI16>$AN$3,AJ16>$AN$4))),(AND(AN16="Tier 2",X16="Yes",AJ16>$AN$5)),(AND(AN16="Tier 3",X16="No",OR(AI16>$AO$3,AJ16>$AO$4))),(AND(AN16="Tier 3",X16="Yes",AJ16>$AO$5))),1,0))) | DB16: =IF(DC16=1,0,IF(B16="",0,IF(OR(AND(AN16="Tier 1",X16="No",OR(AI16>$AP$3,AJ16>$AP$4)),(AND(AN16="Tier 1",X16="Yes",AJ16>$AP$5)),(AND(AN16="Tier 2",X16="No",OR(AI16>$AQ$3,AJ16>$AQ$4))),(AND(AN16="Tier 2",X16="Yes",AJ16>$AQ$5)),(AND(AN16="Tier 3",X16="No",OR(AI16>$AR$3,AJ16>$AR$4))),(AND(AN16="Tier 3",X16="Yes",AJ16>$AR$5))),1,0))) | DC16: =IF(B16="",0,IF(OR(AND(AN16="Tier 1",X16="No",OR(AI16>$AS$3,AJ16>$AS$4)),(AND(AN16="Tier 1",X16="Yes",AJ16>$AS$5)),(AND(AN16="Tier 2",X16="No",OR(AI16>$AT$3,AJ16>$AT$4))),(AND(AN16="Tier 2",X16="Yes",AJ16>$AT$5)),(AND(AN16="Tier 3",X16="No",OR(AI16>$AU$3,AJ16>$AU$4))),(AND(AN16="Tier 3",X16="Yes",AJ16>$AU$5))),1,0)) | DD16: =IF((SUM(CE16:CX16)=0),0,W16) | DE16: =IF(OR(B16="",DD16>0),0,W16) | DF16: =IF(B16="",0,IF(COUNTIF(CE16:CX16,1)>0,0,L16-M16)) | DG16: =DE16+IF(DD16>0,0,DF16) | DH16: =IF(B16="","",M16+DF16) | DI16: =IF(B16="",0,J16-K16) | DJ16: =IF(OR(BF16="EUR",BF16="CAD",BF16="GBP",BF16="AUD"),(GA16*(1-V16))+(HG16)+IF(HX16="",0,HX16*(1-U16)),0) | DK16: =IF(BF16="EUR",33%,IF(BF16="CAD",38%,IF(BF16="GBP",51%,IF(BF16="AUD",61%,0)))) | DL16: =DJ16*DK16 | DN16: =IF(OR(Y16="Second Lien",Y16="Tier 1 Split Lien",Y16="Tier 2 Split Lien"),DG16,0) | DO16: =DN16*DN$6 | DP16: =DG16-DO16 | DQ16: =IF(Y16="Second Lien",DP16,0) | DR16: =DQ16*DQ$6 | DS16: =DP16-DR16 | DT16: =IF(BH16="Yes",DS16,0) | DU16: =DT16*DT$6 | DV16: =DS16-DU16 | DW16: =IF(OR(BG16="Canada",BG16="United Kingdom",BG16="Australia",BG16="Netherlands Antilles",BG16="Bermuda",BG16="Cayman Islands",BG16="British Virgin Islands",BG16="Channel Islands",BG16="Isle of Man",BG16="Australia",BG16="Netherlands",BG16="Germany",BG16="Sweden",BG16="Switzerland",BG16="Austria",BG16="Belgium",BG16="Denmark",BG16="Finland",BG16="Iceland",BG16="Ireland",BG16="Lichtenstein",BG16="Luxemborg",BG16="Norway"),DV16,0) | DX16: =DW16*DW$6 | DY16: =DV16-DX16 | DZ16: =IF(BI16="Yes",DY16,0) | EA16: =DZ16*DZ$6 | EB16: =DY16-EA16 | EC16: =IF(OR(Z16="Delayed Draw",Z16="Revolver"),EB16,0) | ED16: =EC16*EC$6 | EE16: =EB16-ED16 | EF16: =IF(S16="Yes",EE16,0) | EG16: =EF16*EF$6 | EH16: =EE16-EG16 | EI16: =IF(Q16="Yes",EH16,0) | EJ16: =EI16*EI$6 | EK16: =EH16-EJ16 | EL16: =IF(BD16="Semi-Annually",EK16,0) | EM16: =EL16*EL$6 | EN16: =EK16-EM16 | EO16: =IF(BK16="Yes",EN16,0) | EP16: =EO16*EO$6 | EQ16: =EN16-EP16 | ER16: =IF(BL16="Yes",EQ16,0) | ES16: =ER16*ER$6 | ET16: =EQ16-ES16 | EU16: =IF(BM16="Yes",ET16,0) | EV16: =EU16*EU$6 | EW16: =ET16-EV16 | EX16: =IF(BV16="Yes",EW16,0) | EY16: =EX16*EX$6 | EZ16: =EW16-EY16 | FA16: =IF(AR16="Yes",EZ16,0) | FB16: =FA16*FA$6 | FC16: =EZ16-FB16 | FD16: =IF(OR(BF16="EUR",BF16="AUD",BF16="CAD",BF16="GBP"),FC16,0) | FE16: =FD16*FD$6 | FF16: =FC16-FE16 | FG16: =FF16 | FH16: =IF(FF16=0,0,VLOOKUP(C16,$GU$10:$GV$406,2,FALSE)*FF16) | FI16: =FF16-FH16 | FJ16: =FI16 | FK16: =IF(OR(IB16="",FI16<0.01),,VLOOKUP(IB16,$GL$10:$GM$406,2,FALSE)*FI16) | FL16: =FI16-FK16 | FM16: =FL16 | FN16: =IF(FL16=0,0,VLOOKUP(C16,$HD$10:$HE$406,2,FALSE)*FL16) | FO16: =FL16-FN16 | FP16: =IF(SUM(CY16:DC16)>0,0,IF(AND(AL16>=5000000,AL16<7500000),FO16,0)) | FQ16: =IF(B16="",0,FP16*FP$6*(1-$U16)) | FR16: =FO16-FQ16 | FS16: =IF(SUM(CY16:DC16)>0,0,IF(AL16<15000000,FR16,0)) | FT16: =IF(B16="",0,FS16*FS$6*(1-$U16)) | FU16: =FR16-FT16 | FV16: =IF(SUM(CY16:DC16)>0,0,IF(OR(AND(X16="No",AN16="Tier 1",AI16>$AG$3),AND(X16="No",AN16="Tier 2",AI16>$AH$3),AND(X16="No",AN16="Tier 3",AI16>$AI$3)),FU16,0)) | FW16: =IF(SUM(CY16:DC16)>0,0,IF(OR(AND(X16="No",AN16="Tier 1",AJ16>$AG$4),AND(X16="No",AN16="Tier 2",AJ16>$AH$4),AND(X16="No",AN16="Tier 3",AJ16>$AI$4)),FU16,0)) | FX16: =IF(SUM(CY16:DC16)>0,0,IF(OR(AND(X16="Yes",AN16="Tier 1",AJ16>$AG$5),AND(X16="Yes",AN16="Tier 2",AJ16>$AH$5),AND(X16="Yes",AN16="Tier 3",AJ16>$AI$5)),FU16,0)) | FY16: =IF(SUM(FV16:FX16)>0,FU16,0) | FZ16: =IF(B16="",0,FY16*FV$6*(1-MIN(90%,T16))) | GA16: =FU16-FZ16 | GB16: =IF(AND(N16="No",DI16=0),GA16,IF(AND(N16="No",DI16<>0,K16=0),0,IF(AND(N16="No",DI16<>0,K16>0,J16<>K16),MAX(0,M16-(DH16-GA16)),DG16))) | GC16: =+GB16*V16 | GD16: =IFERROR(GC16/K16,"") | GE16: =IF(IB16="","",IB16) | GF16: {=IF(SUM(IF(IB$9:IB15=IB16,1,0))>0,0,SUMIF($IB$10:$IB$406,IB16,$FI$10:$FI$406))} | GG16: =GF16 | GH16: =GH15+1 | GI16: =LARGE($GG$10:$GG$406,GH16) | GJ16: =IF(GH16>GH$6,0,IF(GH16=$GH$2,$GJ$2,IF(GH16<4,$GJ$3,$GJ$4))) | GK16: =MAX(0,GI16-GJ16) | GL16: {=IF(GI16=0,0,LARGE(IF($GF$10:$GF$406=GI16,$GE$10:$GE$406,0),COUNTIF($GI$10:$GI$406,GI16)-COUNTIF(GI$9:GI15,GI16)))} | GM16: =IF(GI16=0,0,GK16/GI16) | GO16: =IF(C16="","",IF(ISERROR(MATCH(C16,C$10:C15,0)),MAX(GO$10:GO15)+1,INDEX(GO$10:GO15,MATCH(C16,C$10:C15,0)))) | GP16: =IF(COUNTIF($A$10:A16,A16)<=1,SUMIF($A$10:$A$406,A16,$FG$10:$FG$406),0) | GQ16: =GQ15+1 | GR16: =LARGE($GP$10:$GP$406,GQ16) | GS16: =IF(GQ16>GQ$6,0,IF(GQ16<=GQ$2,GS$2,IF(AND(GQ16<=$GQ$3,GQ16>$GQ$2),GS$3,GS$4))) | GT16: =MAX(0,GR16-GS16) | GU16: {=IF(GR16=0,0,LARGE(IF($GP$10:$GP$406=GR16,$GO$10:$GO$406,0),COUNTIF($GR$10:$GR$406,GR16)-COUNTIF(GR$9:GR15,GR16)))} | GV16: =IF(GR16=0,0,GT16/GR16) | GX16: =IF(C16="","",IF(ISERROR(MATCH(C16,C$10:C15,0)),MAX(GO$10:GO15)+1,INDEX(GO$10:GO15,MATCH(C16,C$10:C15,0)))) | GY16: =IF(COUNTIF($A$10:A16,A16)<=1,SUMIF($A$10:$A$406,A16,$FG$10:$FG$406),0) | GZ16: =GZ15+1 | HA16: =LARGE($GY$10:$GY$406,GZ16) | HB16: - | HC16: =IF(GZ16<6,MAX(0,$HC$2/5),0) | HD16: {=IF(HA16=0,0,LARGE(IF($GY$10:$GY$406=HA16,$GX$10:$GX$406,0),COUNTIF($HA$10:$HA$406,HA16)-COUNTIF(HA$9:HA15,HA16)))} | HE16: =IF(HA16=0,0,HC16/HA16) | HG16: =DG16-GA16 | HH16: 0 | HI16: =MIN(HH16,DE16) | HK16: =IF(COUNTIF($C$10:$C$406,HK15+1),HK15+1,"") | HL16: =SUMIF($C$10:$C$406,HK16,$DG$10:$DG$406) | HN16: =MIN(HO16:HS16) | HO16: =IF(B16="","",$M16) | HP16: =IF($N16="Yes",IF(P16>=6,0,MIN($T16*$M16,$U16*$M16)),"") | HQ16: =IF(AND(N16="Yes",P16>=6),"",IF($S16="Yes",$R16*$M16,"")) | HR16: =IF($Q16="Yes",MIN($M16,$T16*$M16),"") | HS16: =IF(AND($N16="Yes",$P16>=6),"",IF(OR(CY16=1,DC16=1,),MIN($T16*$M16,$U16*$M16),IF(OR(CZ16=1,DA16=1,DB16=1),IF(AK16>=5000000,MIN($T16*$M16,$IE16*$M16),MIN($T16*$M16,$U16*$M16)),""))) | HT16: =IF(DD16>0,DD16,"") | HU16: =IF(B16="",0,$L16-$M16) | HV16: =IF(OR(SUM(HP16:HT16)>0,P16>=6),"",IF($B16="","",1)) | HW16: =IF(AND($HT16<>0,OR(HT16<=MIN(HP16:HS16),SUM(HP16:HS16)=0)),$HT16,0) | HX16: =IF(AND($HS16<>0,OR(AND($HS16<>$HT16,$HS16<>$HR16,$HS16<>$HQ16,$HS16<>$HP16,$HS16<MIN($HP16:$HR16),$HS16<HT16),SUM($HP16:$HR16)+SUM(HT16)=0),IA16<=0),$HS16,0) | HY16: =IF(AND($HR16<>0,OR(AND($HR16<>$HT16,$HR16<>$HS16,$HR16<>$HQ16,$HR16<>$HP16),$HR16<MIN($HP16:$HQ16),$HR16<MIN($HS16:$HT16),SUM($HP16:$HQ16)+SUM($HS16:$HT16)=0)),$HR16,0) | HZ16: =IF(AND($HQ16<>0,OR(AND($HQ16<>$HT16,HQ16<>HS16,HQ16<>HR16,HQ16<>HP16,HQ16<MIN(HR16:HT16)),SUM(HP16)+SUM(HR16:HT16)=0)),$HQ16,0) | IA16: =IF(AND($HP16<>0,OR(HP16<=MIN(HQ16:HT16),SUM(HQ16:HT16)=0)),$HP16,0) | IB16: 31 | IC16: =HU16=DF16 | IE16: =IF(B16="","",IF(AND(Y16="Second Lien",OR(CZ16=1,DA16=1,DB16=1)),50%,IF(CZ16=1,90%,IF(DA16=1,80%,IF(DB16=1,65%,"No Initial Haircut")))))
A17: =D17 | B17: =IF(D17="","",B16+1) | C17: =IF(COUNTIF($A$10:A16,A17)>0,C16,C16+1) | D17: Crestline Holdings, LLC | E17: Crestline (First Lien Term Loan) | G17: 41568911 | H17: 41568911 | I17: 1 | J17: =IF(B17="","",G17*I17) | K17: =IF(B17="","",H17*I17) | L17: =IF(B17="","",IF(COUNTIF($CE17:$CX17,1)>0,0,J17)) | M17: =IF(B17="","",IF(COUNTIF($CE17:$CX17,1)>0,0,K17)) | N17: No | O17: N/A | P17: =IF(B17="","",IF(OR(O17="N/A",O17=""),0,YEARFRAC('Borrowing Base'!$J$4,'Loan List'!O17)*12)) | Q17: No | R17: 0.98503022 | S17: =IF(B17="","",IF(R17<95%,"Yes","No")) | T17: 0.9875 | U17: =IF(B17="","",IF(OR(Y17="First Lien",Y17="Split First Lien",Y17="Tier 1 Split Lien",Y17="Tier 2 Split Lien"),50%,30%)) | V17: =IF(B17="",0,IF(AND(Y17="First Lien",AN17="Tier 1"),IF(AND(X17="Yes",MIN(AH17,$AJ$5)>4.5),(((4.5/MIN(AH17,$AJ$5))*72.5%)+(((MIN(AH17,$AJ$5)-4.5)/MIN(AH17,$AJ$5))*35%)),72.5%),IF(AND(Y17="First Lien",AN17="Tier 2"),IF(AND(X17="Yes",MIN(AH17,$AK$5)>4.5),(((4.5/MIN(AH17,$AK$5))*72.5%)+(((MIN(AH17,$AK$5)-4.5)/MIN(AH17,$AK$5))*35%)),72.5%),IF(AND(X17="Yes",MIN(AH17,$AL$5)>4),(((4/MIN(AH17,$AL$5))*72.5%)+(((MIN(AH17,$AL$5)-4)/MIN(AH17,$AL$5))*35%)),IF(OR(Y17="First Lien",Y17="Split First Lien"),72.5%,IF(Y17="Split Lien", 53%,35%)))))) | W17: =IF($C17="","",MIN($HO17:$HS17)) | X17: No | Y17: First Lien | Z17: Term | AA17: NR | AB17: NR | AC17: 1.2337514 | AD17: 5.3300119 | AE17: 4.808288 | AF17: 0.53300119 | AG17: 5.037594 | AH17: 5.3300119 | AI17: 4.7445568 | AJ17: 5.1038799 | AK17: 47275000 | AL17: 67742897 | AM17: 45838 | AN17: =IF(C17="","",(IF(AK17>=50000000,"Tier 1",(IF(OR(AK17>=20000000,AND(AK17>5000000,AC17>=1.25,AF17<=0.65)),"Tier 2","Tier 3"))))) | AO17: 47430 | AP17: 4.2722222 | AQ17: =IF(C17="","",AP17) | AR17: No | AS17: 0 | AT17: Yes | AU17: 0.01 | AV17: 0.0675 | AW17: 0.042956 | AX17: =IF(C17="","",MAX(AU17,AW17)) | AY17: 0 | AZ17: 0 | BA17: 0 | BB17: =IF(B17="","",IF(AR17="No",AV17-AZ17,"")) | BC17: =IF(B17="","",IF(AR17="Yes",AS17-BA17,"")) | BD17: Quarterly | BE17: Aerospace & Defense | BF17: USD | BG17: United States | BH17: No | BI17: =IF(B17="","",IF(OR(AND(AZ17>0,BB17>=2.5%,BB17<4%),AND(BA17>0,BC17>=6%,BC17<8%)),"Yes","No")) | BJ17: =IF(B17="","",IF(OR(AND(AZ17>0,BB17<2.5%),AND(BA17>0,BC17<6%)),"Yes","No")) | BK17: No | BL17: No | BM17: No | BN17: No | BO17: No | BP17: No | BQ17: No | BR17: No | BS17: No | BT17: No | BU17: No | BV17: No | BW17: No | BX17: No | BY17: No | BZ17: No | CA17: Yes | CB17: =IF(B17="","",IF(AT17="No",((BB17+AW17)-$AZ$4),((BB17+AX17)-$AZ$4))*IF(DD17>0,0,M17)) | CC17: =IF(B17="","",AY17*(L17-M17)*IF(DD17>0,0,1)) | CE17: =IF(AND(B17<>"",R17<=85%),1,0) | CF17: =IF(B17="",0,(IF(OR(BF17="USD",BF17="CAD",BF17="GBP",BF17="AUD",BF17="EUR"),0,1))) | CG17: =IF(B17="",0,(IF(OR(BG17="United States",BG17="Canada",BG17="United Kingdom",BG17="Australia",BG17="Netherlands Antilles",BG17="Bermuda",BG17="Cayman Islands",BG17="British Virgin Islands",BG17="Channel Islands",BG17="Isle of Man",BG17="Australia",BG17="Netherlands",BG17="Germany",BG17="Sweden",BG17="Switzerland",BG17="Austria",BG17="Belgium",BG17="Denmark",BG17="Finland",BG17="Iceland",BG17="Ireland",BG17="Lichtenstein",BG17="Luxemborg",BG17="Norway"),0,1))) | CH17: =IF(BN17="Yes",1,0) | CI17: =IF(BO17="Yes",1,0) | CJ17: =IF(BP17="Yes",1,0) | CK17: =IF(BQ17="Yes",1,0) | CL17: =IF(BR17="Yes",1,0) | CM17: =IF(BS17="Yes",1,0) | CN17: =IF(OR(AND(BJ17="Yes",N17="No"),AND(BJ17="Yes",N17="Yes",P17>=6)),1,0) | CO17: =IF(BT17="Yes",1,0) | CP17: =IF(AND(BU17="Yes",BV17="No"),1,0) | CQ17: =IF(BW17="Yes",1,0) | CR17: =IF(AP17="",0,IF(AP17>7,1,0)) | CS17: =IF(OR(BD17<>"Monthly",BD17<>"Quarterly",BD17<>"Semi-Annually"),0,1) | CT17: =IF(BX17="Yes",1,0) | CU17: =IF(BY17="Yes",1,0) | CV17: =IF(BZ17="Yes",1,0) | CW17: =IF(CA17="No",1,0) | CX17: =IF(B17="",0,IF(AK17>=5000000,0,1)) | CY17: =IF(B17="",0,IF(AL17>=5000000,0,1)) | CZ17: =IF(OR(DA17=1,DB17=1,DC17=1),0,IF(B17="",0,IF(OR(AND(AN17="Tier 1",X17="No",OR(AI17>$AJ$3,AJ17>$AJ$4)),(AND(AN17="Tier 1",X17="Yes",AJ17>$AJ$5)),(AND(AN17="Tier 2",X17="No",OR(AI17>$AK$3,AJ17>$AK$4))),(AND(AN17="Tier 2",X17="Yes",AJ17>$AK$5)),(AND(AN17="Tier 3",X17="No",OR(AI17>$AL$3,AJ17>$AL$4))),(AND(AN17="Tier 3",X17="Yes",AJ17>$AL$5))),1,0))) | DA17: =IF(OR(DB17=1,DC17=1),0,IF(B17="",0,IF(OR(AND(AN17="Tier 1",X17="No",OR(AI17>$AM$3,AJ17>$AM$4)),(AND(AN17="Tier 1",X17="Yes",AJ17>$AM$5)),(AND(AN17="Tier 2",X17="No",OR(AI17>$AN$3,AJ17>$AN$4))),(AND(AN17="Tier 2",X17="Yes",AJ17>$AN$5)),(AND(AN17="Tier 3",X17="No",OR(AI17>$AO$3,AJ17>$AO$4))),(AND(AN17="Tier 3",X17="Yes",AJ17>$AO$5))),1,0))) | DB17: =IF(DC17=1,0,IF(B17="",0,IF(OR(AND(AN17="Tier 1",X17="No",OR(AI17>$AP$3,AJ17>$AP$4)),(AND(AN17="Tier 1",X17="Yes",AJ17>$AP$5)),(AND(AN17="Tier 2",X17="No",OR(AI17>$AQ$3,AJ17>$AQ$4))),(AND(AN17="Tier 2",X17="Yes",AJ17>$AQ$5)),(AND(AN17="Tier 3",X17="No",OR(AI17>$AR$3,AJ17>$AR$4))),(AND(AN17="Tier 3",X17="Yes",AJ17>$AR$5))),1,0))) | DC17: =IF(B17="",0,IF(OR(AND(AN17="Tier 1",X17="No",OR(AI17>$AS$3,AJ17>$AS$4)),(AND(AN17="Tier 1",X17="Yes",AJ17>$AS$5)),(AND(AN17="Tier 2",X17="No",OR(AI17>$AT$3,AJ17>$AT$4))),(AND(AN17="Tier 2",X17="Yes",AJ17>$AT$5)),(AND(AN17="Tier 3",X17="No",OR(AI17>$AU$3,AJ17>$AU$4))),(AND(AN17="Tier 3",X17="Yes",AJ17>$AU$5))),1,0)) | DD17: =IF((SUM(CE17:CX17)=0),0,W17) | DE17: =IF(OR(B17="",DD17>0),0,W17) | DF17: =IF(B17="",0,IF(COUNTIF(CE17:CX17,1)>0,0,L17-M17)) | DG17: =DE17+IF(DD17>0,0,DF17) | DH17: =IF(B17="","",M17+DF17) | DI17: =IF(B17="",0,J17-K17) | DJ17: =IF(OR(BF17="EUR",BF17="CAD",BF17="GBP",BF17="AUD"),(GA17*(1-V17))+(HG17)+IF(HX17="",0,HX17*(1-U17)),0) | DK17: =IF(BF17="EUR",33%,IF(BF17="CAD",38%,IF(BF17="GBP",51%,IF(BF17="AUD",61%,0)))) | DL17: =DJ17*DK17 | DN17: =IF(OR(Y17="Second Lien",Y17="Tier 1 Split Lien",Y17="Tier 2 Split Lien"),DG17,0) | DO17: =DN17*DN$6 | DP17: =DG17-DO17 | DQ17: =IF(Y17="Second Lien",DP17,0) | DR17: =DQ17*DQ$6 | DS17: =DP17-DR17 | DT17: =IF(BH17="Yes",DS17,0) | DU17: =DT17*DT$6 | DV17: =DS17-DU17 | DW17: =IF(OR(BG17="Canada",BG17="United Kingdom",BG17="Australia",BG17="Netherlands Antilles",BG17="Bermuda",BG17="Cayman Islands",BG17="British Virgin Islands",BG17="Channel Islands",BG17="Isle of Man",BG17="Australia",BG17="Netherlands",BG17="Germany",BG17="Sweden",BG17="Switzerland",BG17="Austria",BG17="Belgium",BG17="Denmark",BG17="Finland",BG17="Iceland",BG17="Ireland",BG17="Lichtenstein",BG17="Luxemborg",BG17="Norway"),DV17,0) | DX17: =DW17*DW$6 | DY17: =DV17-DX17 | DZ17: =IF(BI17="Yes",DY17,0) | EA17: =DZ17*DZ$6 | EB17: =DY17-EA17 | EC17: =IF(OR(Z17="Delayed Draw",Z17="Revolver"),EB17,0) | ED17: =EC17*EC$6 | EE17: =EB17-ED17 | EF17: =IF(S17="Yes",EE17,0) | EG17: =EF17*EF$6 | EH17: =EE17-EG17 | EI17: =IF(Q17="Yes",EH17,0) | EJ17: =EI17*EI$6 | EK17: =EH17-EJ17 | EL17: =IF(BD17="Semi-Annually",EK17,0) | EM17: =EL17*EL$6 | EN17: =EK17-EM17 | EO17: =IF(BK17="Yes",EN17,0) | EP17: =EO17*EO$6 | EQ17: =EN17-EP17 | ER17: =IF(BL17="Yes",EQ17,0) | ES17: =ER17*ER$6 | ET17: =EQ17-ES17 | EU17: =IF(BM17="Yes",ET17,0) | EV17: =EU17*EU$6 | EW17: =ET17-EV17 | EX17: =IF(BV17="Yes",EW17,0) | EY17: =EX17*EX$6 | EZ17: =EW17-EY17 | FA17: =IF(AR17="Yes",EZ17,0) | FB17: =FA17*FA$6 | FC17: =EZ17-FB17 | FD17: =IF(OR(BF17="EUR",BF17="AUD",BF17="CAD",BF17="GBP"),FC17,0) | FE17: =FD17*FD$6 | FF17: =FC17-FE17 | FG17: =FF17 | FH17: =IF(FF17=0,0,VLOOKUP(C17,$GU$10:$GV$406,2,FALSE)*FF17) | FI17: =FF17-FH17 | FJ17: =FI17 | FK17: =IF(OR(IB17="",FI17<0.01),,VLOOKUP(IB17,$GL$10:$GM$406,2,FALSE)*FI17) | FL17: =FI17-FK17 | FM17: =FL17 | FN17: =IF(FL17=0,0,VLOOKUP(C17,$HD$10:$HE$406,2,FALSE)*FL17) | FO17: =FL17-FN17 | FP17: =IF(SUM(CY17:DC17)>0,0,IF(AND(AL17>=5000000,AL17<7500000),FO17,0)) | FQ17: =IF(B17="",0,FP17*FP$6*(1-$U17)) | FR17: =FO17-FQ17 | FS17: =IF(SUM(CY17:DC17)>0,0,IF(AL17<15000000,FR17,0)) | FT17: =IF(B17="",0,FS17*FS$6*(1-$U17)) | FU17: =FR17-FT17 | FV17: =IF(SUM(CY17:DC17)>0,0,IF(OR(AND(X17="No",AN17="Tier 1",AI17>$AG$3),AND(X17="No",AN17="Tier 2",AI17>$AH$3),AND(X17="No",AN17="Tier 3",AI17>$AI$3)),FU17,0)) | FW17: =IF(SUM(CY17:DC17)>0,0,IF(OR(AND(X17="No",AN17="Tier 1",AJ17>$AG$4),AND(X17="No",AN17="Tier 2",AJ17>$AH$4),AND(X17="No",AN17="Tier 3",AJ17>$AI$4)),FU17,0)) | FX17: =IF(SUM(CY17:DC17)>0,0,IF(OR(AND(X17="Yes",AN17="Tier 1",AJ17>$AG$5),AND(X17="Yes",AN17="Tier 2",AJ17>$AH$5),AND(X17="Yes",AN17="Tier 3",AJ17>$AI$5)),FU17,0)) | FY17: =IF(SUM(FV17:FX17)>0,FU17,0) | FZ17: =IF(B17="",0,FY17*FV$6*(1-MIN(90%,T17))) | GA17: =FU17-FZ17 | GB17: =IF(AND(N17="No",DI17=0),GA17,IF(AND(N17="No",DI17<>0,K17=0),0,IF(AND(N17="No",DI17<>0,K17>0,J17<>K17),MAX(0,M17-(DH17-GA17)),DG17))) | GC17: =+GB17*V17 | GD17: =IFERROR(GC17/K17,"") | GE17: =IF(IB17="","",IB17) | GF17: {=IF(SUM(IF(IB$9:IB16=IB17,1,0))>0,0,SUMIF($IB$10:$IB$406,IB17,$FI$10:$FI$406))} | GG17: =GF17 | GH17: =GH16+1 | GI17: =LARGE($GG$10:$GG$406,GH17) | GJ17: =IF(GH17>GH$6,0,IF(GH17=$GH$2,$GJ$2,IF(GH17<4,$GJ$3,$GJ$4))) | GK17: =MAX(0,GI17-GJ17) | GL17: {=IF(GI17=0,0,LARGE(IF($GF$10:$GF$406=GI17,$GE$10:$GE$406,0),COUNTIF($GI$10:$GI$406,GI17)-COUNTIF(GI$9:GI16,GI17)))} | GM17: =IF(GI17=0,0,GK17/GI17) | GO17: =IF(C17="","",IF(ISERROR(MATCH(C17,C$10:C16,0)),MAX(GO$10:GO16)+1,INDEX(GO$10:GO16,MATCH(C17,C$10:C16,0)))) | GP17: =IF(COUNTIF($A$10:A17,A17)<=1,SUMIF($A$10:$A$406,A17,$FG$10:$FG$406),0) | GQ17: =GQ16+1 | GR17: =LARGE($GP$10:$GP$406,GQ17) | GS17: =IF(GQ17>GQ$6,0,IF(GQ17<=GQ$2,GS$2,IF(AND(GQ17<=$GQ$3,GQ17>$GQ$2),GS$3,GS$4))) | GT17: =MAX(0,GR17-GS17) | GU17: {=IF(GR17=0,0,LARGE(IF($GP$10:$GP$406=GR17,$GO$10:$GO$406,0),COUNTIF($GR$10:$GR$406,GR17)-COUNTIF(GR$9:GR16,GR17)))} | GV17: =IF(GR17=0,0,GT17/GR17) | GX17: =IF(C17="","",IF(ISERROR(MATCH(C17,C$10:C16,0)),MAX(GO$10:GO16)+1,INDEX(GO$10:GO16,MATCH(C17,C$10:C16,0)))) | GY17: =IF(COUNTIF($A$10:A17,A17)<=1,SUMIF($A$10:$A$406,A17,$FG$10:$FG$406),0) | GZ17: =GZ16+1 | HA17: =LARGE($GY$10:$GY$406,GZ17) | HB17: - | HC17: =IF(GZ17<6,MAX(0,$HC$2/5),0) | HD17: {=IF(HA17=0,0,LARGE(IF($GY$10:$GY$406=HA17,$GX$10:$GX$406,0),COUNTIF($HA$10:$HA$406,HA17)-COUNTIF(HA$9:HA16,HA17)))} | HE17: =IF(HA17=0,0,HC17/HA17) | HG17: =DG17-GA17 | HH17: 0 | HI17: =MIN(HH17,DE17) | HK17: =IF(COUNTIF($C$10:$C$406,HK16+1),HK16+1,"") | HL17: =SUMIF($C$10:$C$406,HK17,$DG$10:$DG$406) | HN17: =MIN(HO17:HS17) | HO17: =IF(B17="","",$M17) | HP17: =IF($N17="Yes",IF(P17>=6,0,MIN($T17*$M17,$U17*$M17)),"") | HQ17: =IF(AND(N17="Yes",P17>=6),"",IF($S17="Yes",$R17*$M17,"")) | HR17: =IF($Q17="Yes",MIN($M17,$T17*$M17),"") | HS17: =IF(AND($N17="Yes",$P17>=6),"",IF(OR(CY17=1,DC17=1,),MIN($T17*$M17,$U17*$M17),IF(OR(CZ17=1,DA17=1,DB17=1),IF(AK17>=5000000,MIN($T17*$M17,$IE17*$M17),MIN($T17*$M17,$U17*$M17)),""))) | HT17: =IF(DD17>0,DD17,"") | HU17: =IF(B17="",0,$L17-$M17) | HV17: =IF(OR(SUM(HP17:HT17)>0,P17>=6),"",IF($B17="","",1)) | HW17: =IF(AND($HT17<>0,OR(HT17<=MIN(HP17:HS17),SUM(HP17:HS17)=0)),$HT17,0) | HX17: =IF(AND($HS17<>0,OR(AND($HS17<>$HT17,$HS17<>$HR17,$HS17<>$HQ17,$HS17<>$HP17,$HS17<MIN($HP17:$HR17),$HS17<HT17),SUM($HP17:$HR17)+SUM(HT17)=0),IA17<=0),$HS17,0) | HY17: =IF(AND($HR17<>0,OR(AND($HR17<>$HT17,$HR17<>$HS17,$HR17<>$HQ17,$HR17<>$HP17),$HR17<MIN($HP17:$HQ17),$HR17<MIN($HS17:$HT17),SUM($HP17:$HQ17)+SUM($HS17:$HT17)=0)),$HR17,0) | HZ17: =IF(AND($HQ17<>0,OR(AND($HQ17<>$HT17,HQ17<>HS17,HQ17<>HR17,HQ17<>HP17,HQ17<MIN(HR17:HT17)),SUM(HP17)+SUM(HR17:HT17)=0)),$HQ17,0) | IA17: =IF(AND($HP17<>0,OR(HP17<=MIN(HQ17:HT17),SUM(HQ17:HT17)=0)),$HP17,0) | IB17: 1 | IC17: =HU17=DF17 | IE17: =IF(B17="","",IF(AND(Y17="Second Lien",OR(CZ17=1,DA17=1,DB17=1)),50%,IF(CZ17=1,90%,IF(DA17=1,80%,IF(DB17=1,65%,"No Initial Haircut")))))
A18: =D18 | B18: =IF(D18="","",B17+1) | C18: =IF(COUNTIF($A$10:A17,A18)>0,C17,C17+1) | D18: Fieldstone Holdings, LLC | E18: Fieldstone (Term Loan) | G18: 10088880 | H18: 10088880 | I18: 1 | J18: =IF(B18="","",G18*I18) | K18: =IF(B18="","",H18*I18) | L18: =IF(B18="","",IF(COUNTIF($CE18:$CX18,1)>0,0,J18)) | M18: =IF(B18="","",IF(COUNTIF($CE18:$CX18,1)>0,0,K18)) | N18: No | O18: N/A | P18: =IF(B18="","",IF(OR(O18="N/A",O18=""),0,YEARFRAC('Borrowing Base'!$J$4,'Loan List'!O18)*12)) | Q18: No | R18: 0.98257459 | S18: =IF(B18="","",IF(R18<95%,"Yes","No")) | T18: 1 | U18: =IF(B18="","",IF(OR(Y18="First Lien",Y18="Split First Lien",Y18="Tier 1 Split Lien",Y18="Tier 2 Split Lien"),50%,30%)) | V18: =IF(B18="",0,IF(AND(Y18="First Lien",AN18="Tier 1"),IF(AND(X18="Yes",MIN(AH18,$AJ$5)>4.5),(((4.5/MIN(AH18,$AJ$5))*72.5%)+(((MIN(AH18,$AJ$5)-4.5)/MIN(AH18,$AJ$5))*35%)),72.5%),IF(AND(Y18="First Lien",AN18="Tier 2"),IF(AND(X18="Yes",MIN(AH18,$AK$5)>4.5),(((4.5/MIN(AH18,$AK$5))*72.5%)+(((MIN(AH18,$AK$5)-4.5)/MIN(AH18,$AK$5))*35%)),72.5%),IF(AND(X18="Yes",MIN(AH18,$AL$5)>4),(((4/MIN(AH18,$AL$5))*72.5%)+(((MIN(AH18,$AL$5)-4)/MIN(AH18,$AL$5))*35%)),IF(OR(Y18="First Lien",Y18="Split First Lien"),72.5%,IF(Y18="Split Lien", 53%,35%)))))) | W18: =IF($C18="","",MIN($HO18:$HS18)) | X18: No | Y18: First Lien | Z18: Term | AA18: NR | AB18: NR | AC18: 1.58 | AD18: 3.7538419 | AE18: 3.4596842 | AF18: 0.48189321 | AG18: 3.7538419 | AH18: 3.7538419 | AI18: 3.3434574 | AJ18: 3.3434574 | AK18: 32800000 | AL18: 35032000 | AM18: 45838 | AN18: =IF(C18="","",(IF(AK18>=50000000,"Tier 1",(IF(OR(AK18>=20000000,AND(AK18>5000000,AC18>=1.25,AF18<=0.65)),"Tier 2","Tier 3"))))) | AO18: 47543 | AP18: 4.5861111 | AQ18: =IF(C18="","",AP18) | AR18: No | AS18: 0 | AT18: Yes | AU18: 0.01 | AV18: 0.055 | AW18: 0.042956 | AX18: =IF(C18="","",MAX(AU18,AW18)) | AY18: 0 | AZ18: 0 | BA18: 0 | BB18: =IF(B18="","",IF(AR18="No",AV18-AZ18,"")) | BC18: =IF(B18="","",IF(AR18="Yes",AS18-BA18,"")) | BD18: Quarterly | BE18: Construction & Engineering | BF18: USD | BG18: United States | BH18: No | BI18: =IF(B18="","",IF(OR(AND(AZ18>0,BB18>=2.5%,BB18<4%),AND(BA18>0,BC18>=6%,BC18<8%)),"Yes","No")) | BJ18: =IF(B18="","",IF(OR(AND(AZ18>0,BB18<2.5%),AND(BA18>0,BC18<6%)),"Yes","No")) | BK18: No | BL18: No | BM18: No | BN18: No | BO18: No | BP18: No | BQ18: No | BR18: No | BS18: No | BT18: No | BU18: No | BV18: No | BW18: No | BX18: No | BY18: No | BZ18: No | CA18: Yes | CB18: =IF(B18="","",IF(AT18="No",((BB18+AW18)-$AZ$4),((BB18+AX18)-$AZ$4))*IF(DD18>0,0,M18)) | CC18: =IF(B18="","",AY18*(L18-M18)*IF(DD18>0,0,1)) | CE18: =IF(AND(B18<>"",R18<=85%),1,0) | CF18: =IF(B18="",0,(IF(OR(BF18="USD",BF18="CAD",BF18="GBP",BF18="AUD",BF18="EUR"),0,1))) | CG18: =IF(B18="",0,(IF(OR(BG18="United States",BG18="Canada",BG18="United Kingdom",BG18="Australia",BG18="Netherlands Antilles",BG18="Bermuda",BG18="Cayman Islands",BG18="British Virgin Islands",BG18="Channel Islands",BG18="Isle of Man",BG18="Australia",BG18="Netherlands",BG18="Germany",BG18="Sweden",BG18="Switzerland",BG18="Austria",BG18="Belgium",BG18="Denmark",BG18="Finland",BG18="Iceland",BG18="Ireland",BG18="Lichtenstein",BG18="Luxemborg",BG18="Norway"),0,1))) | CH18: =IF(BN18="Yes",1,0) | CI18: =IF(BO18="Yes",1,0) | CJ18: =IF(BP18="Yes",1,0) | CK18: =IF(BQ18="Yes",1,0) | CL18: =IF(BR18="Yes",1,0) | CM18: =IF(BS18="Yes",1,0) | CN18: =IF(OR(AND(BJ18="Yes",N18="No"),AND(BJ18="Yes",N18="Yes",P18>=6)),1,0) | CO18: =IF(BT18="Yes",1,0) | CP18: =IF(AND(BU18="Yes",BV18="No"),1,0) | CQ18: =IF(BW18="Yes",1,0) | CR18: =IF(AP18="",0,IF(AP18>7,1,0)) | CS18: =IF(OR(BD18<>"Monthly",BD18<>"Quarterly",BD18<>"Semi-Annually"),0,1) | CT18: =IF(BX18="Yes",1,0) | CU18: =IF(BY18="Yes",1,0) | CV18: =IF(BZ18="Yes",1,0) | CW18: =IF(CA18="No",1,0) | CX18: =IF(B18="",0,IF(AK18>=5000000,0,1)) | CY18: =IF(B18="",0,IF(AL18>=5000000,0,1)) | CZ18: =IF(OR(DA18=1,DB18=1,DC18=1),0,IF(B18="",0,IF(OR(AND(AN18="Tier 1",X18="No",OR(AI18>$AJ$3,AJ18>$AJ$4)),(AND(AN18="Tier 1",X18="Yes",AJ18>$AJ$5)),(AND(AN18="Tier 2",X18="No",OR(AI18>$AK$3,AJ18>$AK$4))),(AND(AN18="Tier 2",X18="Yes",AJ18>$AK$5)),(AND(AN18="Tier 3",X18="No",OR(AI18>$AL$3,AJ18>$AL$4))),(AND(AN18="Tier 3",X18="Yes",AJ18>$AL$5))),1,0))) | DA18: =IF(OR(DB18=1,DC18=1),0,IF(B18="",0,IF(OR(AND(AN18="Tier 1",X18="No",OR(AI18>$AM$3,AJ18>$AM$4)),(AND(AN18="Tier 1",X18="Yes",AJ18>$AM$5)),(AND(AN18="Tier 2",X18="No",OR(AI18>$AN$3,AJ18>$AN$4))),(AND(AN18="Tier 2",X18="Yes",AJ18>$AN$5)),(AND(AN18="Tier 3",X18="No",OR(AI18>$AO$3,AJ18>$AO$4))),(AND(AN18="Tier 3",X18="Yes",AJ18>$AO$5))),1,0))) | DB18: =IF(DC18=1,0,IF(B18="",0,IF(OR(AND(AN18="Tier 1",X18="No",OR(AI18>$AP$3,AJ18>$AP$4)),(AND(AN18="Tier 1",X18="Yes",AJ18>$AP$5)),(AND(AN18="Tier 2",X18="No",OR(AI18>$AQ$3,AJ18>$AQ$4))),(AND(AN18="Tier 2",X18="Yes",AJ18>$AQ$5)),(AND(AN18="Tier 3",X18="No",OR(AI18>$AR$3,AJ18>$AR$4))),(AND(AN18="Tier 3",X18="Yes",AJ18>$AR$5))),1,0))) | DC18: =IF(B18="",0,IF(OR(AND(AN18="Tier 1",X18="No",OR(AI18>$AS$3,AJ18>$AS$4)),(AND(AN18="Tier 1",X18="Yes",AJ18>$AS$5)),(AND(AN18="Tier 2",X18="No",OR(AI18>$AT$3,AJ18>$AT$4))),(AND(AN18="Tier 2",X18="Yes",AJ18>$AT$5)),(AND(AN18="Tier 3",X18="No",OR(AI18>$AU$3,AJ18>$AU$4))),(AND(AN18="Tier 3",X18="Yes",AJ18>$AU$5))),1,0)) | DD18: =IF((SUM(CE18:CX18)=0),0,W18) | DE18: =IF(OR(B18="",DD18>0),0,W18) | DF18: =IF(B18="",0,IF(COUNTIF(CE18:CX18,1)>0,0,L18-M18)) | DG18: =DE18+IF(DD18>0,0,DF18) | DH18: =IF(B18="","",M18+DF18) | DI18: =IF(B18="",0,J18-K18) | DJ18: =IF(OR(BF18="EUR",BF18="CAD",BF18="GBP",BF18="AUD"),(GA18*(1-V18))+(HG18)+IF(HX18="",0,HX18*(1-U18)),0) | DK18: =IF(BF18="EUR",33%,IF(BF18="CAD",38%,IF(BF18="GBP",51%,IF(BF18="AUD",61%,0)))) | DL18: =DJ18*DK18 | DN18: =IF(OR(Y18="Second Lien",Y18="Tier 1 Split Lien",Y18="Tier 2 Split Lien"),DG18,0) | DO18: =DN18*DN$6 | DP18: =DG18-DO18 | DQ18: =IF(Y18="Second Lien",DP18,0) | DR18: =DQ18*DQ$6 | DS18: =DP18-DR18 | DT18: =IF(BH18="Yes",DS18,0) | DU18: =DT18*DT$6 | DV18: =DS18-DU18 | DW18: =IF(OR(BG18="Canada",BG18="United Kingdom",BG18="Australia",BG18="Netherlands Antilles",BG18="Bermuda",BG18="Cayman Islands",BG18="British Virgin Islands",BG18="Channel Islands",BG18="Isle of Man",BG18="Australia",BG18="Netherlands",BG18="Germany",BG18="Sweden",BG18="Switzerland",BG18="Austria",BG18="Belgium",BG18="Denmark",BG18="Finland",BG18="Iceland",BG18="Ireland",BG18="Lichtenstein",BG18="Luxemborg",BG18="Norway"),DV18,0) | DX18: =DW18*DW$6 | DY18: =DV18-DX18 | DZ18: =IF(BI18="Yes",DY18,0) | EA18: =DZ18*DZ$6 | EB18: =DY18-EA18 | EC18: =IF(OR(Z18="Delayed Draw",Z18="Revolver"),EB18,0) | ED18: =EC18*EC$6 | EE18: =EB18-ED18 | EF18: =IF(S18="Yes",EE18,0) | EG18: =EF18*EF$6 | EH18: =EE18-EG18 | EI18: =IF(Q18="Yes",EH18,0) | EJ18: =EI18*EI$6 | EK18: =EH18-EJ18 | EL18: =IF(BD18="Semi-Annually",EK18,0) | EM18: =EL18*EL$6 | EN18: =EK18-EM18 | EO18: =IF(BK18="Yes",EN18,0) | EP18: =EO18*EO$6 | EQ18: =EN18-EP18 | ER18: =IF(BL18="Yes",EQ18,0) | ES18: =ER18*ER$6 | ET18: =EQ18-ES18 | EU18: =IF(BM18="Yes",ET18,0) | EV18: =EU18*EU$6 | EW18: =ET18-EV18 | EX18: =IF(BV18="Yes",EW18,0) | EY18: =EX18*EX$6 | EZ18: =EW18-EY18 | FA18: =IF(AR18="Yes",EZ18,0) | FB18: =FA18*FA$6 | FC18: =EZ18-FB18 | FD18: =IF(OR(BF18="EUR",BF18="AUD",BF18="CAD",BF18="GBP"),FC18,0) | FE18: =FD18*FD$6 | FF18: =FC18-FE18 | FG18: =FF18 | FH18: =IF(FF18=0,0,VLOOKUP(C18,$GU$10:$GV$406,2,FALSE)*FF18) | FI18: =FF18-FH18 | FJ18: =FI18 | FK18: =IF(OR(IB18="",FI18<0.01),,VLOOKUP(IB18,$GL$10:$GM$406,2,FALSE)*FI18) | FL18: =FI18-FK18 | FM18: =FL18 | FN18: =IF(FL18=0,0,VLOOKUP(C18,$HD$10:$HE$406,2,FALSE)*FL18) | FO18: =FL18-FN18 | FP18: =IF(SUM(CY18:DC18)>0,0,IF(AND(AL18>=5000000,AL18<7500000),FO18,0)) | FQ18: =IF(B18="",0,FP18*FP$6*(1-$U18)) | FR18: =FO18-FQ18 | FS18: =IF(SUM(CY18:DC18)>0,0,IF(AL18<15000000,FR18,0)) | FT18: =IF(B18="",0,FS18*FS$6*(1-$U18)) | FU18: =FR18-FT18 | FV18: =IF(SUM(CY18:DC18)>0,0,IF(OR(AND(X18="No",AN18="Tier 1",AI18>$AG$3),AND(X18="No",AN18="Tier 2",AI18>$AH$3),AND(X18="No",AN18="Tier 3",AI18>$AI$3)),FU18,0)) | FW18: =IF(SUM(CY18:DC18)>0,0,IF(OR(AND(X18="No",AN18="Tier 1",AJ18>$AG$4),AND(X18="No",AN18="Tier 2",AJ18>$AH$4),AND(X18="No",AN18="Tier 3",AJ18>$AI$4)),FU18,0)) | FX18: =IF(SUM(CY18:DC18)>0,0,IF(OR(AND(X18="Yes",AN18="Tier 1",AJ18>$AG$5),AND(X18="Yes",AN18="Tier 2",AJ18>$AH$5),AND(X18="Yes",AN18="Tier 3",AJ18>$AI$5)),FU18,0)) | FY18: =IF(SUM(FV18:FX18)>0,FU18,0) | FZ18: =IF(B18="",0,FY18*FV$6*(1-MIN(90%,T18))) | GA18: =FU18-FZ18 | GB18: =IF(AND(N18="No",DI18=0),GA18,IF(AND(N18="No",DI18<>0,K18=0),0,IF(AND(N18="No",DI18<>0,K18>0,J18<>K18),MAX(0,M18-(DH18-GA18)),DG18))) | GC18: =+GB18*V18 | GD18: =IFERROR(GC18/K18,"") | GE18: =IF(IB18="","",IB18) | GF18: {=IF(SUM(IF(IB$9:IB17=IB18,1,0))>0,0,SUMIF($IB$10:$IB$406,IB18,$FI$10:$FI$406))} | GG18: =GF18 | GH18: =GH17+1 | GI18: =LARGE($GG$10:$GG$406,GH18) | GJ18: =IF(GH18>GH$6,0,IF(GH18=$GH$2,$GJ$2,IF(GH18<4,$GJ$3,$GJ$4))) | GK18: =MAX(0,GI18-GJ18) | GL18: {=IF(GI18=0,0,LARGE(IF($GF$10:$GF$406=GI18,$GE$10:$GE$406,0),COUNTIF($GI$10:$GI$406,GI18)-COUNTIF(GI$9:GI17,GI18)))} | GM18: =IF(GI18=0,0,GK18/GI18) | GO18: =IF(C18="","",IF(ISERROR(MATCH(C18,C$10:C17,0)),MAX(GO$10:GO17)+1,INDEX(GO$10:GO17,MATCH(C18,C$10:C17,0)))) | GP18: =IF(COUNTIF($A$10:A18,A18)<=1,SUMIF($A$10:$A$406,A18,$FG$10:$FG$406),0) | GQ18: =GQ17+1 | GR18: =LARGE($GP$10:$GP$406,GQ18) | GS18: =IF(GQ18>GQ$6,0,IF(GQ18<=GQ$2,GS$2,IF(AND(GQ18<=$GQ$3,GQ18>$GQ$2),GS$3,GS$4))) | GT18: =MAX(0,GR18-GS18) | GU18: {=IF(GR18=0,0,LARGE(IF($GP$10:$GP$406=GR18,$GO$10:$GO$406,0),COUNTIF($GR$10:$GR$406,GR18)-COUNTIF(GR$9:GR17,GR18)))} | GV18: =IF(GR18=0,0,GT18/GR18) | GX18: =IF(C18="","",IF(ISERROR(MATCH(C18,C$10:C17,0)),MAX(GO$10:GO17)+1,INDEX(GO$10:GO17,MATCH(C18,C$10:C17,0)))) | GY18: =IF(COUNTIF($A$10:A18,A18)<=1,SUMIF($A$10:$A$406,A18,$FG$10:$FG$406),0) | GZ18: =GZ17+1 | HA18: =LARGE($GY$10:$GY$406,GZ18) | HB18: - | HC18: =IF(GZ18<6,MAX(0,$HC$2/5),0) | HD18: {=IF(HA18=0,0,LARGE(IF($GY$10:$GY$406=HA18,$GX$10:$GX$406,0),COUNTIF($HA$10:$HA$406,HA18)-COUNTIF(HA$9:HA17,HA18)))} | HE18: =IF(HA18=0,0,HC18/HA18) | HG18: =DG18-GA18 | HH18: 0 | HI18: =MIN(HH18,DE18) | HK18: =IF(COUNTIF($C$10:$C$406,HK17+1),HK17+1,"") | HL18: =SUMIF($C$10:$C$406,HK18,$DG$10:$DG$406) | HN18: =MIN(HO18:HS18) | HO18: =IF(B18="","",$M18) | HP18: =IF($N18="Yes",IF(P18>=6,0,MIN($T18*$M18,$U18*$M18)),"") | HQ18: =IF(AND(N18="Yes",P18>=6),"",IF($S18="Yes",$R18*$M18,"")) | HR18: =IF($Q18="Yes",MIN($M18,$T18*$M18),"") | HS18: =IF(AND($N18="Yes",$P18>=6),"",IF(OR(CY18=1,DC18=1,),MIN($T18*$M18,$U18*$M18),IF(OR(CZ18=1,DA18=1,DB18=1),IF(AK18>=5000000,MIN($T18*$M18,$IE18*$M18),MIN($T18*$M18,$U18*$M18)),""))) | HT18: =IF(DD18>0,DD18,"") | HU18: =IF(B18="",0,$L18-$M18) | HV18: =IF(OR(SUM(HP18:HT18)>0,P18>=6),"",IF($B18="","",1)) | HW18: =IF(AND($HT18<>0,OR(HT18<=MIN(HP18:HS18),SUM(HP18:HS18)=0)),$HT18,0) | HX18: =IF(AND($HS18<>0,OR(AND($HS18<>$HT18,$HS18<>$HR18,$HS18<>$HQ18,$HS18<>$HP18,$HS18<MIN($HP18:$HR18),$HS18<HT18),SUM($HP18:$HR18)+SUM(HT18)=0),IA18<=0),$HS18,0) | HY18: =IF(AND($HR18<>0,OR(AND($HR18<>$HT18,$HR18<>$HS18,$HR18<>$HQ18,$HR18<>$HP18),$HR18<MIN($HP18:$HQ18),$HR18<MIN($HS18:$HT18),SUM($HP18:$HQ18)+SUM($HS18:$HT18)=0)),$HR18,0) | HZ18: =IF(AND($HQ18<>0,OR(AND($HQ18<>$HT18,HQ18<>HS18,HQ18<>HR18,HQ18<>HP18,HQ18<MIN(HR18:HT18)),SUM(HP18)+SUM(HR18:HT18)=0)),$HQ18,0) | IA18: =IF(AND($HP18<>0,OR(HP18<=MIN(HQ18:HT18),SUM(HQ18:HT18)=0)),$HP18,0) | IB18: 14 | IC18: =HU18=DF18 | IE18: =IF(B18="","",IF(AND(Y18="Second Lien",OR(CZ18=1,DA18=1,DB18=1)),50%,IF(CZ18=1,90%,IF(DA18=1,80%,IF(DB18=1,65%,"No Initial Haircut")))))
A19: =D19 | B19: =IF(D19="","",B18+1) | C19: =IF(COUNTIF($A$10:A18,A19)>0,C18,C18+1) | D19: Brightpath Holdings, LLC | E19: Brightpath (TL) | G19: 3661073.9 | H19: 3661073.9 | I19: 1 | J19: =IF(B19="","",G19*I19) | K19: =IF(B19="","",H19*I19) | L19: =IF(B19="","",IF(COUNTIF($CE19:$CX19,1)>0,0,J19)) | M19: =IF(B19="","",IF(COUNTIF($CE19:$CX19,1)>0,0,K19)) | N19: No | O19: N/A | P19: =IF(B19="","",IF(OR(O19="N/A",O19=""),0,YEARFRAC('Borrowing Base'!$J$4,'Loan List'!O19)*12)) | Q19: No | R19: 0.9838 | S19: =IF(B19="","",IF(R19<95%,"Yes","No")) | T19: 0.9775 | U19: =IF(B19="","",IF(OR(Y19="First Lien",Y19="Split First Lien",Y19="Tier 1 Split Lien",Y19="Tier 2 Split Lien"),50%,30%)) | V19: =IF(B19="",0,IF(AND(Y19="First Lien",AN19="Tier 1"),IF(AND(X19="Yes",MIN(AH19,$AJ$5)>4.5),(((4.5/MIN(AH19,$AJ$5))*72.5%)+(((MIN(AH19,$AJ$5)-4.5)/MIN(AH19,$AJ$5))*35%)),72.5%),IF(AND(Y19="First Lien",AN19="Tier 2"),IF(AND(X19="Yes",MIN(AH19,$AK$5)>4.5),(((4.5/MIN(AH19,$AK$5))*72.5%)+(((MIN(AH19,$AK$5)-4.5)/MIN(AH19,$AK$5))*35%)),72.5%),IF(AND(X19="Yes",MIN(AH19,$AL$5)>4),(((4/MIN(AH19,$AL$5))*72.5%)+(((MIN(AH19,$AL$5)-4)/MIN(AH19,$AL$5))*35%)),IF(OR(Y19="First Lien",Y19="Split First Lien"),72.5%,IF(Y19="Split Lien", 53%,35%)))))) | W19: =IF($C19="","",MIN($HO19:$HS19)) | X19: Yes | Y19: First Lien | Z19: Term | AA19: NR | AB19: NR | AC19: 1.8033708 | AD19: 5.1851852 | AE19: 5.7123927 | AF19: 0.58823529 | AG19: 5.1851852 | AH19: 5.1851852 | AI19: 5.7123927 | AJ19: 5.7123927 | AK19: 135000000 | AL19: 136895000 | AM19: 45747 | AN19: =IF(C19="","",(IF(AK19>=50000000,"Tier 1",(IF(OR(AK19>=20000000,AND(AK19>5000000,AC19>=1.25,AF19<=0.65)),"Tier 2","Tier 3"))))) | AO19: 47301 | AP19: 3.9222222 | AQ19: =IF(C19="","",AP19) | AR19: No | AS19: 0 | AT19: Yes | AU19: 0.01 | AV19: 0.0575 | AW19: 0.042956 | AX19: =IF(C19="","",MAX(AU19,AW19)) | AY19: 0 | AZ19: 0 | BA19: 0 | BB19: =IF(B19="","",IF(AR19="No",AV19-AZ19,"")) | BC19: =IF(B19="","",IF(AR19="Yes",AS19-BA19,"")) | BD19: Quarterly | BE19: Software | BF19: USD | BG19: United States | BH19: No | BI19: =IF(B19="","",IF(OR(AND(AZ19>0,BB19>=2.5%,BB19<4%),AND(BA19>0,BC19>=6%,BC19<8%)),"Yes","No")) | BJ19: =IF(B19="","",IF(OR(AND(AZ19>0,BB19<2.5%),AND(BA19>0,BC19<6%)),"Yes","No")) | BK19: No | BL19: No | BM19: No | BN19: No | BO19: No | BP19: No | BQ19: No | BR19: No | BS19: No | BT19: No | BU19: No | BV19: No | BW19: No | BX19: No | BY19: No | BZ19: No | CA19: Yes | CB19: =IF(B19="","",IF(AT19="No",((BB19+AW19)-$AZ$4),((BB19+AX19)-$AZ$4))*IF(DD19>0,0,M19)) | CC19: =IF(B19="","",AY19*(L19-M19)*IF(DD19>0,0,1)) | CE19: =IF(AND(B19<>"",R19<=85%),1,0) | CF19: =IF(B19="",0,(IF(OR(BF19="USD",BF19="CAD",BF19="GBP",BF19="AUD",BF19="EUR"),0,1))) | CG19: =IF(B19="",0,(IF(OR(BG19="United States",BG19="Canada",BG19="United Kingdom",BG19="Australia",BG19="Netherlands Antilles",BG19="Bermuda",BG19="Cayman Islands",BG19="British Virgin Islands",BG19="Channel Islands",BG19="Isle of Man",BG19="Australia",BG19="Netherlands",BG19="Germany",BG19="Sweden",BG19="Switzerland",BG19="Austria",BG19="Belgium",BG19="Denmark",BG19="Finland",BG19="Iceland",BG19="Ireland",BG19="Lichtenstein",BG19="Luxemborg",BG19="Norway"),0,1))) | CH19: =IF(BN19="Yes",1,0) | CI19: =IF(BO19="Yes",1,0) | CJ19: =IF(BP19="Yes",1,0) | CK19: =IF(BQ19="Yes",1,0) | CL19: =IF(BR19="Yes",1,0) | CM19: =IF(BS19="Yes",1,0) | CN19: =IF(OR(AND(BJ19="Yes",N19="No"),AND(BJ19="Yes",N19="Yes",P19>=6)),1,0) | CO19: =IF(BT19="Yes",1,0) | CP19: =IF(AND(BU19="Yes",BV19="No"),1,0) | CQ19: =IF(BW19="Yes",1,0) | CR19: =IF(AP19="",0,IF(AP19>7,1,0)) | CS19: =IF(OR(BD19<>"Monthly",BD19<>"Quarterly",BD19<>"Semi-Annually"),0,1) | CT19: =IF(BX19="Yes",1,0) | CU19: =IF(BY19="Yes",1,0) | CV19: =IF(BZ19="Yes",1,0) | CW19: =IF(CA19="No",1,0) | CX19: =IF(B19="",0,IF(AK19>=5000000,0,1)) | CY19: =IF(B19="",0,IF(AL19>=5000000,0,1)) | CZ19: =IF(OR(DA19=1,DB19=1,DC19=1),0,IF(B19="",0,IF(OR(AND(AN19="Tier 1",X19="No",OR(AI19>$AJ$3,AJ19>$AJ$4)),(AND(AN19="Tier 1",X19="Yes",AJ19>$AJ$5)),(AND(AN19="Tier 2",X19="No",OR(AI19>$AK$3,AJ19>$AK$4))),(AND(AN19="Tier 2",X19="Yes",AJ19>$AK$5)),(AND(AN19="Tier 3",X19="No",OR(AI19>$AL$3,AJ19>$AL$4))),(AND(AN19="Tier 3",X19="Yes",AJ19>$AL$5))),1,0))) | DA19: =IF(OR(DB19=1,DC19=1),0,IF(B19="",0,IF(OR(AND(AN19="Tier 1",X19="No",OR(AI19>$AM$3,AJ19>$AM$4)),(AND(AN19="Tier 1",X19="Yes",AJ19>$AM$5)),(AND(AN19="Tier 2",X19="No",OR(AI19>$AN$3,AJ19>$AN$4))),(AND(AN19="Tier 2",X19="Yes",AJ19>$AN$5)),(AND(AN19="Tier 3",X19="No",OR(AI19>$AO$3,AJ19>$AO$4))),(AND(AN19="Tier 3",X19="Yes",AJ19>$AO$5))),1,0))) | DB19: =IF(DC19=1,0,IF(B19="",0,IF(OR(AND(AN19="Tier 1",X19="No",OR(AI19>$AP$3,AJ19>$AP$4)),(AND(AN19="Tier 1",X19="Yes",AJ19>$AP$5)),(AND(AN19="Tier 2",X19="No",OR(AI19>$AQ$3,AJ19>$AQ$4))),(AND(AN19="Tier 2",X19="Yes",AJ19>$AQ$5)),(AND(AN19="Tier 3",X19="No",OR(AI19>$AR$3,AJ19>$AR$4))),(AND(AN19="Tier 3",X19="Yes",AJ19>$AR$5))),1,0))) | DC19: =IF(B19="",0,IF(OR(AND(AN19="Tier 1",X19="No",OR(AI19>$AS$3,AJ19>$AS$4)),(AND(AN19="Tier 1",X19="Yes",AJ19>$AS$5)),(AND(AN19="Tier 2",X19="No",OR(AI19>$AT$3,AJ19>$AT$4))),(AND(AN19="Tier 2",X19="Yes",AJ19>$AT$5)),(AND(AN19="Tier 3",X19="No",OR(AI19>$AU$3,AJ19>$AU$4))),(AND(AN19="Tier 3",X19="Yes",AJ19>$AU$5))),1,0)) | DD19: =IF((SUM(CE19:CX19)=0),0,W19) | DE19: =IF(OR(B19="",DD19>0),0,W19) | DF19: =IF(B19="",0,IF(COUNTIF(CE19:CX19,1)>0,0,L19-M19)) | DG19: =DE19+IF(DD19>0,0,DF19) | DH19: =IF(B19="","",M19+DF19) | DI19: =IF(B19="",0,J19-K19) | DJ19: =IF(OR(BF19="EUR",BF19="CAD",BF19="GBP",BF19="AUD"),(GA19*(1-V19))+(HG19)+IF(HX19="",0,HX19*(1-U19)),0) | DK19: =IF(BF19="EUR",33%,IF(BF19="CAD",38%,IF(BF19="GBP",51%,IF(BF19="AUD",61%,0)))) | DL19: =DJ19*DK19 | DN19: =IF(OR(Y19="Second Lien",Y19="Tier 1 Split Lien",Y19="Tier 2 Split Lien"),DG19,0) | DO19: =DN19*DN$6 | DP19: =DG19-DO19 | DQ19: =IF(Y19="Second Lien",DP19,0) | DR19: =DQ19*DQ$6 | DS19: =DP19-DR19 | DT19: =IF(BH19="Yes",DS19,0) | DU19: =DT19*DT$6 | DV19: =DS19-DU19 | DW19: =IF(OR(BG19="Canada",BG19="United Kingdom",BG19="Australia",BG19="Netherlands Antilles",BG19="Bermuda",BG19="Cayman Islands",BG19="British Virgin Islands",BG19="Channel Islands",BG19="Isle of Man",BG19="Australia",BG19="Netherlands",BG19="Germany",BG19="Sweden",BG19="Switzerland",BG19="Austria",BG19="Belgium",BG19="Denmark",BG19="Finland",BG19="Iceland",BG19="Ireland",BG19="Lichtenstein",BG19="Luxemborg",BG19="Norway"),DV19,0) | DX19: =DW19*DW$6 | DY19: =DV19-DX19 | DZ19: =IF(BI19="Yes",DY19,0) | EA19: =DZ19*DZ$6 | EB19: =DY19-EA19 | EC19: =IF(OR(Z19="Delayed Draw",Z19="Revolver"),EB19,0) | ED19: =EC19*EC$6 | EE19: =EB19-ED19 | EF19: =IF(S19="Yes",EE19,0) | EG19: =EF19*EF$6 | EH19: =EE19-EG19 | EI19: =IF(Q19="Yes",EH19,0) | EJ19: =EI19*EI$6 | EK19: =EH19-EJ19 | EL19: =IF(BD19="Semi-Annually",EK19,0) | EM19: =EL19*EL$6 | EN19: =EK19-EM19 | EO19: =IF(BK19="Yes",EN19,0) | EP19: =EO19*EO$6 | EQ19: =EN19-EP19 | ER19: =IF(BL19="Yes",EQ19,0) | ES19: =ER19*ER$6 | ET19: =EQ19-ES19 | EU19: =IF(BM19="Yes",ET19,0) | EV19: =EU19*EU$6 | EW19: =ET19-EV19 | EX19: =IF(BV19="Yes",EW19,0) | EY19: =EX19*EX$6 | EZ19: =EW19-EY19 | FA19: =IF(AR19="Yes",EZ19,0) | FB19: =FA19*FA$6 | FC19: =EZ19-FB19 | FD19: =IF(OR(BF19="EUR",BF19="AUD",BF19="CAD",BF19="GBP"),FC19,0) | FE19: =FD19*FD$6 | FF19: =FC19-FE19 | FG19: =FF19 | FH19: =IF(FF19=0,0,VLOOKUP(C19,$GU$10:$GV$406,2,FALSE)*FF19) | FI19: =FF19-FH19 | FJ19: =FI19 | FK19: =IF(OR(IB19="",FI19<0.01),,VLOOKUP(IB19,$GL$10:$GM$406,2,FALSE)*FI19) | FL19: =FI19-FK19 | FM19: =FL19 | FN19: =IF(FL19=0,0,VLOOKUP(C19,$HD$10:$HE$406,2,FALSE)*FL19) | FO19: =FL19-FN19 | FP19: =IF(SUM(CY19:DC19)>0,0,IF(AND(AL19>=5000000,AL19<7500000),FO19,0)) | FQ19: =IF(B19="",0,FP19*FP$6*(1-$U19)) | FR19: =FO19-FQ19 | FS19: =IF(SUM(CY19:DC19)>0,0,IF(AL19<15000000,FR19,0)) | FT19: =IF(B19="",0,FS19*FS$6*(1-$U19)) | FU19: =FR19-FT19 | FV19: =IF(SUM(CY19:DC19)>0,0,IF(OR(AND(X19="No",AN19="Tier 1",AI19>$AG$3),AND(X19="No",AN19="Tier 2",AI19>$AH$3),AND(X19="No",AN19="Tier 3",AI19>$AI$3)),FU19,0)) | FW19: =IF(SUM(CY19:DC19)>0,0,IF(OR(AND(X19="No",AN19="Tier 1",AJ19>$AG$4),AND(X19="No",AN19="Tier 2",AJ19>$AH$4),AND(X19="No",AN19="Tier 3",AJ19>$AI$4)),FU19,0)) | FX19: =IF(SUM(CY19:DC19)>0,0,IF(OR(AND(X19="Yes",AN19="Tier 1",AJ19>$AG$5),AND(X19="Yes",AN19="Tier 2",AJ19>$AH$5),AND(X19="Yes",AN19="Tier 3",AJ19>$AI$5)),FU19,0)) | FY19: =IF(SUM(FV19:FX19)>0,FU19,0) | FZ19: =IF(B19="",0,FY19*FV$6*(1-MIN(90%,T19))) | GA19: =FU19-FZ19 | GB19: =IF(AND(N19="No",DI19=0),GA19,IF(AND(N19="No",DI19<>0,K19=0),0,IF(AND(N19="No",DI19<>0,K19>0,J19<>K19),MAX(0,M19-(DH19-GA19)),DG19))) | GC19: =+GB19*V19 | GD19: =IFERROR(GC19/K19,"") | GE19: =IF(IB19="","",IB19) | GF19: {=IF(SUM(IF(IB$9:IB18=IB19,1,0))>0,0,SUMIF($IB$10:$IB$406,IB19,$FI$10:$FI$406))} | GG19: =GF19 | GH19: =GH18+1 | GI19: =LARGE($GG$10:$GG$406,GH19) | GJ19: =IF(GH19>GH$6,0,IF(GH19=$GH$2,$GJ$2,IF(GH19<4,$GJ$3,$GJ$4))) | GK19: =MAX(0,GI19-GJ19) | GL19: {=IF(GI19=0,0,LARGE(IF($GF$10:$GF$406=GI19,$GE$10:$GE$406,0),COUNTIF($GI$10:$GI$406,GI19)-COUNTIF(GI$9:GI18,GI19)))} | GM19: =IF(GI19=0,0,GK19/GI19) | GO19: =IF(C19="","",IF(ISERROR(MATCH(C19,C$10:C18,0)),MAX(GO$10:GO18)+1,INDEX(GO$10:GO18,MATCH(C19,C$10:C18,0)))) | GP19: =IF(COUNTIF($A$10:A19,A19)<=1,SUMIF($A$10:$A$406,A19,$FG$10:$FG$406),0) | GQ19: =GQ18+1 | GR19: =LARGE($GP$10:$GP$406,GQ19) | GS19: =IF(GQ19>GQ$6,0,IF(GQ19<=GQ$2,GS$2,IF(AND(GQ19<=$GQ$3,GQ19>$GQ$2),GS$3,GS$4))) | GT19: =MAX(0,GR19-GS19) | GU19: {=IF(GR19=0,0,LARGE(IF($GP$10:$GP$406=GR19,$GO$10:$GO$406,0),COUNTIF($GR$10:$GR$406,GR19)-COUNTIF(GR$9:GR18,GR19)))} | GV19: =IF(GR19=0,0,GT19/GR19) | GX19: =IF(C19="","",IF(ISERROR(MATCH(C19,C$10:C18,0)),MAX(GO$10:GO18)+1,INDEX(GO$10:GO18,MATCH(C19,C$10:C18,0)))) | GY19: =IF(COUNTIF($A$10:A19,A19)<=1,SUMIF($A$10:$A$406,A19,$FG$10:$FG$406),0) | GZ19: =GZ18+1 | HA19: =LARGE($GY$10:$GY$406,GZ19) | HB19: - | HC19: =IF(GZ19<6,MAX(0,$HC$2/5),0) | HD19: {=IF(HA19=0,0,LARGE(IF($GY$10:$GY$406=HA19,$GX$10:$GX$406,0),COUNTIF($HA$10:$HA$406,HA19)-COUNTIF(HA$9:HA18,HA19)))} | HE19: =IF(HA19=0,0,HC19/HA19) | HG19: =DG19-GA19 | HH19: 0 | HI19: =MIN(HH19,DE19) | HK19: =IF(COUNTIF($C$10:$C$406,HK18+1),HK18+1,"") | HL19: =SUMIF($C$10:$C$406,HK19,$DG$10:$DG$406) | HN19: =MIN(HO19:HS19) | HO19: =IF(B19="","",$M19) | HP19: =IF($N19="Yes",IF(P19>=6,0,MIN($T19*$M19,$U19*$M19)),"") | HQ19: =IF(AND(N19="Yes",P19>=6),"",IF($S19="Yes",$R19*$M19,"")) | HR19: =IF($Q19="Yes",MIN($M19,$T19*$M19),"") | HS19: =IF(AND($N19="Yes",$P19>=6),"",IF(OR(CY19=1,DC19=1,),MIN($T19*$M19,$U19*$M19),IF(OR(CZ19=1,DA19=1,DB19=1),IF(AK19>=5000000,MIN($T19*$M19,$IE19*$M19),MIN($T19*$M19,$U19*$M19)),""))) | HT19: =IF(DD19>0,DD19,"") | HU19: =IF(B19="",0,$L19-$M19) | HV19: =IF(OR(SUM(HP19:HT19)>0,P19>=6),"",IF($B19="","",1)) | HW19: =IF(AND($HT19<>0,OR(HT19<=MIN(HP19:HS19),SUM(HP19:HS19)=0)),$HT19,0) | HX19: =IF(AND($HS19<>0,OR(AND($HS19<>$HT19,$HS19<>$HR19,$HS19<>$HQ19,$HS19<>$HP19,$HS19<MIN($HP19:$HR19),$HS19<HT19),SUM($HP19:$HR19)+SUM(HT19)=0),IA19<=0),$HS19,0) | HY19: =IF(AND($HR19<>0,OR(AND($HR19<>$HT19,$HR19<>$HS19,$HR19<>$HQ19,$HR19<>$HP19),$HR19<MIN($HP19:$HQ19),$HR19<MIN($HS19:$HT19),SUM($HP19:$HQ19)+SUM($HS19:$HT19)=0)),$HR19,0) | HZ19: =IF(AND($HQ19<>0,OR(AND($HQ19<>$HT19,HQ19<>HS19,HQ19<>HR19,HQ19<>HP19,HQ19<MIN(HR19:HT19)),SUM(HP19)+SUM(HR19:HT19)=0)),$HQ19,0) | IA19: =IF(AND($HP19<>0,OR(HP19<=MIN(HQ19:HT19),SUM(HQ19:HT19)=0)),$HP19,0) | IB19: 59 | IC19: =HU19=DF19 | IE19: =IF(B19="","",IF(AND(Y19="Second Lien",OR(CZ19=1,DA19=1,DB19=1)),50%,IF(CZ19=1,90%,IF(DA19=1,80%,IF(DB19=1,65%,"No Initial Haircut")))))
A20: =D20 | B20: =IF(D20="","",B19+1) | C20: =IF(COUNTIF($A$10:A19,A20)>0,C19,C19+1) | D20: Summit Holdings, LLC | E20: Summit (Term Loan) | G20: 2954760.7 | H20: 2954760.7 | I20: 1 | J20: =IF(B20="","",G20*I20) | K20: =IF(B20="","",H20*I20) | L20: =IF(B20="","",IF(COUNTIF($CE20:$CX20,1)>0,0,J20)) | M20: =IF(B20="","",IF(COUNTIF($CE20:$CX20,1)>0,0,K20)) | N20: No | O20: N/A | P20: =IF(B20="","",IF(OR(O20="N/A",O20=""),0,YEARFRAC('Borrowing Base'!$J$4,'Loan List'!O20)*12)) | Q20: No | R20: 0.98838429 | S20: =IF(B20="","",IF(R20<95%,"Yes","No")) | T20: 1 | U20: =IF(B20="","",IF(OR(Y20="First Lien",Y20="Split First Lien",Y20="Tier 1 Split Lien",Y20="Tier 2 Split Lien"),50%,30%)) | V20: =IF(B20="",0,IF(AND(Y20="First Lien",AN20="Tier 1"),IF(AND(X20="Yes",MIN(AH20,$AJ$5)>4.5),(((4.5/MIN(AH20,$AJ$5))*72.5%)+(((MIN(AH20,$AJ$5)-4.5)/MIN(AH20,$AJ$5))*35%)),72.5%),IF(AND(Y20="First Lien",AN20="Tier 2"),IF(AND(X20="Yes",MIN(AH20,$AK$5)>4.5),(((4.5/MIN(AH20,$AK$5))*72.5%)+(((MIN(AH20,$AK$5)-4.5)/MIN(AH20,$AK$5))*35%)),72.5%),IF(AND(X20="Yes",MIN(AH20,$AL$5)>4),(((4/MIN(AH20,$AL$5))*72.5%)+(((MIN(AH20,$AL$5)-4)/MIN(AH20,$AL$5))*35%)),IF(OR(Y20="First Lien",Y20="Split First Lien"),72.5%,IF(Y20="Split Lien", 53%,35%)))))) | W20: =IF($C20="","",MIN($HO20:$HS20)) | X20: No | Y20: First Lien | Z20: Term | AA20: NR | AB20: NR | AC20: 0.93017378 | AD20: 4.1373071 | AE20: 3.9429105 | AF20: 0.26661656 | AG20: 4.1373071 | AH20: 4.1373071 | AI20: 3.9429105 | AJ20: 3.9429105 | AK20: 10888000 | AL20: 14539723 | AM20: 45808 | AN20: =IF(C20="","",(IF(AK20>=50000000,"Tier 1",(IF(OR(AK20>=20000000,AND(AK20>5000000,AC20>=1.25,AF20<=0.65)),"Tier 2","Tier 3"))))) | AO20: 47807 | AP20: 5.3055556 | AQ20: =IF(C20="","",AP20) | AR20: No | AS20: 0 | AT20: Yes | AU20: 0.01 | AV20: 0.045 | AW20: 0.042956 | AX20: =IF(C20="","",MAX(AU20,AW20)) | AY20: 0 | AZ20: 0 | BA20: 0 | BB20: =IF(B20="","",IF(AR20="No",AV20-AZ20,"")) | BC20: =IF(B20="","",IF(AR20="Yes",AS20-BA20,"")) | BD20: Quarterly | BE20: Professional Services | BF20: USD | BG20: United States | BH20: No | BI20: =IF(B20="","",IF(OR(AND(AZ20>0,BB20>=2.5%,BB20<4%),AND(BA20>0,BC20>=6%,BC20<8%)),"Yes","No")) | BJ20: =IF(B20="","",IF(OR(AND(AZ20>0,BB20<2.5%),AND(BA20>0,BC20<6%)),"Yes","No")) | BK20: No | BL20: No | BM20: No | BN20: No | BO20: No | BP20: No | BQ20: No | BR20: No | BS20: No | BT20: No | BU20: No | BV20: No | BW20: No | BX20: No | BY20: No | BZ20: No | CA20: Yes | CB20: =IF(B20="","",IF(AT20="No",((BB20+AW20)-$AZ$4),((BB20+AX20)-$AZ$4))*IF(DD20>0,0,M20)) | CC20: =IF(B20="","",AY20*(L20-M20)*IF(DD20>0,0,1)) | CE20: =IF(AND(B20<>"",R20<=85%),1,0) | CF20: =IF(B20="",0,(IF(OR(BF20="USD",BF20="CAD",BF20="GBP",BF20="AUD",BF20="EUR"),0,1))) | CG20: =IF(B20="",0,(IF(OR(BG20="United States",BG20="Canada",BG20="United Kingdom",BG20="Australia",BG20="Netherlands Antilles",BG20="Bermuda",BG20="Cayman Islands",BG20="British Virgin Islands",BG20="Channel Islands",BG20="Isle of Man",BG20="Australia",BG20="Netherlands",BG20="Germany",BG20="Sweden",BG20="Switzerland",BG20="Austria",BG20="Belgium",BG20="Denmark",BG20="Finland",BG20="Iceland",BG20="Ireland",BG20="Lichtenstein",BG20="Luxemborg",BG20="Norway"),0,1))) | CH20: =IF(BN20="Yes",1,0) | CI20: =IF(BO20="Yes",1,0) | CJ20: =IF(BP20="Yes",1,0) | CK20: =IF(BQ20="Yes",1,0) | CL20: =IF(BR20="Yes",1,0) | CM20: =IF(BS20="Yes",1,0) | CN20: =IF(OR(AND(BJ20="Yes",N20="No"),AND(BJ20="Yes",N20="Yes",P20>=6)),1,0) | CO20: =IF(BT20="Yes",1,0) | CP20: =IF(AND(BU20="Yes",BV20="No"),1,0) | CQ20: =IF(BW20="Yes",1,0) | CR20: =IF(AP20="",0,IF(AP20>7,1,0)) | CS20: =IF(OR(BD20<>"Monthly",BD20<>"Quarterly",BD20<>"Semi-Annually"),0,1) | CT20: =IF(BX20="Yes",1,0) | CU20: =IF(BY20="Yes",1,0) | CV20: =IF(BZ20="Yes",1,0) | CW20: =IF(CA20="No",1,0) | CX20: =IF(B20="",0,IF(AK20>=5000000,0,1)) | CY20: =IF(B20="",0,IF(AL20>=5000000,0,1)) | CZ20: =IF(OR(DA20=1,DB20=1,DC20=1),0,IF(B20="",0,IF(OR(AND(AN20="Tier 1",X20="No",OR(AI20>$AJ$3,AJ20>$AJ$4)),(AND(AN20="Tier 1",X20="Yes",AJ20>$AJ$5)),(AND(AN20="Tier 2",X20="No",OR(AI20>$AK$3,AJ20>$AK$4))),(AND(AN20="Tier 2",X20="Yes",AJ20>$AK$5)),(AND(AN20="Tier 3",X20="No",OR(AI20>$AL$3,AJ20>$AL$4))),(AND(AN20="Tier 3",X20="Yes",AJ20>$AL$5))),1,0))) | DA20: =IF(OR(DB20=1,DC20=1),0,IF(B20="",0,IF(OR(AND(AN20="Tier 1",X20="No",OR(AI20>$AM$3,AJ20>$AM$4)),(AND(AN20="Tier 1",X20="Yes",AJ20>$AM$5)),(AND(AN20="Tier 2",X20="No",OR(AI20>$AN$3,AJ20>$AN$4))),(AND(AN20="Tier 2",X20="Yes",AJ20>$AN$5)),(AND(AN20="Tier 3",X20="No",OR(AI20>$AO$3,AJ20>$AO$4))),(AND(AN20="Tier 3",X20="Yes",AJ20>$AO$5))),1,0))) | DB20: =IF(DC20=1,0,IF(B20="",0,IF(OR(AND(AN20="Tier 1",X20="No",OR(AI20>$AP$3,AJ20>$AP$4)),(AND(AN20="Tier 1",X20="Yes",AJ20>$AP$5)),(AND(AN20="Tier 2",X20="No",OR(AI20>$AQ$3,AJ20>$AQ$4))),(AND(AN20="Tier 2",X20="Yes",AJ20>$AQ$5)),(AND(AN20="Tier 3",X20="No",OR(AI20>$AR$3,AJ20>$AR$4))),(AND(AN20="Tier 3",X20="Yes",AJ20>$AR$5))),1,0))) | DC20: =IF(B20="",0,IF(OR(AND(AN20="Tier 1",X20="No",OR(AI20>$AS$3,AJ20>$AS$4)),(AND(AN20="Tier 1",X20="Yes",AJ20>$AS$5)),(AND(AN20="Tier 2",X20="No",OR(AI20>$AT$3,AJ20>$AT$4))),(AND(AN20="Tier 2",X20="Yes",AJ20>$AT$5)),(AND(AN20="Tier 3",X20="No",OR(AI20>$AU$3,AJ20>$AU$4))),(AND(AN20="Tier 3",X20="Yes",AJ20>$AU$5))),1,0)) | DD20: =IF((SUM(CE20:CX20)=0),0,W20) | DE20: =IF(OR(B20="",DD20>0),0,W20) | DF20: =IF(B20="",0,IF(COUNTIF(CE20:CX20,1)>0,0,L20-M20)) | DG20: =DE20+IF(DD20>0,0,DF20) | DH20: =IF(B20="","",M20+DF20) | DI20: =IF(B20="",0,J20-K20) | DJ20: =IF(OR(BF20="EUR",BF20="CAD",BF20="GBP",BF20="AUD"),(GA20*(1-V20))+(HG20)+IF(HX20="",0,HX20*(1-U20)),0) | DK20: =IF(BF20="EUR",33%,IF(BF20="CAD",38%,IF(BF20="GBP",51%,IF(BF20="AUD",61%,0)))) | DL20: =DJ20*DK20 | DN20: =IF(OR(Y20="Second Lien",Y20="Tier 1 Split Lien",Y20="Tier 2 Split Lien"),DG20,0) | DO20: =DN20*DN$6 | DP20: =DG20-DO20 | DQ20: =IF(Y20="Second Lien",DP20,0) | DR20: =DQ20*DQ$6 | DS20: =DP20-DR20 | DT20: =IF(BH20="Yes",DS20,0) | DU20: =DT20*DT$6 | DV20: =DS20-DU20 | DW20: =IF(OR(BG20="Canada",BG20="United Kingdom",BG20="Australia",BG20="Netherlands Antilles",BG20="Bermuda",BG20="Cayman Islands",BG20="British Virgin Islands",BG20="Channel Islands",BG20="Isle of Man",BG20="Australia",BG20="Netherlands",BG20="Germany",BG20="Sweden",BG20="Switzerland",BG20="Austria",BG20="Belgium",BG20="Denmark",BG20="Finland",BG20="Iceland",BG20="Ireland",BG20="Lichtenstein",BG20="Luxemborg",BG20="Norway"),DV20,0) | DX20: =DW20*DW$6 | DY20: =DV20-DX20 | DZ20: =IF(BI20="Yes",DY20,0) | EA20: =DZ20*DZ$6 | EB20: =DY20-EA20 | EC20: =IF(OR(Z20="Delayed Draw",Z20="Revolver"),EB20,0) | ED20: =EC20*EC$6 | EE20: =EB20-ED20 | EF20: =IF(S20="Yes",EE20,0) | EG20: =EF20*EF$6 | EH20: =EE20-EG20 | EI20: =IF(Q20="Yes",EH20,0) | EJ20: =EI20*EI$6 | EK20: =EH20-EJ20 | EL20: =IF(BD20="Semi-Annually",EK20,0) | EM20: =EL20*EL$6 | EN20: =EK20-EM20 | EO20: =IF(BK20="Yes",EN20,0) | EP20: =EO20*EO$6 | EQ20: =EN20-EP20 | ER20: =IF(BL20="Yes",EQ20,0) | ES20: =ER20*ER$6 | ET20: =EQ20-ES20 | EU20: =IF(BM20="Yes",ET20,0) | EV20: =EU20*EU$6 | EW20: =ET20-EV20 | EX20: =IF(BV20="Yes",EW20,0) | EY20: =EX20*EX$6 | EZ20: =EW20-EY20 | FA20: =IF(AR20="Yes",EZ20,0) | FB20: =FA20*FA$6 | FC20: =EZ20-FB20 | FD20: =IF(OR(BF20="EUR",BF20="AUD",BF20="CAD",BF20="GBP"),FC20,0) | FE20: =FD20*FD$6 | FF20: =FC20-FE20 | FG20: =FF20 | FH20: =IF(FF20=0,0,VLOOKUP(C20,$GU$10:$GV$406,2,FALSE)*FF20) | FI20: =FF20-FH20 | FJ20: =FI20 | FK20: =IF(OR(IB20="",FI20<0.01),,VLOOKUP(IB20,$GL$10:$GM$406,2,FALSE)*FI20) | FL20: =FI20-FK20 | FM20: =FL20 | FN20: =IF(FL20=0,0,VLOOKUP(C20,$HD$10:$HE$406,2,FALSE)*FL20) | FO20: =FL20-FN20 | FP20: =IF(SUM(CY20:DC20)>0,0,IF(AND(AL20>=5000000,AL20<7500000),FO20,0)) | FQ20: =IF(B20="",0,FP20*FP$6*(1-$U20)) | FR20: =FO20-FQ20 | FS20: =IF(SUM(CY20:DC20)>0,0,IF(AL20<15000000,FR20,0)) | FT20: =IF(B20="",0,FS20*FS$6*(1-$U20)) | FU20: =FR20-FT20 | FV20: =IF(SUM(CY20:DC20)>0,0,IF(OR(AND(X20="No",AN20="Tier 1",AI20>$AG$3),AND(X20="No",AN20="Tier 2",AI20>$AH$3),AND(X20="No",AN20="Tier 3",AI20>$AI$3)),FU20,0)) | FW20: =IF(SUM(CY20:DC20)>0,0,IF(OR(AND(X20="No",AN20="Tier 1",AJ20>$AG$4),AND(X20="No",AN20="Tier 2",AJ20>$AH$4),AND(X20="No",AN20="Tier 3",AJ20>$AI$4)),FU20,0)) | FX20: =IF(SUM(CY20:DC20)>0,0,IF(OR(AND(X20="Yes",AN20="Tier 1",AJ20>$AG$5),AND(X20="Yes",AN20="Tier 2",AJ20>$AH$5),AND(X20="Yes",AN20="Tier 3",AJ20>$AI$5)),FU20,0)) | FY20: =IF(SUM(FV20:FX20)>0,FU20,0) | FZ20: =IF(B20="",0,FY20*FV$6*(1-MIN(90%,T20))) | GA20: =FU20-FZ20 | GB20: =IF(AND(N20="No",DI20=0),GA20,IF(AND(N20="No",DI20<>0,K20=0),0,IF(AND(N20="No",DI20<>0,K20>0,J20<>K20),MAX(0,M20-(DH20-GA20)),DG20))) | GC20: =+GB20*V20 | GD20: =IFERROR(GC20/K20,"") | GE20: =IF(IB20="","",IB20) | GF20: {=IF(SUM(IF(IB$9:IB19=IB20,1,0))>0,0,SUMIF($IB$10:$IB$406,IB20,$FI$10:$FI$406))} | GG20: =GF20 | GH20: =GH19+1 | GI20: =LARGE($GG$10:$GG$406,GH20) | GJ20: =IF(GH20>GH$6,0,IF(GH20=$GH$2,$GJ$2,IF(GH20<4,$GJ$3,$GJ$4))) | GK20: =MAX(0,GI20-GJ20) | GL20: {=IF(GI20=0,0,LARGE(IF($GF$10:$GF$406=GI20,$GE$10:$GE$406,0),COUNTIF($GI$10:$GI$406,GI20)-COUNTIF(GI$9:GI19,GI20)))} | GM20: =IF(GI20=0,0,GK20/GI20) | GO20: =IF(C20="","",IF(ISERROR(MATCH(C20,C$10:C19,0)),MAX(GO$10:GO19)+1,INDEX(GO$10:GO19,MATCH(C20,C$10:C19,0)))) | GP20: =IF(COUNTIF($A$10:A20,A20)<=1,SUMIF($A$10:$A$406,A20,$FG$10:$FG$406),0) | GQ20: =GQ19+1 | GR20: =LARGE($GP$10:$GP$406,GQ20) | GS20: =IF(GQ20>GQ$6,0,IF(GQ20<=GQ$2,GS$2,IF(AND(GQ20<=$GQ$3,GQ20>$GQ$2),GS$3,GS$4))) | GT20: =MAX(0,GR20-GS20) | GU20: {=IF(GR20=0,0,LARGE(IF($GP$10:$GP$406=GR20,$GO$10:$GO$406,0),COUNTIF($GR$10:$GR$406,GR20)-COUNTIF(GR$9:GR19,GR20)))} | GV20: =IF(GR20=0,0,GT20/GR20) | GX20: =IF(C20="","",IF(ISERROR(MATCH(C20,C$10:C19,0)),MAX(GO$10:GO19)+1,INDEX(GO$10:GO19,MATCH(C20,C$10:C19,0)))) | GY20: =IF(COUNTIF($A$10:A20,A20)<=1,SUMIF($A$10:$A$406,A20,$FG$10:$FG$406),0) | GZ20: =GZ19+1 | HA20: =LARGE($GY$10:$GY$406,GZ20) | HB20: - | HC20: =IF(GZ20<6,MAX(0,$HC$2/5),0) | HD20: {=IF(HA20=0,0,LARGE(IF($GY$10:$GY$406=HA20,$GX$10:$GX$406,0),COUNTIF($HA$10:$HA$406,HA20)-COUNTIF(HA$9:HA19,HA20)))} | HE20: =IF(HA20=0,0,HC20/HA20) | HG20: =DG20-GA20 | HH20: 0 | HI20: =MIN(HH20,DE20) | HK20: =IF(COUNTIF($C$10:$C$406,HK19+1),HK19+1,"") | HL20: =SUMIF($C$10:$C$406,HK20,$DG$10:$DG$406) | HN20: =MIN(HO20:HS20) | HO20: =IF(B20="","",$M20) | HP20: =IF($N20="Yes",IF(P20>=6,0,MIN($T20*$M20,$U20*$M20)),"") | HQ20: =IF(AND(N20="Yes",P20>=6),"",IF($S20="Yes",$R20*$M20,"")) | HR20: =IF($Q20="Yes",MIN($M20,$T20*$M20),"") | HS20: =IF(AND($N20="Yes",$P20>=6),"",IF(OR(CY20=1,DC20=1,),MIN($T20*$M20,$U20*$M20),IF(OR(CZ20=1,DA20=1,DB20=1),IF(AK20>=5000000,MIN($T20*$M20,$IE20*$M20),MIN($T20*$M20,$U20*$M20)),""))) | HT20: =IF(DD20>0,DD20,"") | HU20: =IF(B20="",0,$L20-$M20) | HV20: =IF(OR(SUM(HP20:HT20)>0,P20>=6),"",IF($B20="","",1)) | HW20: =IF(AND($HT20<>0,OR(HT20<=MIN(HP20:HS20),SUM(HP20:HS20)=0)),$HT20,0) | HX20: =IF(AND($HS20<>0,OR(AND($HS20<>$HT20,$HS20<>$HR20,$HS20<>$HQ20,$HS20<>$HP20,$HS20<MIN($HP20:$HR20),$HS20<HT20),SUM($HP20:$HR20)+SUM(HT20)=0),IA20<=0),$HS20,0) | HY20: =IF(AND($HR20<>0,OR(AND($HR20<>$HT20,$HR20<>$HS20,$HR20<>$HQ20,$HR20<>$HP20),$HR20<MIN($HP20:$HQ20),$HR20<MIN($HS20:$HT20),SUM($HP20:$HQ20)+SUM($HS20:$HT20)=0)),$HR20,0) | HZ20: =IF(AND($HQ20<>0,OR(AND($HQ20<>$HT20,HQ20<>HS20,HQ20<>HR20,HQ20<>HP20,HQ20<MIN(HR20:HT20)),SUM(HP20)+SUM(HR20:HT20)=0)),$HQ20,0) | IA20: =IF(AND($HP20<>0,OR(HP20<=MIN(HQ20:HT20),SUM(HQ20:HT20)=0)),$HP20,0) | IB20: 55 | IC20: =HU20=DF20 | IE20: =IF(B20="","",IF(AND(Y20="Second Lien",OR(CZ20=1,DA20=1,DB20=1)),50%,IF(CZ20=1,90%,IF(DA20=1,80%,IF(DB20=1,65%,"No Initial Haircut")))))
A21: =D21 | B21: =IF(D21="","",B20+1) | C21: =IF(COUNTIF($A$10:A20,A21)>0,C20,C20+1) | D21: Riverbend Holdings, LLC | E21: Riverbend (Term Loan) | G21: 5882906.3 | H21: 5882906.3 | I21: 1 | J21: =IF(B21="","",G21*I21) | K21: =IF(B21="","",H21*I21) | L21: =IF(B21="","",IF(COUNTIF($CE21:$CX21,1)>0,0,J21)) | M21: =IF(B21="","",IF(COUNTIF($CE21:$CX21,1)>0,0,K21)) | N21: No | O21: N/A | P21: =IF(B21="","",IF(OR(O21="N/A",O21=""),0,YEARFRAC('Borrowing Base'!$J$4,'Loan List'!O21)*12)) | Q21: No | R21: 0.9925 | S21: =IF(B21="","",IF(R21<95%,"Yes","No")) | T21: 1 | U21: =IF(B21="","",IF(OR(Y21="First Lien",Y21="Split First Lien",Y21="Tier 1 Split Lien",Y21="Tier 2 Split Lien"),50%,30%)) | V21: =IF(B21="",0,IF(AND(Y21="First Lien",AN21="Tier 1"),IF(AND(X21="Yes",MIN(AH21,$AJ$5)>4.5),(((4.5/MIN(AH21,$AJ$5))*72.5%)+(((MIN(AH21,$AJ$5)-4.5)/MIN(AH21,$AJ$5))*35%)),72.5%),IF(AND(Y21="First Lien",AN21="Tier 2"),IF(AND(X21="Yes",MIN(AH21,$AK$5)>4.5),(((4.5/MIN(AH21,$AK$5))*72.5%)+(((MIN(AH21,$AK$5)-4.5)/MIN(AH21,$AK$5))*35%)),72.5%),IF(AND(X21="Yes",MIN(AH21,$AL$5)>4),(((4/MIN(AH21,$AL$5))*72.5%)+(((MIN(AH21,$AL$5)-4)/MIN(AH21,$AL$5))*35%)),IF(OR(Y21="First Lien",Y21="Split First Lien"),72.5%,IF(Y21="Split Lien", 53%,35%)))))) | W21: =IF($C21="","",MIN($HO21:$HS21)) | X21: No | Y21: First Lien | Z21: Term | AA21: NR | AB21: NR | AC21: 1.8983182 | AD21: 4.1112872 | AE21: 3.1753383 | AF21: 0.41798846 | AG21: 4.1112872 | AH21: 4.1112872 | AI21: 3.1753383 | AJ21: 3.1753383 | AK21: 10147000 | AL21: 12189228 | AM21: 45838 | AN21: =IF(C21="","",(IF(AK21>=50000000,"Tier 1",(IF(OR(AK21>=20000000,AND(AK21>5000000,AC21>=1.25,AF21<=0.65)),"Tier 2","Tier 3"))))) | AO21: 47844 | AP21: 5.4083333 | AQ21: =IF(C21="","",AP21) | AR21: No | AS21: 0 | AT21: Yes | AU21: 0.01 | AV21: 0.05 | AW21: 0.04317 | AX21: =IF(C21="","",MAX(AU21,AW21)) | AY21: 0 | AZ21: 0 | BA21: 0 | BB21: =IF(B21="","",IF(AR21="No",AV21-AZ21,"")) | BC21: =IF(B21="","",IF(AR21="Yes",AS21-BA21,"")) | BD21: Quarterly | BE21: Industrial Conglomerates | BF21: USD | BG21: United States | BH21: No | BI21: =IF(B21="","",IF(OR(AND(AZ21>0,BB21>=2.5%,BB21<4%),AND(BA21>0,BC21>=6%,BC21<8%)),"Yes","No")) | BJ21: =IF(B21="","",IF(OR(AND(AZ21>0,BB21<2.5%),AND(BA21>0,BC21<6%)),"Yes","No")) | BK21: No | BL21: No | BM21: No | BN21: No | BO21: No | BP21: No | BQ21: No | BR21: No | BS21: No | BT21: No | BU21: No | BV21: No | BW21: No | BX21: No | BY21: No | BZ21: No | CA21: Yes | CB21: =IF(B21="","",IF(AT21="No",((BB21+AW21)-$AZ$4),((BB21+AX21)-$AZ$4))*IF(DD21>0,0,M21)) | CC21: =IF(B21="","",AY21*(L21-M21)*IF(DD21>0,0,1)) | CE21: =IF(AND(B21<>"",R21<=85%),1,0) | CF21: =IF(B21="",0,(IF(OR(BF21="USD",BF21="CAD",BF21="GBP",BF21="AUD",BF21="EUR"),0,1))) | CG21: =IF(B21="",0,(IF(OR(BG21="United States",BG21="Canada",BG21="United Kingdom",BG21="Australia",BG21="Netherlands Antilles",BG21="Bermuda",BG21="Cayman Islands",BG21="British Virgin Islands",BG21="Channel Islands",BG21="Isle of Man",BG21="Australia",BG21="Netherlands",BG21="Germany",BG21="Sweden",BG21="Switzerland",BG21="Austria",BG21="Belgium",BG21="Denmark",BG21="Finland",BG21="Iceland",BG21="Ireland",BG21="Lichtenstein",BG21="Luxemborg",BG21="Norway"),0,1))) | CH21: =IF(BN21="Yes",1,0) | CI21: =IF(BO21="Yes",1,0) | CJ21: =IF(BP21="Yes",1,0) | CK21: =IF(BQ21="Yes",1,0) | CL21: =IF(BR21="Yes",1,0) | CM21: =IF(BS21="Yes",1,0) | CN21: =IF(OR(AND(BJ21="Yes",N21="No"),AND(BJ21="Yes",N21="Yes",P21>=6)),1,0) | CO21: =IF(BT21="Yes",1,0) | CP21: =IF(AND(BU21="Yes",BV21="No"),1,0) | CQ21: =IF(BW21="Yes",1,0) | CR21: =IF(AP21="",0,IF(AP21>7,1,0)) | CS21: =IF(OR(BD21<>"Monthly",BD21<>"Quarterly",BD21<>"Semi-Annually"),0,1) | CT21: =IF(BX21="Yes",1,0) | CU21: =IF(BY21="Yes",1,0) | CV21: =IF(BZ21="Yes",1,0) | CW21: =IF(CA21="No",1,0) | CX21: =IF(B21="",0,IF(AK21>=5000000,0,1)) | CY21: =IF(B21="",0,IF(AL21>=5000000,0,1)) | CZ21: =IF(OR(DA21=1,DB21=1,DC21=1),0,IF(B21="",0,IF(OR(AND(AN21="Tier 1",X21="No",OR(AI21>$AJ$3,AJ21>$AJ$4)),(AND(AN21="Tier 1",X21="Yes",AJ21>$AJ$5)),(AND(AN21="Tier 2",X21="No",OR(AI21>$AK$3,AJ21>$AK$4))),(AND(AN21="Tier 2",X21="Yes",AJ21>$AK$5)),(AND(AN21="Tier 3",X21="No",OR(AI21>$AL$3,AJ21>$AL$4))),(AND(AN21="Tier 3",X21="Yes",AJ21>$AL$5))),1,0))) | DA21: =IF(OR(DB21=1,DC21=1),0,IF(B21="",0,IF(OR(AND(AN21="Tier 1",X21="No",OR(AI21>$AM$3,AJ21>$AM$4)),(AND(AN21="Tier 1",X21="Yes",AJ21>$AM$5)),(AND(AN21="Tier 2",X21="No",OR(AI21>$AN$3,AJ21>$AN$4))),(AND(AN21="Tier 2",X21="Yes",AJ21>$AN$5)),(AND(AN21="Tier 3",X21="No",OR(AI21>$AO$3,AJ21>$AO$4))),(AND(AN21="Tier 3",X21="Yes",AJ21>$AO$5))),1,0))) | DB21: =IF(DC21=1,0,IF(B21="",0,IF(OR(AND(AN21="Tier 1",X21="No",OR(AI21>$AP$3,AJ21>$AP$4)),(AND(AN21="Tier 1",X21="Yes",AJ21>$AP$5)),(AND(AN21="Tier 2",X21="No",OR(AI21>$AQ$3,AJ21>$AQ$4))),(AND(AN21="Tier 2",X21="Yes",AJ21>$AQ$5)),(AND(AN21="Tier 3",X21="No",OR(AI21>$AR$3,AJ21>$AR$4))),(AND(AN21="Tier 3",X21="Yes",AJ21>$AR$5))),1,0))) | DC21: =IF(B21="",0,IF(OR(AND(AN21="Tier 1",X21="No",OR(AI21>$AS$3,AJ21>$AS$4)),(AND(AN21="Tier 1",X21="Yes",AJ21>$AS$5)),(AND(AN21="Tier 2",X21="No",OR(AI21>$AT$3,AJ21>$AT$4))),(AND(AN21="Tier 2",X21="Yes",AJ21>$AT$5)),(AND(AN21="Tier 3",X21="No",OR(AI21>$AU$3,AJ21>$AU$4))),(AND(AN21="Tier 3",X21="Yes",AJ21>$AU$5))),1,0)) | DD21: =IF((SUM(CE21:CX21)=0),0,W21) | DE21: =IF(OR(B21="",DD21>0),0,W21) | DF21: =IF(B21="",0,IF(COUNTIF(CE21:CX21,1)>0,0,L21-M21)) | DG21: =DE21+IF(DD21>0,0,DF21) | DH21: =IF(B21="","",M21+DF21) | DI21: =IF(B21="",0,J21-K21) | DJ21: =IF(OR(BF21="EUR",BF21="CAD",BF21="GBP",BF21="AUD"),(GA21*(1-V21))+(HG21)+IF(HX21="",0,HX21*(1-U21)),0) | DK21: =IF(BF21="EUR",33%,IF(BF21="CAD",38%,IF(BF21="GBP",51%,IF(BF21="AUD",61%,0)))) | DL21: =DJ21*DK21 | DN21: =IF(OR(Y21="Second Lien",Y21="Tier 1 Split Lien",Y21="Tier 2 Split Lien"),DG21,0) | DO21: =DN21*DN$6 | DP21: =DG21-DO21 | DQ21: =IF(Y21="Second Lien",DP21,0) | DR21: =DQ21*DQ$6 | DS21: =DP21-DR21 | DT21: =IF(BH21="Yes",DS21,0) | DU21: =DT21*DT$6 | DV21: =DS21-DU21 | DW21: =IF(OR(BG21="Canada",BG21="United Kingdom",BG21="Australia",BG21="Netherlands Antilles",BG21="Bermuda",BG21="Cayman Islands",BG21="British Virgin Islands",BG21="Channel Islands",BG21="Isle of Man",BG21="Australia",BG21="Netherlands",BG21="Germany",BG21="Sweden",BG21="Switzerland",BG21="Austria",BG21="Belgium",BG21="Denmark",BG21="Finland",BG21="Iceland",BG21="Ireland",BG21="Lichtenstein",BG21="Luxemborg",BG21="Norway"),DV21,0) | DX21: =DW21*DW$6 | DY21: =DV21-DX21 | DZ21: =IF(BI21="Yes",DY21,0) | EA21: =DZ21*DZ$6 | EB21: =DY21-EA21 | EC21: =IF(OR(Z21="Delayed Draw",Z21="Revolver"),EB21,0) | ED21: =EC21*EC$6 | EE21: =EB21-ED21 | EF21: =IF(S21="Yes",EE21,0) | EG21: =EF21*EF$6 | EH21: =EE21-EG21 | EI21: =IF(Q21="Yes",EH21,0) | EJ21: =EI21*EI$6 | EK21: =EH21-EJ21 | EL21: =IF(BD21="Semi-Annually",EK21,0) | EM21: =EL21*EL$6 | EN21: =EK21-EM21 | EO21: =IF(BK21="Yes",EN21,0) | EP21: =EO21*EO$6 | EQ21: =EN21-EP21 | ER21: =IF(BL21="Yes",EQ21,0) | ES21: =ER21*ER$6 | ET21: =EQ21-ES21 | EU21: =IF(BM21="Yes",ET21,0) | EV21: =EU21*EU$6 | EW21: =ET21-EV21 | EX21: =IF(BV21="Yes",EW21,0) | EY21: =EX21*EX$6 | EZ21: =EW21-EY21 | FA21: =IF(AR21="Yes",EZ21,0) | FB21: =FA21*FA$6 | FC21: =EZ21-FB21 | FD21: =IF(OR(BF21="EUR",BF21="AUD",BF21="CAD",BF21="GBP"),FC21,0) | FE21: =FD21*FD$6 | FF21: =FC21-FE21 | FG21: =FF21 | FH21: =IF(FF21=0,0,VLOOKUP(C21,$GU$10:$GV$406,2,FALSE)*FF21) | FI21: =FF21-FH21 | FJ21: =FI21 | FK21: =IF(OR(IB21="",FI21<0.01),,VLOOKUP(IB21,$GL$10:$GM$406,2,FALSE)*FI21) | FL21: =FI21-FK21 | FM21: =FL21 | FN21: =IF(FL21=0,0,VLOOKUP(C21,$HD$10:$HE$406,2,FALSE)*FL21) | FO21: =FL21-FN21 | FP21: =IF(SUM(CY21:DC21)>0,0,IF(AND(AL21>=5000000,AL21<7500000),FO21,0)) | FQ21: =IF(B21="",0,FP21*FP$6*(1-$U21)) | FR21: =FO21-FQ21 | FS21: =IF(SUM(CY21:DC21)>0,0,IF(AL21<15000000,FR21,0)) | FT21: =IF(B21="",0,FS21*FS$6*(1-$U21)) | FU21: =FR21-FT21 | FV21: =IF(SUM(CY21:DC21)>0,0,IF(OR(AND(X21="No",AN21="Tier 1",AI21>$AG$3),AND(X21="No",AN21="Tier 2",AI21>$AH$3),AND(X21="No",AN21="Tier 3",AI21>$AI$3)),FU21,0)) | FW21: =IF(SUM(CY21:DC21)>0,0,IF(OR(AND(X21="No",AN21="Tier 1",AJ21>$AG$4),AND(X21="No",AN21="Tier 2",AJ21>$AH$4),AND(X21="No",AN21="Tier 3",AJ21>$AI$4)),FU21,0)) | FX21: =IF(SUM(CY21:DC21)>0,0,IF(OR(AND(X21="Yes",AN21="Tier 1",AJ21>$AG$5),AND(X21="Yes",AN21="Tier 2",AJ21>$AH$5),AND(X21="Yes",AN21="Tier 3",AJ21>$AI$5)),FU21,0)) | FY21: =IF(SUM(FV21:FX21)>0,FU21,0) | FZ21: =IF(B21="",0,FY21*FV$6*(1-MIN(90%,T21))) | GA21: =FU21-FZ21 | GB21: =IF(AND(N21="No",DI21=0),GA21,IF(AND(N21="No",DI21<>0,K21=0),0,IF(AND(N21="No",DI21<>0,K21>0,J21<>K21),MAX(0,M21-(DH21-GA21)),DG21))) | GC21: =+GB21*V21 | GD21: =IFERROR(GC21/K21,"") | GE21: =IF(IB21="","",IB21) | GF21: {=IF(SUM(IF(IB$9:IB20=IB21,1,0))>0,0,SUMIF($IB$10:$IB$406,IB21,$FI$10:$FI$406))} | GG21: =GF21 | GH21: =GH20+1 | GI21: =LARGE($GG$10:$GG$406,GH21) | GJ21: =IF(GH21>GH$6,0,IF(GH21=$GH$2,$GJ$2,IF(GH21<4,$GJ$3,$GJ$4))) | GK21: =MAX(0,GI21-GJ21) | GL21: {=IF(GI21=0,0,LARGE(IF($GF$10:$GF$406=GI21,$GE$10:$GE$406,0),COUNTIF($GI$10:$GI$406,GI21)-COUNTIF(GI$9:GI20,GI21)))} | GM21: =IF(GI21=0,0,GK21/GI21) | GO21: =IF(C21="","",IF(ISERROR(MATCH(C21,C$10:C20,0)),MAX(GO$10:GO20)+1,INDEX(GO$10:GO20,MATCH(C21,C$10:C20,0)))) | GP21: =IF(COUNTIF($A$10:A21,A21)<=1,SUMIF($A$10:$A$406,A21,$FG$10:$FG$406),0) | GQ21: =GQ20+1 | GR21: =LARGE($GP$10:$GP$406,GQ21) | GS21: =IF(GQ21>GQ$6,0,IF(GQ21<=GQ$2,GS$2,IF(AND(GQ21<=$GQ$3,GQ21>$GQ$2),GS$3,GS$4))) | GT21: =MAX(0,GR21-GS21) | GU21: {=IF(GR21=0,0,LARGE(IF($GP$10:$GP$406=GR21,$GO$10:$GO$406,0),COUNTIF($GR$10:$GR$406,GR21)-COUNTIF(GR$9:GR20,GR21)))} | GV21: =IF(GR21=0,0,GT21/GR21) | GX21: =IF(C21="","",IF(ISERROR(MATCH(C21,C$10:C20,0)),MAX(GO$10:GO20)+1,INDEX(GO$10:GO20,MATCH(C21,C$10:C20,0)))) | GY21: =IF(COUNTIF($A$10:A21,A21)<=1,SUMIF($A$10:$A$406,A21,$FG$10:$FG$406),0) | GZ21: =GZ20+1 | HA21: =LARGE($GY$10:$GY$406,GZ21) | HB21: - | HC21: =IF(GZ21<6,MAX(0,$HC$2/5),0) | HD21: {=IF(HA21=0,0,LARGE(IF($GY$10:$GY$406=HA21,$GX$10:$GX$406,0),COUNTIF($HA$10:$HA$406,HA21)-COUNTIF(HA$9:HA20,HA21)))} | HE21: =IF(HA21=0,0,HC21/HA21) | HG21: =DG21-GA21 | HH21: 0 | HI21: =MIN(HH21,DE21) | HK21: =IF(COUNTIF($C$10:$C$406,HK20+1),HK20+1,"") | HL21: =SUMIF($C$10:$C$406,HK21,$DG$10:$DG$406) | HN21: =MIN(HO21:HS21) | HO21: =IF(B21="","",$M21) | HP21: =IF($N21="Yes",IF(P21>=6,0,MIN($T21*$M21,$U21*$M21)),"") | HQ21: =IF(AND(N21="Yes",P21>=6),"",IF($S21="Yes",$R21*$M21,"")) | HR21: =IF($Q21="Yes",MIN($M21,$T21*$M21),"") | HS21: =IF(AND($N21="Yes",$P21>=6),"",IF(OR(CY21=1,DC21=1,),MIN($T21*$M21,$U21*$M21),IF(OR(CZ21=1,DA21=1,DB21=1),IF(AK21>=5000000,MIN($T21*$M21,$IE21*$M21),MIN($T21*$M21,$U21*$M21)),""))) | HT21: =IF(DD21>0,DD21,"") | HU21: =IF(B21="",0,$L21-$M21) | HV21: =IF(OR(SUM(HP21:HT21)>0,P21>=6),"",IF($B21="","",1)) | HW21: =IF(AND($HT21<>0,OR(HT21<=MIN(HP21:HS21),SUM(HP21:HS21)=0)),$HT21,0) | HX21: =IF(AND($HS21<>0,OR(AND($HS21<>$HT21,$HS21<>$HR21,$HS21<>$HQ21,$HS21<>$HP21,$HS21<MIN($HP21:$HR21),$HS21<HT21),SUM($HP21:$HR21)+SUM(HT21)=0),IA21<=0),$HS21,0) | HY21: =IF(AND($HR21<>0,OR(AND($HR21<>$HT21,$HR21<>$HS21,$HR21<>$HQ21,$HR21<>$HP21),$HR21<MIN($HP21:$HQ21),$HR21<MIN($HS21:$HT21),SUM($HP21:$HQ21)+SUM($HS21:$HT21)=0)),$HR21,0) | HZ21: =IF(AND($HQ21<>0,OR(AND($HQ21<>$HT21,HQ21<>HS21,HQ21<>HR21,HQ21<>HP21,HQ21<MIN(HR21:HT21)),SUM(HP21)+SUM(HR21:HT21)=0)),$HQ21,0) | IA21: =IF(AND($HP21<>0,OR(HP21<=MIN(HQ21:HT21),SUM(HQ21:HT21)=0)),$HP21,0) | IB21: 37 | IC21: =HU21=DF21 | IE21: =IF(B21="","",IF(AND(Y21="Second Lien",OR(CZ21=1,DA21=1,DB21=1)),50%,IF(CZ21=1,90%,IF(DA21=1,80%,IF(DB21=1,65%,"No Initial Haircut")))))
A22: =D22 | B22: =IF(D22="","",B21+1) | C22: =IF(COUNTIF($A$10:A21,A22)>0,C21,C21+1) | D22: Oakhill Holdings, LLC | E22: Oakhill (Term Loan) | G22: 25445610 | H22: 25445610 | I22: 1 | J22: =IF(B22="","",G22*I22) | K22: =IF(B22="","",H22*I22) | L22: =IF(B22="","",IF(COUNTIF($CE22:$CX22,1)>0,0,J22)) | M22: =IF(B22="","",IF(COUNTIF($CE22:$CX22,1)>0,0,K22)) | N22: No | O22: N/A | P22: =IF(B22="","",IF(OR(O22="N/A",O22=""),0,YEARFRAC('Borrowing Base'!$J$4,'Loan List'!O22)*12)) | Q22: No | R22: 0.99814277 | S22: =IF(B22="","",IF(R22<95%,"Yes","No")) | T22: 0.9925 | U22: =IF(B22="","",IF(OR(Y22="First Lien",Y22="Split First Lien",Y22="Tier 1 Split Lien",Y22="Tier 2 Split Lien"),50%,30%)) | V22: =IF(B22="",0,IF(AND(Y22="First Lien",AN22="Tier 1"),IF(AND(X22="Yes",MIN(AH22,$AJ$5)>4.5),(((4.5/MIN(AH22,$AJ$5))*72.5%)+(((MIN(AH22,$AJ$5)-4.5)/MIN(AH22,$AJ$5))*35%)),72.5%),IF(AND(Y22="First Lien",AN22="Tier 2"),IF(AND(X22="Yes",MIN(AH22,$AK$5)>4.5),(((4.5/MIN(AH22,$AK$5))*72.5%)+(((MIN(AH22,$AK$5)-4.5)/MIN(AH22,$AK$5))*35%)),72.5%),IF(AND(X22="Yes",MIN(AH22,$AL$5)>4),(((4/MIN(AH22,$AL$5))*72.5%)+(((MIN(AH22,$AL$5)-4)/MIN(AH22,$AL$5))*35%)),IF(OR(Y22="First Lien",Y22="Split First Lien"),72.5%,IF(Y22="Split Lien", 53%,35%)))))) | W22: =IF($C22="","",MIN($HO22:$HS22)) | X22: Yes | Y22: First Lien | Z22: Term | AA22: NR | AB22: NR | AC22: 1.99 | AD22: 5.2487887 | AE22: 6.1659957 | AF22: 0.52470518 | AG22: 5.4401602 | AH22: 5.771757 | AI22: 5.933921 | AJ22: 6.0060275 | AK22: 60314216 | AL22: 110947000 | AM22: 45838 | AN22: =IF(C22="","",(IF(AK22>=50000000,"Tier 1",(IF(OR(AK22>=20000000,AND(AK22>5000000,AC22>=1.25,AF22<=0.65)),"Tier 2","Tier 3"))))) | AO22: 48044 | AP22: 5.9583333 | AQ22: =IF(C22="","",AP22) | AR22: No | AS22: 0 | AT22: Yes | AU22: 0.01 | AV22: 0.0647 | AW22: 0.033476 | AX22: =IF(C22="","",MAX(AU22,AW22)) | AY22: 0 | AZ22: 0 | BA22: 0 | BB22: =IF(B22="","",IF(AR22="No",AV22-AZ22,"")) | BC22: =IF(B22="","",IF(AR22="Yes",AS22-BA22,"")) | BD22: Quarterly | BE22: IT Services | BF22: USD | BG22: United States | BH22: No | BI22: =IF(B22="","",IF(OR(AND(AZ22>0,BB22>=2.5%,BB22<4%),AND(BA22>0,BC22>=6%,BC22<8%)),"Yes","No")) | BJ22: =IF(B22="","",IF(OR(AND(AZ22>0,BB22<2.5%),AND(BA22>0,BC22<6%)),"Yes","No")) | BK22: No | BL22: No | BM22: No | BN22: No | BO22: No | BP22: No | BQ22: No | BR22: No | BS22: No | BT22: No | BU22: No | BV22: No | BW22: No | BX22: No | BY22: No | BZ22: No | CA22: Yes | CB22: =IF(B22="","",IF(AT22="No",((BB22+AW22)-$AZ$4),((BB22+AX22)-$AZ$4))*IF(DD22>0,0,M22)) | CC22: =IF(B22="","",AY22*(L22-M22)*IF(DD22>0,0,1)) | CE22: =IF(AND(B22<>"",R22<=85%),1,0) | CF22: =IF(B22="",0,(IF(OR(BF22="USD",BF22="CAD",BF22="GBP",BF22="AUD",BF22="EUR"),0,1))) | CG22: =IF(B22="",0,(IF(OR(BG22="United States",BG22="Canada",BG22="United Kingdom",BG22="Australia",BG22="Netherlands Antilles",BG22="Bermuda",BG22="Cayman Islands",BG22="British Virgin Islands",BG22="Channel Islands",BG22="Isle of Man",BG22="Australia",BG22="Netherlands",BG22="Germany",BG22="Sweden",BG22="Switzerland",BG22="Austria",BG22="Belgium",BG22="Denmark",BG22="Finland",BG22="Iceland",BG22="Ireland",BG22="Lichtenstein",BG22="Luxemborg",BG22="Norway"),0,1))) | CH22: =IF(BN22="Yes",1,0) | CI22: =IF(BO22="Yes",1,0) | CJ22: =IF(BP22="Yes",1,0) | CK22: =IF(BQ22="Yes",1,0) | CL22: =IF(BR22="Yes",1,0) | CM22: =IF(BS22="Yes",1,0) | CN22: =IF(OR(AND(BJ22="Yes",N22="No"),AND(BJ22="Yes",N22="Yes",P22>=6)),1,0) | CO22: =IF(BT22="Yes",1,0) | CP22: =IF(AND(BU22="Yes",BV22="No"),1,0) | CQ22: =IF(BW22="Yes",1,0) | CR22: =IF(AP22="",0,IF(AP22>7,1,0)) | CS22: =IF(OR(BD22<>"Monthly",BD22<>"Quarterly",BD22<>"Semi-Annually"),0,1) | CT22: =IF(BX22="Yes",1,0) | CU22: =IF(BY22="Yes",1,0) | CV22: =IF(BZ22="Yes",1,0) | CW22: =IF(CA22="No",1,0) | CX22: =IF(B22="",0,IF(AK22>=5000000,0,1)) | CY22: =IF(B22="",0,IF(AL22>=5000000,0,1)) | CZ22: =IF(OR(DA22=1,DB22=1,DC22=1),0,IF(B22="",0,IF(OR(AND(AN22="Tier 1",X22="No",OR(AI22>$AJ$3,AJ22>$AJ$4)),(AND(AN22="Tier 1",X22="Yes",AJ22>$AJ$5)),(AND(AN22="Tier 2",X22="No",OR(AI22>$AK$3,AJ22>$AK$4))),(AND(AN22="Tier 2",X22="Yes",AJ22>$AK$5)),(AND(AN22="Tier 3",X22="No",OR(AI22>$AL$3,AJ22>$AL$4))),(AND(AN22="Tier 3",X22="Yes",AJ22>$AL$5))),1,0))) | DA22: =IF(OR(DB22=1,DC22=1),0,IF(B22="",0,IF(OR(AND(AN22="Tier 1",X22="No",OR(AI22>$AM$3,AJ22>$AM$4)),(AND(AN22="Tier 1",X22="Yes",AJ22>$AM$5)),(AND(AN22="Tier 2",X22="No",OR(AI22>$AN$3,AJ22>$AN$4))),(AND(AN22="Tier 2",X22="Yes",AJ22>$AN$5)),(AND(AN22="Tier 3",X22="No",OR(AI22>$AO$3,AJ22>$AO$4))),(AND(AN22="Tier 3",X22="Yes",AJ22>$AO$5))),1,0))) | DB22: =IF(DC22=1,0,IF(B22="",0,IF(OR(AND(AN22="Tier 1",X22="No",OR(AI22>$AP$3,AJ22>$AP$4)),(AND(AN22="Tier 1",X22="Yes",AJ22>$AP$5)),(AND(AN22="Tier 2",X22="No",OR(AI22>$AQ$3,AJ22>$AQ$4))),(AND(AN22="Tier 2",X22="Yes",AJ22>$AQ$5)),(AND(AN22="Tier 3",X22="No",OR(AI22>$AR$3,AJ22>$AR$4))),(AND(AN22="Tier 3",X22="Yes",AJ22>$AR$5))),1,0))) | DC22: =IF(B22="",0,IF(OR(AND(AN22="Tier 1",X22="No",OR(AI22>$AS$3,AJ22>$AS$4)),(AND(AN22="Tier 1",X22="Yes",AJ22>$AS$5)),(AND(AN22="Tier 2",X22="No",OR(AI22>$AT$3,AJ22>$AT$4))),(AND(AN22="Tier 2",X22="Yes",AJ22>$AT$5)),(AND(AN22="Tier 3",X22="No",OR(AI22>$AU$3,AJ22>$AU$4))),(AND(AN22="Tier 3",X22="Yes",AJ22>$AU$5))),1,0)) | DD22: =IF((SUM(CE22:CX22)=0),0,W22) | DE22: =IF(OR(B22="",DD22>0),0,W22) | DF22: =IF(B22="",0,IF(COUNTIF(CE22:CX22,1)>0,0,L22-M22)) | DG22: =DE22+IF(DD22>0,0,DF22) | DH22: =IF(B22="","",M22+DF22) | DI22: =IF(B22="",0,J22-K22) | DJ22: =IF(OR(BF22="EUR",BF22="CAD",BF22="GBP",BF22="AUD"),(GA22*(1-V22))+(HG22)+IF(HX22="",0,HX22*(1-U22)),0) | DK22: =IF(BF22="EUR",33%,IF(BF22="CAD",38%,IF(BF22="GBP",51%,IF(BF22="AUD",61%,0)))) | DL22: =DJ22*DK22 | DN22: =IF(OR(Y22="Second Lien",Y22="Tier 1 Split Lien",Y22="Tier 2 Split Lien"),DG22,0) | DO22: =DN22*DN$6 | DP22: =DG22-DO22 | DQ22: =IF(Y22="Second Lien",DP22,0) | DR22: =DQ22*DQ$6 | DS22: =DP22-DR22 | DT22: =IF(BH22="Yes",DS22,0) | DU22: =DT22*DT$6 | DV22: =DS22-DU22 | DW22: =IF(OR(BG22="Canada",BG22="United Kingdom",BG22="Australia",BG22="Netherlands Antilles",BG22="Bermuda",BG22="Cayman Islands",BG22="British Virgin Islands",BG22="Channel Islands",BG22="Isle of Man",BG22="Australia",BG22="Netherlands",BG22="Germany",BG22="Sweden",BG22="Switzerland",BG22="Austria",BG22="Belgium",BG22="Denmark",BG22="Finland",BG22="Iceland",BG22="Ireland",BG22="Lichtenstein",BG22="Luxemborg",BG22="Norway"),DV22,0) | DX22: =DW22*DW$6 | DY22: =DV22-DX22 | DZ22: =IF(BI22="Yes",DY22,0) | EA22: =DZ22*DZ$6 | EB22: =DY22-EA22 | EC22: =IF(OR(Z22="Delayed Draw",Z22="Revolver"),EB22,0) | ED22: =EC22*EC$6 | EE22: =EB22-ED22 | EF22: =IF(S22="Yes",EE22,0) | EG22: =EF22*EF$6 | EH22: =EE22-EG22 | EI22: =IF(Q22="Yes",EH22,0) | EJ22: =EI22*EI$6 | EK22: =EH22-EJ22 | EL22: =IF(BD22="Semi-Annually",EK22,0) | EM22: =EL22*EL$6 | EN22: =EK22-EM22 | EO22: =IF(BK22="Yes",EN22,0) | EP22: =EO22*EO$6 | EQ22: =EN22-EP22 | ER22: =IF(BL22="Yes",EQ22,0) | ES22: =ER22*ER$6 | ET22: =EQ22-ES22 | EU22: =IF(BM22="Yes",ET22,0) | EV22: =EU22*EU$6 | EW22: =ET22-EV22 | EX22: =IF(BV22="Yes",EW22,0) | EY22: =EX22*EX$6 | EZ22: =EW22-EY22 | FA22: =IF(AR22="Yes",EZ22,0) | FB22: =FA22*FA$6 | FC22: =EZ22-FB22 | FD22: =IF(OR(BF22="EUR",BF22="AUD",BF22="CAD",BF22="GBP"),FC22,0) | FE22: =FD22*FD$6 | FF22: =FC22-FE22 | FG22: =FF22 | FH22: =IF(FF22=0,0,VLOOKUP(C22,$GU$10:$GV$406,2,FALSE)*FF22) | FI22: =FF22-FH22 | FJ22: =FI22 | FK22: =IF(OR(IB22="",FI22<0.01),,VLOOKUP(IB22,$GL$10:$GM$406,2,FALSE)*FI22) | FL22: =FI22-FK22 | FM22: =FL22 | FN22: =IF(FL22=0,0,VLOOKUP(C22,$HD$10:$HE$406,2,FALSE)*FL22) | FO22: =FL22-FN22 | FP22: =IF(SUM(CY22:DC22)>0,0,IF(AND(AL22>=5000000,AL22<7500000),FO22,0)) | FQ22: =IF(B22="",0,FP22*FP$6*(1-$U22)) | FR22: =FO22-FQ22 | FS22: =IF(SUM(CY22:DC22)>0,0,IF(AL22<15000000,FR22,0)) | FT22: =IF(B22="",0,FS22*FS$6*(1-$U22)) | FU22: =FR22-FT22 | FV22: =IF(SUM(CY22:DC22)>0,0,IF(OR(AND(X22="No",AN22="Tier 1",AI22>$AG$3),AND(X22="No",AN22="Tier 2",AI22>$AH$3),AND(X22="No",AN22="Tier 3",AI22>$AI$3)),FU22,0)) | FW22: =IF(SUM(CY22:DC22)>0,0,IF(OR(AND(X22="No",AN22="Tier 1",AJ22>$AG$4),AND(X22="No",AN22="Tier 2",AJ22>$AH$4),AND(X22="No",AN22="Tier 3",AJ22>$AI$4)),FU22,0)) | FX22: =IF(SUM(CY22:DC22)>0,0,IF(OR(AND(X22="Yes",AN22="Tier 1",AJ22>$AG$5),AND(X22="Yes",AN22="Tier 2",AJ22>$AH$5),AND(X22="Yes",AN22="Tier 3",AJ22>$AI$5)),FU22,0)) | FY22: =IF(SUM(FV22:FX22)>0,FU22,0) | FZ22: =IF(B22="",0,FY22*FV$6*(1-MIN(90%,T22))) | GA22: =FU22-FZ22 | GB22: =IF(AND(N22="No",DI22=0),GA22,IF(AND(N22="No",DI22<>0,K22=0),0,IF(AND(N22="No",DI22<>0,K22>0,J22<>K22),MAX(0,M22-(DH22-GA22)),DG22))) | GC22: =+GB22*V22 | GD22: =IFERROR(GC22/K22,"") | GE22: =IF(IB22="","",IB22) | GF22: {=IF(SUM(IF(IB$9:IB21=IB22,1,0))>0,0,SUMIF($IB$10:$IB$406,IB22,$FI$10:$FI$406))} | GG22: =GF22 | GH22: =GH21+1 | GI22: =LARGE($GG$10:$GG$406,GH22) | GJ22: =IF(GH22>GH$6,0,IF(GH22=$GH$2,$GJ$2,IF(GH22<4,$GJ$3,$GJ$4))) | GK22: =MAX(0,GI22-GJ22) | GL22: {=IF(GI22=0,0,LARGE(IF($GF$10:$GF$406=GI22,$GE$10:$GE$406,0),COUNTIF($GI$10:$GI$406,GI22)-COUNTIF(GI$9:GI21,GI22)))} | GM22: =IF(GI22=0,0,GK22/GI22) | GO22: =IF(C22="","",IF(ISERROR(MATCH(C22,C$10:C21,0)),MAX(GO$10:GO21)+1,INDEX(GO$10:GO21,MATCH(C22,C$10:C21,0)))) | GP22: =IF(COUNTIF($A$10:A22,A22)<=1,SUMIF($A$10:$A$406,A22,$FG$10:$FG$406),0) | GQ22: =GQ21+1 | GR22: =LARGE($GP$10:$GP$406,GQ22) | GS22: =IF(GQ22>GQ$6,0,IF(GQ22<=GQ$2,GS$2,IF(AND(GQ22<=$GQ$3,GQ22>$GQ$2),GS$3,GS$4))) | GT22: =MAX(0,GR22-GS22) | GU22: {=IF(GR22=0,0,LARGE(IF($GP$10:$GP$406=GR22,$GO$10:$GO$406,0),COUNTIF($GR$10:$GR$406,GR22)-COUNTIF(GR$9:GR21,GR22)))} | GV22: =IF(GR22=0,0,GT22/GR22) | GX22: =IF(C22="","",IF(ISERROR(MATCH(C22,C$10:C21,0)),MAX(GO$10:GO21)+1,INDEX(GO$10:GO21,MATCH(C22,C$10:C21,0)))) | GY22: =IF(COUNTIF($A$10:A22,A22)<=1,SUMIF($A$10:$A$406,A22,$FG$10:$FG$406),0) | GZ22: =GZ21+1 | HA22: =LARGE($GY$10:$GY$406,GZ22) | HB22: - | HC22: =IF(GZ22<6,MAX(0,$HC$2/5),0) | HD22: {=IF(HA22=0,0,LARGE(IF($GY$10:$GY$406=HA22,$GX$10:$GX$406,0),COUNTIF($HA$10:$HA$406,HA22)-COUNTIF(HA$9:HA21,HA22)))} | HE22: =IF(HA22=0,0,HC22/HA22) | HG22: =DG22-GA22 | HH22: 0 | HI22: =MIN(HH22,DE22) | HK22: =IF(COUNTIF($C$10:$C$406,HK21+1),HK21+1,"") | HL22: =SUMIF($C$10:$C$406,HK22,$DG$10:$DG$406) | HN22: =MIN(HO22:HS22) | HO22: =IF(B22="","",$M22) | HP22: =IF($N22="Yes",IF(P22>=6,0,MIN($T22*$M22,$U22*$M22)),"") | HQ22: =IF(AND(N22="Yes",P22>=6),"",IF($S22="Yes",$R22*$M22,"")) | HR22: =IF($Q22="Yes",MIN($M22,$T22*$M22),"") | HS22: =IF(AND($N22="Yes",$P22>=6),"",IF(OR(CY22=1,DC22=1,),MIN($T22*$M22,$U22*$M22),IF(OR(CZ22=1,DA22=1,DB22=1),IF(AK22>=5000000,MIN($T22*$M22,$IE22*$M22),MIN($T22*$M22,$U22*$M22)),""))) | HT22: =IF(DD22>0,DD22,"") | HU22: =IF(B22="",0,$L22-$M22) | HV22: =IF(OR(SUM(HP22:HT22)>0,P22>=6),"",IF($B22="","",1)) | HW22: =IF(AND($HT22<>0,OR(HT22<=MIN(HP22:HS22),SUM(HP22:HS22)=0)),$HT22,0) | HX22: =IF(AND($HS22<>0,OR(AND($HS22<>$HT22,$HS22<>$HR22,$HS22<>$HQ22,$HS22<>$HP22,$HS22<MIN($HP22:$HR22),$HS22<HT22),SUM($HP22:$HR22)+SUM(HT22)=0),IA22<=0),$HS22,0) | HY22: =IF(AND($HR22<>0,OR(AND($HR22<>$HT22,$HR22<>$HS22,$HR22<>$HQ22,$HR22<>$HP22),$HR22<MIN($HP22:$HQ22),$HR22<MIN($HS22:$HT22),SUM($HP22:$HQ22)+SUM($HS22:$HT22)=0)),$HR22,0) | HZ22: =IF(AND($HQ22<>0,OR(AND($HQ22<>$HT22,HQ22<>HS22,HQ22<>HR22,HQ22<>HP22,HQ22<MIN(HR22:HT22)),SUM(HP22)+SUM(HR22:HT22)=0)),$HQ22,0) | IA22: =IF(AND($HP22<>0,OR(HP22<=MIN(HQ22:HT22),SUM(HQ22:HT22)=0)),$HP22,0) | IB22: 41 | IC22: =HU22=DF22 | IE22: =IF(B22="","",IF(AND(Y22="Second Lien",OR(CZ22=1,DA22=1,DB22=1)),50%,IF(CZ22=1,90%,IF(DA22=1,80%,IF(DB22=1,65%,"No Initial Haircut")))))
A23: By Light Professional IT Services, LLC | B23: =IF(D23="","",B22+1) | C23: =IF(COUNTIF($A$10:A22,A23)>0,C22,C22+1) | D23: Pinecrest Holdings, LLC | E23: Pinecrest (Revolver) | G23: 2164811.8 | H23: 2164811.8 | I23: 1 | J23: =IF(B23="","",G23*I23) | K23: =IF(B23="","",H23*I23) | L23: =IF(B23="","",IF(COUNTIF($CE23:$CX23,1)>0,0,J23)) | M23: =IF(B23="","",IF(COUNTIF($CE23:$CX23,1)>0,0,K23)) | N23: No | O23: N/A | P23: =IF(B23="","",IF(OR(O23="N/A",O23=""),0,YEARFRAC('Borrowing Base'!$J$4,'Loan List'!O23)*12)) | Q23: No | R23: 1 | S23: =IF(B23="","",IF(R23<95%,"Yes","No")) | T23: 0.9925 | U23: =IF(B23="","",IF(OR(Y23="First Lien",Y23="Split First Lien",Y23="Tier 1 Split Lien",Y23="Tier 2 Split Lien"),50%,30%)) | V23: =IF(B23="",0,IF(AND(Y23="First Lien",AN23="Tier 1"),IF(AND(X23="Yes",MIN(AH23,$AJ$5)>4.5),(((4.5/MIN(AH23,$AJ$5))*72.5%)+(((MIN(AH23,$AJ$5)-4.5)/MIN(AH23,$AJ$5))*35%)),72.5%),IF(AND(Y23="First Lien",AN23="Tier 2"),IF(AND(X23="Yes",MIN(AH23,$AK$5)>4.5),(((4.5/MIN(AH23,$AK$5))*72.5%)+(((MIN(AH23,$AK$5)-4.5)/MIN(AH23,$AK$5))*35%)),72.5%),IF(AND(X23="Yes",MIN(AH23,$AL$5)>4),(((4/MIN(AH23,$AL$5))*72.5%)+(((MIN(AH23,$AL$5)-4)/MIN(AH23,$AL$5))*35%)),IF(OR(Y23="First Lien",Y23="Split First Lien"),72.5%,IF(Y23="Split Lien", 53%,35%)))))) | W23: =IF($C23="","",MIN($HO23:$HS23)) | X23: Yes | Y23: First Lien | Z23: Revolver | AA23: NR | AB23: NR | AC23: 1.99 | AD23: 5.2487887 | AE23: 6.1659957 | AF23: 0.52470518 | AG23: 5.4401602 | AH23: 5.771757 | AI23: 5.933921 | AJ23: 6.0060275 | AK23: 60314216 | AL23: 110947000 | AM23: 45838 | AN23: =IF(C23="","",(IF(AK23>=50000000,"Tier 1",(IF(OR(AK23>=20000000,AND(AK23>5000000,AC23>=1.25,AF23<=0.65)),"Tier 2","Tier 3"))))) | AO23: 48044 | AP23: 5.9583333 | AQ23: =IF(C23="","",AP23) | AR23: No | AS23: 0 | AT23: Yes | AU23: 0.01 | AV23: 0.0647 | AW23: 0.033476 | AX23: =IF(C23="","",MAX(AU23,AW23)) | AY23: 0 | AZ23: 0 | BA23: 0 | BB23: =IF(B23="","",IF(AR23="No",AV23-AZ23,"")) | BC23: =IF(B23="","",IF(AR23="Yes",AS23-BA23,"")) | BD23: Quarterly | BE23: IT Services | BF23: USD | BG23: United States | BH23: No | BI23: =IF(B23="","",IF(OR(AND(AZ23>0,BB23>=2.5%,BB23<4%),AND(BA23>0,BC23>=6%,BC23<8%)),"Yes","No")) | BJ23: =IF(B23="","",IF(OR(AND(AZ23>0,BB23<2.5%),AND(BA23>0,BC23<6%)),"Yes","No")) | BK23: No | BL23: No | BM23: No | BN23: No | BO23: No | BP23: No | BQ23: No | BR23: No | BS23: No | BT23: No | BU23: No | BV23: No | BW23: No | BX23: No | BY23: No | BZ23: No | CA23: Yes | CB23: =IF(B23="","",IF(AT23="No",((BB23+AW23)-$AZ$4),((BB23+AX23)-$AZ$4))*IF(DD23>0,0,M23)) | CC23: =IF(B23="","",AY23*(L23-M23)*IF(DD23>0,0,1)) | CE23: =IF(AND(B23<>"",R23<=85%),1,0) | CF23: =IF(B23="",0,(IF(OR(BF23="USD",BF23="CAD",BF23="GBP",BF23="AUD",BF23="EUR"),0,1))) | CG23: =IF(B23="",0,(IF(OR(BG23="United States",BG23="Canada",BG23="United Kingdom",BG23="Australia",BG23="Netherlands Antilles",BG23="Bermuda",BG23="Cayman Islands",BG23="British Virgin Islands",BG23="Channel Islands",BG23="Isle of Man",BG23="Australia",BG23="Netherlands",BG23="Germany",BG23="Sweden",BG23="Switzerland",BG23="Austria",BG23="Belgium",BG23="Denmark",BG23="Finland",BG23="Iceland",BG23="Ireland",BG23="Lichtenstein",BG23="Luxemborg",BG23="Norway"),0,1))) | CH23: =IF(BN23="Yes",1,0) | CI23: =IF(BO23="Yes",1,0) | CJ23: =IF(BP23="Yes",1,0) | CK23: =IF(BQ23="Yes",1,0) | CL23: =IF(BR23="Yes",1,0) | CM23: =IF(BS23="Yes",1,0) | CN23: =IF(OR(AND(BJ23="Yes",N23="No"),AND(BJ23="Yes",N23="Yes",P23>=6)),1,0) | CO23: =IF(BT23="Yes",1,0) | CP23: =IF(AND(BU23="Yes",BV23="No"),1,0) | CQ23: =IF(BW23="Yes",1,0) | CR23: =IF(AP23="",0,IF(AP23>7,1,0)) | CS23: =IF(OR(BD23<>"Monthly",BD23<>"Quarterly",BD23<>"Semi-Annually"),0,1) | CT23: =IF(BX23="Yes",1,0) | CU23: =IF(BY23="Yes",1,0) | CV23: =IF(BZ23="Yes",1,0) | CW23: =IF(CA23="No",1,0) | CX23: =IF(B23="",0,IF(AK23>=5000000,0,1)) | CY23: =IF(B23="",0,IF(AL23>=5000000,0,1)) | CZ23: =IF(OR(DA23=1,DB23=1,DC23=1),0,IF(B23="",0,IF(OR(AND(AN23="Tier 1",X23="No",OR(AI23>$AJ$3,AJ23>$AJ$4)),(AND(AN23="Tier 1",X23="Yes",AJ23>$AJ$5)),(AND(AN23="Tier 2",X23="No",OR(AI23>$AK$3,AJ23>$AK$4))),(AND(AN23="Tier 2",X23="Yes",AJ23>$AK$5)),(AND(AN23="Tier 3",X23="No",OR(AI23>$AL$3,AJ23>$AL$4))),(AND(AN23="Tier 3",X23="Yes",AJ23>$AL$5))),1,0))) | DA23: =IF(OR(DB23=1,DC23=1),0,IF(B23="",0,IF(OR(AND(AN23="Tier 1",X23="No",OR(AI23>$AM$3,AJ23>$AM$4)),(AND(AN23="Tier 1",X23="Yes",AJ23>$AM$5)),(AND(AN23="Tier 2",X23="No",OR(AI23>$AN$3,AJ23>$AN$4))),(AND(AN23="Tier 2",X23="Yes",AJ23>$AN$5)),(AND(AN23="Tier 3",X23="No",OR(AI23>$AO$3,AJ23>$AO$4))),(AND(AN23="Tier 3",X23="Yes",AJ23>$AO$5))),1,0))) | DB23: =IF(DC23=1,0,IF(B23="",0,IF(OR(AND(AN23="Tier 1",X23="No",OR(AI23>$AP$3,AJ23>$AP$4)),(AND(AN23="Tier 1",X23="Yes",AJ23>$AP$5)),(AND(AN23="Tier 2",X23="No",OR(AI23>$AQ$3,AJ23>$AQ$4))),(AND(AN23="Tier 2",X23="Yes",AJ23>$AQ$5)),(AND(AN23="Tier 3",X23="No",OR(AI23>$AR$3,AJ23>$AR$4))),(AND(AN23="Tier 3",X23="Yes",AJ23>$AR$5))),1,0))) | DC23: =IF(B23="",0,IF(OR(AND(AN23="Tier 1",X23="No",OR(AI23>$AS$3,AJ23>$AS$4)),(AND(AN23="Tier 1",X23="Yes",AJ23>$AS$5)),(AND(AN23="Tier 2",X23="No",OR(AI23>$AT$3,AJ23>$AT$4))),(AND(AN23="Tier 2",X23="Yes",AJ23>$AT$5)),(AND(AN23="Tier 3",X23="No",OR(AI23>$AU$3,AJ23>$AU$4))),(AND(AN23="Tier 3",X23="Yes",AJ23>$AU$5))),1,0)) | DD23: =IF((SUM(CE23:CX23)=0),0,W23) | DE23: =IF(OR(B23="",DD23>0),0,W23) | DF23: =IF(B23="",0,IF(COUNTIF(CE23:CX23,1)>0,0,L23-M23)) | DG23: =DE23+IF(DD23>0,0,DF23) | DH23: =IF(B23="","",M23+DF23) | DI23: =IF(B23="",0,J23-K23) | DJ23: =IF(OR(BF23="EUR",BF23="CAD",BF23="GBP",BF23="AUD"),(GA23*(1-V23))+(HG23)+IF(HX23="",0,HX23*(1-U23)),0) | DK23: =IF(BF23="EUR",33%,IF(BF23="CAD",38%,IF(BF23="GBP",51%,IF(BF23="AUD",61%,0)))) | DL23: =DJ23*DK23 | DN23: =IF(OR(Y23="Second Lien",Y23="Tier 1 Split Lien",Y23="Tier 2 Split Lien"),DG23,0) | DO23: =DN23*DN$6 | DP23: =DG23-DO23 | DQ23: =IF(Y23="Second Lien",DP23,0) | DR23: =DQ23*DQ$6 | DS23: =DP23-DR23 | DT23: =IF(BH23="Yes",DS23,0) | DU23: =DT23*DT$6 | DV23: =DS23-DU23 | DW23: =IF(OR(BG23="Canada",BG23="United Kingdom",BG23="Australia",BG23="Netherlands Antilles",BG23="Bermuda",BG23="Cayman Islands",BG23="British Virgin Islands",BG23="Channel Islands",BG23="Isle of Man",BG23="Australia",BG23="Netherlands",BG23="Germany",BG23="Sweden",BG23="Switzerland",BG23="Austria",BG23="Belgium",BG23="Denmark",BG23="Finland",BG23="Iceland",BG23="Ireland",BG23="Lichtenstein",BG23="Luxemborg",BG23="Norway"),DV23,0) | DX23: =DW23*DW$6 | DY23: =DV23-DX23 | DZ23: =IF(BI23="Yes",DY23,0) | EA23: =DZ23*DZ$6 | EB23: =DY23-EA23 | EC23: =IF(OR(Z23="Delayed Draw",Z23="Revolver"),EB23,0) | ED23: =EC23*EC$6 | EE23: =EB23-ED23 | EF23: =IF(S23="Yes",EE23,0) | EG23: =EF23*EF$6 | EH23: =EE23-EG23 | EI23: =IF(Q23="Yes",EH23,0) | EJ23: =EI23*EI$6 | EK23: =EH23-EJ23 | EL23: =IF(BD23="Semi-Annually",EK23,0) | EM23: =EL23*EL$6 | EN23: =EK23-EM23 | EO23: =IF(BK23="Yes",EN23,0) | EP23: =EO23*EO$6 | EQ23: =EN23-EP23 | ER23: =IF(BL23="Yes",EQ23,0) | ES23: =ER23*ER$6 | ET23: =EQ23-ES23 | EU23: =IF(BM23="Yes",ET23,0) | EV23: =EU23*EU$6 | EW23: =ET23-EV23 | EX23: =IF(BV23="Yes",EW23,0) | EY23: =EX23*EX$6 | EZ23: =EW23-EY23 | FA23: =IF(AR23="Yes",EZ23,0) | FB23: =FA23*FA$6 | FC23: =EZ23-FB23 | FD23: =IF(OR(BF23="EUR",BF23="AUD",BF23="CAD",BF23="GBP"),FC23,0) | FE23: =FD23*FD$6 | FF23: =FC23-FE23 | FG23: =FF23 | FH23: =IF(FF23=0,0,VLOOKUP(C23,$GU$10:$GV$406,2,FALSE)*FF23) | FI23: =FF23-FH23 | FJ23: =FI23 | FK23: =IF(OR(IB23="",FI23<0.01),,VLOOKUP(IB23,$GL$10:$GM$406,2,FALSE)*FI23) | FL23: =FI23-FK23 | FM23: =FL23 | FN23: =IF(FL23=0,0,VLOOKUP(C23,$HD$10:$HE$406,2,FALSE)*FL23) | FO23: =FL23-FN23 | FP23: =IF(SUM(CY23:DC23)>0,0,IF(AND(AL23>=5000000,AL23<7500000),FO23,0)) | FQ23: =IF(B23="",0,FP23*FP$6*(1-$U23)) | FR23: =FO23-FQ23 | FS23: =IF(SUM(CY23:DC23)>0,0,IF(AL23<15000000,FR23,0)) | FT23: =IF(B23="",0,FS23*FS$6*(1-$U23)) | FU23: =FR23-FT23 | FV23: =IF(SUM(CY23:DC23)>0,0,IF(OR(AND(X23="No",AN23="Tier 1",AI23>$AG$3),AND(X23="No",AN23="Tier 2",AI23>$AH$3),AND(X23="No",AN23="Tier 3",AI23>$AI$3)),FU23,0)) | FW23: =IF(SUM(CY23:DC23)>0,0,IF(OR(AND(X23="No",AN23="Tier 1",AJ23>$AG$4),AND(X23="No",AN23="Tier 2",AJ23>$AH$4),AND(X23="No",AN23="Tier 3",AJ23>$AI$4)),FU23,0)) | FX23: =IF(SUM(CY23:DC23)>0,0,IF(OR(AND(X23="Yes",AN23="Tier 1",AJ23>$AG$5),AND(X23="Yes",AN23="Tier 2",AJ23>$AH$5),AND(X23="Yes",AN23="Tier 3",AJ23>$AI$5)),FU23,0)) | FY23: =IF(SUM(FV23:FX23)>0,FU23,0) | FZ23: =IF(B23="",0,FY23*FV$6*(1-MIN(90%,T23))) | GA23: =FU23-FZ23 | GB23: =IF(AND(N23="No",DI23=0),GA23,IF(AND(N23="No",DI23<>0,K23=0),0,IF(AND(N23="No",DI23<>0,K23>0,J23<>K23),MAX(0,M23-(DH23-GA23)),DG23))) | GC23: =+GB23*V23 | GD23: =IFERROR(GC23/K23,"") | GE23: =IF(IB23="","",IB23) | GF23: {=IF(SUM(IF(IB$9:IB22=IB23,1,0))>0,0,SUMIF($IB$10:$IB$406,IB23,$FI$10:$FI$406))} | GG23: =GF23 | GH23: =GH22+1 | GI23: =LARGE($GG$10:$GG$406,GH23) | GJ23: =IF(GH23>GH$6,0,IF(GH23=$GH$2,$GJ$2,IF(GH23<4,$GJ$3,$GJ$4))) | GK23: =MAX(0,GI23-GJ23) | GL23: {=IF(GI23=0,0,LARGE(IF($GF$10:$GF$406=GI23,$GE$10:$GE$406,0),COUNTIF($GI$10:$GI$406,GI23)-COUNTIF(GI$9:GI22,GI23)))} | GM23: =IF(GI23=0,0,GK23/GI23) | GO23: =IF(C23="","",IF(ISERROR(MATCH(C23,C$10:C22,0)),MAX(GO$10:GO22)+1,INDEX(GO$10:GO22,MATCH(C23,C$10:C22,0)))) | GP23: =IF(COUNTIF($A$10:A23,A23)<=1,SUMIF($A$10:$A$406,A23,$FG$10:$FG$406),0) | GQ23: =GQ22+1 | GR23: =LARGE($GP$10:$GP$406,GQ23) | GS23: =IF(GQ23>GQ$6,0,IF(GQ23<=GQ$2,GS$2,IF(AND(GQ23<=$GQ$3,GQ23>$GQ$2),GS$3,GS$4))) | GT23: =MAX(0,GR23-GS23) | GU23: {=IF(GR23=0,0,LARGE(IF($GP$10:$GP$406=GR23,$GO$10:$GO$406,0),COUNTIF($GR$10:$GR$406,GR23)-COUNTIF(GR$9:GR22,GR23)))} | GV23: =IF(GR23=0,0,GT23/GR23) | GX23: =IF(C23="","",IF(ISERROR(MATCH(C23,C$10:C22,0)),MAX(GO$10:GO22)+1,INDEX(GO$10:GO22,MATCH(C23,C$10:C22,0)))) | GY23: =IF(COUNTIF($A$10:A23,A23)<=1,SUMIF($A$10:$A$406,A23,$FG$10:$FG$406),0) | GZ23: =GZ22+1 | HA23: =LARGE($GY$10:$GY$406,GZ23) | HB23: - | HC23: =IF(GZ23<6,MAX(0,$HC$2/5),0) | HD23: {=IF(HA23=0,0,LARGE(IF($GY$10:$GY$406=HA23,$GX$10:$GX$406,0),COUNTIF($HA$10:$HA$406,HA23)-COUNTIF(HA$9:HA22,HA23)))} | HE23: =IF(HA23=0,0,HC23/HA23) | HG23: =DG23-GA23 | HH23: 0 | HI23: =MIN(HH23,DE23) | HK23: =IF(COUNTIF($C$10:$C$406,HK22+1),HK22+1,"") | HL23: =SUMIF($C$10:$C$406,HK23,$DG$10:$DG$406) | HN23: =MIN(HO23:HS23) | HO23: =IF(B23="","",$M23) | HP23: =IF($N23="Yes",IF(P23>=6,0,MIN($T23*$M23,$U23*$M23)),"") | HQ23: =IF(AND(N23="Yes",P23>=6),"",IF($S23="Yes",$R23*$M23,"")) | HR23: =IF($Q23="Yes",MIN($M23,$T23*$M23),"") | HS23: =IF(AND($N23="Yes",$P23>=6),"",IF(OR(CY23=1,DC23=1,),MIN($T23*$M23,$U23*$M23),IF(OR(CZ23=1,DA23=1,DB23=1),IF(AK23>=5000000,MIN($T23*$M23,$IE23*$M23),MIN($T23*$M23,$U23*$M23)),""))) | HT23: =IF(DD23>0,DD23,"") | HU23: =IF(B23="",0,$L23-$M23) | HV23: =IF(OR(SUM(HP23:HT23)>0,P23>=6),"",IF($B23="","",1)) | HW23: =IF(AND($HT23<>0,OR(HT23<=MIN(HP23:HS23),SUM(HP23:HS23)=0)),$HT23,0) | HX23: =IF(AND($HS23<>0,OR(AND($HS23<>$HT23,$HS23<>$HR23,$HS23<>$HQ23,$HS23<>$HP23,$HS23<MIN($HP23:$HR23),$HS23<HT23),SUM($HP23:$HR23)+SUM(HT23)=0),IA23<=0),$HS23,0) | HY23: =IF(AND($HR23<>0,OR(AND($HR23<>$HT23,$HR23<>$HS23,$HR23<>$HQ23,$HR23<>$HP23),$HR23<MIN($HP23:$HQ23),$HR23<MIN($HS23:$HT23),SUM($HP23:$HQ23)+SUM($HS23:$HT23)=0)),$HR23,0) | HZ23: =IF(AND($HQ23<>0,OR(AND($HQ23<>$HT23,HQ23<>HS23,HQ23<>HR23,HQ23<>HP23,HQ23<MIN(HR23:HT23)),SUM(HP23)+SUM(HR23:HT23)=0)),$HQ23,0) | IA23: =IF(AND($HP23<>0,OR(HP23<=MIN(HQ23:HT23),SUM(HQ23:HT23)=0)),$HP23,0) | IB23: 41 | IC23: =HU23=DF23 | IE23: =IF(B23="","",IF(AND(Y23="Second Lien",OR(CZ23=1,DA23=1,DB23=1)),50%,IF(CZ23=1,90%,IF(DA23=1,80%,IF(DB23=1,65%,"No Initial Haircut")))))
A24: =D24 | B24: =IF(D24="","",B23+1) | C24: =IF(COUNTIF($A$10:A23,A24)>0,C23,C23+1) | D24: Westbrook Holdings, LLC | E24: Westbrook (Term Loan) | G24: 9905100.3 | H24: 9905100.3 | I24: 1 | J24: =IF(B24="","",G24*I24) | K24: =IF(B24="","",H24*I24) | L24: =IF(B24="","",IF(COUNTIF($CE24:$CX24,1)>0,0,J24)) | M24: =IF(B24="","",IF(COUNTIF($CE24:$CX24,1)>0,0,K24)) | N24: No | O24: N/A | P24: =IF(B24="","",IF(OR(O24="N/A",O24=""),0,YEARFRAC('Borrowing Base'!$J$4,'Loan List'!O24)*12)) | Q24: No | R24: 0.98910763 | S24: =IF(B24="","",IF(R24<95%,"Yes","No")) | T24: 1 | U24: =IF(B24="","",IF(OR(Y24="First Lien",Y24="Split First Lien",Y24="Tier 1 Split Lien",Y24="Tier 2 Split Lien"),50%,30%)) | V24: =IF(B24="",0,IF(AND(Y24="First Lien",AN24="Tier 1"),IF(AND(X24="Yes",MIN(AH24,$AJ$5)>4.5),(((4.5/MIN(AH24,$AJ$5))*72.5%)+(((MIN(AH24,$AJ$5)-4.5)/MIN(AH24,$AJ$5))*35%)),72.5%),IF(AND(Y24="First Lien",AN24="Tier 2"),IF(AND(X24="Yes",MIN(AH24,$AK$5)>4.5),(((4.5/MIN(AH24,$AK$5))*72.5%)+(((MIN(AH24,$AK$5)-4.5)/MIN(AH24,$AK$5))*35%)),72.5%),IF(AND(X24="Yes",MIN(AH24,$AL$5)>4),(((4/MIN(AH24,$AL$5))*72.5%)+(((MIN(AH24,$AL$5)-4)/MIN(AH24,$AL$5))*35%)),IF(OR(Y24="First Lien",Y24="Split First Lien"),72.5%,IF(Y24="Split Lien", 53%,35%)))))) | W24: =IF($C24="","",MIN($HO24:$HS24)) | X24: No | Y24: First Lien | Z24: Term | AA24: NR | AB24: NR | AC24: 1.4542788 | AD24: 4.3355975 | AE24: 4.9058238 | AF24: 0.47281324 | AG24: 4.3355975 | AH24: 4.3355975 | AI24: 4.3348178 | AJ24: 4.9690259 | AK24: 19997244 | AL24: 18152112 | AM24: 45838 | AN24: =IF(C24="","",(IF(AK24>=50000000,"Tier 1",(IF(OR(AK24>=20000000,AND(AK24>5000000,AC24>=1.25,AF24<=0.65)),"Tier 2","Tier 3"))))) | AO24: 47330 | AP24: 4 | AQ24: =IF(C24="","",AP24) | AR24: No | AS24: 0 | AT24: Yes | AU24: 0.01 | AV24: 0.06 | AW24: 0.042956 | AX24: =IF(C24="","",MAX(AU24,AW24)) | AY24: 0 | AZ24: 0 | BA24: 0 | BB24: =IF(B24="","",IF(AR24="No",AV24-AZ24,"")) | BC24: =IF(B24="","",IF(AR24="Yes",AS24-BA24,"")) | BD24: Monthly | BE24: IT Services | BF24: USD | BG24: United States | BH24: No | BI24: =IF(B24="","",IF(OR(AND(AZ24>0,BB24>=2.5%,BB24<4%),AND(BA24>0,BC24>=6%,BC24<8%)),"Yes","No")) | BJ24: =IF(B24="","",IF(OR(AND(AZ24>0,BB24<2.5%),AND(BA24>0,BC24<6%)),"Yes","No")) | BK24: No | BL24: No | BM24: No | BN24: No | BO24: No | BP24: No | BQ24: No | BR24: No | BS24: No | BT24: No | BU24: No | BV24: No | BW24: No | BX24: No | BY24: No | BZ24: No | CA24: Yes | CB24: =IF(B24="","",IF(AT24="No",((BB24+AW24)-$AZ$4),((BB24+AX24)-$AZ$4))*IF(DD24>0,0,M24)) | CC24: =IF(B24="","",AY24*(L24-M24)*IF(DD24>0,0,1)) | CE24: =IF(AND(B24<>"",R24<=85%),1,0) | CF24: =IF(B24="",0,(IF(OR(BF24="USD",BF24="CAD",BF24="GBP",BF24="AUD",BF24="EUR"),0,1))) | CG24: =IF(B24="",0,(IF(OR(BG24="United States",BG24="Canada",BG24="United Kingdom",BG24="Australia",BG24="Netherlands Antilles",BG24="Bermuda",BG24="Cayman Islands",BG24="British Virgin Islands",BG24="Channel Islands",BG24="Isle of Man",BG24="Australia",BG24="Netherlands",BG24="Germany",BG24="Sweden",BG24="Switzerland",BG24="Austria",BG24="Belgium",BG24="Denmark",BG24="Finland",BG24="Iceland",BG24="Ireland",BG24="Lichtenstein",BG24="Luxemborg",BG24="Norway"),0,1))) | CH24: =IF(BN24="Yes",1,0) | CI24: =IF(BO24="Yes",1,0) | CJ24: =IF(BP24="Yes",1,0) | CK24: =IF(BQ24="Yes",1,0) | CL24: =IF(BR24="Yes",1,0) | CM24: =IF(BS24="Yes",1,0) | CN24: =IF(OR(AND(BJ24="Yes",N24="No"),AND(BJ24="Yes",N24="Yes",P24>=6)),1,0) | CO24: =IF(BT24="Yes",1,0) | CP24: =IF(AND(BU24="Yes",BV24="No"),1,0) | CQ24: =IF(BW24="Yes",1,0) | CR24: =IF(AP24="",0,IF(AP24>7,1,0)) | CS24: =IF(OR(BD24<>"Monthly",BD24<>"Quarterly",BD24<>"Semi-Annually"),0,1) | CT24: =IF(BX24="Yes",1,0) | CU24: =IF(BY24="Yes",1,0) | CV24: =IF(BZ24="Yes",1,0) | CW24: =IF(CA24="No",1,0) | CX24: =IF(B24="",0,IF(AK24>=5000000,0,1)) | CY24: =IF(B24="",0,IF(AL24>=5000000,0,1)) | CZ24: =IF(OR(DA24=1,DB24=1,DC24=1),0,IF(B24="",0,IF(OR(AND(AN24="Tier 1",X24="No",OR(AI24>$AJ$3,AJ24>$AJ$4)),(AND(AN24="Tier 1",X24="Yes",AJ24>$AJ$5)),(AND(AN24="Tier 2",X24="No",OR(AI24>$AK$3,AJ24>$AK$4))),(AND(AN24="Tier 2",X24="Yes",AJ24>$AK$5)),(AND(AN24="Tier 3",X24="No",OR(AI24>$AL$3,AJ24>$AL$4))),(AND(AN24="Tier 3",X24="Yes",AJ24>$AL$5))),1,0))) | DA24: =IF(OR(DB24=1,DC24=1),0,IF(B24="",0,IF(OR(AND(AN24="Tier 1",X24="No",OR(AI24>$AM$3,AJ24>$AM$4)),(AND(AN24="Tier 1",X24="Yes",AJ24>$AM$5)),(AND(AN24="Tier 2",X24="No",OR(AI24>$AN$3,AJ24>$AN$4))),(AND(AN24="Tier 2",X24="Yes",AJ24>$AN$5)),(AND(AN24="Tier 3",X24="No",OR(AI24>$AO$3,AJ24>$AO$4))),(AND(AN24="Tier 3",X24="Yes",AJ24>$AO$5))),1,0))) | DB24: =IF(DC24=1,0,IF(B24="",0,IF(OR(AND(AN24="Tier 1",X24="No",OR(AI24>$AP$3,AJ24>$AP$4)),(AND(AN24="Tier 1",X24="Yes",AJ24>$AP$5)),(AND(AN24="Tier 2",X24="No",OR(AI24>$AQ$3,AJ24>$AQ$4))),(AND(AN24="Tier 2",X24="Yes",AJ24>$AQ$5)),(AND(AN24="Tier 3",X24="No",OR(AI24>$AR$3,AJ24>$AR$4))),(AND(AN24="Tier 3",X24="Yes",AJ24>$AR$5))),1,0))) | DC24: =IF(B24="",0,IF(OR(AND(AN24="Tier 1",X24="No",OR(AI24>$AS$3,AJ24>$AS$4)),(AND(AN24="Tier 1",X24="Yes",AJ24>$AS$5)),(AND(AN24="Tier 2",X24="No",OR(AI24>$AT$3,AJ24>$AT$4))),(AND(AN24="Tier 2",X24="Yes",AJ24>$AT$5)),(AND(AN24="Tier 3",X24="No",OR(AI24>$AU$3,AJ24>$AU$4))),(AND(AN24="Tier 3",X24="Yes",AJ24>$AU$5))),1,0)) | DD24: =IF((SUM(CE24:CX24)=0),0,W24) | DE24: =IF(OR(B24="",DD24>0),0,W24) | DF24: =IF(B24="",0,IF(COUNTIF(CE24:CX24,1)>0,0,L24-M24)) | DG24: =DE24+IF(DD24>0,0,DF24) | DH24: =IF(B24="","",M24+DF24) | DI24: =IF(B24="",0,J24-K24) | DJ24: =IF(OR(BF24="EUR",BF24="CAD",BF24="GBP",BF24="AUD"),(GA24*(1-V24))+(HG24)+IF(HX24="",0,HX24*(1-U24)),0) | DK24: =IF(BF24="EUR",33%,IF(BF24="CAD",38%,IF(BF24="GBP",51%,IF(BF24="AUD",61%,0)))) | DL24: =DJ24*DK24 | DN24: =IF(OR(Y24="Second Lien",Y24="Tier 1 Split Lien",Y24="Tier 2 Split Lien"),DG24,0) | DO24: =DN24*DN$6 | DP24: =DG24-DO24 | DQ24: =IF(Y24="Second Lien",DP24,0) | DR24: =DQ24*DQ$6 | DS24: =DP24-DR24 | DT24: =IF(BH24="Yes",DS24,0) | DU24: =DT24*DT$6 | DV24: =DS24-DU24 | DW24: =IF(OR(BG24="Canada",BG24="United Kingdom",BG24="Australia",BG24="Netherlands Antilles",BG24="Bermuda",BG24="Cayman Islands",BG24="British Virgin Islands",BG24="Channel Islands",BG24="Isle of Man",BG24="Australia",BG24="Netherlands",BG24="Germany",BG24="Sweden",BG24="Switzerland",BG24="Austria",BG24="Belgium",BG24="Denmark",BG24="Finland",BG24="Iceland",BG24="Ireland",BG24="Lichtenstein",BG24="Luxemborg",BG24="Norway"),DV24,0) | DX24: =DW24*DW$6 | DY24: =DV24-DX24 | DZ24: =IF(BI24="Yes",DY24,0) | EA24: =DZ24*DZ$6 | EB24: =DY24-EA24 | EC24: =IF(OR(Z24="Delayed Draw",Z24="Revolver"),EB24,0) | ED24: =EC24*EC$6 | EE24: =EB24-ED24 | EF24: =IF(S24="Yes",EE24,0) | EG24: =EF24*EF$6 | EH24: =EE24-EG24 | EI24: =IF(Q24="Yes",EH24,0) | EJ24: =EI24*EI$6 | EK24: =EH24-EJ24 | EL24: =IF(BD24="Semi-Annually",EK24,0) | EM24: =EL24*EL$6 | EN24: =EK24-EM24 | EO24: =IF(BK24="Yes",EN24,0) | EP24: =EO24*EO$6 | EQ24: =EN24-EP24 | ER24: =IF(BL24="Yes",EQ24,0) | ES24: =ER24*ER$6 | ET24: =EQ24-ES24 | EU24: =IF(BM24="Yes",ET24,0) | EV24: =EU24*EU$6 | EW24: =ET24-EV24 | EX24: =IF(BV24="Yes",EW24,0) | EY24: =EX24*EX$6 | EZ24: =EW24-EY24 | FA24: =IF(AR24="Yes",EZ24,0) | FB24: =FA24*FA$6 | FC24: =EZ24-FB24 | FD24: =IF(OR(BF24="EUR",BF24="AUD",BF24="CAD",BF24="GBP"),FC24,0) | FE24: =FD24*FD$6 | FF24: =FC24-FE24 | FG24: =FF24 | FH24: =IF(FF24=0,0,VLOOKUP(C24,$GU$10:$GV$406,2,FALSE)*FF24) | FI24: =FF24-FH24 | FJ24: =FI24 | FK24: =IF(OR(IB24="",FI24<0.01),,VLOOKUP(IB24,$GL$10:$GM$406,2,FALSE)*FI24) | FL24: =FI24-FK24 | FM24: =FL24 | FN24: =IF(FL24=0,0,VLOOKUP(C24,$HD$10:$HE$406,2,FALSE)*FL24) | FO24: =FL24-FN24 | FP24: =IF(SUM(CY24:DC24)>0,0,IF(AND(AL24>=5000000,AL24<7500000),FO24,0)) | FQ24: =IF(B24="",0,FP24*FP$6*(1-$U24)) | FR24: =FO24-FQ24 | FS24: =IF(SUM(CY24:DC24)>0,0,IF(AL24<15000000,FR24,0)) | FT24: =IF(B24="",0,FS24*FS$6*(1-$U24)) | FU24: =FR24-FT24 | FV24: =IF(SUM(CY24:DC24)>0,0,IF(OR(AND(X24="No",AN24="Tier 1",AI24>$AG$3),AND(X24="No",AN24="Tier 2",AI24>$AH$3),AND(X24="No",AN24="Tier 3",AI24>$AI$3)),FU24,0)) | FW24: =IF(SUM(CY24:DC24)>0,0,IF(OR(AND(X24="No",AN24="Tier 1",AJ24>$AG$4),AND(X24="No",AN24="Tier 2",AJ24>$AH$4),AND(X24="No",AN24="Tier 3",AJ24>$AI$4)),FU24,0)) | FX24: =IF(SUM(CY24:DC24)>0,0,IF(OR(AND(X24="Yes",AN24="Tier 1",AJ24>$AG$5),AND(X24="Yes",AN24="Tier 2",AJ24>$AH$5),AND(X24="Yes",AN24="Tier 3",AJ24>$AI$5)),FU24,0)) | FY24: =IF(SUM(FV24:FX24)>0,FU24,0) | FZ24: =IF(B24="",0,FY24*FV$6*(1-MIN(90%,T24))) | GA24: =FU24-FZ24 | GB24: =IF(AND(N24="No",DI24=0),GA24,IF(AND(N24="No",DI24<>0,K24=0),0,IF(AND(N24="No",DI24<>0,K24>0,J24<>K24),MAX(0,M24-(DH24-GA24)),DG24))) | GC24: =+GB24*V24 | GD24: =IFERROR(GC24/K24,"") | GE24: =IF(IB24="","",IB24) | GF24: {=IF(SUM(IF(IB$9:IB23=IB24,1,0))>0,0,SUMIF($IB$10:$IB$406,IB24,$FI$10:$FI$406))} | GG24: =GF24 | GH24: =GH23+1 | GI24: =LARGE($GG$10:$GG$406,GH24) | GJ24: =IF(GH24>GH$6,0,IF(GH24=$GH$2,$GJ$2,IF(GH24<4,$GJ$3,$GJ$4))) | GK24: =MAX(0,GI24-GJ24) | GL24: {=IF(GI24=0,0,LARGE(IF($GF$10:$GF$406=GI24,$GE$10:$GE$406,0),COUNTIF($GI$10:$GI$406,GI24)-COUNTIF(GI$9:GI23,GI24)))} | GM24: =IF(GI24=0,0,GK24/GI24) | GO24: =IF(C24="","",IF(ISERROR(MATCH(C24,C$10:C23,0)),MAX(GO$10:GO23)+1,INDEX(GO$10:GO23,MATCH(C24,C$10:C23,0)))) | GP24: =IF(COUNTIF($A$10:A24,A24)<=1,SUMIF($A$10:$A$406,A24,$FG$10:$FG$406),0) | GQ24: =GQ23+1 | GR24: =LARGE($GP$10:$GP$406,GQ24) | GS24: =IF(GQ24>GQ$6,0,IF(GQ24<=GQ$2,GS$2,IF(AND(GQ24<=$GQ$3,GQ24>$GQ$2),GS$3,GS$4))) | GT24: =MAX(0,GR24-GS24) | GU24: {=IF(GR24=0,0,LARGE(IF($GP$10:$GP$406=GR24,$GO$10:$GO$406,0),COUNTIF($GR$10:$GR$406,GR24)-COUNTIF(GR$9:GR23,GR24)))} | GV24: =IF(GR24=0,0,GT24/GR24) | GX24: =IF(C24="","",IF(ISERROR(MATCH(C24,C$10:C23,0)),MAX(GO$10:GO23)+1,INDEX(GO$10:GO23,MATCH(C24,C$10:C23,0)))) | GY24: =IF(COUNTIF($A$10:A24,A24)<=1,SUMIF($A$10:$A$406,A24,$FG$10:$FG$406),0) | GZ24: =GZ23+1 | HA24: =LARGE($GY$10:$GY$406,GZ24) | HB24: - | HC24: =IF(GZ24<6,MAX(0,$HC$2/5),0) | HD24: {=IF(HA24=0,0,LARGE(IF($GY$10:$GY$406=HA24,$GX$10:$GX$406,0),COUNTIF($HA$10:$HA$406,HA24)-COUNTIF(HA$9:HA23,HA24)))} | HE24: =IF(HA24=0,0,HC24/HA24) | HG24: =DG24-GA24 | HH24: 0 | HI24: =MIN(HH24,DE24) | HK24: =IF(COUNTIF($C$10:$C$406,HK23+1),HK23+1,"") | HL24: =SUMIF($C$10:$C$406,HK24,$DG$10:$DG$406) | HN24: =MIN(HO24:HS24) | HO24: =IF(B24="","",$M24) | HP24: =IF($N24="Yes",IF(P24>=6,0,MIN($T24*$M24,$U24*$M24)),"") | HQ24: =IF(AND(N24="Yes",P24>=6),"",IF($S24="Yes",$R24*$M24,"")) | HR24: =IF($Q24="Yes",MIN($M24,$T24*$M24),"") | HS24: =IF(AND($N24="Yes",$P24>=6),"",IF(OR(CY24=1,DC24=1,),MIN($T24*$M24,$U24*$M24),IF(OR(CZ24=1,DA24=1,DB24=1),IF(AK24>=5000000,MIN($T24*$M24,$IE24*$M24),MIN($T24*$M24,$U24*$M24)),""))) | HT24: =IF(DD24>0,DD24,"") | HU24: =IF(B24="",0,$L24-$M24) | HV24: =IF(OR(SUM(HP24:HT24)>0,P24>=6),"",IF($B24="","",1)) | HW24: =IF(AND($HT24<>0,OR(HT24<=MIN(HP24:HS24),SUM(HP24:HS24)=0)),$HT24,0) | HX24: =IF(AND($HS24<>0,OR(AND($HS24<>$HT24,$HS24<>$HR24,$HS24<>$HQ24,$HS24<>$HP24,$HS24<MIN($HP24:$HR24),$HS24<HT24),SUM($HP24:$HR24)+SUM(HT24)=0),IA24<=0),$HS24,0) | HY24: =IF(AND($HR24<>0,OR(AND($HR24<>$HT24,$HR24<>$HS24,$HR24<>$HQ24,$HR24<>$HP24),$HR24<MIN($HP24:$HQ24),$HR24<MIN($HS24:$HT24),SUM($HP24:$HQ24)+SUM($HS24:$HT24)=0)),$HR24,0) | HZ24: =IF(AND($HQ24<>0,OR(AND($HQ24<>$HT24,HQ24<>HS24,HQ24<>HR24,HQ24<>HP24,HQ24<MIN(HR24:HT24)),SUM(HP24)+SUM(HR24:HT24)=0)),$HQ24,0) | IA24: =IF(AND($HP24<>0,OR(HP24<=MIN(HQ24:HT24),SUM(HQ24:HT24)=0)),$HP24,0) | IB24: 41 | IC24: =HU24=DF24 | IE24: =IF(B24="","",IF(AND(Y24="Second Lien",OR(CZ24=1,DA24=1,DB24=1)),50%,IF(CZ24=1,90%,IF(DA24=1,80%,IF(DB24=1,65%,"No Initial Haircut")))))
