Workbook
Name a: #REF!
Name a: #REF!
Name AUGUST: #REF!
Name AUGUST: #REF!
Name CAPSTOCK: #REF!
Name CAPSTOCK: #REF!
Name CASHREC: #REF!
Name CASHREC: #REF!
Name check1: #REF!
Name check1: #REF!
Name CHECKLIST: #REF!
Name CHECKLIST: #REF!
Name cklst: [3]Chklst!$A$1:$C$26
Name CLASSEXP: #REF!
Name CLASSEXP: #REF!
Name COST: #REF!
Name COST: #REF!
Name COST2: #REF!
Name COST2: #REF!
Name Days: '[4]Cost Rollforward - PTO'!$C$45
Name Days_2: '[5]Cost Roll'!$C$52
Name DERIVATIVE: #REF!
Name DERIVATIVE: #REF!
Name DETAIL: #REF!
Name DETAIL: #REF!
Name DISTREC: #REF!
Name DISTREC: #REF!
Name DISTRIBUTION: #REF!
Name DISTRIBUTION: #REF!
Name DVD: #REF!
Name DVD: #REF!
Name DVDII: #REF!
Name DVDII: #REF!
Name EntityNames: [6]EntityLookup!$A$3:$A$5
Name EXPENSES: #REF!
Name EXPENSES: #REF!
Name Facility_Name: '[7]PAR Settled'!$B:$B
Name fadfs: '[8]Cost Roll'!$C$24
Name FAX: #REF!
Name FAX: #REF!
Name foursixtythree: #REF!
Name foursixtythree: #REF!
Name GAIN: #REF!
Name GAIN: #REF!
Name Gain_Loss_01: #REF!
Name Gain_Loss_01: #REF!
Name Gain_Loss_02: #REF!
Name Gain_Loss_02: #REF!
Name Gain_Loss_03: #REF!
Name Gain_Loss_03: #REF!
Name Gain_Loss_04: #REF!
Name Gain_Loss_04: #REF!
Name Gain_Loss_05: #REF!
Name Gain_Loss_05: #REF!
Name Gain_Loss_06: #REF!
Name Gain_Loss_06: #REF!
Name Gain_Loss_07: #REF!
Name Gain_Loss_07: #REF!
Name Gain_Loss_08: #REF!
Name Gain_Loss_08: #REF!

Sheet Inputs
A1: PENNANTPARK FLOATING RATE FUNDING I, LLC
A2: SERVICING REPORT
A4: Amounts are pro forma for proposed borrowing and related use of proceeds
A6: INPUTS
A8: Determination Date | J8: 45893
A9: Minimum Equity Amount Floor | J9: 30000000
A11: Exchange Rates
A12: USD | J12: 1
A13: CAD | J13: 0.72138
A14: AUD | J14: 0.64344
A15: EUR | J15: 1.1659
A17: Temporary Participation Pool Acquisition Date | J17: 45897

Sheet Borrowing Base
A1: PENNANTPARK FLOATING RATE FUNDING I, LLC
A2: BORROWING BASE CERTIFICATE
A3: Amounts are pro forma for proposed borrowing and related use of proceeds
A4: DETERMINATION DATE | J4: =Inputs!$J$8 -> 45893
A5: CONCENTRATION TEST AMOUNT | J5: ='Loan List'!DI6 -> 1.0192857e+09 | O5: Cash and Credit Facility Balance Projections
A8: BORROWING BASE - (A) minus (B) minus (A)(iv) | J8: =J10-J18-J14 -> 9.6501187e+08 | O8: AUD
K9: Check | O9: 0 | P9: Current Credit Facility Balance
B10: (A) | C10: Aggregate Collateral Balance (without duplication) sum of (i)-(vi) | J10: =SUM(J11:J16) -> 9.7268796e+08 | O10: =+O71 -> 0 | P10: Borrowing
C11: (i) Aggregate Principal Balance of all Collateral Loans (other than Defaulted, Restructured, Haircut Ineligible, and Discount) | J11: ='Loan List'!HW8 -> 8.6554057e+08 | O11: =SUM(O9:O10) -> 0 | P11: Projected Credit Facility Balance
C12: (ii) Defaulted Collateral Loan Balance | J12: ='Loan List'!IB8 -> 0 | O12: USD
C13: (iii) The aggregate purchase price of all Discount Loans that are Eligible Collateral Loans and not Defaulted, Haircut or Restructured | J13: ='Loan List'!IA8 -> 6259376.3 | O13: =325500000-20800000+23000000+3000000-12000000+1200000+6000000+9500000+7500000-3000000-17000000+5000000+15000000+4000000+35500000-13000000+19000000+5000000+6000000+3500000-27000000+18000000+10000000+5000000+5000000-10000000+17000000+19000000+13000000-200000000-6000000+4000000+4000000-10000000+8000000+18000000+10000000+16000000+5000000+21000000+27000000+40000000+5000000+15000000+16000000-27000000+15000000+8000000+15000000+18000000-54000000+20000000-58000000-23000000-43000000-15000000-46000000+10000000+10000000+7500000-6500000-115000000+32000000+46000000-81000000+8000000+50000000+12000000+69000000+11000000-80000000-50000000-25500000+11000000+20000000+10000000+10000000+20000000+20000000-5000000-65000000+20000000+60000000+30000000+20000000-35000000-7000000+10000000-40000000-50000000+30000000-48000000+20000000-45000000-35000000+15000000-35000000-55000000+15000000+160000000+75000000+50000000+30000000-130000000-42000000+50000000+55000000+40000000+50000000+80000000+20000000+100000000+20000000+25000000+50000000-320000000-30000000+20000000-55000000+25000000+20000000+75000000+70000000 -> 462400000 | P13: Current Credit Facility Balance
C14: (iv) The aggregate Unfunded Commitments of all Delayed Drawdown and Revolvers that are Eligible Loans | J14: ='Loan List'!HV8 -> 6719880.5 | O14: =+O33 -> 220000000 | P14: Borrowing
C15: (v) The Credit Improved Loan Balance | J15: ='Loan List'!HZ8 -> 0 | O15: =SUM(O13:O14) -> 682400000 | P15: Projected Credit Facility Balance
C16: (vi) The Haircut Collateral Loan Balance | J16: ='Loan List'!HY8 -> 94168133 | O16: CAD
O17: 2000000 | P17: Current Credit Facility Balance
B18: (B) | C18: Excess Concentration Amount | J18: ='Loan List'!HH6 -> 956213.27 | O18: 0 | P18: Borrowing
O19: =SUM(O17:O18) -> 2000000 | P19: Projected Credit Facility Balance
A20: MAXIMUM AVAILABLE AMOUNT - Least of (A), (B) and (C) | J20: =MIN(J27,J35,J40) -> 6.9232108e+08 | O20: EUR
O21: 0 | P21: Current Credit Facility Balance
C22: Least of: | O22: 0 | P22: Borrowing
O23: =SUM(O21:O22) -> 0 | P23: Projected Credit Facility Balance
B24: (A) | D24: Facility Amount, less | J24: 718000000
D25: Revolving Exposure, plus | J25: ='Loan List'!$DG$6 -> 6719880.5 | O25: =+O11*Inputs!J14+'Borrowing Base'!O15+'Borrowing Base'!O19*Inputs!J13+'Borrowing Base'!O23*Inputs!J15 -> 683842760
D26: Amount on deposit in the Revolving Reserve Account | J26: 0 | O26: =+J46-O25 -> 0 | P26: Check
J27: =J24-J25+J26 -> 7.1128012e+08
O28: =+J53 -> 8478317.6 | P28: Equity/Cushion
B29: (B) | C29: (i) | D29: (x) Borrowing Base, multipled by | J29: ='Borrowing Base'!J8 -> 9.6501187e+08 | O29: =+J18 -> 956213.27 | P29: Net Penalty
D30: (y) Weighted Average Advance Rate, minus | J30: ='Loan List'!AZ2 -> 0.71355359
C31: (ii) | D31: Foreign Currency Variability Reserve, minus | J31: ='Loan List'!DM6 -> 130314.39 | O31: USD
C32: (iii) | D32: Revolving Exposure, plus | J32: ='Loan List'!$DG$6 -> 6719880.5 | O32: 29681562 | P32: Cash - Current & PreBorrowing
C33: (iv) | D33: Cash on deposit in Principal Collection Subaccount | J33: =+O51+O59*Inputs!J13+'Borrowing Base'!O67*Inputs!J15+'Borrowing Base'!O75*Inputs!J14 -> 10583588 | O33: 220000000 | P33: Borrowing
C34: (v) | D34: Amount on deposit in the Revolving Reserve Account | J34: =J26 -> 0 | O34: =SUM(O32:O33) -> 2.4968156e+08 | P34: Cash - Budgeted & PostBorrowing
J35: =(J29*J30)-J31-J32+J33+J34 -> 6.9232108e+08 | O35: -189760365 | P35: Asset Purchases
O36: -49500000 | P36: NARS Purchase
B37: (C) | C37: (A) | D37: Aggregate Collateral Balance, minus | J37: =J10-J14 -> 9.6596808e+08
C38: (B) | D38: Minimum Equity Amount, plus | J38: =MAX(Inputs!J9,SUM(LARGE('Loan List'!$HM$10:$HM$406,1),LARGE('Loan List'!$HM$10:$HM$406,2),LARGE('Loan List'!$HM$10:$HM$406,3))) -> 128975161
C39: (C) | D39: Cash on deposit in Principal Collection Subaccount | J39: =J33 -> 10583588
J40: =J37-J38+J39 -> 8.4757651e+08
A42: ADVANCES OUTSTANDING
A44: Advances Outstanding at beginning of the Interest Accrual Period | J44: =+O13+O9*Inputs!J14+'Borrowing Base'!O17*Inputs!J13+'Borrowing Base'!O21*Inputs!J15 -> 463842760
A45: ="Advances/(Repayments) during the period through and including " & TEXT(Inputs!J8,"mm/dd/yyyy") -> Advances/(Repayments) during the period through and including 08/24/2025 | J45: =+O14+O10*Inputs!J14+'Borrowing Base'!O18*Inputs!J13+'Borrowing Base'!O22*Inputs!J15 -> 220000000
A46: ="Advances Outstanding as of " & TEXT(Inputs!J8,"m/d/yy") -> Advances Outstanding as of 8/24/25 | J46: =J44+J45 -> 683842760
A48: MAXIMUM AVAILABILITY
B50: (a) | C50: Maximum Available Amount | J50: =$J$20 -> 6.9232108e+08
B51: (b) | C51: Advances | J51: =J46 -> 683842760 | O51: =SUM(O34:O50) -> 10421197 | P51: Cash - Net of UnSettled Trades
A53: AVAILABILITY - (a) minus (b) | J53: =J50-J51 -> 8478317.6 | O53: CAD
O54: 225112.54 | P54: Cash - Current & PreBorrowing
P55: Borrowing
A56: EVENTS OF DEFAULT | J56: =Compliance!J75 -> PASS
A57: COVERAGE TESTS | J57: =Compliance!J5 -> PASS | O57: =SUM(O54:O56) -> 225112.54 | P57: Cash - Budgeted & PostBorrowing
A58: PORTFOLIO QUALITY TESTS | J58: =Concentrations!O5 -> PASS
B59: If not satisfied, improving: | J59: Yes | O59: =SUM(O57:O58) -> 225112.54 | P59: Cash - Net of UnSettled Trades
B61: IN WITNESS WHEREOF, the undersigned has duly executed this Report. | O61: EUR
B62: By: | O62: 0 | P62: Cash - Current & PreBorrowing
P63: Borrowing
C65: Signature | O65: =SUM(O62:O64) -> 0 | P65: Cash - Budgeted & PostBorrowing
C67: Andrew Jordan | O67: =SUM(O65:O66) -> 0 | P67: Cash - Net of UnSettled Trades
C68: (Print Name)
O69: AUD
C70: Managing Director | O70: 0 | P70: Cash - Current & PreBorrowing
C71: Title | P71: Borrowing
C73: =TODAY() -> 45896 | O73: =SUM(O70:O72) -> 0 | P73: Cash - Budgeted & PostBorrowing
C74: Date
O75: =SUM(O73:O74) -> 0 | P75: Cash - Net of UnSettled Trades

Sheet Loan List
B1: ='Borrowing Base'!A1 -> PENNANTPARK FLOATING RATE FUNDING I, LLC | AG1: 20% Conc. Limit | AJ1: Level 1 - 10% Haircut | AM1: Level 2 - 20% Haircut | AP1: Level 3 - 35% Haircut | AS1: Level 4 - Max Eligibility - 50% Haircut | GI1: No of Industry | GJ1: Limit | GK1: Limit $ | GR1: No of Obligor | GS1: Limit % | GT1: Limit $ | HA1: No of Obligor | HB1: Limit % | HC1: Limit $ | HD1: Total Excess
B2: Loan List | AG2: Tier 1 Obligor | AH2: Tier 2 Obligor | AI2: Tier 3 Obligor | AJ2: Tier 1 Obligor | AK2: Tier 2 Obligor | AL2: Tier 3 Obligor | AM2: Tier 1 Obligor | AN2: Tier 2 Obligor | AO2: Tier 3 Obligor | AP2: Tier 1 Obligor | AQ2: Tier 2 Obligor | AR2: Tier 3 Obligor | AS2: Tier 1 Obligor | AT2: Tier 2 Obligor | AU2: Tier 3 Obligor | AY2: Weighted Average Advance Rate: | AZ2: =SUMPRODUCT(($GC10:$GC406>0)*$GC10:$GC406*$V10:$V406)/SUMPRODUCT(($GC10:$GC406>0)*$GC10:$GC406) -> 0.71355359 | DN2: Limit % | DO2: 0.15 | DR2: 0.1 | DU2: 0.05 | DX2: 0.15 | EA2: 0.1 | ED2: 0.15 | EG2: 0.1 | EJ2: 0.25 | EM2: 0.1 | EP2: 0.03 | ES2: 0.15 | EV2: 0.05 | EY2: 0.15 | FB2: 0.1 | FE2: 0.15 | FQ2: 0.05 | FT2: 0.2 | FW2: 0.2 | GI2: 1 | GJ2: 0.25 | GK2: ='Borrowing Base'!J5*GJ2 -> 2.5482142e+08 | GR2: 3 | GS2: 0.06666666 | GT2: ='Borrowing Base'!J5*GS2 -> 67952372 | HA2: 5 | HB2: 0.3 | HC2: =HB2*'Borrowing Base'!J5 -> 3.0578571e+08 | HD2: =MAX(0,SUM(HB10:HB11)-HC2) -> 0
B3: ="Loan Portfolio as of: "&TEXT(Inputs!$J$8,"mmmm d, yyyy") -> Loan Portfolio as of: August 24, 2025 | AF3: SD/EBITDA | AG3: 5 | AH3: 4.25 | AI3: 3.75 | AJ3: 5.5 | AK3: 4.75 | AL3: 4.25 | AM3: 6 | AN3: 5.25 | AO3: 4.75 | AP3: 6.5 | AQ3: 5.75 | AR3: 5.25 | AS3: 7 | AT3: 6.25 | AU3: 5.75 | AY3: Weighted Average Coupon: | AZ3: =IFERROR(SUMPRODUCT((AS10:AS406>0)*DH10:DH406*AS10:AS406)/SUMPRODUCT((AS10:AS406>0)*DH10:DH406),"N/A") -> N/A | DN3: Limit | DO3: =DO2*'Borrowing Base'!$J$5 -> 1.5289285e+08 | DR3: =DR2*'Borrowing Base'!$J$5 -> 1.0192857e+08 | DU3: =DU2*'Borrowing Base'!$J$5 -> 50964284 | DX3: =DX2*'Borrowing Base'!$J$5 -> 1.5289285e+08 | EA3: =EA2*'Borrowing Base'!$J$5 -> 1.0192857e+08 | ED3: =ED2*'Borrowing Base'!$J$5 -> 1.5289285e+08 | EG3: =EG2*'Borrowing Base'!$J$5 -> 1.0192857e+08 | EJ3: =EJ2*'Borrowing Base'!$J$5 -> 2.5482142e+08 | EM3: =EM2*'Borrowing Base'!$J$5 -> 1.0192857e+08 | EP3: =EP2*'Borrowing Base'!$J$5 -> 30578571 | ES3: =ES2*'Borrowing Base'!$J$5 -> 1.5289285e+08 | EV3: =EV2*'Borrowing Base'!$J$5 -> 50964284 | EY3: =EY2*'Borrowing Base'!$J$5 -> 1.5289285e+08 | FB3: =FB2*'Borrowing Base'!$J$5 -> 1.0192857e+08 | FE3: =FE2*'Borrowing Base'!$J$5 -> 1.5289285e+08 | FQ3: =FQ2*'Borrowing Base'!$J$5 -> 50964284 | FT3: =FT2*'Borrowing Base'!$J$5 -> 2.0385714e+08 | FW3: =FW2*'Borrowing Base'!$J$5 -> 2.0385714e+08 | GI3: 2 and 3 | GJ3: 0.15 | GK3: ='Borrowing Base'!J5*GJ3 -> 1.5289285e+08 | GR3: 5 | GS3: 0.06 | GT3: ='Borrowing Base'!J5*GS3 -> 61157141
AF4: TD/EBITDA | AG4: 7 | AH4: 6 | AI4: 5 | AJ4: 7.5 | AK4: 6.5 | AL4: 5.5 | AM4: 8 | AN4: 7 | AO4: 6 | AP4: 8.5 | AQ4: 7.5 | AR4: 6.5 | AS4: 9 | AT4: 8 | AU4: 7 | AY4: Specified Term SOFR: | AZ4: 0.0432224 | DN4: Total | DO4: =SUM(DO10:DO406) -> 1000000 | DR4: =SUM(DR10:DR406) -> 1000000 | DU4: =SUM(DU10:DU406) -> 0 | DX4: =SUM(DX10:DX406) -> 0 | EA4: =SUM(EA10:EA406) -> 15340518 | ED4: =SUM(ED10:ED406) -> 21097586 | EG4: =SUM(EG10:EG406) -> 14663827 | EJ4: =SUM(EJ10:EJ406) -> 0 | EM4: =SUM(EM10:EM406) -> 0 | EP4: =SUM(EP10:EP406) -> 0 | ES4: =SUM(ES10:ES406) -> 0 | EV4: =SUM(EV10:EV406) -> 0 | EY4: =SUM(EY10:EY406) -> 11464651 | FB4: =SUM(FB10:FB406) -> 0 | FE4: =SUM(FE10:FE406) -> 1232469.6 | FQ4: =SUM(FQ10:FQ406) -> 8000000 | FT4: =SUM(FT10:FT406) -> 79136453 | FW4: =SUM(FZ10:FZ406) -> 2.1341927e+08 | FX4: =SUM(FX10:FX406) -> 0 | FY4: =SUM(FY10:FY406) -> 62147861 | FZ4: =SUM(FZ10:FZ406) -> 2.1341927e+08 | GI4: Other | GJ4: 0.15 | GK4: ='Borrowing Base'!J5*GJ4 -> 1.5289285e+08 | GR4: All others | GS4: 0.05 | GT4: ='Borrowing Base'!J5*GS4 -> 50964284
AF5: UD/EBITDA | AG5: 6 | AH5: 5.25 | AI5: 4.5 | AJ5: 6.5 | AK5: 5.75 | AL5: 5 | AM5: 7 | AN5: 6.25 | AO5: 5.5 | AP5: 7.5 | AQ5: 6.75 | AR5: 6 | AS5: 8 | AT5: 7.25 | AU5: 6.5 | AV5: Weighted Average Life: | AW5: =SUMPRODUCT(AQ10:AQ406,$DH$10:$DH$406)/SUM($DH$10:$DH$406) -> 4.1797276 | AY5: Weighted Average Spread: | AZ5: =SUM($CC$10:$CD$406)/SUMIF($AR$10:$AR$406,"No",$DF$10:$DF$406) -> 0.058597603 | CY5: =SUM(CY10:CY406) -> 1 | CZ5: =SUM(CZ10:CZ406) -> 6 | DA5: =SUM(DA10:DA406) -> 24 | DB5: =SUM(DB10:DB406) -> 2 | DC5: =SUM(DC10:DC406) -> 1 | DD5: =SUM(DD10:DD406) -> 18 | DN5: Excess | DO5: =MAX(0,DO4-DO3) -> 0 | DR5: =MAX(0,DR4-DR3) -> 0 | DU5: =MAX(0,DU4-DU3) -> 0 | DX5: =MAX(0,DX4-DX3) -> 0 | EA5: =MAX(0,EA4-EA3) -> 0 | ED5: =MAX(0,ED4-ED3) -> 0 | EG5: =MAX(0,EG4-EG3) -> 0 | EJ5: =MAX(0,EJ4-EJ3) -> 0 | EM5: =MAX(0,EM4-EM3) -> 0 | EP5: =MAX(0,EP4-EP3) -> 0 | ES5: =MAX(0,ES4-ES3) -> 0 | EV5: =MAX(0,EV4-EV3) -> 0 | EY5: =MAX(0,EY4-EY3) -> 0 | FB5: =MAX(0,FB4-FB3) -> 0 | FE5: =MAX(0,FE4-FE3) -> 0 | FQ5: =MAX(0,FQ4-FQ3) -> 0 | FR5: Haircut Excess | FT5: =MAX(0,FT4-FT3) -> 0 | FU5: Haircut Excess | FW5: =MAX(0,SUM(FZ4:FZ4)-FW3) -> 9562132.7 | GA5: Haircut Excess | GH5: =COUNTIF(GG10:GG406,">"&0) -> 25 | GQ5: =COUNTIF(GQ10:GQ406,">"&0) -> 106 | GZ5: =COUNTIF(GZ10:GZ406,">"&0) -> 106
DF6: =SUM(DF10:DF406) -> 9.1115754e+08 | DG6: =SUM(DG10:DG406) -> 6719880.5 | DH6: =SUM(DH10:DH406) -> 9.1787742e+08 | DI6: =SUM(DI10:DI406) -> 1.0192857e+09 | DJ6: =SUM(DJ10:DJ406) -> 6719880.5 | DM6: =SUM(DM10:DM406) -> 130314.39 | DN6: Haircut | DO6: =IF(DO4<0.01,0,DO5/DO4) -> 0 | DP6: =SUM(DP10:DP406) -> 0 | DQ6: =SUM(DQ10:DQ406) -> 9.1787742e+08 | DR6: =IF(DR4<0.01,0,DR5/DR4) -> 0 | DS6: =SUM(DS10:DS406) -> 0 | DT6: =SUM(DT10:DT406) -> 9.1787742e+08 | DU6: =IF(DU4<0.01,0,DU5/DU4) -> 0 | DV6: =SUM(DV10:DV406) -> 0 | DW6: =SUM(DW10:DW406) -> 9.1787742e+08 | DX6: =IF(DX4<0.01,0,DX5/DX4) -> 0 | DY6: =SUM(DY10:DY406) -> 0 | DZ6: =SUM(DZ10:DZ406) -> 9.1787742e+08 | EA6: =IF(EA4<0.01,0,EA5/EA4) -> 0 | EB6: =SUM(EB10:EB406) -> 0 | EC6: =SUM(EC10:EC406) -> 9.1787742e+08 | ED6: =IF(ED4<0.01,0,ED5/ED4) -> 0 | EE6: =SUM(EE10:EE406) -> 0 | EF6: =SUM(EF10:EF406) -> 9.1787742e+08 | EG6: =IF(EG4<0.01,0,EG5/EG4) -> 0 | EH6: =SUM(EH10:EH406) -> 0 | EI6: =SUM(EI10:EI406) -> 9.1787742e+08 | EJ6: =IF(EJ4<0.01,0,EJ5/EJ4) -> 0 | EK6: =SUM(EK10:EK406) -> 0 | EL6: =SUM(EL10:EL406) -> 9.1787742e+08 | EM6: =IF(EM4<0.01,0,EM5/EM4) -> 0 | EN6: =SUM(EN10:EN406) -> 0 | EO6: =SUM(EO10:EO406) -> 9.1787742e+08 | EP6: =IF(EP4<0.01,0,EP5/EP4) -> 0 | EQ6: =SUM(EQ10:EQ406) -> 0 | ER6: =SUM(ER10:ER406) -> 9.1787742e+08 | ES6: =IF(ES4<0.01,0,ES5/ES4) -> 0 | ET6: =SUM(ET10:ET406) -> 0 | EU6: =SUM(EU10:EU406) -> 9.1787742e+08 | EV6: =IF(EV4<0.01,0,EV5/EV4) -> 0 | EW6: =SUM(EW10:EW406) -> 0 | EX6: =SUM(EX10:EX406) -> 9.1787742e+08 | EY6: =IF(EY4<0.01,0,EY5/EY4) -> 0 | EZ6: =SUM(EZ10:EZ406) -> 0 | FA6: =SUM(FA10:FA406) -> 9.1787742e+08 | FB6: =IF(FB4<0.01,0,FB5/FB4) -> 0 | FC6: =SUM(FC10:FC406) -> 0 | FD6: =SUM(FD10:FD406) -> 9.1787742e+08 | FE6: =IF(FE4<0.01,0,FE5/FE4) -> 0 | FF6: =SUM(FF10:FF406) -> 0 | FG6: =SUM(FG10:FG406) -> 9.1787742e+08 | FI6: =SUM(FI10:FI406) -> 0 | FJ6: =SUM(FJ10:FJ406) -> 9.1787742e+08 | FK6: =SUM(FK10:FK406) -> 9.1787742e+08 | FL6: =SUM(FL10:FL406) -> 0 | FM6: =SUM(FM10:FM406) -> 9.1787742e+08 | FO6: =SUM(FO10:FO406) -> 0 | FP6: =SUM(FP10:FP406) -> 9.1787742e+08 | FQ6: =IF(FQ4<0.01,0,FQ5/FQ4) -> 0 | FR6: =SUM(FR10:FR406) -> 0 | FS6: =SUM(FS10:FS406) -> 9.1787742e+08 | FT6: =IF(FT4<0.01,0,FT5/FT4) -> 0 | FU6: =SUM(FU10:FU406) -> 0 | FV6: =SUM(FV10:FV406) -> 9.1787742e+08 | FW6: =IF(SUM(FW4:FZ4)<0.01,0,FW5/SUM(FZ4:FZ4)) -> 0.044804449 | GA6: =SUM(GA10:GA406) -> 956213.27 | GB6: =SUM(GB10:GB406) -> 9.1692121e+08 | GC6: =SUM(GC10:GC406) -> 9.1022573e+08 | GD6: =SUM(GD10:GD406) -> 6.4949484e+08 | GH6: =SUM(GH10:GH406) -> 9.1787742e+08 | GI6: =GH5 -> 25 | GJ6: =SUM(GJ10:GJ406) -> 9.1787742e+08 | GL6: =SUM(GL10:GL406) -> 0 | GQ6: =SUM(GQ10:GQ406) -> 9.1787742e+08 | GR6: =GQ5 -> 106 | GS6: =SUM(GS10:GS406) -> 9.1787742e+08 | GU6: =SUM(GU10:GU406) -> 0 | GZ6: =SUM(GZ10:GZ406) -> 9.1787742e+08 | HA6: =GZ5 -> 106 | HB6: =SUM(HB10:HB406) -> 9.1787742e+08 | HD6: =SUM(HD10:HD406) -> 0 | HH6: =SUM(HH10:HH406) -> 956213.27 | HI6: =SUM(HI10:HI406) -> 0 | HV6: Eligible Unfunded
G7: =SUM(G10:G406) -> 1.0406533e+09 | H7: =SUM(H10:H406) -> 1.0339334e+09 | J7: =SUM(J10:J406) -> 1.0401773e+09 | K7: =SUM(K10:K406) -> 1.0334574e+09 | L7: =SUM(L10:L406) -> 1.0192857e+09 | M7: =SUM(M10:M406) -> 1.0125658e+09 | O7: =SUMIF(N10:N406,"Yes",K10:K406) -> 1701302.6 | W7: =SUM(W10:W406) -> 9.1115754e+08 | HT7: =SUM(HT10:HT406) -> 97553268
L8: Eligible Balances | N8: Loan Value Criteria | AA8: Credit/Performance Metrics | AR8: Interest Metrics | BE8: Other Loan Characteristics | BO8: Eligibility Criteria | CF8: Eligibility Criteria | DO8: Excess Concentrations | HO8: =SUM(HO10:HO406) -> 9.1115754e+08 | HP8: =SUM(HP10:HP406) -> 1.0125658e+09 | HV8: =SUMIF($HU$10:$HU$406,"",$HV$10:$HV$406) -> 6719880.5 | HW8: =SUMIF(HW10:HW406,"> 0",HP10:HP406) -> 8.6554057e+08 | HX8: =SUM(HX10:HX406) -> 0 | HY8: =SUM(HY10:HY406) -> 94168133 | HZ8: =SUM(HZ10:HZ406) -> 0 | IA8: =SUM(IA10:IA406) -> 6259376.3 | IB8: =SUM(IB10:IB406) -> 0
B9: Loan Number | C9: Obligor | D9: Obligor Name | E9: Security Name | F9: Purchase Date (Date Loan contributed to the facility) | G9: Total Commitment (Issue Currency) | H9: Outstanding Principal Balance (Issue Currency) | I9: Exchange Rate | J9: Total Commitment (USD) | K9: Outstanding Principal Balance (USD) | L9: Eligible Commitment (USD) | M9: Eligible Outstanding Principal Balance (USD) | N9: Defaulted Collateral Loan / Material Mod (Y/N) | O9: Date of Default | P9: Months Since Default | Q9: Credit Improved Loan (Y/N) | R9: Purchase Price | S9: Discount Collateral Loan (Y/N) | T9: Market Value | U9: Applicable Recovery Rate | V9: Advance Rate | W9: Aggregate Collateral Balance (Pre-Eligibility; Excluding Unfunded; Excluding Principal Acct) | X9: Stretch Senior Loan (Y/N) | Y9: Lien Type (First Lien / Split First Lien / Split Lien / Second Lien) | Z9: Loan Type (Term / Delayed Draw / Revolver) | AA9: Current Moody's Rating | AB9: Current S&P Rating | AC9: Initial Fixed Charge Coverage Ratio | AD9: Current Fixed Charge Coverage Ratio | AE9: Current Interest Coverage Ratio | AF9: Initial Debt to Capitalization Ratio | AG9: Initial Senior Debt/ EBITDA | AH9: Initial Total Debt/ EBITDA | AI9: Current Senior Debt/ EBITDA | AJ9: Current Total Debt/ EBITDA | AK9: Initial TTM EBITDA | AL9: Current TTM EBITDA | AM9: Current As of Date For Leverage and EBITDA | AN9: Tier 1 / Tier 2 Obligor | AO9: Maturity Date | AP9: Rem. Term to Maturity | AQ9: Avg Life | AR9: Fixed Rate (Y/N) | AS9: Coupon incl. PIK and PIK'able (if Fixed) | AT9: Floor Obligation (Y/N) | AU9: Floor | AV9: Spread incl. PIK and PIK'able | AW9: Base Rate | AX9: Greater of Base Rate and Floor | AY9: For Revolvers/Delayed Draw, commitment or other unused fee | AZ9: PIK / PIK'able For Floating Rate Loans | BA9: PIK / PIK'able For Fixed Rate Loans | BB9: Cash Spread On Floating Rate Loans | BC9: Cash Spread On Fixed Rate Loans | BD9: Interest Paid | BE9: Obligor Industry | BF9: Currency (USD / CAD / GBP / AUD / EUR) | BG9: Obligor Country | BH9: DIP Loan (Y/N) | BI9: Partial PIK Loan (Y/N) | BJ9: Non-Cash PIK Loan (Y/N) | BK9: Warrants to Purchase Equity (Y/N) | BL9: LBO Loan (Y/N) | BM9: Parti-cipation (Y/N) | BN9: Fifth Amendment Participation Pool | BO9: Convertible to Equity (Y/N) | BP9: Equity Security (Y/N) | BQ9: At Acquisition - Subject to offer or called for redemption (Y/N) | BR9: Margin Stock (Y/N) | BS9: Subject to withholding tax (Y/N) | BT9: At Acquisition - Defaulted Collateral Loan | BU9: Zero Coupon Obligation(Y/N) | BV9: Covenant Lite (Y/N) | BW9: Eligible Covenant Lite (Y/N) | BX9: Structured Finance Obligation, finance lease or chattel paper (Y/N) | BY9: Material Non-Credit Related Risk (Y/N) | BZ9: Primarily Secured by Real Estate, Construction Loan or Project Finance Loan (Y/N) | CA9: Interest Only Security (Y/N) | CB9: Satisfies all Other Eligibility Criteria (Y/N) | CC9: Aggregate Funded Spread | CD9: Aggregate Unfunded Spread | CF9: Purchased Below 85% of Par | CG9: Eligible Currency | CH9: Eligible Country | CI9: Convertible to Equity | CJ9: Equity Security | CK9: Subject to offer or called for redemption | CL9: Margin Stock | CM9: Subject to withholding tax | CN9: At Acquisition - Defaulted Collateral Loan | CO9: Non-cash PIK | CP9: Zero Coupon Obligation | CQ9: Covenant Lite | CR9: Structured Finance Obligation | CS9: Remaining term > 7 yrs | CT9: Interest Paid At Least Semi Annually | CU9: Material Non-Credit Related Risk | CV9: Real Estate, Construction or Project Finance Loan | CW9: Interest Only Security | CX9: Satisfies all Other Eligibility Criteria | CY9: EBITDA Requirement at Acquisition | CZ9: EBITDA Requirement Ongoing | DA9: Leverage 10% Haircut | DB9: Leverage 20% Haircut | DC9: Leverage 35% Haircut | DD9: Leverage - Final Haircut - 50% | DE9: Total Ineligible (excl. EBITDA and Leverage Ongoing) | DF9: Aggregate Collateral Balance (Post Eligibility; Including Haircut Ineligible; Excluding Unfunded) | DG9: Eligible Unfunded | DH9: Aggregate Collateral Balance (Post Eligibility; Including Eligible Unfunded) | DI9: Concentration Test Balance - OPB + Eligible Unfunded | DJ9: Revolving Exposure | DK9: Foreign Currency Loan OC Balance | DL9: Foreign Currency Variability Factor | DM9: Foreign Currency Variability Reserve | DO9: Second Lien and Split Lien | DP9: Excess | DQ9: Net Loan Balance | DR9: Second Lien | DS9: Excess | DT9: Net Loan Balance | DU9: DIP Collateral Loans | DV9: Excess | DW9: Net Loan Balance | DX9: Eligible Foreign Country | DY9: Excess | DZ9: Net Loan Balance | EA9: Partial PIK Loan | EB9: Excess | EC9: Net Loan Balance | ED9: Revolving / Delayed Drawdown | EE9: Excess | EF9: Net Loan Balance | EG9: Discount Loans | EH9: Excess | EI9: Net Loan Balance | EJ9: Credit Improved Loans | EK9: Excess | EL9: Net Loan Balance | EM9: Less than Quarterly Pay | EN9: Excess | EO9: Net Loan Balance | EP9: Warrants to Purchase Equity Securities | EQ9: Excess | ER9: Net Loan Balance | ES9: LBO Loan with Equity to Cap <25% | ET9: Excess | EU9: Net Loan Balance | EV9: Participation Interests | EW9: Excess | EX9: Net Loan Balance | EY9: Eligible Covenant Lite Loans | EZ9: Excess | FA9: Net Loan Balance | FB9: Fixed Rate Loan | FC9: Excess | FD9: Net Loan Balance | FE9: Agreed Foreign Currency | FF9: Excess | FG9: Net Loan Balance | FH9: Obligor | FI9: Excess | FJ9: Net Loan Balance | FK9: Obligor Industry | FL9: Excess | FM9: Net Loan Balance | FN9: Top 5 Obligors | FO9: Excess | FP9: Net Loan Balance | FQ9: LTM EBITDA >= 5,000,000 but < 7,500,000 | FR9: Excess; Haircut to 1-Recovery Rate | FS9: Net Loan Balance | FT9: LTM EBITDA < 15,000,000 | FU9: Excess; Haircut to 1-Recovery Rate | FV9: Net Loan Balance | FW9: LTM Snr Debt / EBITDA | FX9: LTM Total Debt / EBITDA | FY9: Stretch Senior LTM Total Debt / EBITDA | FZ9: Exceeds Leverage Limitation | GA9: Excess; Haircut to 1-Min(90% and Market Value) | GB9: Excess Concentration Test | GC9: Net Loan Balance | GD9: Borrowing Base | GF9: Industry No | GG9: Lookups'!F2:F3 Loan Balance | GH9: Industry Loan Balance | GI9: Industry Order | GJ9: Outstanding Loan Balance | GK9: Limit | GL9: Excess | GM9: Industry No (Matched) | GN9: Haircut | GP9: Obligor No | GQ9: Obligor Loan Balance | GR9: Obligor Order | GS9: Obligor Loan Balance | GT9: Limit | GU9: Excess | GV9: Obligor No | GW9: Haircut | GY9: Obligor No | GZ9: Obligor Loan Balance | HA9: Obligor Order | HB9: Obligor Loan Balance | HC9: Limit | HD9: Excess | HE9: Obligor No | HF9: Haircut | HH9: Excess Concentration Amount (Dynamic) | HI9: Excess Concentration Amount (HARD CODE on Last Day of Reinvestment Period) | HJ9: Applicable Excess Concentration Amount (Last Day of Reinvestment Period) | HL9: Obligor No | HM9: Obligor Loan Balance | HO9: Aggregate Collateral Balance (Pre-Eligibility; Excluding Unfunded; Excluding Principal Acct) | HP9: Outstanding Principal Balance | HQ9: Defaulted Collateral Loan Balance | HR9: Discount Loan Balance | HS9: Credit Improved Balance | HT9: Haircut Ineligible | HU9: Ineligibles | HV9: Total Unfunded | HW9: APB (Other Than Def, Inelib, Restructured, Haircut) | HX9: Ineligibles Test | HY9: Haircut Test | HZ9: Credit Improved Test | IA9: Discount Test | IB9: Defaulted Test | IC9: Lookups'!F2:F3 No | IF9: Initial Haircut Level
A10: ACP Avenu Buyer, LLC | B10: 1 | C10: 1 | D10: ACP Avenu Buyer, LLC | E10: Avenu (TL) | G10: 25589358 | H10: 25589358 | I10: =IF(B10="","",VLOOKUP(BF10,Inputs!$A$12:$J$15,10,FALSE)) -> 1 | J10: =IF(B10="","",G10*I10) -> 25589358 | K10: =IF(B10="","",H10*I10) -> 25589358 | L10: =IF(B10="","",IF(COUNTIF($CF10:$CY10,1)>0,0,J10)) -> 25589358 | M10: =IF(B10="","",IF(COUNTIF($CF10:$CY10,1)>0,0,K10)) -> 25589358 | N10: No | O10: N/A | P10: =IF(B10="","",IF(OR(O10="N/A",O10=""),0,YEARFRAC('Borrowing Base'!$J$4,'Loan List'!O10)*12)) -> 0 | Q10: No | R10: 0.99733768 | S10: =IF(B10="","",IF(R10<95%,"Yes","No")) -> No | T10: 0.99 | U10: =IF(B10="","",IF(OR(Y10="First Lien",Y10="Split First Lien",Y10="Tier 1 Split Lien",Y10="Tier 2 Split Lien"),50%,30%)) -> 0.5 | V10: =IF(B10="",0,IF(AND(Y10="First Lien",AN10="Tier 1"),IF(AND(X10="Yes",MIN(AH10,$AJ$5)>4.5),(((4.5/MIN(AH10,$AJ$5))*72.5%)+(((MIN(AH10,$AJ$5)-4.5)/MIN(AH10,$AJ$5))*35%)),72.5%),IF(AND(Y10="First Lien",AN10="Tier 2"),IF(AND(X10="Yes",MIN(AH10,$AK$5)>4.5),(((4.5/MIN(AH10,$AK$5))*72.5%)+(((MIN(AH10,$AK$5)-4.5)/MIN(AH10,$AK$5))*35%)),72.5%),IF(AND(X10="Yes",MIN(AH10,$AL$5)>4),(((4/MIN(AH10,$AL$5))*72.5%)+(((MIN(AH10,$AL$5)-4)/MIN(AH10,$AL$5))*35%)),IF(OR(Y10="First Lien",Y10="Split First Lien"),72.5%,IF(Y10="Split Lien", 53%,35%)))))) -> 0.67533071 | W10: =IF($C10="","",MIN($HP10:$HT10)) -> 25589358 | X10: Yes | Y10: First Lien | Z10: Term | AA10: NR | AB10: NR | AC10: 1.1174448 | AD10: 1.4275347 | AE10: 2.224929 | AF10: 0.4590766 | AG10: 5.1870295 | AH10: 5.1870295 | AI10: 4.6060902 | AJ10: 4.6060902 | AK10: 33738000 | AL10: 77650021 | AM10: 45747 | AN10: =IF(C10="","",(IF(AK10>=50000000,"Tier 1",(IF(OR(AK10>=20000000,AND(AK10>5000000,AC10>=1.25,AF10<=0.65)),"Tier 2","Tier 3"))))) -> Tier 2 | AO10: 47393 | AP10: =IF(C10="","",DAYS360(Inputs!$J$8,AO10)/360) -> 4.1055556 | AQ10: =IF(C10="","",AP10) -> 4.1055556 | AR10: No | AS10: 0 | AT10: Yes | AU10: 0.01 | AV10: 0.0475 | AW10: 0.042906 | AX10: =IF(C10="","",MAX(AU10,AW10)) -> 0.042906 | AY10: 0 | AZ10: 0 | BA10: 0 | BB10: =IF(B10="","",IF(AR10="No",AV10-AZ10,"")) -> 0.0475 | BC10: =IF(B10="","",IF(AR10="Yes",AS10-BA10,"")) | BD10: Quarterly | BE10: IT Services | BF10: USD | BG10: United States | BH10: No | BI10: =IF(B10="","",IF(OR(AND(AZ10>0,BB10>=2.5%,BB10<4%),AND(BA10>0,BC10>=6%,BC10<8%)),"Yes","No")) -> No | BJ10: =IF(B10="","",IF(OR(AND(AZ10>0,BB10<2.5%),AND(BA10>0,BC10<6%)),"Yes","No")) -> No | BK10: No | BL10: No | BM10: No | BN10: No | BO10: No | BP10: No | BQ10: No | BR10: No | BS10: No | BT10: No | BU10: No | BV10: No | BW10: No | BX10: No | BY10: No | BZ10: No | CA10: No | CB10: Yes | CC10: =IF(B10="","",IF(AT10="No",((BB10+AW10)-$AZ$4),((BB10+AX10)-$AZ$4))*IF(DE10>0,0,M10)) -> 1207398 | CD10: =IF(B10="","",AY10*(L10-M10)*IF(DE10>0,0,1)) -> 0 | CF10: =IF(AND(B10<>"",R10<=85%),1,0) -> 0 | CG10: =IF(B10="",0,(IF(OR(BF10="USD",BF10="CAD",BF10="GBP",BF10="AUD",BF10="EUR"),0,1))) -> 0 | CH10: =IF(B10="",0,(IF(OR(BG10="United States",BG10="Canada",BG10="United Kingdom",BG10="Australia",BG10="Netherlands Antilles",BG10="Bermuda",BG10="Cayman Islands",BG10="British Virgin Islands",BG10="Channel Islands",BG10="Isle of Man",BG10="Australia",BG10="Netherlands",BG10="Germany",BG10="Sweden",BG10="Switzerland",BG10="Austria",BG10="Belgium",BG10="Denmark",BG10="Finland",BG10="Iceland",BG10="Ireland",BG10="Lichtenstein",BG10="Luxemborg",BG10="Norway"),0,1))) -> 0 | CI10: =IF(BO10="Yes",1,0) -> 0 | CJ10: =IF(BP10="Yes",1,0) -> 0 | CK10: =IF(BQ10="Yes",1,0) -> 0 | CL10: =IF(BR10="Yes",1,0) -> 0 | CM10: =IF(BS10="Yes",1,0) -> 0 | CN10: =IF(BT10="Yes",1,0) -> 0 | CO10: =IF(OR(AND(BJ10="Yes",N10="No"),AND(BJ10="Yes",N10="Yes",P10>=6)),1,0) -> 0 | CP10: =IF(BU10="Yes",1,0) -> 0 | CQ10: =IF(AND(BV10="Yes",BW10="No"),1,0) -> 0 | CR10: =IF(BX10="Yes",1,0) -> 0 | CS10: =IF(AP10="",0,IF(AP10>7,1,0)) -> 0 | CT10: =IF(OR(BD10<>"Monthly",BD10<>"Quarterly",BD10<>"Semi-Annually"),0,1) -> 0 | CU10: =IF(BY10="Yes",1,0) -> 0 | CV10: =IF(BZ10="Yes",1,0) -> 0 | CW10: =IF(CA10="Yes",1,0) -> 0 | CX10: =IF(CB10="No",1,0) -> 0 | CY10: =IF(B10="",0,IF(AK10>=5000000,0,1)) -> 0 | CZ10: =IF(B10="",0,IF(AL10>=5000000,0,1)) -> 0 | DA10: =IF(OR(DB10=1,DC10=1,DD10=1),0,IF(B10="",0,IF(OR(AND(AN10="Tier 1",X10="No",OR(AI10>$AJ$3,AJ10>$AJ$4)),(AND(AN10="Tier 1",X10="Yes",AJ10>$AJ$5)),(AND(AN10="Tier 2",X10="No",OR(AI10>$AK$3,AJ10>$AK$4))),(AND(AN10="Tier 2",X10="Yes",AJ10>$AK$5)),(AND(AN10="Tier 3",X10="No",OR(AI10>$AL$3,AJ10>$AL$4))),(AND(AN10="Tier 3",X10="Yes",AJ10>$AL$5))),1,0))) -> 0 | DB10: =IF(OR(DC10=1,DD10=1),0,IF(B10="",0,IF(OR(AND(AN10="Tier 1",X10="No",OR(AI10>$AM$3,AJ10>$AM$4)),(AND(AN10="Tier 1",X10="Yes",AJ10>$AM$5)),(AND(AN10="Tier 2",X10="No",OR(AI10>$AN$3,AJ10>$AN$4))),(AND(AN10="Tier 2",X10="Yes",AJ10>$AN$5)),(AND(AN10="Tier 3",X10="No",OR(AI10>$AO$3,AJ10>$AO$4))),(AND(AN10="Tier 3",X10="Yes",AJ10>$AO$5))),1,0))) -> 0 | DC10: =IF(DD10=1,0,IF(B10="",0,IF(OR(AND(AN10="Tier 1",X10="No",OR(AI10>$AP$3,AJ10>$AP$4)),(AND(AN10="Tier 1",X10="Yes",AJ10>$AP$5)),(AND(AN10="Tier 2",X10="No",OR(AI10>$AQ$3,AJ10>$AQ$4))),(AND(AN10="Tier 2",X10="Yes",AJ10>$AQ$5)),(AND(AN10="Tier 3",X10="No",OR(AI10>$AR$3,AJ10>$AR$4))),(AND(AN10="Tier 3",X10="Yes",AJ10>$AR$5))),1,0))) -> 0 | DD10: =IF(B10="",0,IF(OR(AND(AN10="Tier 1",X10="No",OR(AI10>$AS$3,AJ10>$AS$4)),(AND(AN10="Tier 1",X10="Yes",AJ10>$AS$5)),(AND(AN10="Tier 2",X10="No",OR(AI10>$AT$3,AJ10>$AT$4))),(AND(AN10="Tier 2",X10="Yes",AJ10>$AT$5)),(AND(AN10="Tier 3",X10="No",OR(AI10>$AU$3,AJ10>$AU$4))),(AND(AN10="Tier 3",X10="Yes",AJ10>$AU$5))),1,0)) -> 0 | DE10: =IF((SUM(CF10:CY10)=0),0,W10) -> 0 | DF10: =IF(OR(B10="",DE10>0),0,W10) -> 25589358 | DG10: =IF(B10="",0,IF(COUNTIF(CF10:CY10,1)>0,0,L10-M10)) -> 0 | DH10: =DF10+IF(DE10>0,0,DG10) -> 25589358 | DI10: =IF(B10="","",M10+DG10) -> 25589358 | DJ10: =IF(B10="",0,J10-K10) -> 0 | DK10: =IF(OR(BF10="EUR",BF10="CAD",BF10="GBP",BF10="AUD"),(GB10*(1-V10))+(HH10)+IF(HY10="",0,HY10*(1-U10)),0) -> 0 | DL10: =IF(BF10="EUR",33%,IF(BF10="CAD",38%,IF(BF10="GBP",51%,IF(BF10="AUD",61%,0)))) -> 0 | DM10: =DK10*DL10 -> 0 | DO10: =IF(OR(Y10="Second Lien",Y10="Tier 1 Split Lien",Y10="Tier 2 Split Lien"),DH10,0) -> 0 | DP10: =DO10*DO$6 -> 0 | DQ10: =DH10-DP10 -> 25589358 | DR10: =IF(Y10="Second Lien",DQ10,0) -> 0 | DS10: =DR10*DR$6 -> 0 | DT10: =DQ10-DS10 -> 25589358 | DU10: =IF(BH10="Yes",DT10,0) -> 0 | DV10: =DU10*DU$6 -> 0 | DW10: =DT10-DV10 -> 25589358 | DX10: =IF(OR(BG10="Canada",BG10="United Kingdom",BG10="Australia",BG10="Netherlands Antilles",BG10="Bermuda",BG10="Cayman Islands",BG10="British Virgin Islands",BG10="Channel Islands",BG10="Isle of Man",BG10="Australia",BG10="Netherlands",BG10="Germany",BG10="Sweden",BG10="Switzerland",BG10="Austria",BG10="Belgium",BG10="Denmark",BG10="Finland",BG10="Iceland",BG10="Ireland",BG10="Lichtenstein",BG10="Luxemborg",BG10="Norway"),DW10,0) -> 0 | DY10: =DX10*DX$6 -> 0 | DZ10: =DW10-DY10 -> 25589358 | EA10: =IF(BI10="Yes",DZ10,0) -> 0 | EB10: =EA10*EA$6 -> 0 | EC10: =DZ10-EB10 -> 25589358 | ED10: =IF(OR(Z10="Delayed Draw",Z10="Revolver"),EC10,0) -> 0 | EE10: =ED10*ED$6 -> 0 | EF10: =EC10-EE10 -> 25589358 | EG10: =IF(S10="Yes",EF10,0) -> 0 | EH10: =EG10*EG$6 -> 0 | EI10: =EF10-EH10 -> 25589358 | EJ10: =IF(Q10="Yes",EI10,0) -> 0 | EK10: =EJ10*EJ$6 -> 0 | EL10: =EI10-EK10 -> 25589358 | EM10: =IF(BD10="Semi-Annually",EL10,0) -> 0 | EN10: =EM10*EM$6 -> 0 | EO10: =EL10-EN10 -> 25589358 | EP10: =IF(BK10="Yes",EO10,0) -> 0 | EQ10: =EP10*EP$6 -> 0 | ER10: =EO10-EQ10 -> 25589358 | ES10: =IF(BL10="Yes",ER10,0) -> 0 | ET10: =ES10*ES$6 -> 0 | EU10: =ER10-ET10 -> 25589358 | EV10: =IF(AND(BM10="Yes",OR(BN10="No",AND(BN10="Yes",Inputs!$J$8=Inputs!$J$17+75))),EU10,0) -> 0 | EW10: =EV10*EV$6 -> 0 | EX10: =EU10-EW10 -> 25589358 | EY10: =IF(BW10="Yes",EX10,0) -> 0 | EZ10: =EY10*EY$6 -> 0 | FA10: =EX10-EZ10 -> 25589358 | FB10: =IF(AR10="Yes",FA10,0) -> 0 | FC10: =FB10*FB$6 -> 0 | FD10: =FA10-FC10 -> 25589358 | FE10: =IF(OR(BF10="EUR",BF10="AUD",BF10="CAD",BF10="GBP"),FD10,0) -> 0 | FF10: =FE10*FE$6 -> 0 | FG10: =FD10-FF10 -> 25589358 | FH10: =FG10 -> 25589358 | FI10: =IF(FG10=0,0,VLOOKUP(C10,$GV$10:$GW$406,2,FALSE)*FG10) -> 0 | FJ10: =FG10-FI10 -> 25589358 | FK10: =FJ10 -> 25589358 | FL10: =IF(OR(IC10="",FJ10<0.01),,VLOOKUP(IC10,$GM$10:$GN$406,2,FALSE)*FJ10) -> 0 | FM10: =FJ10-FL10 -> 25589358 | FN10: =FM10 -> 25589358 | FO10: =IF(FM10=0,0,VLOOKUP(C10,$HE$10:$HF$406,2,FALSE)*FM10) -> 0 | FP10: =FM10-FO10 -> 25589358 | FQ10: =IF(SUM(CZ10:DD10)>0,0,IF(AND(AL10>=5000000,AL10<7500000),FP10,0)) -> 0 | FR10: =IF(B10="",0,FQ10*FQ$6*(1-$U10)) -> 0 | FS10: =FP10-FR10 -> 25589358 | FT10: =IF(SUM(CZ10:DD10)>0,0,IF(AL10<15000000,FS10,0)) -> 0 | FU10: =IF(B10="",0,FT10*FT$6*(1-$U10)) -> 0 | FV10: =FS10-FU10 -> 25589358 | FW10: =IF(SUM(CZ10:DD10)>0,0,IF(OR(AND(X10="No",AN10="Tier 1",AI10>$AG$3),AND(X10="No",AN10="Tier 2",AI10>$AH$3),AND(X10="No",AN10="Tier 3",AI10>$AI$3)),FV10,0)) -> 0 | FX10: =IF(SUM(CZ10:DD10)>0,0,IF(OR(AND(X10="No",AN10="Tier 1",AJ10>$AG$4),AND(X10="No",AN10="Tier 2",AJ10>$AH$4),AND(X10="No",AN10="Tier 3",AJ10>$AI$4)),FV10,0)) -> 0 | FY10: =IF(SUM(CZ10:DD10)>0,0,IF(OR(AND(X10="Yes",AN10="Tier 1",AJ10>$AG$5),AND(X10="Yes",AN10="Tier 2",AJ10>$AH$5),AND(X10="Yes",AN10="Tier 3",AJ10>$AI$5)),FV10,0)) -> 0 | FZ10: =IF(SUM(FW10:FY10)>0,FV10,0) -> 0 | GA10: =IF(B10="",0,FZ10*FW$6*(1-MIN(90%,T10))) -> 0 | GB10: =FV10-GA10 -> 25589358 | GC10: =IF(AND(N10="No",DJ10=0),GB10,IF(AND(N10="No",DJ10<>0,K10=0),0,IF(AND(N10="No",DJ10<>0,K10>0,J10<>K10),MAX(0,M10-(DI10-GB10)),DH10))) -> 25589358 | GD10: =+GC10*V10 -> 17281279 | GE10: =IFERROR(GD10/K10,"") -> 0.67533071 | GF10: =IF(IC10="","",IC10) -> 41 | GG10: {=IF(SUM(IF(IC$9:IC9=IC10,1,0))>0,0,SUMIF($IC$10:$IC$406,IC10,$FJ$10:$FJ$406))} -> 1.2675e+08 | GH10: =GG10 -> 1.2675e+08 | GI10: 1 | GJ10: =LARGE($GH$10:$GH$406,GI10) -> 1.2675e+08 | GK10: =IF(GI10>GI$6,0,IF(GI10=$GI$2,$GK$2,IF(GI10<4,$GK$3,$GK$4))) -> 2.5482142e+08 | GL10: =MAX(0,GJ10-GK10) -> 0 | GM10: {=IF(GJ10=0,0,LARGE(IF($GG$10:$GG$406=GJ10,$GF$10:$GF$406,0),COUNTIF($GJ$10:$GJ$406,GJ10)-COUNTIF(GJ$9:GJ9,GJ10)))} -> 41 | GN10: =IF(GJ10=0,0,GL10/GJ10) -> 0 | GP10: 1 | GQ10: =IF(COUNTIF($A$10:A10,A10)<=1,SUMIF($A$10:$A$406,A10,$FH$10:$FH$406),0) -> 26818060 | GR10: 1 | GS10: =LARGE($GQ$10:$GQ$406,GR10) -> 50000000 | GT10: =IF(GR10>GR$6,0,IF(GR10<=GR$2,GT$2,IF(AND(GR10<=$GR$3,GR10>$GR$2),GT$3,GT$4))) -> 67952372 | GU10: =MAX(0,GS10-GT10) -> 0 | GV10: {=IF(GS10=0,0,LARGE(IF($GQ$10:$GQ$406=GS10,$GP$10:$GP$406,0),COUNTIF($GS$10:$GS$406,GS10)-COUNTIF(GS$9:GS9,GS10)))} -> 78 | GW10: =IF(GS10=0,0,GU10/GS10) -> 0 | GY10: 1 | GZ10: =IF(COUNTIF($A$10:A10,A10)<=1,SUMIF($A$10:$A$406,A10,$FH$10:$FH$406),0) -> 26818060 | HA10: 1 | HB10: =LARGE($GZ$10:$GZ$406,HA10) -> 50000000 | HC10: - | HD10: =IF(HA10<6,MAX(0,$HD$2/5),0) -> 0 | HE10: {=IF(HB10=0,0,LARGE(IF($GZ$10:$GZ$406=HB10,$GY$10:$GY$406,0),COUNTIF($HB$10:$HB$406,HB10)-COUNTIF(HB$9:HB9,HB10)))} -> 78 | HF10: =IF(HB10=0,0,HD10/HB10) -> 0 | HH10: =DH10-GB10 -> 0 | HI10: 0 | HJ10: =MIN(HI10,DF10) -> 0 | HL10: 1 | HM10: =SUMIF($C$10:$C$406,HL10,$DH$10:$DH$406) -> 25589358 | HO10: =MIN(HP10:HT10) -> 25589358 | HP10: =IF(B10="","",$M10) -> 25589358 | HQ10: =IF($N10="Yes",IF(P10>=6,0,MIN($T10*$M10,$U10*$M10)),"") | HR10: =IF(AND(N10="Yes",P10>=6),"",IF($S10="Yes",$R10*$M10,"")) | HS10: =IF($Q10="Yes",MIN($M10,$T10*$M10),"") | HT10: =IF(AND($N10="Yes",$P10>=6),"",IF(OR(CZ10=1,DD10=1,),MIN($T10*$M10,$U10*$M10),IF(OR(DA10=1,DB10=1,DC10=1),IF(AK10>=5000000,MIN($T10*$M10,$IF10*$M10),MIN($T10*$M10,$U10*$M10)),""))) | HU10: =IF(DE10>0,DE10,"") | HV10: =IF(B10="",0,$L10-$M10) -> 0 | HW10: =IF(OR(SUM(HQ10:HU10)>0,P10>=6),"",IF($B10="","",1)) -> 1 | HX10: =IF(AND($HU10<>0,OR(HU10<=MIN(HQ10:HT10),SUM(HQ10:HT10)=0)),$HU10,0) | HY10: =IF(AND($HT10<>0,OR(AND($HT10<>$HU10,$HT10<>$HS10,$HT10<>$HR10,$HT10<>$HQ10,$HT10<MIN($HQ10:$HS10),$HT10<HU10),SUM($HQ10:$HS10)+SUM(HU10)=0),IB10<=0),$HT10,0) -> 0 | HZ10: =IF(AND($HS10<>0,OR(AND($HS10<>$HU10,$HS10<>$HT10,$HS10<>$HR10,$HS10<>$HQ10),$HS10<MIN($HQ10:$HR10),$HS10<MIN($HT10:$HU10),SUM($HQ10:$HR10)+SUM($HT10:$HU10)=0)),$HS10,0) | IA10: =IF(AND($HR10<>0,OR(AND($HR10<>$HU10,HR10<>HT10,HR10<>HS10,HR10<>HQ10,HR10<MIN(HS10:HU10)),SUM(HQ10)+SUM(HS10:HU10)=0)),$HR10,0) | IB10: =IF(AND($HQ10<>0,OR(HQ10<=MIN(HR10:HU10),SUM(HR10:HU10)=0)),$HQ10,0) | IC10: =IF(C10="","",INDEX(Lookups!$E$2:$E$69,MATCH('Loan List'!BE10,Lookups!$F$2:$F$69,0))) -> 41 | ID10: =HV10=DG10 -> TRUE | IF10: =IF(B10="","",IF(AND(Y10="Second Lien",OR(DA10=1,DB10=1,DC10=1)),50%,IF(DA10=1,90%,IF(DB10=1,80%,IF(DC10=1,65%,"No Initial Haircut"))))) -> No Initial Haircut
A11: Arcfield Acquisition Corp. | B11: =IF(D11="","",B10+1) -> 2 | C11: =IF(COUNTIF($A$10:A10,A11)>0,C10,C10+1) -> 2 | D11: Arcfield Acquisition Corp. | E11: Arcfield (Term Loan) | G11: 6009486.5 | H11: 6009486.5 | I11: =IF(B11="","",VLOOKUP(BF11,Inputs!$A$12:$J$15,10,FALSE)) -> 1 | J11: =IF(B11="","",G11*I11) -> 6009486.5 | K11: =IF(B11="","",H11*I11) -> 6009486.5 | L11: =IF(B11="","",IF(COUNTIF($CF11:$CY11,1)>0,0,J11)) -> 6009486.5 | M11: =IF(B11="","",IF(COUNTIF($CF11:$CY11,1)>0,0,K11)) -> 6009486.5 | N11: No | O11: N/A | P11: =IF(B11="","",IF(OR(O11="N/A",O11=""),0,YEARFRAC('Borrowing Base'!$J$4,'Loan List'!O11)*12)) -> 0 | Q11: No | R11: 0.9975 | S11: =IF(B11="","",IF(R11<95%,"Yes","No")) -> No | T11: 0.995 | U11: =IF(B11="","",IF(OR(Y11="First Lien",Y11="Split First Lien",Y11="Tier 1 Split Lien",Y11="Tier 2 Split Lien"),50%,30%)) -> 0.5 | V11: =IF(B11="",0,IF(AND(Y11="First Lien",AN11="Tier 1"),IF(AND(X11="Yes",MIN(AH11,$AJ$5)>4.5),(((4.5/MIN(AH11,$AJ$5))*72.5%)+(((MIN(AH11,$AJ$5)-4.5)/MIN(AH11,$AJ$5))*35%)),72.5%),IF(AND(Y11="First Lien",AN11="Tier 2"),IF(AND(X11="Yes",MIN(AH11,$AK$5)>4.5),(((4.5/MIN(AH11,$AK$5))*72.5%)+(((MIN(AH11,$AK$5)-4.5)/MIN(AH11,$AK$5))*35%)),72.5%),IF(AND(X11="Yes",MIN(AH11,$AL$5)>4),(((4/MIN(AH11,$AL$5))*72.5%)+(((MIN(AH11,$AL$5)-4)/MIN(AH11,$AL$5))*35%)),IF(OR(Y11="First Lien",Y11="Split First Lien"),72.5%,IF(Y11="Split Lien", 53%,35%)))))) -> 0.725 | W11: =IF($C11="","",MIN($HP11:$HT11)) -> 6009486.5 | X11: Yes | Y11: First Lien | Z11: Term | AA11: NR | AB11: NR | AC11: 2.68 | AD11: 1.2512861 | AE11: 1.8366382 | AF11: 0.42754938 | AG11: 3.76 | AH11: 3.76 | AI11: 4.3704657 | AJ11: 4.3704657 | AK11: 35900000 | AL11: 61779000 | AM11: 45747 | AN11: =IF(C11="","",(IF(AK11>=50000000,"Tier 1",(IF(OR(AK11>=20000000,AND(AK11>5000000,AC11>=1.25,AF11<=0.65)),"Tier 2","Tier 3"))))) -> Tier 2 | AO11: 48149 | AP11: =IF(C11="","",DAYS360(Inputs!$J$8,AO11)/360) -> 6.1777778 | AQ11: =IF(C11="","",AP11) -> 6.1777778 | AR11: No | AS11: 0 | AT11: Yes | AU11: 0.01 | AV11: 0.05 | AW11: 0.043079 | AX11: =IF(C11="","",MAX(AU11,AW11)) -> 0.043079 | AY11: 0 | AZ11: 0 | BA11: 0 | BB11: =IF(B11="","",IF(AR11="No",AV11-AZ11,"")) -> 0.05 | BC11: =IF(B11="","",IF(AR11="Yes",AS11-BA11,"")) | BD11: Quarterly | BE11: Aerospace & Defense | BF11: USD | BG11: United States | BH11: No | BI11: =IF(B11="","",IF(OR(AND(AZ11>0,BB11>=2.5%,BB11<4%),AND(BA11>0,BC11>=6%,BC11<8%)),"Yes","No")) -> No | BJ11: =IF(B11="","",IF(OR(AND(AZ11>0,BB11<2.5%),AND(BA11>0,BC11<6%)),"Yes","No")) -> No | BK11: No | BL11: No | BM11: No | BN11: No | BO11: No | BP11: No | BQ11: No | BR11: No | BS11: No | BT11: No | BU11: No | BV11: No | BW11: No | BX11: No | BY11: No | BZ11: No | CA11: No | CB11: Yes | CC11: =IF(B11="","",IF(AT11="No",((BB11+AW11)-$AZ$4),((BB11+AX11)-$AZ$4))*IF(DE11>0,0,M11)) -> 299612.56 | CD11: =IF(B11="","",AY11*(L11-M11)*IF(DE11>0,0,1)) -> 0 | CF11: =IF(AND(B11<>"",R11<=85%),1,0) -> 0 | CG11: =IF(B11="",0,(IF(OR(BF11="USD",BF11="CAD",BF11="GBP",BF11="AUD",BF11="EUR"),0,1))) -> 0 | CH11: =IF(B11="",0,(IF(OR(BG11="United States",BG11="Canada",BG11="United Kingdom",BG11="Australia",BG11="Netherlands Antilles",BG11="Bermuda",BG11="Cayman Islands",BG11="British Virgin Islands",BG11="Channel Islands",BG11="Isle of Man",BG11="Australia",BG11="Netherlands",BG11="Germany",BG11="Sweden",BG11="Switzerland",BG11="Austria",BG11="Belgium",BG11="Denmark",BG11="Finland",BG11="Iceland",BG11="Ireland",BG11="Lichtenstein",BG11="Luxemborg",BG11="Norway"),0,1))) -> 0 | CI11: =IF(BO11="Yes",1,0) -> 0 | CJ11: =IF(BP11="Yes",1,0) -> 0 | CK11: =IF(BQ11="Yes",1,0) -> 0 | CL11: =IF(BR11="Yes",1,0) -> 0 | CM11: =IF(BS11="Yes",1,0) -> 0 | CN11: =IF(BT11="Yes",1,0) -> 0 | CO11: =IF(OR(AND(BJ11="Yes",N11="No"),AND(BJ11="Yes",N11="Yes",P11>=6)),1,0) -> 0 | CP11: =IF(BU11="Yes",1,0) -> 0 | CQ11: =IF(AND(BV11="Yes",BW11="No"),1,0) -> 0 | CR11: =IF(BX11="Yes",1,0) -> 0 | CS11: =IF(AP11="",0,IF(AP11>7,1,0)) -> 0 | CT11: =IF(OR(BD11<>"Monthly",BD11<>"Quarterly",BD11<>"Semi-Annually"),0,1) -> 0 | CU11: =IF(BY11="Yes",1,0) -> 0 | CV11: =IF(BZ11="Yes",1,0) -> 0 | CW11: =IF(CA11="Yes",1,0) -> 0 | CX11: =IF(CB11="No",1,0) -> 0 | CY11: =IF(B11="",0,IF(AK11>=5000000,0,1)) -> 0 | CZ11: =IF(B11="",0,IF(AL11>=5000000,0,1)) -> 0 | DA11: =IF(OR(DB11=1,DC11=1,DD11=1),0,IF(B11="",0,IF(OR(AND(AN11="Tier 1",X11="No",OR(AI11>$AJ$3,AJ11>$AJ$4)),(AND(AN11="Tier 1",X11="Yes",AJ11>$AJ$5)),(AND(AN11="Tier 2",X11="No",OR(AI11>$AK$3,AJ11>$AK$4))),(AND(AN11="Tier 2",X11="Yes",AJ11>$AK$5)),(AND(AN11="Tier 3",X11="No",OR(AI11>$AL$3,AJ11>$AL$4))),(AND(AN11="Tier 3",X11="Yes",AJ11>$AL$5))),1,0))) -> 0 | DB11: =IF(OR(DC11=1,DD11=1),0,IF(B11="",0,IF(OR(AND(AN11="Tier 1",X11="No",OR(AI11>$AM$3,AJ11>$AM$4)),(AND(AN11="Tier 1",X11="Yes",AJ11>$AM$5)),(AND(AN11="Tier 2",X11="No",OR(AI11>$AN$3,AJ11>$AN$4))),(AND(AN11="Tier 2",X11="Yes",AJ11>$AN$5)),(AND(AN11="Tier 3",X11="No",OR(AI11>$AO$3,AJ11>$AO$4))),(AND(AN11="Tier 3",X11="Yes",AJ11>$AO$5))),1,0))) -> 0 | DC11: =IF(DD11=1,0,IF(B11="",0,IF(OR(AND(AN11="Tier 1",X11="No",OR(AI11>$AP$3,AJ11>$AP$4)),(AND(AN11="Tier 1",X11="Yes",AJ11>$AP$5)),(AND(AN11="Tier 2",X11="No",OR(AI11>$AQ$3,AJ11>$AQ$4))),(AND(AN11="Tier 2",X11="Yes",AJ11>$AQ$5)),(AND(AN11="Tier 3",X11="No",OR(AI11>$AR$3,AJ11>$AR$4))),(AND(AN11="Tier 3",X11="Yes",AJ11>$AR$5))),1,0))) -> 0 | DD11: =IF(B11="",0,IF(OR(AND(AN11="Tier 1",X11="No",OR(AI11>$AS$3,AJ11>$AS$4)),(AND(AN11="Tier 1",X11="Yes",AJ11>$AS$5)),(AND(AN11="Tier 2",X11="No",OR(AI11>$AT$3,AJ11>$AT$4))),(AND(AN11="Tier 2",X11="Yes",AJ11>$AT$5)),(AND(AN11="Tier 3",X11="No",OR(AI11>$AU$3,AJ11>$AU$4))),(AND(AN11="Tier 3",X11="Yes",AJ11>$AU$5))),1,0)) -> 0 | DE11: =IF((SUM(CF11:CY11)=0),0,W11) -> 0 | DF11: =IF(OR(B11="",DE11>0),0,W11) -> 6009486.5 | DG11: =IF(B11="",0,IF(COUNTIF(CF11:CY11,1)>0,0,L11-M11)) -> 0 | DH11: =DF11+IF(DE11>0,0,DG11) -> 6009486.5 | DI11: =IF(B11="","",M11+DG11) -> 6009486.5 | DJ11: =IF(B11="",0,J11-K11) -> 0 | DK11: =IF(OR(BF11="EUR",BF11="CAD",BF11="GBP",BF11="AUD"),(GB11*(1-V11))+(HH11)+IF(HY11="",0,HY11*(1-U11)),0) -> 0 | DL11: =IF(BF11="EUR",33%,IF(BF11="CAD",38%,IF(BF11="GBP",51%,IF(BF11="AUD",61%,0)))) -> 0 | DM11: =DK11*DL11 -> 0 | DO11: =IF(OR(Y11="Second Lien",Y11="Tier 1 Split Lien",Y11="Tier 2 Split Lien"),DH11,0) -> 0 | DP11: =DO11*DO$6 -> 0 | DQ11: =DH11-DP11 -> 6009486.5 | DR11: =IF(Y11="Second Lien",DQ11,0) -> 0 | DS11: =DR11*DR$6 -> 0 | DT11: =DQ11-DS11 -> 6009486.5 | DU11: =IF(BH11="Yes",DT11,0) -> 0 | DV11: =DU11*DU$6 -> 0 | DW11: =DT11-DV11 -> 6009486.5 | DX11: =IF(OR(BG11="Canada",BG11="United Kingdom",BG11="Australia",BG11="Netherlands Antilles",BG11="Bermuda",BG11="Cayman Islands",BG11="British Virgin Islands",BG11="Channel Islands",BG11="Isle of Man",BG11="Australia",BG11="Netherlands",BG11="Germany",BG11="Sweden",BG11="Switzerland",BG11="Austria",BG11="Belgium",BG11="Denmark",BG11="Finland",BG11="Iceland",BG11="Ireland",BG11="Lichtenstein",BG11="Luxemborg",BG11="Norway"),DW11,0) -> 0 | DY11: =DX11*DX$6 -> 0 | DZ11: =DW11-DY11 -> 6009486.5 | EA11: =IF(BI11="Yes",DZ11,0) -> 0 | EB11: =EA11*EA$6 -> 0 | EC11: =DZ11-EB11 -> 6009486.5 | ED11: =IF(OR(Z11="Delayed Draw",Z11="Revolver"),EC11,0) -> 0 | EE11: =ED11*ED$6 -> 0 | EF11: =EC11-EE11 -> 6009486.5 | EG11: =IF(S11="Yes",EF11,0) -> 0 | EH11: =EG11*EG$6 -> 0 | EI11: =EF11-EH11 -> 6009486.5 | EJ11: =IF(Q11="Yes",EI11,0) -> 0 | EK11: =EJ11*EJ$6 -> 0 | EL11: =EI11-EK11 -> 6009486.5 | EM11: =IF(BD11="Semi-Annually",EL11,0) -> 0 | EN11: =EM11*EM$6 -> 0 | EO11: =EL11-EN11 -> 6009486.5 | EP11: =IF(BK11="Yes",EO11,0) -> 0 | EQ11: =EP11*EP$6 -> 0 | ER11: =EO11-EQ11 -> 6009486.5 | ES11: =IF(BL11="Yes",ER11,0) -> 0 | ET11: =ES11*ES$6 -> 0 | EU11: =ER11-ET11 -> 6009486.5 | EV11: =IF(AND(BM11="Yes",OR(BN11="No",AND(BN11="Yes",Inputs!$J$8=Inputs!$J$17+75))),EU11,0) -> 0 | EW11: =EV11*EV$6 -> 0 | EX11: =EU11-EW11 -> 6009486.5 | EY11: =IF(BW11="Yes",EX11,0) -> 0 | EZ11: =EY11*EY$6 -> 0 | FA11: =EX11-EZ11 -> 6009486.5 | FB11: =IF(AR11="Yes",FA11,0) -> 0 | FC11: =FB11*FB$6 -> 0 | FD11: =FA11-FC11 -> 6009486.5 | FE11: =IF(OR(BF11="EUR",BF11="AUD",BF11="CAD",BF11="GBP"),FD11,0) -> 0 | FF11: =FE11*FE$6 -> 0 | FG11: =FD11-FF11 -> 6009486.5 | FH11: =FG11 -> 6009486.5 | FI11: =IF(FG11=0,0,VLOOKUP(C11,$GV$10:$GW$406,2,FALSE)*FG11) -> 0 | FJ11: =FG11-FI11 -> 6009486.5 | FK11: =FJ11 -> 6009486.5 | FL11: =IF(OR(IC11="",FJ11<0.01),,VLOOKUP(IC11,$GM$10:$GN$406,2,FALSE)*FJ11) -> 0 | FM11: =FJ11-FL11 -> 6009486.5 | FN11: =FM11 -> 6009486.5 | FO11: =IF(FM11=0,0,VLOOKUP(C11,$HE$10:$HF$406,2,FALSE)*FM11) -> 0 | FP11: =FM11-FO11 -> 6009486.5 | FQ11: =IF(SUM(CZ11:DD11)>0,0,IF(AND(AL11>=5000000,AL11<7500000),FP11,0)) -> 0 | FR11: =IF(B11="",0,FQ11*FQ$6*(1-$U11)) -> 0 | FS11: =FP11-FR11 -> 6009486.5 | FT11: =IF(SUM(CZ11:DD11)>0,0,IF(AL11<15000000,FS11,0)) -> 0 | FU11: =IF(B11="",0,FT11*FT$6*(1-$U11)) -> 0 | FV11: =FS11-FU11 -> 6009486.5 | FW11: =IF(SUM(CZ11:DD11)>0,0,IF(OR(AND(X11="No",AN11="Tier 1",AI11>$AG$3),AND(X11="No",AN11="Tier 2",AI11>$AH$3),AND(X11="No",AN11="Tier 3",AI11>$AI$3)),FV11,0)) -> 0 | FX11: =IF(SUM(CZ11:DD11)>0,0,IF(OR(AND(X11="No",AN11="Tier 1",AJ11>$AG$4),AND(X11="No",AN11="Tier 2",AJ11>$AH$4),AND(X11="No",AN11="Tier 3",AJ11>$AI$4)),FV11,0)) -> 0 | FY11: =IF(SUM(CZ11:DD11)>0,0,IF(OR(AND(X11="Yes",AN11="Tier 1",AJ11>$AG$5),AND(X11="Yes",AN11="Tier 2",AJ11>$AH$5),AND(X11="Yes",AN11="Tier 3",AJ11>$AI$5)),FV11,0)) -> 0 | FZ11: =IF(SUM(FW11:FY11)>0,FV11,0) -> 0 | GA11: =IF(B11="",0,FZ11*FW$6*(1-MIN(90%,T11))) -> 0 | GB11: =FV11-GA11 -> 6009486.5 | GC11: =IF(AND(N11="No",DJ11=0),GB11,IF(AND(N11="No",DJ11<>0,K11=0),0,IF(AND(N11="No",DJ11<>0,K11>0,J11<>K11),MAX(0,M11-(DI11-GB11)),DH11))) -> 6009486.5 | GD11: =+GC11*V11 -> 4356877.7 | GE11: =IFERROR(GD11/K11,"") -> 0.725 | GF11: =IF(IC11="","",IC11) -> 1 | GG11: {=IF(SUM(IF(IC$9:IC10=IC11,1,0))>0,0,SUMIF($IC$10:$IC$406,IC11,$FJ$10:$FJ$406))} -> 57413376 | GH11: =GG11 -> 57413376 | GI11: =GI10+1 -> 2 | GJ11: =LARGE($GH$10:$GH$406,GI11) -> 1.0592467e+08 | GK11: =IF(GI11>GI$6,0,IF(GI11=$GI$2,$GK$2,IF(GI11<4,$GK$3,$GK$4))) -> 1.5289285e+08 | GL11: =MAX(0,GJ11-GK11) -> 0 | GM11: {=IF(GJ11=0,0,LARGE(IF($GG$10:$GG$406=GJ11,$GF$10:$GF$406,0),COUNTIF($GJ$10:$GJ$406,GJ11)-COUNTIF(GJ$9:GJ10,GJ11)))} -> 46 | GN11: =IF(GJ11=0,0,GL11/GJ11) -> 0 | GP11: =IF(C11="","",IF(ISERROR(MATCH(C11,C10:C$10,0)),MAX(GP10:GP$10)+1,INDEX(GP10:GP$10,MATCH(C11,C10:C$10,0)))) -> 2 | GQ11: =IF(COUNTIF($A$10:A11,A11)<=1,SUMIF($A$10:$A$406,A11,$FH$10:$FH$406),0) -> 6009486.5 | GR11: =GR10+1 -> 2 | GS11: =LARGE($GQ$10:$GQ$406,GR11) -> 41568911 | GT11: =IF(GR11>GR$6,0,IF(GR11<=GR$2,GT$2,IF(AND(GR11<=$GR$3,GR11>$GR$2),GT$3,GT$4))) -> 67952372 | GU11: =MAX(0,GS11-GT11) -> 0 | GV11: {=IF(GS11=0,0,LARGE(IF($GQ$10:$GQ$406=GS11,$GP$10:$GP$406,0),COUNTIF($GS$10:$GS$406,GS11)-COUNTIF(GS$9:GS10,GS11)))} -> 11 | GW11: =IF(GS11=0,0,GU11/GS11) -> 0 | GY11: =IF(C11="","",IF(ISERROR(MATCH(C11,C10:C$10,0)),MAX(GP10:GP$10)+1,INDEX(GP10:GP$10,MATCH(C11,C10:C$10,0)))) -> 2 | GZ11: =IF(COUNTIF($A$10:A11,A11)<=1,SUMIF($A$10:$A$406,A11,$FH$10:$FH$406),0) -> 6009486.5 | HA11: =HA10+1 -> 2 | HB11: =LARGE($GZ$10:$GZ$406,HA11) -> 41568911 | HC11: - | HD11: =IF(HA11<6,MAX(0,$HD$2/5),0) -> 0 | HE11: {=IF(HB11=0,0,LARGE(IF($GZ$10:$GZ$406=HB11,$GY$10:$GY$406,0),COUNTIF($HB$10:$HB$406,HB11)-COUNTIF(HB$9:HB10,HB11)))} -> 11 | HF11: =IF(HB11=0,0,HD11/HB11) -> 0 | HH11: =DH11-GB11 -> 0 | HI11: 0 | HJ11: =MIN(HI11,DF11) -> 0 | HL11: =IF(COUNTIF($C$10:$C$406,HL10+1),HL10+1,"") -> 2 | HM11: =SUMIF($C$10:$C$406,HL11,$DH$10:$DH$406) -> 6009486.5 | HO11: =MIN(HP11:HT11) -> 6009486.5 | HP11: =IF(B11="","",$M11) -> 6009486.5 | HQ11: =IF($N11="Yes",IF(P11>=6,0,MIN($T11*$M11,$U11*$M11)),"") | HR11: =IF(AND(N11="Yes",P11>=6),"",IF($S11="Yes",$R11*$M11,"")) | HS11: =IF($Q11="Yes",MIN($M11,$T11*$M11),"") | HT11: =IF(AND($N11="Yes",$P11>=6),"",IF(OR(CZ11=1,DD11=1,),MIN($T11*$M11,$U11*$M11),IF(OR(DA11=1,DB11=1,DC11=1),IF(AK11>=5000000,MIN($T11*$M11,$IF11*$M11),MIN($T11*$M11,$U11*$M11)),""))) | HU11: =IF(DE11>0,DE11,"") | HV11: =IF(B11="",0,$L11-$M11) -> 0 | HW11: =IF(OR(SUM(HQ11:HU11)>0,P11>=6),"",IF($B11="","",1)) -> 1 | HX11: =IF(AND($HU11<>0,OR(HU11<=MIN(HQ11:HT11),SUM(HQ11:HT11)=0)),$HU11,0) | HY11: =IF(AND($HT11<>0,OR(AND($HT11<>$HU11,$HT11<>$HS11,$HT11<>$HR11,$HT11<>$HQ11,$HT11<MIN($HQ11:$HS11),$HT11<HU11),SUM($HQ11:$HS11)+SUM(HU11)=0),IB11<=0),$HT11,0) -> 0 | HZ11: =IF(AND($HS11<>0,OR(AND($HS11<>$HU11,$HS11<>$HT11,$HS11<>$HR11,$HS11<>$HQ11),$HS11<MIN($HQ11:$HR11),$HS11<MIN($HT11:$HU11),SUM($HQ11:$HR11)+SUM($HT11:$HU11)=0)),$HS11,0) | IA11: =IF(AND($HR11<>0,OR(AND($HR11<>$HU11,HR11<>HT11,HR11<>HS11,HR11<>HQ11,HR11<MIN(HS11:HU11)),SUM(HQ11)+SUM(HS11:HU11)=0)),$HR11,0) | IB11: =IF(AND($HQ11<>0,OR(HQ11<=MIN(HR11:HU11),SUM(HR11:HU11)=0)),$HQ11,0) | IC11: =IF(C11="","",INDEX(Lookups!$E$2:$E$69,MATCH('Loan List'!BE11,Lookups!$F$2:$F$69,0))) -> 1 | ID11: =HV11=DG11 -> TRUE | IF11: =IF(B11="","",IF(AND(Y11="Second Lien",OR(DA11=1,DB11=1,DC11=1)),50%,IF(DA11=1,90%,IF(DB11=1,80%,IF(DC11=1,65%,"No Initial Haircut"))))) -> No Initial Haircut
A12: Archer Lewis, LLC | B12: =IF(D12="","",B11+1) -> 3 | C12: =IF(COUNTIF($A$10:A11,A12)>0,C11,C11+1) -> 3 | D12: Archer Lewis, LLC | E12: Archer Lewis (Term Loan) | G12: 5271860.2 | H12: 5271860.2 | I12: =IF(B12="","",VLOOKUP(BF12,Inputs!$A$12:$J$15,10,FALSE)) -> 1 | J12: =IF(B12="","",G12*I12) -> 5271860.2 | K12: =IF(B12="","",H12*I12) -> 5271860.2 | L12: =IF(B12="","",IF(COUNTIF($CF12:$CY12,1)>0,0,J12)) -> 5271860.2 | M12: =IF(B12="","",IF(COUNTIF($CF12:$CY12,1)>0,0,K12)) -> 5271860.2 | N12: No | O12: N/A | P12: =IF(B12="","",IF(OR(O12="N/A",O12=""),0,YEARFRAC('Borrowing Base'!$J$4,'Loan List'!O12)*12)) -> 0 | Q12: No | R12: 0.99000524 | S12: =IF(B12="","",IF(R12<95%,"Yes","No")) -> No | T12: 1 | U12: =IF(B12="","",IF(OR(Y12="First Lien",Y12="Split First Lien",Y12="Tier 1 Split Lien",Y12="Tier 2 Split Lien"),50%,30%)) -> 0.5 | V12: =IF(B12="",0,IF(AND(Y12="First Lien",AN12="Tier 1"),IF(AND(X12="Yes",MIN(AH12,$AJ$5)>4.5),(((4.5/MIN(AH12,$AJ$5))*72.5%)+(((MIN(AH12,$AJ$5)-4.5)/MIN(AH12,$AJ$5))*35%)),72.5%),IF(AND(Y12="First Lien",AN12="Tier 2"),IF(AND(X12="Yes",MIN(AH12,$AK$5)>4.5),(((4.5/MIN(AH12,$AK$5))*72.5%)+(((MIN(AH12,$AK$5)-4.5)/MIN(AH12,$AK$5))*35%)),72.5%),IF(AND(X12="Yes",MIN(AH12,$AL$5)>4),(((4/MIN(AH12,$AL$5))*72.5%)+(((MIN(AH12,$AL$5)-4)/MIN(AH12,$AL$5))*35%)),IF(OR(Y12="First Lien",Y12="Split First Lien"),72.5%,IF(Y12="Split Lien", 53%,35%)))))) -> 0.725 | W12: =IF($C12="","",MIN($HP12:$HT12)) -> 5271860.2 | X12: No | Y12: First Lien | Z12: Term | AA12: NR | AB12: NR | AC12: 1.633068 | AD12: 2.3463154 | AE12: 3.2232536 | AF12: 0.48220859 | AG12: 3.4364287 | AH12: 3.4364287 | AI12: 3.8376355 | AJ12: 3.8376355 | AK12: 11436291 | AL12: 15496061 | AM12: 45838 | AN12: =IF(C12="","",(IF(AK12>=50000000,"Tier 1",(IF(OR(AK12>=20000000,AND(AK12>5000000,AC12>=1.25,AF12<=0.65)),"Tier 2","Tier 3"))))) -> Tier 2 | AO12: 47358 | AP12: =IF(C12="","",DAYS360(Inputs!$J$8,AO12)/360) -> 4.0111111 | AQ12: =IF(C12="","",AP12) -> 4.0111111 | AR12: No | AS12: 0 | AT12: Yes | AU12: 0.01 | AV12: 0.0575 | AW12: 0.042956 | AX12: =IF(C12="","",MAX(AU12,AW12)) -> 0.042956 | AY12: 0 | AZ12: 0 | BA12: 0 | BB12: =IF(B12="","",IF(AR12="No",AV12-AZ12,"")) -> 0.0575 | BC12: =IF(B12="","",IF(AR12="Yes",AS12-BA12,"")) | BD12: Quarterly | BE12: Diversified Financial Services | BF12: USD | BG12: United States | BH12: No | BI12: =IF(B12="","",IF(OR(AND(AZ12>0,BB12>=2.5%,BB12<4%),AND(BA12>0,BC12>=6%,BC12<8%)),"Yes","No")) -> No | BJ12: =IF(B12="","",IF(OR(AND(AZ12>0,BB12<2.5%),AND(BA12>0,BC12<6%)),"Yes","No")) -> No | BK12: No | BL12: No | BM12: No | BN12: No | BO12: No | BP12: No | BQ12: No | BR12: No | BS12: No | BT12: No | BU12: No | BV12: No | BW12: No | BX12: No | BY12: No | BZ12: No | CA12: No | CB12: Yes | CC12: =IF(B12="","",IF(AT12="No",((BB12+AW12)-$AZ$4),((BB12+AX12)-$AZ$4))*IF(DE12>0,0,M12)) -> 301727.54 | CD12: =IF(B12="","",AY12*(L12-M12)*IF(DE12>0,0,1)) -> 0 | CF12: =IF(AND(B12<>"",R12<=85%),1,0) -> 0 | CG12: =IF(B12="",0,(IF(OR(BF12="USD",BF12="CAD",BF12="GBP",BF12="AUD",BF12="EUR"),0,1))) -> 0 | CH12: =IF(B12="",0,(IF(OR(BG12="United States",BG12="Canada",BG12="United Kingdom",BG12="Australia",BG12="Netherlands Antilles",BG12="Bermuda",BG12="Cayman Islands",BG12="British Virgin Islands",BG12="Channel Islands",BG12="Isle of Man",BG12="Australia",BG12="Netherlands",BG12="Germany",BG12="Sweden",BG12="Switzerland",BG12="Austria",BG12="Belgium",BG12="Denmark",BG12="Finland",BG12="Iceland",BG12="Ireland",BG12="Lichtenstein",BG12="Luxemborg",BG12="Norway"),0,1))) -> 0 | CI12: =IF(BO12="Yes",1,0) -> 0 | CJ12: =IF(BP12="Yes",1,0) -> 0 | CK12: =IF(BQ12="Yes",1,0) -> 0 | CL12: =IF(BR12="Yes",1,0) -> 0 | CM12: =IF(BS12="Yes",1,0) -> 0 | CN12: =IF(BT12="Yes",1,0) -> 0 | CO12: =IF(OR(AND(BJ12="Yes",N12="No"),AND(BJ12="Yes",N12="Yes",P12>=6)),1,0) -> 0 | CP12: =IF(BU12="Yes",1,0) -> 0 | CQ12: =IF(AND(BV12="Yes",BW12="No"),1,0) -> 0 | CR12: =IF(BX12="Yes",1,0) -> 0 | CS12: =IF(AP12="",0,IF(AP12>7,1,0)) -> 0 | CT12: =IF(OR(BD12<>"Monthly",BD12<>"Quarterly",BD12<>"Semi-Annually"),0,1) -> 0 | CU12: =IF(BY12="Yes",1,0) -> 0 | CV12: =IF(BZ12="Yes",1,0) -> 0 | CW12: =IF(CA12="Yes",1,0) -> 0 | CX12: =IF(CB12="No",1,0) -> 0 | CY12: =IF(B12="",0,IF(AK12>=5000000,0,1)) -> 0 | CZ12: =IF(B12="",0,IF(AL12>=5000000,0,1)) -> 0 | DA12: =IF(OR(DB12=1,DC12=1,DD12=1),0,IF(B12="",0,IF(OR(AND(AN12="Tier 1",X12="No",OR(AI12>$AJ$3,AJ12>$AJ$4)),(AND(AN12="Tier 1",X12="Yes",AJ12>$AJ$5)),(AND(AN12="Tier 2",X12="No",OR(AI12>$AK$3,AJ12>$AK$4))),(AND(AN12="Tier 2",X12="Yes",AJ12>$AK$5)),(AND(AN12="Tier 3",X12="No",OR(AI12>$AL$3,AJ12>$AL$4))),(AND(AN12="Tier 3",X12="Yes",AJ12>$AL$5))),1,0))) -> 0 | DB12: =IF(OR(DC12=1,DD12=1),0,IF(B12="",0,IF(OR(AND(AN12="Tier 1",X12="No",OR(AI12>$AM$3,AJ12>$AM$4)),(AND(AN12="Tier 1",X12="Yes",AJ12>$AM$5)),(AND(AN12="Tier 2",X12="No",OR(AI12>$AN$3,AJ12>$AN$4))),(AND(AN12="Tier 2",X12="Yes",AJ12>$AN$5)),(AND(AN12="Tier 3",X12="No",OR(AI12>$AO$3,AJ12>$AO$4))),(AND(AN12="Tier 3",X12="Yes",AJ12>$AO$5))),1,0))) -> 0 | DC12: =IF(DD12=1,0,IF(B12="",0,IF(OR(AND(AN12="Tier 1",X12="No",OR(AI12>$AP$3,AJ12>$AP$4)),(AND(AN12="Tier 1",X12="Yes",AJ12>$AP$5)),(AND(AN12="Tier 2",X12="No",OR(AI12>$AQ$3,AJ12>$AQ$4))),(AND(AN12="Tier 2",X12="Yes",AJ12>$AQ$5)),(AND(AN12="Tier 3",X12="No",OR(AI12>$AR$3,AJ12>$AR$4))),(AND(AN12="Tier 3",X12="Yes",AJ12>$AR$5))),1,0))) -> 0 | DD12: =IF(B12="",0,IF(OR(AND(AN12="Tier 1",X12="No",OR(AI12>$AS$3,AJ12>$AS$4)),(AND(AN12="Tier 1",X12="Yes",AJ12>$AS$5)),(AND(AN12="Tier 2",X12="No",OR(AI12>$AT$3,AJ12>$AT$4))),(AND(AN12="Tier 2",X12="Yes",AJ12>$AT$5)),(AND(AN12="Tier 3",X12="No",OR(AI12>$AU$3,AJ12>$AU$4))),(AND(AN12="Tier 3",X12="Yes",AJ12>$AU$5))),1,0)) -> 0 | DE12: =IF((SUM(CF12:CY12)=0),0,W12) -> 0 | DF12: =IF(OR(B12="",DE12>0),0,W12) -> 5271860.2 | DG12: =IF(B12="",0,IF(COUNTIF(CF12:CY12,1)>0,0,L12-M12)) -> 0 | DH12: =DF12+IF(DE12>0,0,DG12) -> 5271860.2 | DI12: =IF(B12="","",M12+DG12) -> 5271860.2 | DJ12: =IF(B12="",0,J12-K12) -> 0 | DK12: =IF(OR(BF12="EUR",BF12="CAD",BF12="GBP",BF12="AUD"),(GB12*(1-V12))+(HH12)+IF(HY12="",0,HY12*(1-U12)),0) -> 0 | DL12: =IF(BF12="EUR",33%,IF(BF12="CAD",38%,IF(BF12="GBP",51%,IF(BF12="AUD",61%,0)))) -> 0 | DM12: =DK12*DL12 -> 0 | DO12: =IF(OR(Y12="Second Lien",Y12="Tier 1 Split Lien",Y12="Tier 2 Split Lien"),DH12,0) -> 0 | DP12: =DO12*DO$6 -> 0 | DQ12: =DH12-DP12 -> 5271860.2 | DR12: =IF(Y12="Second Lien",DQ12,0) -> 0 | DS12: =DR12*DR$6 -> 0 | DT12: =DQ12-DS12 -> 5271860.2 | DU12: =IF(BH12="Yes",DT12,0) -> 0 | DV12: =DU12*DU$6 -> 0 | DW12: =DT12-DV12 -> 5271860.2 | DX12: =IF(OR(BG12="Canada",BG12="United Kingdom",BG12="Australia",BG12="Netherlands Antilles",BG12="Bermuda",BG12="Cayman Islands",BG12="British Virgin Islands",BG12="Channel Islands",BG12="Isle of Man",BG12="Australia",BG12="Netherlands",BG12="Germany",BG12="Sweden",BG12="Switzerland",BG12="Austria",BG12="Belgium",BG12="Denmark",BG12="Finland",BG12="Iceland",BG12="Ireland",BG12="Lichtenstein",BG12="Luxemborg",BG12="Norway"),DW12,0) -> 0 | DY12: =DX12*DX$6 -> 0 | DZ12: =DW12-DY12 -> 5271860.2 | EA12: =IF(BI12="Yes",DZ12,0) -> 0 | EB12: =EA12*EA$6 -> 0 | EC12: =DZ12-EB12 -> 5271860.2 | ED12: =IF(OR(Z12="Delayed Draw",Z12="Revolver"),EC12,0) -> 0 | EE12: =ED12*ED$6 -> 0 | EF12: =EC12-EE12 -> 5271860.2 | EG12: =IF(S12="Yes",EF12,0) -> 0 | EH12: =EG12*EG$6 -> 0 | EI12: =EF12-EH12 -> 5271860.2 | EJ12: =IF(Q12="Yes",EI12,0) -> 0 | EK12: =EJ12*EJ$6 -> 0 | EL12: =EI12-EK12 -> 5271860.2 | EM12: =IF(BD12="Semi-Annually",EL12,0) -> 0 | EN12: =EM12*EM$6 -> 0 | EO12: =EL12-EN12 -> 5271860.2 | EP12: =IF(BK12="Yes",EO12,0) -> 0 | EQ12: =EP12*EP$6 -> 0 | ER12: =EO12-EQ12 -> 5271860.2 | ES12: =IF(BL12="Yes",ER12,0) -> 0 | ET12: =ES12*ES$6 -> 0 | EU12: =ER12-ET12 -> 5271860.2 | EV12: =IF(AND(BM12="Yes",OR(BN12="No",AND(BN12="Yes",Inputs!$J$8=Inputs!$J$17+75))),EU12,0) -> 0 | EW12: =EV12*EV$6 -> 0 | EX12: =EU12-EW12 -> 5271860.2 | EY12: =IF(BW12="Yes",EX12,0) -> 0 | EZ12: =EY12*EY$6 -> 0 | FA12: =EX12-EZ12 -> 5271860.2 | FB12: =IF(AR12="Yes",FA12,0) -> 0 | FC12: =FB12*FB$6 -> 0 | FD12: =FA12-FC12 -> 5271860.2 | FE12: =IF(OR(BF12="EUR",BF12="AUD",BF12="CAD",BF12="GBP"),FD12,0) -> 0 | FF12: =FE12*FE$6 -> 0 | FG12: =FD12-FF12 -> 5271860.2 | FH12: =FG12 -> 5271860.2 | FI12: =IF(FG12=0,0,VLOOKUP(C12,$GV$10:$GW$406,2,FALSE)*FG12) -> 0 | FJ12: =FG12-FI12 -> 5271860.2 | FK12: =FJ12 -> 5271860.2 | FL12: =IF(OR(IC12="",FJ12<0.01),,VLOOKUP(IC12,$GM$10:$GN$406,2,FALSE)*FJ12) -> 0 | FM12: =FJ12-FL12 -> 5271860.2 | FN12: =FM12 -> 5271860.2 | FO12: =IF(FM12=0,0,VLOOKUP(C12,$HE$10:$HF$406,2,FALSE)*FM12) -> 0 | FP12: =FM12-FO12 -> 5271860.2 | FQ12: =IF(SUM(CZ12:DD12)>0,0,IF(AND(AL12>=5000000,AL12<7500000),FP12,0)) -> 0 | FR12: =IF(B12="",0,FQ12*FQ$6*(1-$U12)) -> 0 | FS12: =FP12-FR12 -> 5271860.2 | FT12: =IF(SUM(CZ12:DD12)>0,0,IF(AL12<15000000,FS12,0)) -> 0 | FU12: =IF(B12="",0,FT12*FT$6*(1-$U12)) -> 0 | FV12: =FS12-FU12 -> 5271860.2 | FW12: =IF(SUM(CZ12:DD12)>0,0,IF(OR(AND(X12="No",AN12="Tier 1",AI12>$AG$3),AND(X12="No",AN12="Tier 2",AI12>$AH$3),AND(X12="No",AN12="Tier 3",AI12>$AI$3)),FV12,0)) -> 0 | FX12: =IF(SUM(CZ12:DD12)>0,0,IF(OR(AND(X12="No",AN12="Tier 1",AJ12>$AG$4),AND(X12="No",AN12="Tier 2",AJ12>$AH$4),AND(X12="No",AN12="Tier 3",AJ12>$AI$4)),FV12,0)) -> 0 | FY12: =IF(SUM(CZ12:DD12)>0,0,IF(OR(AND(X12="Yes",AN12="Tier 1",AJ12>$AG$5),AND(X12="Yes",AN12="Tier 2",AJ12>$AH$5),AND(X12="Yes",AN12="Tier 3",AJ12>$AI$5)),FV12,0)) -> 0 | FZ12: =IF(SUM(FW12:FY12)>0,FV12,0) -> 0 | GA12: =IF(B12="",0,FZ12*FW$6*(1-MIN(90%,T12))) -> 0 | GB12: =FV12-GA12 -> 5271860.2 | GC12: =IF(AND(N12="No",DJ12=0),GB12,IF(AND(N12="No",DJ12<>0,K12=0),0,IF(AND(N12="No",DJ12<>0,K12>0,J12<>K12),MAX(0,M12-(DI12-GB12)),DH12))) -> 5271860.2 | GD12: =+GC12*V12 -> 3822098.6 | GE12: =IFERROR(GD12/K12,"") -> 0.725 | GF12: =IF(IC12="","",IC12) -> 20 | GG12: {=IF(SUM(IF(IC$9:IC11=IC12,1,0))>0,0,SUMIF($IC$10:$IC$406,IC12,$FJ$10:$FJ$406))} -> 51605989 | GH12: =GG12 -> 51605989 | GI12: =GI11+1 -> 3 | GJ12: =LARGE($GH$10:$GH$406,GI12) -> 84429923 | GK12: =IF(GI12>GI$6,0,IF(GI12=$GI$2,$GK$2,IF(GI12<4,$GK$3,$GK$4))) -> 1.5289285e+08 | GL12: =MAX(0,GJ12-GK12) -> 0 | GM12: {=IF(GJ12=0,0,LARGE(IF($GG$10:$GG$406=GJ12,$GF$10:$GF$406,0),COUNTIF($GJ$10:$GJ$406,GJ12)-COUNTIF(GJ$9:GJ11,GJ12)))} -> 31 | GN12: =IF(GJ12=0,0,GL12/GJ12) -> 0 | GP12: =IF(C12="","",IF(ISERROR(MATCH(C12,C$10:C11,0)),MAX(GP$10:GP11)+1,INDEX(GP$10:GP11,MATCH(C12,C$10:C11,0)))) -> 3 | GQ12: =IF(COUNTIF($A$10:A12,A12)<=1,SUMIF($A$10:$A$406,A12,$FH$10:$FH$406),0) -> 5271860.2 | GR12: =GR11+1 -> 3 | GS12: =LARGE($GQ$10:$GQ$406,GR12) -> 37406250 | GT12: =IF(GR12>GR$6,0,IF(GR12<=GR$2,GT$2,IF(AND(GR12<=$GR$3,GR12>$GR$2),GT$3,GT$4))) -> 67952372 | GU12: =MAX(0,GS12-GT12) -> 0 | GV12: {=IF(GS12=0,0,LARGE(IF($GQ$10:$GQ$406=GS12,$GP$10:$GP$406,0),COUNTIF($GS$10:$GS$406,GS12)-COUNTIF(GS$9:GS11,GS12)))} -> 71 | GW12: =IF(GS12=0,0,GU12/GS12) -> 0 | GY12: =IF(C12="","",IF(ISERROR(MATCH(C12,C$10:C11,0)),MAX(GP$10:GP11)+1,INDEX(GP$10:GP11,MATCH(C12,C$10:C11,0)))) -> 3 | GZ12: =IF(COUNTIF($A$10:A12,A12)<=1,SUMIF($A$10:$A$406,A12,$FH$10:$FH$406),0) -> 5271860.2 | HA12: =HA11+1 -> 3 | HB12: =LARGE($GZ$10:$GZ$406,HA12) -> 37406250 | HC12: - | HD12: =IF(HA12<6,MAX(0,$HD$2/5),0) -> 0 | HE12: {=IF(HB12=0,0,LARGE(IF($GZ$10:$GZ$406=HB12,$GY$10:$GY$406,0),COUNTIF($HB$10:$HB$406,HB12)-COUNTIF(HB$9:HB11,HB12)))} -> 71 | HF12: =IF(HB12=0,0,HD12/HB12) -> 0 | HH12: =DH12-GB12 -> 0 | HI12: 0 | HJ12: =MIN(HI12,DF12) -> 0 | HL12: =IF(COUNTIF($C$10:$C$406,HL11+1),HL11+1,"") -> 3 | HM12: =SUMIF($C$10:$C$406,HL12,$DH$10:$DH$406) -> 5271860.2 | HO12: =MIN(HP12:HT12) -> 5271860.2 | HP12: =IF(B12="","",$M12) -> 5271860.2 | HQ12: =IF($N12="Yes",IF(P12>=6,0,MIN($T12*$M12,$U12*$M12)),"") | HR12: =IF(AND(N12="Yes",P12>=6),"",IF($S12="Yes",$R12*$M12,"")) | HS12: =IF($Q12="Yes",MIN($M12,$T12*$M12),"") | HT12: =IF(AND($N12="Yes",$P12>=6),"",IF(OR(CZ12=1,DD12=1,),MIN($T12*$M12,$U12*$M12),IF(OR(DA12=1,DB12=1,DC12=1),IF(AK12>=5000000,MIN($T12*$M12,$IF12*$M12),MIN($T12*$M12,$U12*$M12)),""))) | HU12: =IF(DE12>0,DE12,"") | HV12: =IF(B12="",0,$L12-$M12) -> 0 | HW12: =IF(OR(SUM(HQ12:HU12)>0,P12>=6),"",IF($B12="","",1)) -> 1 | HX12: =IF(AND($HU12<>0,OR(HU12<=MIN(HQ12:HT12),SUM(HQ12:HT12)=0)),$HU12,0) | HY12: =IF(AND($HT12<>0,OR(AND($HT12<>$HU12,$HT12<>$HS12,$HT12<>$HR12,$HT12<>$HQ12,$HT12<MIN($HQ12:$HS12),$HT12<HU12),SUM($HQ12:$HS12)+SUM(HU12)=0),IB12<=0),$HT12,0) -> 0 | HZ12: =IF(AND($HS12<>0,OR(AND($HS12<>$HU12,$HS12<>$HT12,$HS12<>$HR12,$HS12<>$HQ12),$HS12<MIN($HQ12:$HR12),$HS12<MIN($HT12:$HU12),SUM($HQ12:$HR12)+SUM($HT12:$HU12)=0)),$HS12,0) | IA12: =IF(AND($HR12<>0,OR(AND($HR12<>$HU12,HR12<>HT12,HR12<>HS12,HR12<>HQ12,HR12<MIN(HS12:HU12)),SUM(HQ12)+SUM(HS12:HU12)=0)),$HR12,0) | IB12: =IF(AND($HQ12<>0,OR(HQ12<=MIN(HR12:HU12),SUM(HR12:HU12)=0)),$HQ12,0) | IC12: =IF(C12="","",INDEX(Lookups!$E$2:$E$69,MATCH('Loan List'!BE12,Lookups!$F$2:$F$69,0))) -> 20 | ID12: =HV12=DG12 -> TRUE | IF12: =IF(B12="","",IF(AND(Y12="Second Lien",OR(DA12=1,DB12=1,DC12=1)),50%,IF(DA12=1,90%,IF(DB12=1,80%,IF(DC12=1,65%,"No Initial Haircut"))))) -> No Initial Haircut
A13: ARGANO, LLC | B13: =IF(D13="","",B12+1) -> 4 | C13: =IF(COUNTIF($A$10:A12,A13)>0,C12,C12+1) -> 4 | D13: ARGANO, LLC | E13: Argano (Term Loan) | G13: 34673920 | H13: 34673920 | I13: =IF(B13="","",VLOOKUP(BF13,Inputs!$A$12:$J$15,10,FALSE)) -> 1 | J13: =IF(B13="","",G13*I13) -> 34673920 | K13: =IF(B13="","",H13*I13) -> 34673920 | L13: =IF(B13="","",IF(COUNTIF($CF13:$CY13,1)>0,0,J13)) -> 34673920 | M13: =IF(B13="","",IF(COUNTIF($CF13:$CY13,1)>0,0,K13)) -> 34673920 | N13: No | O13: N/A | P13: =IF(B13="","",IF(OR(O13="N/A",O13=""),0,YEARFRAC('Borrowing Base'!$J$4,'Loan List'!O13)*12)) -> 0 | Q13: No | R13: 0.99010093 | S13: =IF(B13="","",IF(R13<95%,"Yes","No")) -> No | T13: 0.991 | U13: =IF(B13="","",IF(OR(Y13="First Lien",Y13="Split First Lien",Y13="Tier 1 Split Lien",Y13="Tier 2 Split Lien"),50%,30%)) -> 0.5 | V13: =IF(B13="",0,IF(AND(Y13="First Lien",AN13="Tier 1"),IF(AND(X13="Yes",MIN(AH13,$AJ$5)>4.5),(((4.5/MIN(AH13,$AJ$5))*72.5%)+(((MIN(AH13,$AJ$5)-4.5)/MIN(AH13,$AJ$5))*35%)),72.5%),IF(AND(Y13="First Lien",AN13="Tier 2"),IF(AND(X13="Yes",MIN(AH13,$AK$5)>4.5),(((4.5/MIN(AH13,$AK$5))*72.5%)+(((MIN(AH13,$AK$5)-4.5)/MIN(AH13,$AK$5))*35%)),72.5%),IF(AND(X13="Yes",MIN(AH13,$AL$5)>4),(((4/MIN(AH13,$AL$5))*72.5%)+(((MIN(AH13,$AL$5)-4)/MIN(AH13,$AL$5))*35%)),IF(OR(Y13="First Lien",Y13="Split First Lien"),72.5%,IF(Y13="Split Lien", 53%,35%)))))) -> 0.725 | W13: =IF($C13="","",MIN($HP13:$HT13)) -> 34673920 | X13: No | Y13: First Lien | Z13: Term | AA13: NR | AB13: NR | AC13: 1.8301481 | AD13: 1.6327847 | AE13: 1.9659379 | AF13: 0.34427481 | AG13: 3.5191248 | AH13: 3.5191248 | AI13: 5.1371733 | AJ13: 6.9590511 | AK13: 64078433 | AL13: 82332636 | AM13: 45838 | AN13: =IF(C13="","",(IF(AK13>=50000000,"Tier 1",(IF(OR(AK13>=20000000,AND(AK13>5000000,AC13>=1.25,AF13<=0.65)),"Tier 2","Tier 3"))))) -> Tier 1 | AO13: 47374 | AP13: =IF(C13="","",DAYS360(Inputs!$J$8,AO13)/360) -> 4.0527778 | AQ13: =IF(C13="","",AP13) -> 4.0527778 | AR13: No | AS13: 0 | AT13: Yes | AU13: 0.01 | AV13: 0.0575 | AW13: 0.043507 | AX13: =IF(C13="","",MAX(AU13,AW13)) -> 0.043507 | AY13: 0 | AZ13: 0 | BA13: 0 | BB13: =IF(B13="","",IF(AR13="No",AV13-AZ13,"")) -> 0.0575 | BC13: =IF(B13="","",IF(AR13="Yes",AS13-BA13,"")) | BD13: Quarterly | BE13: IT Services | BF13: USD | BG13: United States | BH13: No | BI13: =IF(B13="","",IF(OR(AND(AZ13>0,BB13>=2.5%,BB13<4%),AND(BA13>0,BC13>=6%,BC13<8%)),"Yes","No")) -> No | BJ13: =IF(B13="","",IF(OR(AND(AZ13>0,BB13<2.5%),AND(BA13>0,BC13<6%)),"Yes","No")) -> No | BK13: No | BL13: No | BM13: No | BN13: No | BO13: No | BP13: No | BQ13: No | BR13: No | BS13: No | BT13: No | BU13: No | BV13: No | BW13: No | BX13: No | BY13: No | BZ13: No | CA13: No | CB13: Yes | CC13: =IF(B13="","",IF(AT13="No",((BB13+AW13)-$AZ$4),((BB13+AX13)-$AZ$4))*IF(DE13>0,0,M13)) -> 2003618.6 | CD13: =IF(B13="","",AY13*(L13-M13)*IF(DE13>0,0,1)) -> 0 | CF13: =IF(AND(B13<>"",R13<=85%),1,0) -> 0 | CG13: =IF(B13="",0,(IF(OR(BF13="USD",BF13="CAD",BF13="GBP",BF13="AUD",BF13="EUR"),0,1))) -> 0 | CH13: =IF(B13="",0,(IF(OR(BG13="United States",BG13="Canada",BG13="United Kingdom",BG13="Australia",BG13="Netherlands Antilles",BG13="Bermuda",BG13="Cayman Islands",BG13="British Virgin Islands",BG13="Channel Islands",BG13="Isle of Man",BG13="Australia",BG13="Netherlands",BG13="Germany",BG13="Sweden",BG13="Switzerland",BG13="Austria",BG13="Belgium",BG13="Denmark",BG13="Finland",BG13="Iceland",BG13="Ireland",BG13="Lichtenstein",BG13="Luxemborg",BG13="Norway"),0,1))) -> 0 | CI13: =IF(BO13="Yes",1,0) -> 0 | CJ13: =IF(BP13="Yes",1,0) -> 0 | CK13: =IF(BQ13="Yes",1,0) -> 0 | CL13: =IF(BR13="Yes",1,0) -> 0 | CM13: =IF(BS13="Yes",1,0) -> 0 | CN13: =IF(BT13="Yes",1,0) -> 0 | CO13: =IF(OR(AND(BJ13="Yes",N13="No"),AND(BJ13="Yes",N13="Yes",P13>=6)),1,0) -> 0 | CP13: =IF(BU13="Yes",1,0) -> 0 | CQ13: =IF(AND(BV13="Yes",BW13="No"),1,0) -> 0 | CR13: =IF(BX13="Yes",1,0) -> 0 | CS13: =IF(AP13="",0,IF(AP13>7,1,0)) -> 0 | CT13: =IF(OR(BD13<>"Monthly",BD13<>"Quarterly",BD13<>"Semi-Annually"),0,1) -> 0 | CU13: =IF(BY13="Yes",1,0) -> 0 | CV13: =IF(BZ13="Yes",1,0) -> 0 | CW13: =IF(CA13="Yes",1,0) -> 0 | CX13: =IF(CB13="No",1,0) -> 0 | CY13: =IF(B13="",0,IF(AK13>=5000000,0,1)) -> 0 | CZ13: =IF(B13="",0,IF(AL13>=5000000,0,1)) -> 0 | DA13: =IF(OR(DB13=1,DC13=1,DD13=1),0,IF(B13="",0,IF(OR(AND(AN13="Tier 1",X13="No",OR(AI13>$AJ$3,AJ13>$AJ$4)),(AND(AN13="Tier 1",X13="Yes",AJ13>$AJ$5)),(AND(AN13="Tier 2",X13="No",OR(AI13>$AK$3,AJ13>$AK$4))),(AND(AN13="Tier 2",X13="Yes",AJ13>$AK$5)),(AND(AN13="Tier 3",X13="No",OR(AI13>$AL$3,AJ13>$AL$4))),(AND(AN13="Tier 3",X13="Yes",AJ13>$AL$5))),1,0))) -> 0 | DB13: =IF(OR(DC13=1,DD13=1),0,IF(B13="",0,IF(OR(AND(AN13="Tier 1",X13="No",OR(AI13>$AM$3,AJ13>$AM$4)),(AND(AN13="Tier 1",X13="Yes",AJ13>$AM$5)),(AND(AN13="Tier 2",X13="No",OR(AI13>$AN$3,AJ13>$AN$4))),(AND(AN13="Tier 2",X13="Yes",AJ13>$AN$5)),(AND(AN13="Tier 3",X13="No",OR(AI13>$AO$3,AJ13>$AO$4))),(AND(AN13="Tier 3",X13="Yes",AJ13>$AO$5))),1,0))) -> 0 | DC13: =IF(DD13=1,0,IF(B13="",0,IF(OR(AND(AN13="Tier 1",X13="No",OR(AI13>$AP$3,AJ13>$AP$4)),(AND(AN13="Tier 1",X13="Yes",AJ13>$AP$5)),(AND(AN13="Tier 2",X13="No",OR(AI13>$AQ$3,AJ13>$AQ$4))),(AND(AN13="Tier 2",X13="Yes",AJ13>$AQ$5)),(AND(AN13="Tier 3",X13="No",OR(AI13>$AR$3,AJ13>$AR$4))),(AND(AN13="Tier 3",X13="Yes",AJ13>$AR$5))),1,0))) -> 0 | DD13: =IF(B13="",0,IF(OR(AND(AN13="Tier 1",X13="No",OR(AI13>$AS$3,AJ13>$AS$4)),(AND(AN13="Tier 1",X13="Yes",AJ13>$AS$5)),(AND(AN13="Tier 2",X13="No",OR(AI13>$AT$3,AJ13>$AT$4))),(AND(AN13="Tier 2",X13="Yes",AJ13>$AT$5)),(AND(AN13="Tier 3",X13="No",OR(AI13>$AU$3,AJ13>$AU$4))),(AND(AN13="Tier 3",X13="Yes",AJ13>$AU$5))),1,0)) -> 0 | DE13: =IF((SUM(CF13:CY13)=0),0,W13) -> 0 | DF13: =IF(OR(B13="",DE13>0),0,W13) -> 34673920 | DG13: =IF(B13="",0,IF(COUNTIF(CF13:CY13,1)>0,0,L13-M13)) -> 0 | DH13: =DF13+IF(DE13>0,0,DG13) -> 34673920 | DI13: =IF(B13="","",M13+DG13) -> 34673920 | DJ13: =IF(B13="",0,J13-K13) -> 0 | DK13: =IF(OR(BF13="EUR",BF13="CAD",BF13="GBP",BF13="AUD"),(GB13*(1-V13))+(HH13)+IF(HY13="",0,HY13*(1-U13)),0) -> 0 | DL13: =IF(BF13="EUR",33%,IF(BF13="CAD",38%,IF(BF13="GBP",51%,IF(BF13="AUD",61%,0)))) -> 0 | DM13: =DK13*DL13 -> 0 | DO13: =IF(OR(Y13="Second Lien",Y13="Tier 1 Split Lien",Y13="Tier 2 Split Lien"),DH13,0) -> 0 | DP13: =DO13*DO$6 -> 0 | DQ13: =DH13-DP13 -> 34673920 | DR13: =IF(Y13="Second Lien",DQ13,0) -> 0 | DS13: =DR13*DR$6 -> 0 | DT13: =DQ13-DS13 -> 34673920 | DU13: =IF(BH13="Yes",DT13,0) -> 0 | DV13: =DU13*DU$6 -> 0 | DW13: =DT13-DV13 -> 34673920 | DX13: =IF(OR(BG13="Canada",BG13="United Kingdom",BG13="Australia",BG13="Netherlands Antilles",BG13="Bermuda",BG13="Cayman Islands",BG13="British Virgin Islands",BG13="Channel Islands",BG13="Isle of Man",BG13="Australia",BG13="Netherlands",BG13="Germany",BG13="Sweden",BG13="Switzerland",BG13="Austria",BG13="Belgium",BG13="Denmark",BG13="Finland",BG13="Iceland",BG13="Ireland",BG13="Lichtenstein",BG13="Luxemborg",BG13="Norway"),DW13,0) -> 0 | DY13: =DX13*DX$6 -> 0 | DZ13: =DW13-DY13 -> 34673920 | EA13: =IF(BI13="Yes",DZ13,0) -> 0 | EB13: =EA13*EA$6 -> 0 | EC13: =DZ13-EB13 -> 34673920 | ED13: =IF(OR(Z13="Delayed Draw",Z13="Revolver"),EC13,0) -> 0 | EE13: =ED13*ED$6 -> 0 | EF13: =EC13-EE13 -> 34673920 | EG13: =IF(S13="Yes",EF13,0) -> 0 | EH13: =EG13*EG$6 -> 0 | EI13: =EF13-EH13 -> 34673920 | EJ13: =IF(Q13="Yes",EI13,0) -> 0 | EK13: =EJ13*EJ$6 -> 0 | EL13: =EI13-EK13 -> 34673920 | EM13: =IF(BD13="Semi-Annually",EL13,0) -> 0 | EN13: =EM13*EM$6 -> 0 | EO13: =EL13-EN13 -> 34673920 | EP13: =IF(BK13="Yes",EO13,0) -> 0 | EQ13: =EP13*EP$6 -> 0 | ER13: =EO13-EQ13 -> 34673920 | ES13: =IF(BL13="Yes",ER13,0) -> 0 | ET13: =ES13*ES$6 -> 0 | EU13: =ER13-ET13 -> 34673920 | EV13: =IF(AND(BM13="Yes",OR(BN13="No",AND(BN13="Yes",Inputs!$J$8=Inputs!$J$17+75))),EU13,0) -> 0 | EW13: =EV13*EV$6 -> 0 | EX13: =EU13-EW13 -> 34673920 | EY13: =IF(BW13="Yes",EX13,0) -> 0 | EZ13: =EY13*EY$6 -> 0 | FA13: =EX13-EZ13 -> 34673920 | FB13: =IF(AR13="Yes",FA13,0) -> 0 | FC13: =FB13*FB$6 -> 0 | FD13: =FA13-FC13 -> 34673920 | FE13: =IF(OR(BF13="EUR",BF13="AUD",BF13="CAD",BF13="GBP"),FD13,0) -> 0 | FF13: =FE13*FE$6 -> 0 | FG13: =FD13-FF13 -> 34673920 | FH13: =FG13 -> 34673920 | FI13: =IF(FG13=0,0,VLOOKUP(C13,$GV$10:$GW$406,2,FALSE)*FG13) -> 0 | FJ13: =FG13-FI13 -> 34673920 | FK13: =FJ13 -> 34673920 | FL13: =IF(OR(IC13="",FJ13<0.01),,VLOOKUP(IC13,$GM$10:$GN$406,2,FALSE)*FJ13) -> 0 | FM13: =FJ13-FL13 -> 34673920 | FN13: =FM13 -> 34673920 | FO13: =IF(FM13=0,0,VLOOKUP(C13,$HE$10:$HF$406,2,FALSE)*FM13) -> 0 | FP13: =FM13-FO13 -> 34673920 | FQ13: =IF(SUM(CZ13:DD13)>0,0,IF(AND(AL13>=5000000,AL13<7500000),FP13,0)) -> 0 | FR13: =IF(B13="",0,FQ13*FQ$6*(1-$U13)) -> 0 | FS13: =FP13-FR13 -> 34673920 | FT13: =IF(SUM(CZ13:DD13)>0,0,IF(AL13<15000000,FS13,0)) -> 0 | FU13: =IF(B13="",0,FT13*FT$6*(1-$U13)) -> 0 | FV13: =FS13-FU13 -> 34673920 | FW13: =IF(SUM(CZ13:DD13)>0,0,IF(OR(AND(X13="No",AN13="Tier 1",AI13>$AG$3),AND(X13="No",AN13="Tier 2",AI13>$AH$3),AND(X13="No",AN13="Tier 3",AI13>$AI$3)),FV13,0)) -> 34673920 | FX13: =IF(SUM(CZ13:DD13)>0,0,IF(OR(AND(X13="No",AN13="Tier 1",AJ13>$AG$4),AND(X13="No",AN13="Tier 2",AJ13>$AH$4),AND(X13="No",AN13="Tier 3",AJ13>$AI$4)),FV13,0)) -> 0 | FY13: =IF(SUM(CZ13:DD13)>0,0,IF(OR(AND(X13="Yes",AN13="Tier 1",AJ13>$AG$5),AND(X13="Yes",AN13="Tier 2",AJ13>$AH$5),AND(X13="Yes",AN13="Tier 3",AJ13>$AI$5)),FV13,0)) -> 0 | FZ13: =IF(SUM(FW13:FY13)>0,FV13,0) -> 34673920 | GA13: =IF(B13="",0,FZ13*FW$6*(1-MIN(90%,T13))) -> 155354.59 | GB13: =FV13-GA13 -> 34518566 | GC13: =IF(AND(N13="No",DJ13=0),GB13,IF(AND(N13="No",DJ13<>0,K13=0),0,IF(AND(N13="No",DJ13<>0,K13>0,J13<>K13),MAX(0,M13-(DI13-GB13)),DH13))) -> 34518566 | GD13: =+GC13*V13 -> 25025960 | GE13: =IFERROR(GD13/K13,"") -> 0.72175168 | GF13: =IF(IC13="","",IC13) -> 41 | GG13: {=IF(SUM(IF(IC$9:IC12=IC13,1,0))>0,0,SUMIF($IC$10:$IC$406,IC13,$FJ$10:$FJ$406))} -> 0 | GH13: =GG13 -> 0 | GI13: =GI12+1 -> 4 | GJ13: =LARGE($GH$10:$GH$406,GI13) -> 66360671 | GK13: =IF(GI13>GI$6,0,IF(GI13=$GI$2,$GK$2,IF(GI13<4,$GK$3,$GK$4))) -> 1.5289285e+08 | GL13: =MAX(0,GJ13-GK13) -> 0 | GM13: {=IF(GJ13=0,0,LARGE(IF($GG$10:$GG$406=GJ13,$GF$10:$GF$406,0),COUNTIF($GJ$10:$GJ$406,GJ13)-COUNTIF(GJ$9:GJ12,GJ13)))} -> 55 | GN13: =IF(GJ13=0,0,GL13/GJ13) -> 0 | GP13: =IF(C13="","",IF(ISERROR(MATCH(C13,C$10:C12,0)),MAX(GP$10:GP12)+1,INDEX(GP$10:GP12,MATCH(C13,C$10:C12,0)))) -> 4 | GQ13: =IF(COUNTIF($A$10:A13,A13)<=1,SUMIF($A$10:$A$406,A13,$FH$10:$FH$406),0) -> 34673920 | GR13: =GR12+1 -> 4 | GS13: =LARGE($GQ$10:$GQ$406,GR13) -> 34673920 | GT13: =IF(GR13>GR$6,0,IF(GR13<=GR$2,GT$2,IF(AND(GR13<=$GR$3,GR13>$GR$2),GT$3,GT$4))) -> 61157141 | GU13: =MAX(0,GS13-GT13) -> 0 | GV13: {=IF(GS13=0,0,LARGE(IF($GQ$10:$GQ$406=GS13,$GP$10:$GP$406,0),COUNTIF($GS$10:$GS$406,GS13)-COUNTIF(GS$9:GS12,GS13)))} -> 4 | GW13: =IF(GS13=0,0,GU13/GS13) -> 0 | GY13: =IF(C13="","",IF(ISERROR(MATCH(C13,C$10:C12,0)),MAX(GP$10:GP12)+1,INDEX(GP$10:GP12,MATCH(C13,C$10:C12,0)))) -> 4 | GZ13: =IF(COUNTIF($A$10:A13,A13)<=1,SUMIF($A$10:$A$406,A13,$FH$10:$FH$406),0) -> 34673920 | HA13: =HA12+1 -> 4 | HB13: =LARGE($GZ$10:$GZ$406,HA13) -> 34673920 | HC13: - | HD13: =IF(HA13<6,MAX(0,$HD$2/5),0) -> 0 | HE13: {=IF(HB13=0,0,LARGE(IF($GZ$10:$GZ$406=HB13,$GY$10:$GY$406,0),COUNTIF($HB$10:$HB$406,HB13)-COUNTIF(HB$9:HB12,HB13)))} -> 4 | HF13: =IF(HB13=0,0,HD13/HB13) -> 0 | HH13: =DH13-GB13 -> 155354.59 | HI13: 0 | HJ13: =MIN(HI13,DF13) -> 0 | HL13: =IF(COUNTIF($C$10:$C$406,HL12+1),HL12+1,"") -> 4 | HM13: =SUMIF($C$10:$C$406,HL13,$DH$10:$DH$406) -> 34673920 | HO13: =MIN(HP13:HT13) -> 34673920 | HP13: =IF(B13="","",$M13) -> 34673920 | HQ13: =IF($N13="Yes",IF(P13>=6,0,MIN($T13*$M13,$U13*$M13)),"") | HR13: =IF(AND(N13="Yes",P13>=6),"",IF($S13="Yes",$R13*$M13,"")) | HS13: =IF($Q13="Yes",MIN($M13,$T13*$M13),"") | HT13: =IF(AND($N13="Yes",$P13>=6),"",IF(OR(CZ13=1,DD13=1,),MIN($T13*$M13,$U13*$M13),IF(OR(DA13=1,DB13=1,DC13=1),IF(AK13>=5000000,MIN($T13*$M13,$IF13*$M13),MIN($T13*$M13,$U13*$M13)),""))) | HU13: =IF(DE13>0,DE13,"") | HV13: =IF(B13="",0,$L13-$M13) -> 0 | HW13: =IF(OR(SUM(HQ13:HU13)>0,P13>=6),"",IF($B13="","",1)) -> 1 | HX13: =IF(AND($HU13<>0,OR(HU13<=MIN(HQ13:HT13),SUM(HQ13:HT13)=0)),$HU13,0) | HY13: =IF(AND($HT13<>0,OR(AND($HT13<>$HU13,$HT13<>$HS13,$HT13<>$HR13,$HT13<>$HQ13,$HT13<MIN($HQ13:$HS13),$HT13<HU13),SUM($HQ13:$HS13)+SUM(HU13)=0),IB13<=0),$HT13,0) -> 0 | HZ13: =IF(AND($HS13<>0,OR(AND($HS13<>$HU13,$HS13<>$HT13,$HS13<>$HR13,$HS13<>$HQ13),$HS13<MIN($HQ13:$HR13),$HS13<MIN($HT13:$HU13),SUM($HQ13:$HR13)+SUM($HT13:$HU13)=0)),$HS13,0) | IA13: =IF(AND($HR13<>0,OR(AND($HR13<>$HU13,HR13<>HT13,HR13<>HS13,HR13<>HQ13,HR13<MIN(HS13:HU13)),SUM(HQ13)+SUM(HS13:HU13)=0)),$HR13,0) | IB13: =IF(AND($HQ13<>0,OR(HQ13<=MIN(HR13:HU13),SUM(HR13:HU13)=0)),$HQ13,0) | IC13: =IF(C13="","",INDEX(Lookups!$E$2:$E$69,MATCH('Loan List'!BE13,Lookups!$F$2:$F$69,0))) -> 41 | ID13: =HV13=DG13 -> TRUE | IF13: =IF(B13="","",IF(AND(Y13="Second Lien",OR(DA13=1,DB13=1,DC13=1)),50%,IF(DA13=1,90%,IF(DB13=1,80%,IF(DC13=1,65%,"No Initial Haircut"))))) -> No Initial Haircut
A14: Aphix Buyer, Inc | B14: =IF(D14="","",B13+1) -> 5 | C14: =IF(COUNTIF($A$10:A13,A14)>0,C13,C13+1) -> 5 | D14: Aphix Buyer, Inc | E14: Aphix (Term Loan) | G14: 18000000 | H14: 18000000 | I14: =IF(B14="","",VLOOKUP(BF14,Inputs!$A$12:$J$15,10,FALSE)) -> 1 | J14: =IF(B14="","",G14*I14) -> 18000000 | K14: =IF(B14="","",H14*I14) -> 18000000 | L14: =IF(B14="","",IF(COUNTIF($CF14:$CY14,1)>0,0,J14)) -> 18000000 | M14: =IF(B14="","",IF(COUNTIF($CF14:$CY14,1)>0,0,K14)) -> 18000000 | N14: No | O14: N/A | P14: =IF(B14="","",IF(OR(O14="N/A",O14=""),0,YEARFRAC('Borrowing Base'!$J$4,'Loan List'!O14)*12)) -> 0 | Q14: No | R14: 0.99181993 | S14: =IF(B14="","",IF(R14<95%,"Yes","No")) -> No | T14: 0.99178565 | U14: =IF(B14="","",IF(OR(Y14="First Lien",Y14="Split First Lien",Y14="Tier 1 Split Lien",Y14="Tier 2 Split Lien"),50%,30%)) -> 0.5 | V14: =IF(B14="",0,IF(AND(Y14="First Lien",AN14="Tier 1"),IF(AND(X14="Yes",MIN(AH14,$AJ$5)>4.5),(((4.5/MIN(AH14,$AJ$5))*72.5%)+(((MIN(AH14,$AJ$5)-4.5)/MIN(AH14,$AJ$5))*35%)),72.5%),IF(AND(Y14="First Lien",AN14="Tier 2"),IF(AND(X14="Yes",MIN(AH14,$AK$5)>4.5),(((4.5/MIN(AH14,$AK$5))*72.5%)+(((MIN(AH14,$AK$5)-4.5)/MIN(AH14,$AK$5))*35%)),72.5%),IF(AND(X14="Yes",MIN(AH14,$AL$5)>4),(((4/MIN(AH14,$AL$5))*72.5%)+(((MIN(AH14,$AL$5)-4)/MIN(AH14,$AL$5))*35%)),IF(OR(Y14="First Lien",Y14="Split First Lien"),72.5%,IF(Y14="Split Lien", 53%,35%)))))) -> 0.725 | W14: =IF($C14="","",MIN($HP14:$HT14)) -> 18000000 | X14: No | Y14: First Lien | Z14: Term | AA14: NR | AB14: NR | AC14: 1.5400113 | AD14: 1.5400113 | AE14: 2.3477094 | AF14: 0.36153846 | AG14: 4.4470089 | AH14: 4.4470089 | AI14: 4.4470089 | AJ14: 4.4470089 | AK14: 10568902 | AL14: 10568902 | AM14: 45777 | AN14: =IF(C14="","",(IF(AK14>=50000000,"Tier 1",(IF(OR(AK14>=20000000,AND(AK14>5000000,AC14>=1.25,AF14<=0.65)),"Tier 2","Tier 3"))))) -> Tier 2 | AO14: 48046 | AP14: =IF(C14="","",DAYS360(Inputs!$J$8,AO14)/360) -> 5.8972222 | AQ14: =IF(C14="","",AP14) -> 5.8972222 | AR14: No | AS14: 0 | AT14: Yes | AU14: 0.01 | AV14: 0.055 | AW14: 0.035931 | AX14: =IF(C14="","",MAX(AU14,AW14)) -> 0.035931 | AY14: 0 | AZ14: 0 | BA14: 0 | BB14: =IF(B14="","",IF(AR14="No",AV14-AZ14,"")) -> 0.055 | BC14: =IF(B14="","",IF(AR14="Yes",AS14-BA14,"")) | BD14: Quarterly | BE14: Commercial Services & Supplies | BF14: USD | BG14: United States | BH14: No | BI14: =IF(B14="","",IF(OR(AND(AZ14>0,BB14>=2.5%,BB14<4%),AND(BA14>0,BC14>=6%,BC14<8%)),"Yes","No")) -> No | BJ14: =IF(B14="","",IF(OR(AND(AZ14>0,BB14<2.5%),AND(BA14>0,BC14<6%)),"Yes","No")) -> No | BK14: No | BL14: No | BM14: No | BN14: No | BO14: No | BP14: No | BQ14: No | BR14: No | BS14: No | BT14: No | BU14: No | BV14: No | BW14: No | BX14: No | BY14: No | BZ14: No | CA14: No | CB14: Yes | CC14: =IF(B14="","",IF(AT14="No",((BB14+AW14)-$AZ$4),((BB14+AX14)-$AZ$4))*IF(DE14>0,0,M14)) -> 858754.8 | CD14: =IF(B14="","",AY14*(L14-M14)*IF(DE14>0,0,1)) -> 0 | CF14: =IF(AND(B14<>"",R14<=85%),1,0) -> 0 | CG14: =IF(B14="",0,(IF(OR(BF14="USD",BF14="CAD",BF14="GBP",BF14="AUD",BF14="EUR"),0,1))) -> 0 | CH14: =IF(B14="",0,(IF(OR(BG14="United States",BG14="Canada",BG14="United Kingdom",BG14="Australia",BG14="Netherlands Antilles",BG14="Bermuda",BG14="Cayman Islands",BG14="British Virgin Islands",BG14="Channel Islands",BG14="Isle of Man",BG14="Australia",BG14="Netherlands",BG14="Germany",BG14="Sweden",BG14="Switzerland",BG14="Austria",BG14="Belgium",BG14="Denmark",BG14="Finland",BG14="Iceland",BG14="Ireland",BG14="Lichtenstein",BG14="Luxemborg",BG14="Norway"),0,1))) -> 0 | CI14: =IF(BO14="Yes",1,0) -> 0 | CJ14: =IF(BP14="Yes",1,0) -> 0 | CK14: =IF(BQ14="Yes",1,0) -> 0 | CL14: =IF(BR14="Yes",1,0) -> 0 | CM14: =IF(BS14="Yes",1,0) -> 0 | CN14: =IF(BT14="Yes",1,0) -> 0 | CO14: =IF(OR(AND(BJ14="Yes",N14="No"),AND(BJ14="Yes",N14="Yes",P14>=6)),1,0) -> 0 | CP14: =IF(BU14="Yes",1,0) -> 0 | CQ14: =IF(AND(BV14="Yes",BW14="No"),1,0) -> 0 | CR14: =IF(BX14="Yes",1,0) -> 0 | CS14: =IF(AP14="",0,IF(AP14>7,1,0)) -> 0 | CT14: =IF(OR(BD14<>"Monthly",BD14<>"Quarterly",BD14<>"Semi-Annually"),0,1) -> 0 | CU14: =IF(BY14="Yes",1,0) -> 0 | CV14: =IF(BZ14="Yes",1,0) -> 0 | CW14: =IF(CA14="Yes",1,0) -> 0 | CX14: =IF(CB14="No",1,0) -> 0 | CY14: =IF(B14="",0,IF(AK14>=5000000,0,1)) -> 0 | CZ14: =IF(B14="",0,IF(AL14>=5000000,0,1)) -> 0 | DA14: =IF(OR(DB14=1,DC14=1,DD14=1),0,IF(B14="",0,IF(OR(AND(AN14="Tier 1",X14="No",OR(AI14>$AJ$3,AJ14>$AJ$4)),(AND(AN14="Tier 1",X14="Yes",AJ14>$AJ$5)),(AND(AN14="Tier 2",X14="No",OR(AI14>$AK$3,AJ14>$AK$4))),(AND(AN14="Tier 2",X14="Yes",AJ14>$AK$5)),(AND(AN14="Tier 3",X14="No",OR(AI14>$AL$3,AJ14>$AL$4))),(AND(AN14="Tier 3",X14="Yes",AJ14>$AL$5))),1,0))) -> 0 | DB14: =IF(OR(DC14=1,DD14=1),0,IF(B14="",0,IF(OR(AND(AN14="Tier 1",X14="No",OR(AI14>$AM$3,AJ14>$AM$4)),(AND(AN14="Tier 1",X14="Yes",AJ14>$AM$5)),(AND(AN14="Tier 2",X14="No",OR(AI14>$AN$3,AJ14>$AN$4))),(AND(AN14="Tier 2",X14="Yes",AJ14>$AN$5)),(AND(AN14="Tier 3",X14="No",OR(AI14>$AO$3,AJ14>$AO$4))),(AND(AN14="Tier 3",X14="Yes",AJ14>$AO$5))),1,0))) -> 0 | DC14: =IF(DD14=1,0,IF(B14="",0,IF(OR(AND(AN14="Tier 1",X14="No",OR(AI14>$AP$3,AJ14>$AP$4)),(AND(AN14="Tier 1",X14="Yes",AJ14>$AP$5)),(AND(AN14="Tier 2",X14="No",OR(AI14>$AQ$3,AJ14>$AQ$4))),(AND(AN14="Tier 2",X14="Yes",AJ14>$AQ$5)),(AND(AN14="Tier 3",X14="No",OR(AI14>$AR$3,AJ14>$AR$4))),(AND(AN14="Tier 3",X14="Yes",AJ14>$AR$5))),1,0))) -> 0 | DD14: =IF(B14="",0,IF(OR(AND(AN14="Tier 1",X14="No",OR(AI14>$AS$3,AJ14>$AS$4)),(AND(AN14="Tier 1",X14="Yes",AJ14>$AS$5)),(AND(AN14="Tier 2",X14="No",OR(AI14>$AT$3,AJ14>$AT$4))),(AND(AN14="Tier 2",X14="Yes",AJ14>$AT$5)),(AND(AN14="Tier 3",X14="No",OR(AI14>$AU$3,AJ14>$AU$4))),(AND(AN14="Tier 3",X14="Yes",AJ14>$AU$5))),1,0)) -> 0 | DE14: =IF((SUM(CF14:CY14)=0),0,W14) -> 0 | DF14: =IF(OR(B14="",DE14>0),0,W14) -> 18000000 | DG14: =IF(B14="",0,IF(COUNTIF(CF14:CY14,1)>0,0,L14-M14)) -> 0 | DH14: =DF14+IF(DE14>0,0,DG14) -> 18000000 | DI14: =IF(B14="","",M14+DG14) -> 18000000 | DJ14: =IF(B14="",0,J14-K14) -> 0 | DK14: =IF(OR(BF14="EUR",BF14="CAD",BF14="GBP",BF14="AUD"),(GB14*(1-V14))+(HH14)+IF(HY14="",0,HY14*(1-U14)),0) -> 0 | DL14: =IF(BF14="EUR",33%,IF(BF14="CAD",38%,IF(BF14="GBP",51%,IF(BF14="AUD",61%,0)))) -> 0 | DM14: =DK14*DL14 -> 0 | DO14: =IF(OR(Y14="Second Lien",Y14="Tier 1 Split Lien",Y14="Tier 2 Split Lien"),DH14,0) -> 0 | DP14: =DO14*DO$6 -> 0 | DQ14: =DH14-DP14 -> 18000000 | DR14: =IF(Y14="Second Lien",DQ14,0) -> 0 | DS14: =DR14*DR$6 -> 0 | DT14: =DQ14-DS14 -> 18000000 | DU14: =IF(BH14="Yes",DT14,0) -> 0 | DV14: =DU14*DU$6 -> 0 | DW14: =DT14-DV14 -> 18000000 | DX14: =IF(OR(BG14="Canada",BG14="United Kingdom",BG14="Australia",BG14="Netherlands Antilles",BG14="Bermuda",BG14="Cayman Islands",BG14="British Virgin Islands",BG14="Channel Islands",BG14="Isle of Man",BG14="Australia",BG14="Netherlands",BG14="Germany",BG14="Sweden",BG14="Switzerland",BG14="Austria",BG14="Belgium",BG14="Denmark",BG14="Finland",BG14="Iceland",BG14="Ireland",BG14="Lichtenstein",BG14="Luxemborg",BG14="Norway"),DW14,0) -> 0 | DY14: =DX14*DX$6 -> 0 | DZ14: =DW14-DY14 -> 18000000 | EA14: =IF(BI14="Yes",DZ14,0) -> 0 | EB14: =EA14*EA$6 -> 0 | EC14: =DZ14-EB14 -> 18000000 | ED14: =IF(OR(Z14="Delayed Draw",Z14="Revolver"),EC14,0) -> 0 | EE14: =ED14*ED$6 -> 0 | EF14: =EC14-EE14 -> 18000000 | EG14: =IF(S14="Yes",EF14,0) -> 0 | EH14: =EG14*EG$6 -> 0 | EI14: =EF14-EH14 -> 18000000 | EJ14: =IF(Q14="Yes",EI14,0) -> 0 | EK14: =EJ14*EJ$6 -> 0 | EL14: =EI14-EK14 -> 18000000 | EM14: =IF(BD14="Semi-Annually",EL14,0) -> 0 | EN14: =EM14*EM$6 -> 0 | EO14: =EL14-EN14 -> 18000000 | EP14: =IF(BK14="Yes",EO14,0) -> 0 | EQ14: =EP14*EP$6 -> 0 | ER14: =EO14-EQ14 -> 18000000 | ES14: =IF(BL14="Yes",ER14,0) -> 0 | ET14: =ES14*ES$6 -> 0 | EU14: =ER14-ET14 -> 18000000 | EV14: =IF(AND(BM14="Yes",OR(BN14="No",AND(BN14="Yes",Inputs!$J$8=Inputs!$J$17+75))),EU14,0) -> 0 | EW14: =EV14*EV$6 -> 0 | EX14: =EU14-EW14 -> 18000000 | EY14: =IF(BW14="Yes",EX14,0) -> 0 | EZ14: =EY14*EY$6 -> 0 | FA14: =EX14-EZ14 -> 18000000 | FB14: =IF(AR14="Yes",FA14,0) -> 0 | FC14: =FB14*FB$6 -> 0 | FD14: =FA14-FC14 -> 18000000 | FE14: =IF(OR(BF14="EUR",BF14="AUD",BF14="CAD",BF14="GBP"),FD14,0) -> 0 | FF14: =FE14*FE$6 -> 0 | FG14: =FD14-FF14 -> 18000000 | FH14: =FG14 -> 18000000 | FI14: =IF(FG14=0,0,VLOOKUP(C14,$GV$10:$GW$406,2,FALSE)*FG14) -> 0 | FJ14: =FG14-FI14 -> 18000000 | FK14: =FJ14 -> 18000000 | FL14: =IF(OR(IC14="",FJ14<0.01),,VLOOKUP(IC14,$GM$10:$GN$406,2,FALSE)*FJ14) -> 0 | FM14: =FJ14-FL14 -> 18000000 | FN14: =FM14 -> 18000000 | FO14: =IF(FM14=0,0,VLOOKUP(C14,$HE$10:$HF$406,2,FALSE)*FM14) -> 0 | FP14: =FM14-FO14 -> 18000000 | FQ14: =IF(SUM(CZ14:DD14)>0,0,IF(AND(AL14>=5000000,AL14<7500000),FP14,0)) -> 0 | FR14: =IF(B14="",0,FQ14*FQ$6*(1-$U14)) -> 0 | FS14: =FP14-FR14 -> 18000000 | FT14: =IF(SUM(CZ14:DD14)>0,0,IF(AL14<15000000,FS14,0)) -> 18000000 | FU14: =IF(B14="",0,FT14*FT$6*(1-$U14)) -> 0 | FV14: =FS14-FU14 -> 18000000 | FW14: =IF(SUM(CZ14:DD14)>0,0,IF(OR(AND(X14="No",AN14="Tier 1",AI14>$AG$3),AND(X14="No",AN14="Tier 2",AI14>$AH$3),AND(X14="No",AN14="Tier 3",AI14>$AI$3)),FV14,0)) -> 18000000 | FX14: =IF(SUM(CZ14:DD14)>0,0,IF(OR(AND(X14="No",AN14="Tier 1",AJ14>$AG$4),AND(X14="No",AN14="Tier 2",AJ14>$AH$4),AND(X14="No",AN14="Tier 3",AJ14>$AI$4)),FV14,0)) -> 0 | FY14: =IF(SUM(CZ14:DD14)>0,0,IF(OR(AND(X14="Yes",AN14="Tier 1",AJ14>$AG$5),AND(X14="Yes",AN14="Tier 2",AJ14>$AH$5),AND(X14="Yes",AN14="Tier 3",AJ14>$AI$5)),FV14,0)) -> 0 | FZ14: =IF(SUM(FW14:FY14)>0,FV14,0) -> 18000000 | GA14: =IF(B14="",0,FZ14*FW$6*(1-MIN(90%,T14))) -> 80648.008 | GB14: =FV14-GA14 -> 17919352 | GC14: =IF(AND(N14="No",DJ14=0),GB14,IF(AND(N14="No",DJ14<>0,K14=0),0,IF(AND(N14="No",DJ14<>0,K14>0,J14<>K14),MAX(0,M14-(DI14-GB14)),DH14))) -> 17919352 | GD14: =+GC14*V14 -> 12991530 | GE14: =IFERROR(GD14/K14,"") -> 0.72175168 | GF14: =IF(IC14="","",IC14) -> 12 | GG14: {=IF(SUM(IF(IC$9:IC13=IC14,1,0))>0,0,SUMIF($IC$10:$IC$406,IC14,$FJ$10:$FJ$406))} -> 52656704 | GH14: =GG14 -> 52656704 | GI14: =GI13+1 -> 5 | GJ14: =LARGE($GH$10:$GH$406,GI14) -> 57413376 | GK14: =IF(GI14>GI$6,0,IF(GI14=$GI$2,$GK$2,IF(GI14<4,$GK$3,$GK$4))) -> 1.5289285e+08 | GL14: =MAX(0,GJ14-GK14) -> 0 | GM14: {=IF(GJ14=0,0,LARGE(IF($GG$10:$GG$406=GJ14,$GF$10:$GF$406,0),COUNTIF($GJ$10:$GJ$406,GJ14)-COUNTIF(GJ$9:GJ13,GJ14)))} -> 1 | GN14: =IF(GJ14=0,0,GL14/GJ14) -> 0 | GP14: =IF(C14="","",IF(ISERROR(MATCH(C14,C$10:C13,0)),MAX(GP$10:GP13)+1,INDEX(GP$10:GP13,MATCH(C14,C$10:C13,0)))) -> 5 | GQ14: =IF(COUNTIF($A$10:A14,A14)<=1,SUMIF($A$10:$A$406,A14,$FH$10:$FH$406),0) -> 18000000 | GR14: =GR13+1 -> 5 | GS14: =LARGE($GQ$10:$GQ$406,GR14) -> 34155778 | GT14: =IF(GR14>GR$6,0,IF(GR14<=GR$2,GT$2,IF(AND(GR14<=$GR$3,GR14>$GR$2),GT$3,GT$4))) -> 61157141 | GU14: =MAX(0,GS14-GT14) -> 0 | GV14: {=IF(GS14=0,0,LARGE(IF($GQ$10:$GQ$406=GS14,$GP$10:$GP$406,0),COUNTIF($GS$10:$GS$406,GS14)-COUNTIF(GS$9:GS13,GS14)))} -> 70 | GW14: =IF(GS14=0,0,GU14/GS14) -> 0 | GY14: =IF(C14="","",IF(ISERROR(MATCH(C14,C$10:C13,0)),MAX(GP$10:GP13)+1,INDEX(GP$10:GP13,MATCH(C14,C$10:C13,0)))) -> 5 | GZ14: =IF(COUNTIF($A$10:A14,A14)<=1,SUMIF($A$10:$A$406,A14,$FH$10:$FH$406),0) -> 18000000 | HA14: =HA13+1 -> 5 | HB14: =LARGE($GZ$10:$GZ$406,HA14) -> 34155778 | HC14: - | HD14: =IF(HA14<6,MAX(0,$HD$2/5),0) -> 0 | HE14: {=IF(HB14=0,0,LARGE(IF($GZ$10:$GZ$406=HB14,$GY$10:$GY$406,0),COUNTIF($HB$10:$HB$406,HB14)-COUNTIF(HB$9:HB13,HB14)))} -> 70 | HF14: =IF(HB14=0,0,HD14/HB14) -> 0 | HH14: =DH14-GB14 -> 80648.008 | HI14: 0 | HJ14: =MIN(HI14,DF14) -> 0 | HL14: =IF(COUNTIF($C$10:$C$406,HL13+1),HL13+1,"") -> 5 | HM14: =SUMIF($C$10:$C$406,HL14,$DH$10:$DH$406) -> 18000000 | HO14: =MIN(HP14:HT14) -> 18000000 | HP14: =IF(B14="","",$M14) -> 18000000 | HQ14: =IF($N14="Yes",IF(P14>=6,0,MIN($T14*$M14,$U14*$M14)),"") | HR14: =IF(AND(N14="Yes",P14>=6),"",IF($S14="Yes",$R14*$M14,"")) | HS14: =IF($Q14="Yes",MIN($M14,$T14*$M14),"") | HT14: =IF(AND($N14="Yes",$P14>=6),"",IF(OR(CZ14=1,DD14=1,),MIN($T14*$M14,$U14*$M14),IF(OR(DA14=1,DB14=1,DC14=1),IF(AK14>=5000000,MIN($T14*$M14,$IF14*$M14),MIN($T14*$M14,$U14*$M14)),""))) | HU14: =IF(DE14>0,DE14,"") | HV14: =IF(B14="",0,$L14-$M14) -> 0 | HW14: =IF(OR(SUM(HQ14:HU14)>0,P14>=6),"",IF($B14="","",1)) -> 1 | HX14: =IF(AND($HU14<>0,OR(HU14<=MIN(HQ14:HT14),SUM(HQ14:HT14)=0)),$HU14,0) | HY14: =IF(AND($HT14<>0,OR(AND($HT14<>$HU14,$HT14<>$HS14,$HT14<>$HR14,$HT14<>$HQ14,$HT14<MIN($HQ14:$HS14),$HT14<HU14),SUM($HQ14:$HS14)+SUM(HU14)=0),IB14<=0),$HT14,0) -> 0 | HZ14: =IF(AND($HS14<>0,OR(AND($HS14<>$HU14,$HS14<>$HT14,$HS14<>$HR14,$HS14<>$HQ14),$HS14<MIN($HQ14:$HR14),$HS14<MIN($HT14:$HU14),SUM($HQ14:$HR14)+SUM($HT14:$HU14)=0)),$HS14,0) | IA14: =IF(AND($HR14<>0,OR(AND($HR14<>$HU14,HR14<>HT14,HR14<>HS14,HR14<>HQ14,HR14<MIN(HS14:HU14)),SUM(HQ14)+SUM(HS14:HU14)=0)),$HR14,0) | IB14: =IF(AND($HQ14<>0,OR(HQ14<=MIN(HR14:HU14),SUM(HR14:HU14)=0)),$HQ14,0) | IC14: =IF(C14="","",INDEX(Lookups!$E$2:$E$69,MATCH('Loan List'!BE14,Lookups!$F$2:$F$69,0))) -> 12 | ID14: =HV14=DG14 -> TRUE
A15: Azureon, LLC | B15: =IF(D15="","",B14+1) -> 6 | C15: =IF(COUNTIF($A$10:A14,A15)>0,C14,C14+1) -> 6 | D15: Azureon, LLC | E15: TPCN (Term Loan) | G15: 4247877.1 | H15: 4247877.1 | I15: =IF(B15="","",VLOOKUP(BF15,Inputs!$A$12:$J$15,10,FALSE)) -> 1 | J15: =IF(B15="","",G15*I15) -> 4247877.1 | K15: =IF(B15="","",H15*I15) -> 4247877.1 | L15: =IF(B15="","",IF(COUNTIF($CF15:$CY15,1)>0,0,J15)) -> 4247877.1 | M15: =IF(B15="","",IF(COUNTIF($CF15:$CY15,1)>0,0,K15)) -> 4247877.1 | N15: No | O15: N/A | P15: =IF(B15="","",IF(OR(O15="N/A",O15=""),0,YEARFRAC('Borrowing Base'!$J$4,'Loan List'!O15)*12)) -> 0 | Q15: No | R15: 0.9901553 | S15: =IF(B15="","",IF(R15<95%,"Yes","No")) -> No | T15: 0.977 | U15: =IF(B15="","",IF(OR(Y15="First Lien",Y15="Split First Lien",Y15="Tier 1 Split Lien",Y15="Tier 2 Split Lien"),50%,30%)) -> 0.5 | V15: =IF(B15="",0,IF(AND(Y15="First Lien",AN15="Tier 1"),IF(AND(X15="Yes",MIN(AH15,$AJ$5)>4.5),(((4.5/MIN(AH15,$AJ$5))*72.5%)+(((MIN(AH15,$AJ$5)-4.5)/MIN(AH15,$AJ$5))*35%)),72.5%),IF(AND(Y15="First Lien",AN15="Tier 2"),IF(AND(X15="Yes",MIN(AH15,$AK$5)>4.5),(((4.5/MIN(AH15,$AK$5))*72.5%)+(((MIN(AH15,$AK$5)-4.5)/MIN(AH15,$AK$5))*35%)),72.5%),IF(AND(X15="Yes",MIN(AH15,$AL$5)>4),(((4/MIN(AH15,$AL$5))*72.5%)+(((MIN(AH15,$AL$5)-4)/MIN(AH15,$AL$5))*35%)),IF(OR(Y15="First Lien",Y15="Split First Lien"),72.5%,IF(Y15="Split Lien", 53%,35%)))))) -> 0.725 | W15: =IF($C15="","",MIN($HP15:$HT15)) -> 4247877.1 | X15: No | Y15: First Lien | Z15: Term | AA15: NR | AB15: NR | AC15: 2.0309022 | AD15: 1.634954 | AE15: 3.0181648 | AF15: 0.32838249 | AG15: 2.3080215 | AH15: 2.3080215 | AI15: 3.2384246 | AJ15: 3.2384246 | AK15: 7235634.7 | AL15: 13442171 | AM15: 45838 | AN15: =IF(C15="","",(IF(AK15>=50000000,"Tier 1",(IF(OR(AK15>=20000000,AND(AK15>5000000,AC15>=1.25,AF15<=0.65)),"Tier 2","Tier 3"))))) -> Tier 2 | AO15: 47295 | AP15: =IF(C15="","",DAYS360(Inputs!$J$8,AO15)/360) -> 3.8388889 | AQ15: =IF(C15="","",AP15) -> 3.8388889 | AR15: No | AS15: 0 | AT15: Yes | AU15: 0.01 | AV15: 0.0575 | AW15: 0.043507 | AX15: =IF(C15="","",MAX(AU15,AW15)) -> 0.043507 | AY15: 0 | AZ15: 0 | BA15: 0 | BB15: =IF(B15="","",IF(AR15="No",AV15-AZ15,"")) -> 0.0575 | BC15: =IF(B15="","",IF(AR15="Yes",AS15-BA15,"")) | BD15: Quarterly | BE15: Diversified Consumer Services | BF15: USD | BG15: United States | BH15: No | BI15: =IF(B15="","",IF(OR(AND(AZ15>0,BB15>=2.5%,BB15<4%),AND(BA15>0,BC15>=6%,BC15<8%)),"Yes","No")) -> No | BJ15: =IF(B15="","",IF(OR(AND(AZ15>0,BB15<2.5%),AND(BA15>0,BC15<6%)),"Yes","No")) -> No | BK15: No | BL15: No | BM15: No | BN15: No | BO15: No | BP15: No | BQ15: No | BR15: No | BS15: No | BT15: No | BU15: No | BV15: No | BW15: No | BX15: No | BY15: No | BZ15: No | CA15: No | CB15: Yes | CC15: =IF(B15="","",IF(AT15="No",((BB15+AW15)-$AZ$4),((BB15+AX15)-$AZ$4))*IF(DE15>0,0,M15)) -> 245461.88 | CD15: =IF(B15="","",AY15*(L15-M15)*IF(DE15>0,0,1)) -> 0 | CF15: =IF(AND(B15<>"",R15<=85%),1,0) -> 0 | CG15: =IF(B15="",0,(IF(OR(BF15="USD",BF15="CAD",BF15="GBP",BF15="AUD",BF15="EUR"),0,1))) -> 0 | CH15: =IF(B15="",0,(IF(OR(BG15="United States",BG15="Canada",BG15="United Kingdom",BG15="Australia",BG15="Netherlands Antilles",BG15="Bermuda",BG15="Cayman Islands",BG15="British Virgin Islands",BG15="Channel Islands",BG15="Isle of Man",BG15="Australia",BG15="Netherlands",BG15="Germany",BG15="Sweden",BG15="Switzerland",BG15="Austria",BG15="Belgium",BG15="Denmark",BG15="Finland",BG15="Iceland",BG15="Ireland",BG15="Lichtenstein",BG15="Luxemborg",BG15="Norway"),0,1))) -> 0 | CI15: =IF(BO15="Yes",1,0) -> 0 | CJ15: =IF(BP15="Yes",1,0) -> 0 | CK15: =IF(BQ15="Yes",1,0) -> 0 | CL15: =IF(BR15="Yes",1,0) -> 0 | CM15: =IF(BS15="Yes",1,0) -> 0 | CN15: =IF(BT15="Yes",1,0) -> 0 | CO15: =IF(OR(AND(BJ15="Yes",N15="No"),AND(BJ15="Yes",N15="Yes",P15>=6)),1,0) -> 0 | CP15: =IF(BU15="Yes",1,0) -> 0 | CQ15: =IF(AND(BV15="Yes",BW15="No"),1,0) -> 0 | CR15: =IF(BX15="Yes",1,0) -> 0 | CS15: =IF(AP15="",0,IF(AP15>7,1,0)) -> 0 | CT15: =IF(OR(BD15<>"Monthly",BD15<>"Quarterly",BD15<>"Semi-Annually"),0,1) -> 0 | CU15: =IF(BY15="Yes",1,0) -> 0 | CV15: =IF(BZ15="Yes",1,0) -> 0 | CW15: =IF(CA15="Yes",1,0) -> 0 | CX15: =IF(CB15="No",1,0) -> 0 | CY15: =IF(B15="",0,IF(AK15>=5000000,0,1)) -> 0 | CZ15: =IF(B15="",0,IF(AL15>=5000000,0,1)) -> 0 | DA15: =IF(OR(DB15=1,DC15=1,DD15=1),0,IF(B15="",0,IF(OR(AND(AN15="Tier 1",X15="No",OR(AI15>$AJ$3,AJ15>$AJ$4)),(AND(AN15="Tier 1",X15="Yes",AJ15>$AJ$5)),(AND(AN15="Tier 2",X15="No",OR(AI15>$AK$3,AJ15>$AK$4))),(AND(AN15="Tier 2",X15="Yes",AJ15>$AK$5)),(AND(AN15="Tier 3",X15="No",OR(AI15>$AL$3,AJ15>$AL$4))),(AND(AN15="Tier 3",X15="Yes",AJ15>$AL$5))),1,0))) -> 0 | DB15: =IF(OR(DC15=1,DD15=1),0,IF(B15="",0,IF(OR(AND(AN15="Tier 1",X15="No",OR(AI15>$AM$3,AJ15>$AM$4)),(AND(AN15="Tier 1",X15="Yes",AJ15>$AM$5)),(AND(AN15="Tier 2",X15="No",OR(AI15>$AN$3,AJ15>$AN$4))),(AND(AN15="Tier 2",X15="Yes",AJ15>$AN$5)),(AND(AN15="Tier 3",X15="No",OR(AI15>$AO$3,AJ15>$AO$4))),(AND(AN15="Tier 3",X15="Yes",AJ15>$AO$5))),1,0))) -> 0 | DC15: =IF(DD15=1,0,IF(B15="",0,IF(OR(AND(AN15="Tier 1",X15="No",OR(AI15>$AP$3,AJ15>$AP$4)),(AND(AN15="Tier 1",X15="Yes",AJ15>$AP$5)),(AND(AN15="Tier 2",X15="No",OR(AI15>$AQ$3,AJ15>$AQ$4))),(AND(AN15="Tier 2",X15="Yes",AJ15>$AQ$5)),(AND(AN15="Tier 3",X15="No",OR(AI15>$AR$3,AJ15>$AR$4))),(AND(AN15="Tier 3",X15="Yes",AJ15>$AR$5))),1,0))) -> 0 | DD15: =IF(B15="",0,IF(OR(AND(AN15="Tier 1",X15="No",OR(AI15>$AS$3,AJ15>$AS$4)),(AND(AN15="Tier 1",X15="Yes",AJ15>$AS$5)),(AND(AN15="Tier 2",X15="No",OR(AI15>$AT$3,AJ15>$AT$4))),(AND(AN15="Tier 2",X15="Yes",AJ15>$AT$5)),(AND(AN15="Tier 3",X15="No",OR(AI15>$AU$3,AJ15>$AU$4))),(AND(AN15="Tier 3",X15="Yes",AJ15>$AU$5))),1,0)) -> 0 | DE15: =IF((SUM(CF15:CY15)=0),0,W15) -> 0 | DF15: =IF(OR(B15="",DE15>0),0,W15) -> 4247877.1 | DG15: =IF(B15="",0,IF(COUNTIF(CF15:CY15,1)>0,0,L15-M15)) -> 0 | DH15: =DF15+IF(DE15>0,0,DG15) -> 4247877.1 | DI15: =IF(B15="","",M15+DG15) -> 4247877.1 | DJ15: =IF(B15="",0,J15-K15) -> 0 | DK15: =IF(OR(BF15="EUR",BF15="CAD",BF15="GBP",BF15="AUD"),(GB15*(1-V15))+(HH15)+IF(HY15="",0,HY15*(1-U15)),0) -> 0 | DL15: =IF(BF15="EUR",33%,IF(BF15="CAD",38%,IF(BF15="GBP",51%,IF(BF15="AUD",61%,0)))) -> 0 | DM15: =DK15*DL15 -> 0 | DO15: =IF(OR(Y15="Second Lien",Y15="Tier 1 Split Lien",Y15="Tier 2 Split Lien"),DH15,0) -> 0 | DP15: =DO15*DO$6 -> 0 | DQ15: =DH15-DP15 -> 4247877.1 | DR15: =IF(Y15="Second Lien",DQ15,0) -> 0 | DS15: =DR15*DR$6 -> 0 | DT15: =DQ15-DS15 -> 4247877.1 | DU15: =IF(BH15="Yes",DT15,0) -> 0 | DV15: =DU15*DU$6 -> 0 | DW15: =DT15-DV15 -> 4247877.1 | DX15: =IF(OR(BG15="Canada",BG15="United Kingdom",BG15="Australia",BG15="Netherlands Antilles",BG15="Bermuda",BG15="Cayman Islands",BG15="British Virgin Islands",BG15="Channel Islands",BG15="Isle of Man",BG15="Australia",BG15="Netherlands",BG15="Germany",BG15="Sweden",BG15="Switzerland",BG15="Austria",BG15="Belgium",BG15="Denmark",BG15="Finland",BG15="Iceland",BG15="Ireland",BG15="Lichtenstein",BG15="Luxemborg",BG15="Norway"),DW15,0) -> 0 | DY15: =DX15*DX$6 -> 0 | DZ15: =DW15-DY15 -> 4247877.1 | EA15: =IF(BI15="Yes",DZ15,0) -> 0 | EB15: =EA15*EA$6 -> 0 | EC15: =DZ15-EB15 -> 4247877.1 | ED15: =IF(OR(Z15="Delayed Draw",Z15="Revolver"),EC15,0) -> 0 | EE15: =ED15*ED$6 -> 0 | EF15: =EC15-EE15 -> 4247877.1 | EG15: =IF(S15="Yes",EF15,0) -> 0 | EH15: =EG15*EG$6 -> 0 | EI15: =EF15-EH15 -> 4247877.1 | EJ15: =IF(Q15="Yes",EI15,0) -> 0 | EK15: =EJ15*EJ$6 -> 0 | EL15: =EI15-EK15 -> 4247877.1 | EM15: =IF(BD15="Semi-Annually",EL15,0) -> 0 | EN15: =EM15*EM$6 -> 0 | EO15: =EL15-EN15 -> 4247877.1 | EP15: =IF(BK15="Yes",EO15,0) -> 0 | EQ15: =EP15*EP$6 -> 0 | ER15: =EO15-EQ15 -> 4247877.1 | ES15: =IF(BL15="Yes",ER15,0) -> 0 | ET15: =ES15*ES$6 -> 0 | EU15: =ER15-ET15 -> 4247877.1 | EV15: =IF(AND(BM15="Yes",OR(BN15="No",AND(BN15="Yes",Inputs!$J$8=Inputs!$J$17+75))),EU15,0) -> 0 | EW15: =EV15*EV$6 -> 0 | EX15: =EU15-EW15 -> 4247877.1 | EY15: =IF(BW15="Yes",EX15,0) -> 0 | EZ15: =EY15*EY$6 -> 0 | FA15: =EX15-EZ15 -> 4247877.1 | FB15: =IF(AR15="Yes",FA15,0) -> 0 | FC15: =FB15*FB$6 -> 0 | FD15: =FA15-FC15 -> 4247877.1 | FE15: =IF(OR(BF15="EUR",BF15="AUD",BF15="CAD",BF15="GBP"),FD15,0) -> 0 | FF15: =FE15*FE$6 -> 0 | FG15: =FD15-FF15 -> 4247877.1 | FH15: =FG15 -> 4247877.1 | FI15: =IF(FG15=0,0,VLOOKUP(C15,$GV$10:$GW$406,2,FALSE)*FG15) -> 0 | FJ15: =FG15-FI15 -> 4247877.1 | FK15: =FJ15 -> 4247877.1 | FL15: =IF(OR(IC15="",FJ15<0.01),,VLOOKUP(IC15,$GM$10:$GN$406,2,FALSE)*FJ15) -> 0 | FM15: =FJ15-FL15 -> 4247877.1 | FN15: =FM15 -> 4247877.1 | FO15: =IF(FM15=0,0,VLOOKUP(C15,$HE$10:$HF$406,2,FALSE)*FM15) -> 0 | FP15: =FM15-FO15 -> 4247877.1 | FQ15: =IF(SUM(CZ15:DD15)>0,0,IF(AND(AL15>=5000000,AL15<7500000),FP15,0)) -> 0 | FR15: =IF(B15="",0,FQ15*FQ$6*(1-$U15)) -> 0 | FS15: =FP15-FR15 -> 4247877.1 | FT15: =IF(SUM(CZ15:DD15)>0,0,IF(AL15<15000000,FS15,0)) -> 4247877.1 | FU15: =IF(B15="",0,FT15*FT$6*(1-$U15)) -> 0 | FV15: =FS15-FU15 -> 4247877.1 | FW15: =IF(SUM(CZ15:DD15)>0,0,IF(OR(AND(X15="No",AN15="Tier 1",AI15>$AG$3),AND(X15="No",AN15="Tier 2",AI15>$AH$3),AND(X15="No",AN15="Tier 3",AI15>$AI$3)),FV15,0)) -> 0 | FX15: =IF(SUM(CZ15:DD15)>0,0,IF(OR(AND(X15="No",AN15="Tier 1",AJ15>$AG$4),AND(X15="No",AN15="Tier 2",AJ15>$AH$4),AND(X15="No",AN15="Tier 3",AJ15>$AI$4)),FV15,0)) -> 0 | FY15: =IF(SUM(CZ15:DD15)>0,0,IF(OR(AND(X15="Yes",AN15="Tier 1",AJ15>$AG$5),AND(X15="Yes",AN15="Tier 2",AJ15>$AH$5),AND(X15="Yes",AN15="Tier 3",AJ15>$AI$5)),FV15,0)) -> 0 | FZ15: =IF(SUM(FW15:FY15)>0,FV15,0) -> 0 | GA15: =IF(B15="",0,FZ15*FW$6*(1-MIN(90%,T15))) -> 0 | GB15: =FV15-GA15 -> 4247877.1 | GC15: =IF(AND(N15="No",DJ15=0),GB15,IF(AND(N15="No",DJ15<>0,K15=0),0,IF(AND(N15="No",DJ15<>0,K15>0,J15<>K15),MAX(0,M15-(DI15-GB15)),DH15))) -> 4247877.1 | GD15: =+GC15*V15 -> 3079710.9 | GE15: =IFERROR(GD15/K15,"") -> 0.725 | GF15: =IF(IC15="","",IC15) -> 19 | GG15: {=IF(SUM(IF(IC$9:IC14=IC15,1,0))>0,0,SUMIF($IC$10:$IC$406,IC15,$FJ$10:$FJ$406))} -> 56358065 | GH15: =GG15 -> 56358065 | GI15: =GI14+1 -> 6 | GJ15: =LARGE($GH$10:$GH$406,GI15) -> 56358065 | GK15: =IF(GI15>GI$6,0,IF(GI15=$GI$2,$GK$2,IF(GI15<4,$GK$3,$GK$4))) -> 1.5289285e+08 | GL15: =MAX(0,GJ15-GK15) -> 0 | GM15: {=IF(GJ15=0,0,LARGE(IF($GG$10:$GG$406=GJ15,$GF$10:$GF$406,0),COUNTIF($GJ$10:$GJ$406,GJ15)-COUNTIF(GJ$9:GJ14,GJ15)))} -> 19 | GN15: =IF(GJ15=0,0,GL15/GJ15) -> 0 | GP15: =IF(C15="","",IF(ISERROR(MATCH(C15,C$10:C14,0)),MAX(GP$10:GP14)+1,INDEX(GP$10:GP14,MATCH(C15,C$10:C14,0)))) -> 6 | GQ15: =IF(COUNTIF($A$10:A15,A15)<=1,SUMIF($A$10:$A$406,A15,$FH$10:$FH$406),0) -> 4247877.1 | GR15: =GR14+1 -> 6 | GS15: =LARGE($GQ$10:$GQ$406,GR15) -> 29454621 | GT15: =IF(GR15>GR$6,0,IF(GR15<=GR$2,GT$2,IF(AND(GR15<=$GR$3,GR15>$GR$2),GT$3,GT$4))) -> 50964284 | GU15: =MAX(0,GS15-GT15) -> 0 | GV15: {=IF(GS15=0,0,LARGE(IF($GQ$10:$GQ$406=GS15,$GP$10:$GP$406,0),COUNTIF($GS$10:$GS$406,GS15)-COUNTIF(GS$9:GS14,GS15)))} -> 51 | GW15: =IF(GS15=0,0,GU15/GS15) -> 0 | GY15: =IF(C15="","",IF(ISERROR(MATCH(C15,C$10:C14,0)),MAX(GP$10:GP14)+1,INDEX(GP$10:GP14,MATCH(C15,C$10:C14,0)))) -> 6 | GZ15: =IF(COUNTIF($A$10:A15,A15)<=1,SUMIF($A$10:$A$406,A15,$FH$10:$FH$406),0) -> 4247877.1 | HA15: =HA14+1 -> 6 | HB15: =LARGE($GZ$10:$GZ$406,HA15) -> 29454621 | HC15: - | HD15: =IF(HA15<6,MAX(0,$HD$2/5),0) -> 0 | HE15: {=IF(HB15=0,0,LARGE(IF($GZ$10:$GZ$406=HB15,$GY$10:$GY$406,0),COUNTIF($HB$10:$HB$406,HB15)-COUNTIF(HB$9:HB14,HB15)))} -> 51 | HF15: =IF(HB15=0,0,HD15/HB15) -> 0 | HH15: =DH15-GB15 -> 0 | HI15: 0 | HJ15: =MIN(HI15,DF15) -> 0 | HL15: =IF(COUNTIF($C$10:$C$406,HL14+1),HL14+1,"") -> 6 | HM15: =SUMIF($C$10:$C$406,HL15,$DH$10:$DH$406) -> 4247877.1 | HO15: =MIN(HP15:HT15) -> 4247877.1 | HP15: =IF(B15="","",$M15) -> 4247877.1 | HQ15: =IF($N15="Yes",IF(P15>=6,0,MIN($T15*$M15,$U15*$M15)),"") | HR15: =IF(AND(N15="Yes",P15>=6),"",IF($S15="Yes",$R15*$M15,"")) | HS15: =IF($Q15="Yes",MIN($M15,$T15*$M15),"") | HT15: =IF(AND($N15="Yes",$P15>=6),"",IF(OR(CZ15=1,DD15=1,),MIN($T15*$M15,$U15*$M15),IF(OR(DA15=1,DB15=1,DC15=1),IF(AK15>=5000000,MIN($T15*$M15,$IF15*$M15),MIN($T15*$M15,$U15*$M15)),""))) | HU15: =IF(DE15>0,DE15,"") | HV15: =IF(B15="",0,$L15-$M15) -> 0 | HW15: =IF(OR(SUM(HQ15:HU15)>0,P15>=6),"",IF($B15="","",1)) -> 1 | HX15: =IF(AND($HU15<>0,OR(HU15<=MIN(HQ15:HT15),SUM(HQ15:HT15)=0)),$HU15,0) | HY15: =IF(AND($HT15<>0,OR(AND($HT15<>$HU15,$HT15<>$HS15,$HT15<>$HR15,$HT15<>$HQ15,$HT15<MIN($HQ15:$HS15),$HT15<HU15),SUM($HQ15:$HS15)+SUM(HU15)=0),IB15<=0),$HT15,0) -> 0 | HZ15: =IF(AND($HS15<>0,OR(AND($HS15<>$HU15,$HS15<>$HT15,$HS15<>$HR15,$HS15<>$HQ15),$HS15<MIN($HQ15:$HR15),$HS15<MIN($HT15:$HU15),SUM($HQ15:$HR15)+SUM($HT15:$HU15)=0)),$HS15,0) | IA15: =IF(AND($HR15<>0,OR(AND($HR15<>$HU15,HR15<>HT15,HR15<>HS15,HR15<>HQ15,HR15<MIN(HS15:HU15)),SUM(HQ15)+SUM(HS15:HU15)=0)),$HR15,0) | IB15: =IF(AND($HQ15<>0,OR(HQ15<=MIN(HR15:HU15),SUM(HR15:HU15)=0)),$HQ15,0) | IC15: =IF(C15="","",INDEX(Lookups!$E$2:$E$69,MATCH('Loan List'!BE15,Lookups!$F$2:$F$69,0))) -> 19 | ID15: =HV15=DG15 -> TRUE | IF15: =IF(B15="","",IF(AND(Y15="Second Lien",OR(DA15=1,DB15=1,DC15=1)),50%,IF(DA15=1,90%,IF(DB15=1,80%,IF(DC15=1,65%,"No Initial Haircut"))))) -> No Initial Haircut
A16: A1 Garage Merger Sub, LLC | B16: =IF(D16="","",B15+1) -> 7 | C16: =IF(COUNTIF($A$10:A15,A16)>0,C15,C15+1) -> 7 | D16: A1 Garage Merger Sub, LLC | E16: A1 Garage (Term Loan) | G16: 1984732.8 | H16: 1984732.8 | I16: =IF(B16="","",VLOOKUP(BF16,Inputs!$A$12:$J$15,10,FALSE)) -> 1 | J16: =IF(B16="","",G16*I16) -> 1984732.8 | K16: =IF(B16="","",H16*I16) -> 1984732.8 | L16: =IF(B16="","",IF(COUNTIF($CF16:$CY16,1)>0,0,J16)) -> 1984732.8 | M16: =IF(B16="","",IF(COUNTIF($CF16:$CY16,1)>0,0,K16)) -> 1984732.8 | N16: No | O16: N/A | P16: =IF(B16="","",IF(OR(O16="N/A",O16=""),0,YEARFRAC('Borrowing Base'!$J$4,'Loan List'!O16)*12)) -> 0 | Q16: No | R16: 1 | S16: =IF(B16="","",IF(R16<95%,"Yes","No")) -> No | T16: 1 | U16: =IF(B16="","",IF(OR(Y16="First Lien",Y16="Split First Lien",Y16="Tier 1 Split Lien",Y16="Tier 2 Split Lien"),50%,30%)) -> 0.5 | V16: =IF(B16="",0,IF(AND(Y16="First Lien",AN16="Tier 1"),IF(AND(X16="Yes",MIN(AH16,$AJ$5)>4.5),(((4.5/MIN(AH16,$AJ$5))*72.5%)+(((MIN(AH16,$AJ$5)-4.5)/MIN(AH16,$AJ$5))*35%)),72.5%),IF(AND(Y16="First Lien",AN16="Tier 2"),IF(AND(X16="Yes",MIN(AH16,$AK$5)>4.5),(((4.5/MIN(AH16,$AK$5))*72.5%)+(((MIN(AH16,$AK$5)-4.5)/MIN(AH16,$AK$5))*35%)),72.5%),IF(AND(X16="Yes",MIN(AH16,$AL$5)>4),(((4/MIN(AH16,$AL$5))*72.5%)+(((MIN(AH16,$AL$5)-4)/MIN(AH16,$AL$5))*35%)),IF(OR(Y16="First Lien",Y16="Split First Lien"),72.5%,IF(Y16="Split Lien", 53%,35%)))))) -> 0.69284999 | W16: =IF($C16="","",MIN($HP16:$HT16)) -> 1984732.8 | X16: Yes | Y16: First Lien | Z16: Term | AA16: NR | AB16: NR | AC16: 1.4657154 | AD16: 3.3313022 | AE16: 3.8492242 | AF16: 0.25227 | AG16: 4.9219777 | AH16: 4.9219777 | AI16: 1.9726985 | AJ16: 1.9726985 | AK16: 26534050 | AL16: 68148598 | AM16: 45838 | AN16: =IF(C16="","",(IF(AK16>=50000000,"Tier 1",(IF(OR(AK16>=20000000,AND(AK16>5000000,AC16>=1.25,AF16<=0.65)),"Tier 2","Tier 3"))))) -> Tier 2 | AO16: 47109 | AP16: =IF(C16="","",DAYS360(Inputs!$J$8,AO16)/360) -> 3.3277778 | AQ16: =IF(C16="","",AP16) -> 3.3277778 | AR16: No | AS16: 0 | AT16: Yes | AU16: 0.01 | AV16: 0.0575 | AW16: 0.043507 | AX16: =IF(C16="","",MAX(AU16,AW16)) -> 0.043507 | AY16: 0 | AZ16: 0 | BA16: 0 | BB16: =IF(B16="","",IF(AR16="No",AV16-AZ16,"")) -> 0.0575 | BC16: =IF(B16="","",IF(AR16="Yes",AS16-BA16,"")) | BD16: Quarterly | BE16: Diversified Consumer Services | BF16: USD | BG16: United States | BH16: No | BI16: =IF(B16="","",IF(OR(AND(AZ16>0,BB16>=2.5%,BB16<4%),AND(BA16>0,BC16>=6%,BC16<8%)),"Yes","No")) -> No | BJ16: =IF(B16="","",IF(OR(AND(AZ16>0,BB16<2.5%),AND(BA16>0,BC16<6%)),"Yes","No")) -> No | BK16: No | BL16: No | BM16: Yes | BN16: Yes | BO16: No | BP16: No | BQ16: No | BR16: No | BS16: No | BT16: No | BU16: No | BV16: No | BW16: No | BX16: No | BY16: No | BZ16: No | CA16: No | CB16: Yes | CC16: =IF(B16="","",IF(AT16="No",((BB16+AW16)-$AZ$4),((BB16+AX16)-$AZ$4))*IF(DE16>0,0,M16)) -> 114686.99 | CD16: =IF(B16="","",AY16*(L16-M16)*IF(DE16>0,0,1)) -> 0 | CF16: =IF(AND(B16<>"",R16<=85%),1,0) -> 0 | CG16: =IF(B16="",0,(IF(OR(BF16="USD",BF16="CAD",BF16="GBP",BF16="AUD",BF16="EUR"),0,1))) -> 0 | CH16: =IF(B16="",0,(IF(OR(BG16="United States",BG16="Canada",BG16="United Kingdom",BG16="Australia",BG16="Netherlands Antilles",BG16="Bermuda",BG16="Cayman Islands",BG16="British Virgin Islands",BG16="Channel Islands",BG16="Isle of Man",BG16="Australia",BG16="Netherlands",BG16="Germany",BG16="Sweden",BG16="Switzerland",BG16="Austria",BG16="Belgium",BG16="Denmark",BG16="Finland",BG16="Iceland",BG16="Ireland",BG16="Lichtenstein",BG16="Luxemborg",BG16="Norway"),0,1))) -> 0 | CI16: =IF(BO16="Yes",1,0) -> 0 | CJ16: =IF(BP16="Yes",1,0) -> 0 | CK16: =IF(BQ16="Yes",1,0) -> 0 | CL16: =IF(BR16="Yes",1,0) -> 0 | CM16: =IF(BS16="Yes",1,0) -> 0 | CN16: =IF(BT16="Yes",1,0) -> 0 | CO16: =IF(OR(AND(BJ16="Yes",N16="No"),AND(BJ16="Yes",N16="Yes",P16>=6)),1,0) -> 0 | CP16: =IF(BU16="Yes",1,0) -> 0 | CQ16: =IF(AND(BV16="Yes",BW16="No"),1,0) -> 0 | CR16: =IF(BX16="Yes",1,0) -> 0 | CS16: =IF(AP16="",0,IF(AP16>7,1,0)) -> 0 | CT16: =IF(OR(BD16<>"Monthly",BD16<>"Quarterly",BD16<>"Semi-Annually"),0,1) -> 0 | CU16: =IF(BY16="Yes",1,0) -> 0 | CV16: =IF(BZ16="Yes",1,0) -> 0 | CW16: =IF(CA16="Yes",1,0) -> 0 | CX16: =IF(CB16="No",1,0) -> 0 | CY16: =IF(B16="",0,IF(AK16>=5000000,0,1)) -> 0 | CZ16: =IF(B16="",0,IF(AL16>=5000000,0,1)) -> 0 | DA16: =IF(OR(DB16=1,DC16=1,DD16=1),0,IF(B16="",0,IF(OR(AND(AN16="Tier 1",X16="No",OR(AI16>$AJ$3,AJ16>$AJ$4)),(AND(AN16="Tier 1",X16="Yes",AJ16>$AJ$5)),(AND(AN16="Tier 2",X16="No",OR(AI16>$AK$3,AJ16>$AK$4))),(AND(AN16="Tier 2",X16="Yes",AJ16>$AK$5)),(AND(AN16="Tier 3",X16="No",OR(AI16>$AL$3,AJ16>$AL$4))),(AND(AN16="Tier 3",X16="Yes",AJ16>$AL$5))),1,0))) -> 0 | DB16: =IF(OR(DC16=1,DD16=1),0,IF(B16="",0,IF(OR(AND(AN16="Tier 1",X16="No",OR(AI16>$AM$3,AJ16>$AM$4)),(AND(AN16="Tier 1",X16="Yes",AJ16>$AM$5)),(AND(AN16="Tier 2",X16="No",OR(AI16>$AN$3,AJ16>$AN$4))),(AND(AN16="Tier 2",X16="Yes",AJ16>$AN$5)),(AND(AN16="Tier 3",X16="No",OR(AI16>$AO$3,AJ16>$AO$4))),(AND(AN16="Tier 3",X16="Yes",AJ16>$AO$5))),1,0))) -> 0 | DC16: =IF(DD16=1,0,IF(B16="",0,IF(OR(AND(AN16="Tier 1",X16="No",OR(AI16>$AP$3,AJ16>$AP$4)),(AND(AN16="Tier 1",X16="Yes",AJ16>$AP$5)),(AND(AN16="Tier 2",X16="No",OR(AI16>$AQ$3,AJ16>$AQ$4))),(AND(AN16="Tier 2",X16="Yes",AJ16>$AQ$5)),(AND(AN16="Tier 3",X16="No",OR(AI16>$AR$3,AJ16>$AR$4))),(AND(AN16="Tier 3",X16="Yes",AJ16>$AR$5))),1,0))) -> 0 | DD16: =IF(B16="",0,IF(OR(AND(AN16="Tier 1",X16="No",OR(AI16>$AS$3,AJ16>$AS$4)),(AND(AN16="Tier 1",X16="Yes",AJ16>$AS$5)),(AND(AN16="Tier 2",X16="No",OR(AI16>$AT$3,AJ16>$AT$4))),(AND(AN16="Tier 2",X16="Yes",AJ16>$AT$5)),(AND(AN16="Tier 3",X16="No",OR(AI16>$AU$3,AJ16>$AU$4))),(AND(AN16="Tier 3",X16="Yes",AJ16>$AU$5))),1,0)) -> 0 | DE16: =IF((SUM(CF16:CY16)=0),0,W16) -> 0 | DF16: =IF(OR(B16="",DE16>0),0,W16) -> 1984732.8 | DG16: =IF(B16="",0,IF(COUNTIF(CF16:CY16,1)>0,0,L16-M16)) -> 0 | DH16: =DF16+IF(DE16>0,0,DG16) -> 1984732.8 | DI16: =IF(B16="","",M16+DG16) -> 1984732.8 | DJ16: =IF(B16="",0,J16-K16) -> 0 | DK16: =IF(OR(BF16="EUR",BF16="CAD",BF16="GBP",BF16="AUD"),(GB16*(1-V16))+(HH16)+IF(HY16="",0,HY16*(1-U16)),0) -> 0 | DL16: =IF(BF16="EUR",33%,IF(BF16="CAD",38%,IF(BF16="GBP",51%,IF(BF16="AUD",61%,0)))) -> 0 | DM16: =DK16*DL16 -> 0 | DO16: =IF(OR(Y16="Second Lien",Y16="Tier 1 Split Lien",Y16="Tier 2 Split Lien"),DH16,0) -> 0 | DP16: =DO16*DO$6 -> 0 | DQ16: =DH16-DP16 -> 1984732.8 | DR16: =IF(Y16="Second Lien",DQ16,0) -> 0 | DS16: =DR16*DR$6 -> 0 | DT16: =DQ16-DS16 -> 1984732.8 | DU16: =IF(BH16="Yes",DT16,0) -> 0 | DV16: =DU16*DU$6 -> 0 | DW16: =DT16-DV16 -> 1984732.8 | DX16: =IF(OR(BG16="Canada",BG16="United Kingdom",BG16="Australia",BG16="Netherlands Antilles",BG16="Bermuda",BG16="Cayman Islands",BG16="British Virgin Islands",BG16="Channel Islands",BG16="Isle of Man",BG16="Australia",BG16="Netherlands",BG16="Germany",BG16="Sweden",BG16="Switzerland",BG16="Austria",BG16="Belgium",BG16="Denmark",BG16="Finland",BG16="Iceland",BG16="Ireland",BG16="Lichtenstein",BG16="Luxemborg",BG16="Norway"),DW16,0) -> 0 | DY16: =DX16*DX$6 -> 0 | DZ16: =DW16-DY16 -> 1984732.8 | EA16: =IF(BI16="Yes",DZ16,0) -> 0 | EB16: =EA16*EA$6 -> 0 | EC16: =DZ16-EB16 -> 1984732.8 | ED16: =IF(OR(Z16="Delayed Draw",Z16="Revolver"),EC16,0) -> 0 | EE16: =ED16*ED$6 -> 0 | EF16: =EC16-EE16 -> 1984732.8 | EG16: =IF(S16="Yes",EF16,0) -> 0 | EH16: =EG16*EG$6 -> 0 | EI16: =EF16-EH16 -> 1984732.8 | EJ16: =IF(Q16="Yes",EI16,0) -> 0 | EK16: =EJ16*EJ$6 -> 0 | EL16: =EI16-EK16 -> 1984732.8 | EM16: =IF(BD16="Semi-Annually",EL16,0) -> 0 | EN16: =EM16*EM$6 -> 0 | EO16: =EL16-EN16 -> 1984732.8 | EP16: =IF(BK16="Yes",EO16,0) -> 0 | EQ16: =EP16*EP$6 -> 0 | ER16: =EO16-EQ16 -> 1984732.8 | ES16: =IF(BL16="Yes",ER16,0) -> 0 | ET16: =ES16*ES$6 -> 0 | EU16: =ER16-ET16 -> 1984732.8 | EV16: =IF(AND(BM16="Yes",OR(BN16="No",AND(BN16="Yes",Inputs!$J$8=Inputs!$J$17+75))),EU16,0) -> 0 | EW16: =EV16*EV$6 -> 0 | EX16: =EU16-EW16 -> 1984732.8 | EY16: =IF(BW16="Yes",EX16,0) -> 0 | EZ16: =EY16*EY$6 -> 0 | FA16: =EX16-EZ16 -> 1984732.8 | FB16: =IF(AR16="Yes",FA16,0) -> 0 | FC16: =FB16*FB$6 -> 0 | FD16: =FA16-FC16 -> 1984732.8 | FE16: =IF(OR(BF16="EUR",BF16="AUD",BF16="CAD",BF16="GBP"),FD16,0) -> 0 | FF16: =FE16*FE$6 -> 0 | FG16: =FD16-FF16 -> 1984732.8 | FH16: =FG16 -> 1984732.8 | FI16: =IF(FG16=0,0,VLOOKUP(C16,$GV$10:$GW$406,2,FALSE)*FG16) -> 0 | FJ16: =FG16-FI16 -> 1984732.8 | FK16: =FJ16 -> 1984732.8 | FL16: =IF(OR(IC16="",FJ16<0.01),,VLOOKUP(IC16,$GM$10:$GN$406,2,FALSE)*FJ16) -> 0 | FM16: =FJ16-FL16 -> 1984732.8 | FN16: =FM16 -> 1984732.8 | FO16: =IF(FM16=0,0,VLOOKUP(C16,$HE$10:$HF$406,2,FALSE)*FM16) -> 0 | FP16: =FM16-FO16 -> 1984732.8 | FQ16: =IF(SUM(CZ16:DD16)>0,0,IF(AND(AL16>=5000000,AL16<7500000),FP16,0)) -> 0 | FR16: =IF(B16="",0,FQ16*FQ$6*(1-$U16)) -> 0 | FS16: =FP16-FR16 -> 1984732.8 | FT16: =IF(SUM(CZ16:DD16)>0,0,IF(AL16<15000000,FS16,0)) -> 0 | FU16: =IF(B16="",0,FT16*FT$6*(1-$U16)) -> 0 | FV16: =FS16-FU16 -> 1984732.8 | FW16: =IF(SUM(CZ16:DD16)>0,0,IF(OR(AND(X16="No",AN16="Tier 1",AI16>$AG$3),AND(X16="No",AN16="Tier 2",AI16>$AH$3),AND(X16="No",AN16="Tier 3",AI16>$AI$3)),FV16,0)) -> 0 | FX16: =IF(SUM(CZ16:DD16)>0,0,IF(OR(AND(X16="No",AN16="Tier 1",AJ16>$AG$4),AND(X16="No",AN16="Tier 2",AJ16>$AH$4),AND(X16="No",AN16="Tier 3",AJ16>$AI$4)),FV16,0)) -> 0 | FY16: =IF(SUM(CZ16:DD16)>0,0,IF(OR(AND(X16="Yes",AN16="Tier 1",AJ16>$AG$5),AND(X16="Yes",AN16="Tier 2",AJ16>$AH$5),AND(X16="Yes",AN16="Tier 3",AJ16>$AI$5)),FV16,0)) -> 0 | FZ16: =IF(SUM(FW16:FY16)>0,FV16,0) -> 0 | GA16: =IF(B16="",0,FZ16*FW$6*(1-MIN(90%,T16))) -> 0 | GB16: =FV16-GA16 -> 1984732.8 | GC16: =IF(AND(N16="No",DJ16=0),GB16,IF(AND(N16="No",DJ16<>0,K16=0),0,IF(AND(N16="No",DJ16<>0,K16>0,J16<>K16),MAX(0,M16-(DI16-GB16)),DH16))) -> 1984732.8 | GD16: =+GC16*V16 -> 1375122.1 | GE16: =IFERROR(GD16/K16,"") -> 0.69284999 | GF16: =IF(IC16="","",IC16) -> 19 | GG16: {=IF(SUM(IF(IC$9:IC15=IC16,1,0))>0,0,SUMIF($IC$10:$IC$406,IC16,$FJ$10:$FJ$406))} -> 0 | GH16: =GG16 -> 0 | GI16: =GI15+1 -> 7 | GJ16: =LARGE($GH$10:$GH$406,GI16) -> 56100012 | GK16: =IF(GI16>GI$6,0,IF(GI16=$GI$2,$GK$2,IF(GI16<4,$GK$3,$GK$4))) -> 1.5289285e+08 | GL16: =MAX(0,GJ16-GK16) -> 0 | GM16: {=IF(GJ16=0,0,LARGE(IF($GG$10:$GG$406=GJ16,$GF$10:$GF$406,0),COUNTIF($GJ$10:$GJ$406,GJ16)-COUNTIF(GJ$9:GJ15,GJ16)))} -> 42 | GN16: =IF(GJ16=0,0,GL16/GJ16) -> 0 | GP16: =IF(C16="","",IF(ISERROR(MATCH(C16,C$10:C15,0)),MAX(GP$10:GP15)+1,INDEX(GP$10:GP15,MATCH(C16,C$10:C15,0)))) -> 7 | GQ16: =IF(COUNTIF($A$10:A16,A16)<=1,SUMIF($A$10:$A$406,A16,$FH$10:$FH$406),0) -> 1984732.8 | GR16: =GR15+1 -> 7 | GS16: =LARGE($GQ$10:$GQ$406,GR16) -> 27620404 | GT16: =IF(GR16>GR$6,0,IF(GR16<=GR$2,GT$2,IF(AND(GR16<=$GR$3,GR16>$GR$2),GT$3,GT$4))) -> 50964284 | GU16: =MAX(0,GS16-GT16) -> 0 | GV16: {=IF(GS16=0,0,LARGE(IF($GQ$10:$GQ$406=GS16,$GP$10:$GP$406,0),COUNTIF($GS$10:$GS$406,GS16)-COUNTIF(GS$9:GS15,GS16)))} -> 99 | GW16: =IF(GS16=0,0,GU16/GS16) -> 0 | GY16: =IF(C16="","",IF(ISERROR(MATCH(C16,C$10:C15,0)),MAX(GP$10:GP15)+1,INDEX(GP$10:GP15,MATCH(C16,C$10:C15,0)))) -> 7 | GZ16: =IF(COUNTIF($A$10:A16,A16)<=1,SUMIF($A$10:$A$406,A16,$FH$10:$FH$406),0) -> 1984732.8 | HA16: =HA15+1 -> 7 | HB16: =LARGE($GZ$10:$GZ$406,HA16) -> 27620404 | HC16: - | HD16: =IF(HA16<6,MAX(0,$HD$2/5),0) -> 0 | HE16: {=IF(HB16=0,0,LARGE(IF($GZ$10:$GZ$406=HB16,$GY$10:$GY$406,0),COUNTIF($HB$10:$HB$406,HB16)-COUNTIF(HB$9:HB15,HB16)))} -> 99 | HF16: =IF(HB16=0,0,HD16/HB16) -> 0 | HH16: =DH16-GB16 -> 0 | HI16: 0 | HJ16: =MIN(HI16,DF16) -> 0 | HL16: =IF(COUNTIF($C$10:$C$406,HL15+1),HL15+1,"") -> 7 | HM16: =SUMIF($C$10:$C$406,HL16,$DH$10:$DH$406) -> 3213434.8 | HO16: =MIN(HP16:HT16) -> 1984732.8 | HP16: =IF(B16="","",$M16) -> 1984732.8 | HQ16: =IF($N16="Yes",IF(P16>=6,0,MIN($T16*$M16,$U16*$M16)),"") | HR16: =IF(AND(N16="Yes",P16>=6),"",IF($S16="Yes",$R16*$M16,"")) | HS16: =IF($Q16="Yes",MIN($M16,$T16*$M16),"") | HT16: =IF(AND($N16="Yes",$P16>=6),"",IF(OR(CZ16=1,DD16=1,),MIN($T16*$M16,$U16*$M16),IF(OR(DA16=1,DB16=1,DC16=1),IF(AK16>=5000000,MIN($T16*$M16,$IF16*$M16),MIN($T16*$M16,$U16*$M16)),""))) | HU16: =IF(DE16>0,DE16,"") | HV16: =IF(B16="",0,$L16-$M16) -> 0 | HW16: =IF(OR(SUM(HQ16:HU16)>0,P16>=6),"",IF($B16="","",1)) -> 1 | HX16: =IF(AND($HU16<>0,OR(HU16<=MIN(HQ16:HT16),SUM(HQ16:HT16)=0)),$HU16,0) | HY16: =IF(AND($HT16<>0,OR(AND($HT16<>$HU16,$HT16<>$HS16,$HT16<>$HR16,$HT16<>$HQ16,$HT16<MIN($HQ16:$HS16),$HT16<HU16),SUM($HQ16:$HS16)+SUM(HU16)=0),IB16<=0),$HT16,0) -> 0 | HZ16: =IF(AND($HS16<>0,OR(AND($HS16<>$HU16,$HS16<>$HT16,$HS16<>$HR16,$HS16<>$HQ16),$HS16<MIN($HQ16:$HR16),$HS16<MIN($HT16:$HU16),SUM($HQ16:$HR16)+SUM($HT16:$HU16)=0)),$HS16,0) | IA16: =IF(AND($HR16<>0,OR(AND($HR16<>$HU16,HR16<>HT16,HR16<>HS16,HR16<>HQ16,HR16<MIN(HS16:HU16)),SUM(HQ16)+SUM(HS16:HU16)=0)),$HR16,0) | IB16: =IF(AND($HQ16<>0,OR(HQ16<=MIN(HR16:HU16),SUM(HR16:HU16)=0)),$HQ16,0) | IC16: =IF(C16="","",INDEX(Lookups!$E$2:$E$69,MATCH('Loan List'!BE16,Lookups!$F$2:$F$69,0))) -> 19 | ID16: =HV16=DG16 -> TRUE | IF16: =IF(B16="","",IF(AND(Y16="Second Lien",OR(DA16=1,DB16=1,DC16=1)),50%,IF(DA16=1,90%,IF(DB16=1,80%,IF(DC16=1,65%,"No Initial Haircut"))))) -> No Initial Haircut
A17: ACP Avenu Buyer, LLC | B17: =IF(D17="","",B16+1) -> 8 | C17: =IF(COUNTIF($A$10:A16,A17)>0,C16,C16+1) -> 7 | D17: ACP Avenu Buyer, LLC 2 | E17: Avenu (TL) | G17: 1228702 | H17: 1228702 | I17: =IF(B17="","",VLOOKUP(BF17,Inputs!$A$12:$J$15,10,FALSE)) -> 1 | J17: =IF(B17="","",G17*I17) -> 1228702 | K17: =IF(B17="","",H17*I17) -> 1228702 | L17: =IF(B17="","",IF(COUNTIF($CF17:$CY17,1)>0,0,J17)) -> 1228702 | M17: =IF(B17="","",IF(COUNTIF($CF17:$CY17,1)>0,0,K17)) -> 1228702 | N17: No | O17: N/A | P17: =IF(B17="","",IF(OR(O17="N/A",O17=""),0,YEARFRAC('Borrowing Base'!$J$4,'Loan List'!O17)*12)) -> 0 | Q17: No | R17: 0.99733768 | S17: =IF(B17="","",IF(R17<95%,"Yes","No")) -> No | T17: 0.99 | U17: =IF(B17="","",IF(OR(Y17="First Lien",Y17="Split First Lien",Y17="Tier 1 Split Lien",Y17="Tier 2 Split Lien"),50%,30%)) -> 0.5 | V17: =IF(B17="",0,IF(AND(Y17="First Lien",AN17="Tier 1"),IF(AND(X17="Yes",MIN(AH17,$AJ$5)>4.5),(((4.5/MIN(AH17,$AJ$5))*72.5%)+(((MIN(AH17,$AJ$5)-4.5)/MIN(AH17,$AJ$5))*35%)),72.5%),IF(AND(Y17="First Lien",AN17="Tier 2"),IF(AND(X17="Yes",MIN(AH17,$AK$5)>4.5),(((4.5/MIN(AH17,$AK$5))*72.5%)+(((MIN(AH17,$AK$5)-4.5)/MIN(AH17,$AK$5))*35%)),72.5%),IF(AND(X17="Yes",MIN(AH17,$AL$5)>4),(((4/MIN(AH17,$AL$5))*72.5%)+(((MIN(AH17,$AL$5)-4)/MIN(AH17,$AL$5))*35%)),IF(OR(Y17="First Lien",Y17="Split First Lien"),72.5%,IF(Y17="Split Lien", 53%,35%)))))) -> 0.71636278 | W17: =IF($C17="","",MIN($HP17:$HT17)) -> 1228702 | X17: Yes | Y17: First Lien | Z17: Term | AA17: NR | AB17: NR | AC17: 5.1870295 | AD17: 1.4275347 | AE17: 2.224929 | AF17: 0.4590766 | AG17: 4.6060902 | AH17: 4.6060902 | AI17: 4.6060902 | AJ17: 4.6060902 | AK17: 77650021 | AL17: 77650021 | AM17: 45747 | AN17: =IF(C17="","",(IF(AK17>=50000000,"Tier 1",(IF(OR(AK17>=20000000,AND(AK17>5000000,AC17>=1.25,AF17<=0.65)),"Tier 2","Tier 3"))))) -> Tier 1 | AO17: 47393 | AP17: =IF(C17="","",DAYS360(Inputs!$J$8,AO17)/360) -> 4.1055556 | AQ17: =IF(C17="","",AP17) -> 4.1055556 | AR17: No | AS17: 0 | AT17: Yes | AU17: 0.01 | AV17: 0.0475 | AW17: 0.042906 | AX17: =IF(C17="","",MAX(AU17,AW17)) -> 0.042906 | AY17: 0 | AZ17: 0 | BA17: 0 | BB17: =IF(B17="","",IF(AR17="No",AV17-AZ17,"")) -> 0.0475 | BC17: =IF(B17="","",IF(AR17="Yes",AS17-BA17,"")) | BD17: Quarterly | BE17: IT Services | BF17: USD | BG17: United States | BH17: No | BI17: =IF(B17="","",IF(OR(AND(AZ17>0,BB17>=2.5%,BB17<4%),AND(BA17>0,BC17>=6%,BC17<8%)),"Yes","No")) -> No | BJ17: =IF(B17="","",IF(OR(AND(AZ17>0,BB17<2.5%),AND(BA17>0,BC17<6%)),"Yes","No")) -> No | BK17: No | BL17: No | BM17: Yes | BN17: Yes | BO17: No | BP17: No | BQ17: No | BR17: No | BS17: No | BT17: No | BU17: No | BV17: No | BW17: No | BX17: No | BY17: No | BZ17: No | CA17: No | CB17: Yes | CC17: =IF(B17="","",IF(AT17="No",((BB17+AW17)-$AZ$4),((BB17+AX17)-$AZ$4))*IF(DE17>0,0,M17)) -> 57974.584 | CD17: =IF(B17="","",AY17*(L17-M17)*IF(DE17>0,0,1)) -> 0 | CF17: =IF(AND(B17<>"",R17<=85%),1,0) -> 0 | CG17: =IF(B17="",0,(IF(OR(BF17="USD",BF17="CAD",BF17="GBP",BF17="AUD",BF17="EUR"),0,1))) -> 0 | CH17: =IF(B17="",0,(IF(OR(BG17="United States",BG17="Canada",BG17="United Kingdom",BG17="Australia",BG17="Netherlands Antilles",BG17="Bermuda",BG17="Cayman Islands",BG17="British Virgin Islands",BG17="Channel Islands",BG17="Isle of Man",BG17="Australia",BG17="Netherlands",BG17="Germany",BG17="Sweden",BG17="Switzerland",BG17="Austria",BG17="Belgium",BG17="Denmark",BG17="Finland",BG17="Iceland",BG17="Ireland",BG17="Lichtenstein",BG17="Luxemborg",BG17="Norway"),0,1))) -> 0 | CI17: =IF(BO17="Yes",1,0) -> 0 | CJ17: =IF(BP17="Yes",1,0) -> 0 | CK17: =IF(BQ17="Yes",1,0) -> 0 | CL17: =IF(BR17="Yes",1,0) -> 0 | CM17: =IF(BS17="Yes",1,0) -> 0 | CN17: =IF(BT17="Yes",1,0) -> 0 | CO17: =IF(OR(AND(BJ17="Yes",N17="No"),AND(BJ17="Yes",N17="Yes",P17>=6)),1,0) -> 0 | CP17: =IF(BU17="Yes",1,0) -> 0 | CQ17: =IF(AND(BV17="Yes",BW17="No"),1,0) -> 0 | CR17: =IF(BX17="Yes",1,0) -> 0 | CS17: =IF(AP17="",0,IF(AP17>7,1,0)) -> 0 | CT17: =IF(OR(BD17<>"Monthly",BD17<>"Quarterly",BD17<>"Semi-Annually"),0,1) -> 0 | CU17: =IF(BY17="Yes",1,0) -> 0 | CV17: =IF(BZ17="Yes",1,0) -> 0 | CW17: =IF(CA17="Yes",1,0) -> 0 | CX17: =IF(CB17="No",1,0) -> 0 | CY17: =IF(B17="",0,IF(AK17>=5000000,0,1)) -> 0 | CZ17: =IF(B17="",0,IF(AL17>=5000000,0,1)) -> 0 | DA17: =IF(OR(DB17=1,DC17=1,DD17=1),0,IF(B17="",0,IF(OR(AND(AN17="Tier 1",X17="No",OR(AI17>$AJ$3,AJ17>$AJ$4)),(AND(AN17="Tier 1",X17="Yes",AJ17>$AJ$5)),(AND(AN17="Tier 2",X17="No",OR(AI17>$AK$3,AJ17>$AK$4))),(AND(AN17="Tier 2",X17="Yes",AJ17>$AK$5)),(AND(AN17="Tier 3",X17="No",OR(AI17>$AL$3,AJ17>$AL$4))),(AND(AN17="Tier 3",X17="Yes",AJ17>$AL$5))),1,0))) -> 0 | DB17: =IF(OR(DC17=1,DD17=1),0,IF(B17="",0,IF(OR(AND(AN17="Tier 1",X17="No",OR(AI17>$AM$3,AJ17>$AM$4)),(AND(AN17="Tier 1",X17="Yes",AJ17>$AM$5)),(AND(AN17="Tier 2",X17="No",OR(AI17>$AN$3,AJ17>$AN$4))),(AND(AN17="Tier 2",X17="Yes",AJ17>$AN$5)),(AND(AN17="Tier 3",X17="No",OR(AI17>$AO$3,AJ17>$AO$4))),(AND(AN17="Tier 3",X17="Yes",AJ17>$AO$5))),1,0))) -> 0 | DC17: =IF(DD17=1,0,IF(B17="",0,IF(OR(AND(AN17="Tier 1",X17="No",OR(AI17>$AP$3,AJ17>$AP$4)),(AND(AN17="Tier 1",X17="Yes",AJ17>$AP$5)),(AND(AN17="Tier 2",X17="No",OR(AI17>$AQ$3,AJ17>$AQ$4))),(AND(AN17="Tier 2",X17="Yes",AJ17>$AQ$5)),(AND(AN17="Tier 3",X17="No",OR(AI17>$AR$3,AJ17>$AR$4))),(AND(AN17="Tier 3",X17="Yes",AJ17>$AR$5))),1,0))) -> 0 | DD17: =IF(B17="",0,IF(OR(AND(AN17="Tier 1",X17="No",OR(AI17>$AS$3,AJ17>$AS$4)),(AND(AN17="Tier 1",X17="Yes",AJ17>$AS$5)),(AND(AN17="Tier 2",X17="No",OR(AI17>$AT$3,AJ17>$AT$4))),(AND(AN17="Tier 2",X17="Yes",AJ17>$AT$5)),(AND(AN17="Tier 3",X17="No",OR(AI17>$AU$3,AJ17>$AU$4))),(AND(AN17="Tier 3",X17="Yes",AJ17>$AU$5))),1,0)) -> 0 | DE17: =IF((SUM(CF17:CY17)=0),0,W17) -> 0 | DF17: =IF(OR(B17="",DE17>0),0,W17) -> 1228702 | DG17: =IF(B17="",0,IF(COUNTIF(CF17:CY17,1)>0,0,L17-M17)) -> 0 | DH17: =DF17+IF(DE17>0,0,DG17) -> 1228702 | DI17: =IF(B17="","",M17+DG17) -> 1228702 | DJ17: =IF(B17="",0,J17-K17) -> 0 | DK17: =IF(OR(BF17="EUR",BF17="CAD",BF17="GBP",BF17="AUD"),(GB17*(1-V17))+(HH17)+IF(HY17="",0,HY17*(1-U17)),0) -> 0 | DL17: =IF(BF17="EUR",33%,IF(BF17="CAD",38%,IF(BF17="GBP",51%,IF(BF17="AUD",61%,0)))) -> 0 | DM17: =DK17*DL17 -> 0 | DO17: =IF(OR(Y17="Second Lien",Y17="Tier 1 Split Lien",Y17="Tier 2 Split Lien"),DH17,0) -> 0 | DP17: =DO17*DO$6 -> 0 | DQ17: =DH17-DP17 -> 1228702 | DR17: =IF(Y17="Second Lien",DQ17,0) -> 0 | DS17: =DR17*DR$6 -> 0 | DT17: =DQ17-DS17 -> 1228702 | DU17: =IF(BH17="Yes",DT17,0) -> 0 | DV17: =DU17*DU$6 -> 0 | DW17: =DT17-DV17 -> 1228702 | DX17: =IF(OR(BG17="Canada",BG17="United Kingdom",BG17="Australia",BG17="Netherlands Antilles",BG17="Bermuda",BG17="Cayman Islands",BG17="British Virgin Islands",BG17="Channel Islands",BG17="Isle of Man",BG17="Australia",BG17="Netherlands",BG17="Germany",BG17="Sweden",BG17="Switzerland",BG17="Austria",BG17="Belgium",BG17="Denmark",BG17="Finland",BG17="Iceland",BG17="Ireland",BG17="Lichtenstein",BG17="Luxemborg",BG17="Norway"),DW17,0) -> 0 | DY17: =DX17*DX$6 -> 0 | DZ17: =DW17-DY17 -> 1228702 | EA17: =IF(BI17="Yes",DZ17,0) -> 0 | EB17: =EA17*EA$6 -> 0 | EC17: =DZ17-EB17 -> 1228702 | ED17: =IF(OR(Z17="Delayed Draw",Z17="Revolver"),EC17,0) -> 0 | EE17: =ED17*ED$6 -> 0 | EF17: =EC17-EE17 -> 1228702 | EG17: =IF(S17="Yes",EF17,0) -> 0 | EH17: =EG17*EG$6 -> 0 | EI17: =EF17-EH17 -> 1228702 | EJ17: =IF(Q17="Yes",EI17,0) -> 0 | EK17: =EJ17*EJ$6 -> 0 | EL17: =EI17-EK17 -> 1228702 | EM17: =IF(BD17="Semi-Annually",EL17,0) -> 0 | EN17: =EM17*EM$6 -> 0 | EO17: =EL17-EN17 -> 1228702 | EP17: =IF(BK17="Yes",EO17,0) -> 0 | EQ17: =EP17*EP$6 -> 0 | ER17: =EO17-EQ17 -> 1228702 | ES17: =IF(BL17="Yes",ER17,0) -> 0 | ET17: =ES17*ES$6 -> 0 | EU17: =ER17-ET17 -> 1228702 | EV17: =IF(AND(BM17="Yes",OR(BN17="No",AND(BN17="Yes",Inputs!$J$8=Inputs!$J$17+75))),EU17,0) -> 0 | EW17: =EV17*EV$6 -> 0 | EX17: =EU17-EW17 -> 1228702 | EY17: =IF(BW17="Yes",EX17,0) -> 0 | EZ17: =EY17*EY$6 -> 0 | FA17: =EX17-EZ17 -> 1228702 | FB17: =IF(AR17="Yes",FA17,0) -> 0 | FC17: =FB17*FB$6 -> 0 | FD17: =FA17-FC17 -> 1228702 | FE17: =IF(OR(BF17="EUR",BF17="AUD",BF17="CAD",BF17="GBP"),FD17,0) -> 0 | FF17: =FE17*FE$6 -> 0 | FG17: =FD17-FF17 -> 1228702 | FH17: =FG17 -> 1228702 | FI17: =IF(FG17=0,0,VLOOKUP(C17,$GV$10:$GW$406,2,FALSE)*FG17) -> 0 | FJ17: =FG17-FI17 -> 1228702 | FK17: =FJ17 -> 1228702 | FL17: =IF(OR(IC17="",FJ17<0.01),,VLOOKUP(IC17,$GM$10:$GN$406,2,FALSE)*FJ17) -> 0 | FM17: =FJ17-FL17 -> 1228702 | FN17: =FM17 -> 1228702 | FO17: =IF(FM17=0,0,VLOOKUP(C17,$HE$10:$HF$406,2,FALSE)*FM17) -> 0 | FP17: =FM17-FO17 -> 1228702 | FQ17: =IF(SUM(CZ17:DD17)>0,0,IF(AND(AL17>=5000000,AL17<7500000),FP17,0)) -> 0 | FR17: =IF(B17="",0,FQ17*FQ$6*(1-$U17)) -> 0 | FS17: =FP17-FR17 -> 1228702 | FT17: =IF(SUM(CZ17:DD17)>0,0,IF(AL17<15000000,FS17,0)) -> 0 | FU17: =IF(B17="",0,FT17*FT$6*(1-$U17)) -> 0 | FV17: =FS17-FU17 -> 1228702 | FW17: =IF(SUM(CZ17:DD17)>0,0,IF(OR(AND(X17="No",AN17="Tier 1",AI17>$AG$3),AND(X17="No",AN17="Tier 2",AI17>$AH$3),AND(X17="No",AN17="Tier 3",AI17>$AI$3)),FV17,0)) -> 0 | FX17: =IF(SUM(CZ17:DD17)>0,0,IF(OR(AND(X17="No",AN17="Tier 1",AJ17>$AG$4),AND(X17="No",AN17="Tier 2",AJ17>$AH$4),AND(X17="No",AN17="Tier 3",AJ17>$AI$4)),FV17,0)) -> 0 | FY17: =IF(SUM(CZ17:DD17)>0,0,IF(OR(AND(X17="Yes",AN17="Tier 1",AJ17>$AG$5),AND(X17="Yes",AN17="Tier 2",AJ17>$AH$5),AND(X17="Yes",AN17="Tier 3",AJ17>$AI$5)),FV17,0)) -> 0 | FZ17: =IF(SUM(FW17:FY17)>0,FV17,0) -> 0 | GA17: =IF(B17="",0,FZ17*FW$6*(1-MIN(90%,T17))) -> 0 | GB17: =FV17-GA17 -> 1228702 | GC17: =IF(AND(N17="No",DJ17=0),GB17,IF(AND(N17="No",DJ17<>0,K17=0),0,IF(AND(N17="No",DJ17<>0,K17>0,J17<>K17),MAX(0,M17-(DI17-GB17)),DH17))) -> 1228702 | GD17: =+GC17*V17 -> 880196.38 | GE17: =IFERROR(GD17/K17,"") -> 0.71636278 | GF17: =IF(IC17="","",IC17) -> 41 | GG17: {=IF(SUM(IF(IC$9:IC16=IC17,1,0))>0,0,SUMIF($IC$10:$IC$406,IC17,$FJ$10:$FJ$406))} -> 0 | GH17: =GG17 -> 0 | GI17: =GI16+1 -> 8 | GJ17: =LARGE($GH$10:$GH$406,GI17) -> 52656704 | GK17: =IF(GI17>GI$6,0,IF(GI17=$GI$2,$GK$2,IF(GI17<4,$GK$3,$GK$4))) -> 1.5289285e+08 | GL17: =MAX(0,GJ17-GK17) -> 0 | GM17: {=IF(GJ17=0,0,LARGE(IF($GG$10:$GG$406=GJ17,$GF$10:$GF$406,0),COUNTIF($GJ$10:$GJ$406,GJ17)-COUNTIF(GJ$9:GJ16,GJ17)))} -> 12 | GN17: =IF(GJ17=0,0,GL17/GJ17) -> 0 | GP17: =IF(C17="","",IF(ISERROR(MATCH(C17,C$10:C16,0)),MAX(GP$10:GP16)+1,INDEX(GP$10:GP16,MATCH(C17,C$10:C16,0)))) -> 7 | GQ17: =IF(COUNTIF($A$10:A17,A17)<=1,SUMIF($A$10:$A$406,A17,$FH$10:$FH$406),0) -> 0 | GR17: =GR16+1 -> 8 | GS17: =LARGE($GQ$10:$GQ$406,GR17) -> 27610422 | GT17: =IF(GR17>GR$6,0,IF(GR17<=GR$2,GT$2,IF(AND(GR17<=$GR$3,GR17>$GR$2),GT$3,GT$4))) -> 50964284 | GU17: =MAX(0,GS17-GT17) -> 0 | GV17: {=IF(GS17=0,0,LARGE(IF($GQ$10:$GQ$406=GS17,$GP$10:$GP$406,0),COUNTIF($GS$10:$GS$406,GS17)-COUNTIF(GS$9:GS16,GS17)))} -> 19 | GW17: =IF(GS17=0,0,GU17/GS17) -> 0 | GY17: =IF(C17="","",IF(ISERROR(MATCH(C17,C$10:C16,0)),MAX(GP$10:GP16)+1,INDEX(GP$10:GP16,MATCH(C17,C$10:C16,0)))) -> 7 | GZ17: =IF(COUNTIF($A$10:A17,A17)<=1,SUMIF($A$10:$A$406,A17,$FH$10:$FH$406),0) -> 0 | HA17: =HA16+1 -> 8 | HB17: =LARGE($GZ$10:$GZ$406,HA17) -> 27610422 | HC17: - | HD17: =IF(HA17<6,MAX(0,$HD$2/5),0) -> 0 | HE17: {=IF(HB17=0,0,LARGE(IF($GZ$10:$GZ$406=HB17,$GY$10:$GY$406,0),COUNTIF($HB$10:$HB$406,HB17)-COUNTIF(HB$9:HB16,HB17)))} -> 19 | HF17: =IF(HB17=0,0,HD17/HB17) -> 0 | HH17: =DH17-GB17 -> 0 | HI17: 0 | HJ17: =MIN(HI17,DF17) -> 0 | HL17: =IF(COUNTIF($C$10:$C$406,HL16+1),HL16+1,"") -> 8 | HM17: =SUMIF($C$10:$C$406,HL17,$DH$10:$DH$406) -> 4800000 | HO17: =MIN(HP17:HT17) -> 1228702 | HP17: =IF(B17="","",$M17) -> 1228702 | HQ17: =IF($N17="Yes",IF(P17>=6,0,MIN($T17*$M17,$U17*$M17)),"") | HR17: =IF(AND(N17="Yes",P17>=6),"",IF($S17="Yes",$R17*$M17,"")) | HS17: =IF($Q17="Yes",MIN($M17,$T17*$M17),"") | HT17: =IF(AND($N17="Yes",$P17>=6),"",IF(OR(CZ17=1,DD17=1,),MIN($T17*$M17,$U17*$M17),IF(OR(DA17=1,DB17=1,DC17=1),IF(AK17>=5000000,MIN($T17*$M17,$IF17*$M17),MIN($T17*$M17,$U17*$M17)),""))) | HU17: =IF(DE17>0,DE17,"") | HV17: =IF(B17="",0,$L17-$M17) -> 0 | HW17: =IF(OR(SUM(HQ17:HU17)>0,P17>=6),"",IF($B17="","",1)) -> 1 | HX17: =IF(AND($HU17<>0,OR(HU17<=MIN(HQ17:HT17),SUM(HQ17:HT17)=0)),$HU17,0) | HY17: =IF(AND($HT17<>0,OR(AND($HT17<>$HU17,$HT17<>$HS17,$HT17<>$HR17,$HT17<>$HQ17,$HT17<MIN($HQ17:$HS17),$HT17<HU17),SUM($HQ17:$HS17)+SUM(HU17)=0),IB17<=0),$HT17,0) -> 0 | HZ17: =IF(AND($HS17<>0,OR(AND($HS17<>$HU17,$HS17<>$HT17,$HS17<>$HR17,$HS17<>$HQ17),$HS17<MIN($HQ17:$HR17),$HS17<MIN($HT17:$HU17),SUM($HQ17:$HR17)+SUM($HT17:$HU17)=0)),$HS17,0) | IA17: =IF(AND($HR17<>0,OR(AND($HR17<>$HU17,HR17<>HT17,HR17<>HS17,HR17<>HQ17,HR17<MIN(HS17:HU17)),SUM(HQ17)+SUM(HS17:HU17)=0)),$HR17,0) | IB17: =IF(AND($HQ17<>0,OR(HQ17<=MIN(HR17:HU17),SUM(HR17:HU17)=0)),$HQ17,0) | IC17: =IF(C17="","",INDEX(Lookups!$E$2:$E$69,MATCH('Loan List'!BE17,Lookups!$F$2:$F$69,0))) -> 41 | ID17: =HV17=DG17 -> TRUE | IF17: =IF(B17="","",IF(AND(Y17="Second Lien",OR(DA17=1,DB17=1,DC17=1)),50%,IF(DA17=1,90%,IF(DB17=1,80%,IF(DC17=1,65%,"No Initial Haircut"))))) -> No Initial Haircut
A18: Ad.net Acquisition, LLC | B18: =IF(D18="","",B17+1) -> 9 | C18: =IF(COUNTIF($A$10:A17,A18)>0,C17,C17+1) -> 8 | D18: Ad.net Acquisition, LLC | E18: Ad.net (Term Loan) | G18: 4800000 | H18: 4800000 | I18: =IF(B18="","",VLOOKUP(BF18,Inputs!$A$12:$J$15,10,FALSE)) -> 1 | J18: =IF(B18="","",G18*I18) -> 4800000 | K18: =IF(B18="","",H18*I18) -> 4800000 | L18: =IF(B18="","",IF(COUNTIF($CF18:$CY18,1)>0,0,J18)) -> 4800000 | M18: =IF(B18="","",IF(COUNTIF($CF18:$CY18,1)>0,0,K18)) -> 4800000 | N18: No | O18: N/A | P18: =IF(B18="","",IF(OR(O18="N/A",O18=""),0,YEARFRAC('Borrowing Base'!$J$4,'Loan List'!O18)*12)) -> 0 | Q18: No | R18: 1 | S18: =IF(B18="","",IF(R18<95%,"Yes","No")) -> No | T18: 1 | U18: =IF(B18="","",IF(OR(Y18="First Lien",Y18="Split First Lien",Y18="Tier 1 Split Lien",Y18="Tier 2 Split Lien"),50%,30%)) -> 0.5 | V18: =IF(B18="",0,IF(AND(Y18="First Lien",AN18="Tier 1"),IF(AND(X18="Yes",MIN(AH18,$AJ$5)>4.5),(((4.5/MIN(AH18,$AJ$5))*72.5%)+(((MIN(AH18,$AJ$5)-4.5)/MIN(AH18,$AJ$5))*35%)),72.5%),IF(AND(Y18="First Lien",AN18="Tier 2"),IF(AND(X18="Yes",MIN(AH18,$AK$5)>4.5),(((4.5/MIN(AH18,$AK$5))*72.5%)+(((MIN(AH18,$AK$5)-4.5)/MIN(AH18,$AK$5))*35%)),72.5%),IF(AND(X18="Yes",MIN(AH18,$AL$5)>4),(((4/MIN(AH18,$AL$5))*72.5%)+(((MIN(AH18,$AL$5)-4)/MIN(AH18,$AL$5))*35%)),IF(OR(Y18="First Lien",Y18="Split First Lien"),72.5%,IF(Y18="Split Lien", 53%,35%)))))) -> 0.70963024 | W18: =IF($C18="","",MIN($HP18:$HT18)) -> 4800000 | X18: Yes | Y18: First Lien | Z18: Term | AA18: NR | AB18: NR | AC18: 1.5 | AD18: 0.81284538 | AE18: 1.685302 | AF18: 0.43201988 | AG18: 4.6923196 | AH18: 4.6923196 | AI18: 5.1659335 | AJ18: 5.1659335 | AK18: 12968000 | AL18: 11275995 | AM18: 45838 | AN18: =IF(C18="","",(IF(AK18>=50000000,"Tier 1",(IF(OR(AK18>=20000000,AND(AK18>5000000,AC18>=1.25,AF18<=0.65)),"Tier 2","Tier 3"))))) -> Tier 2 | AO18: 46149 | AP18: =IF(C18="","",DAYS360(Inputs!$J$8,AO18)/360) -> 0.70277778 | AQ18: =IF(C18="","",AP18) -> 0.70277778 | AR18: No | AS18: 0 | AT18: Yes | AU18: 0.01 | AV18: 0.0575 | AW18: 0.043507 | AX18: =IF(C18="","",MAX(AU18,AW18)) -> 0.043507 | AY18: 0 | AZ18: 0 | BA18: 0 | BB18: =IF(B18="","",IF(AR18="No",AV18-AZ18,"")) -> 0.0575 | BC18: =IF(B18="","",IF(AR18="Yes",AS18-BA18,"")) | BD18: Quarterly | BE18: Media | BF18: USD | BG18: United States | BH18: No | BI18: =IF(B18="","",IF(OR(AND(AZ18>0,BB18>=2.5%,BB18<4%),AND(BA18>0,BC18>=6%,BC18<8%)),"Yes","No")) -> No | BJ18: =IF(B18="","",IF(OR(AND(AZ18>0,BB18<2.5%),AND(BA18>0,BC18<6%)),"Yes","No")) -> No | BK18: No | BL18: No | BM18: Yes | BN18: Yes | BO18: No | BP18: No | BQ18: No | BR18: No | BS18: No | BT18: No | BU18: No | BV18: No | BW18: No | BX18: No | BY18: No | BZ18: No | CA18: No | CB18: Yes | CC18: =IF(B18="","",IF(AT18="No",((BB18+AW18)-$AZ$4),((BB18+AX18)-$AZ$4))*IF(DE18>0,0,M18)) -> 277366.08 | CD18: =IF(B18="","",AY18*(L18-M18)*IF(DE18>0,0,1)) -> 0 | CF18: =IF(AND(B18<>"",R18<=85%),1,0) -> 0 | CG18: =IF(B18="",0,(IF(OR(BF18="USD",BF18="CAD",BF18="GBP",BF18="AUD",BF18="EUR"),0,1))) -> 0 | CH18: =IF(B18="",0,(IF(OR(BG18="United States",BG18="Canada",BG18="United Kingdom",BG18="Australia",BG18="Netherlands Antilles",BG18="Bermuda",BG18="Cayman Islands",BG18="British Virgin Islands",BG18="Channel Islands",BG18="Isle of Man",BG18="Australia",BG18="Netherlands",BG18="Germany",BG18="Sweden",BG18="Switzerland",BG18="Austria",BG18="Belgium",BG18="Denmark",BG18="Finland",BG18="Iceland",BG18="Ireland",BG18="Lichtenstein",BG18="Luxemborg",BG18="Norway"),0,1))) -> 0 | CI18: =IF(BO18="Yes",1,0) -> 0 | CJ18: =IF(BP18="Yes",1,0) -> 0 | CK18: =IF(BQ18="Yes",1,0) -> 0 | CL18: =IF(BR18="Yes",1,0) -> 0 | CM18: =IF(BS18="Yes",1,0) -> 0 | CN18: =IF(BT18="Yes",1,0) -> 0 | CO18: =IF(OR(AND(BJ18="Yes",N18="No"),AND(BJ18="Yes",N18="Yes",P18>=6)),1,0) -> 0 | CP18: =IF(BU18="Yes",1,0) -> 0 | CQ18: =IF(AND(BV18="Yes",BW18="No"),1,0) -> 0 | CR18: =IF(BX18="Yes",1,0) -> 0 | CS18: =IF(AP18="",0,IF(AP18>7,1,0)) -> 0 | CT18: =IF(OR(BD18<>"Monthly",BD18<>"Quarterly",BD18<>"Semi-Annually"),0,1) -> 0 | CU18: =IF(BY18="Yes",1,0) -> 0 | CV18: =IF(BZ18="Yes",1,0) -> 0 | CW18: =IF(CA18="Yes",1,0) -> 0 | CX18: =IF(CB18="No",1,0) -> 0 | CY18: =IF(B18="",0,IF(AK18>=5000000,0,1)) -> 0 | CZ18: =IF(B18="",0,IF(AL18>=5000000,0,1)) -> 0 | DA18: =IF(OR(DB18=1,DC18=1,DD18=1),0,IF(B18="",0,IF(OR(AND(AN18="Tier 1",X18="No",OR(AI18>$AJ$3,AJ18>$AJ$4)),(AND(AN18="Tier 1",X18="Yes",AJ18>$AJ$5)),(AND(AN18="Tier 2",X18="No",OR(AI18>$AK$3,AJ18>$AK$4))),(AND(AN18="Tier 2",X18="Yes",AJ18>$AK$5)),(AND(AN18="Tier 3",X18="No",OR(AI18>$AL$3,AJ18>$AL$4))),(AND(AN18="Tier 3",X18="Yes",AJ18>$AL$5))),1,0))) -> 0 | DB18: =IF(OR(DC18=1,DD18=1),0,IF(B18="",0,IF(OR(AND(AN18="Tier 1",X18="No",OR(AI18>$AM$3,AJ18>$AM$4)),(AND(AN18="Tier 1",X18="Yes",AJ18>$AM$5)),(AND(AN18="Tier 2",X18="No",OR(AI18>$AN$3,AJ18>$AN$4))),(AND(AN18="Tier 2",X18="Yes",AJ18>$AN$5)),(AND(AN18="Tier 3",X18="No",OR(AI18>$AO$3,AJ18>$AO$4))),(AND(AN18="Tier 3",X18="Yes",AJ18>$AO$5))),1,0))) -> 0 | DC18: =IF(DD18=1,0,IF(B18="",0,IF(OR(AND(AN18="Tier 1",X18="No",OR(AI18>$AP$3,AJ18>$AP$4)),(AND(AN18="Tier 1",X18="Yes",AJ18>$AP$5)),(AND(AN18="Tier 2",X18="No",OR(AI18>$AQ$3,AJ18>$AQ$4))),(AND(AN18="Tier 2",X18="Yes",AJ18>$AQ$5)),(AND(AN18="Tier 3",X18="No",OR(AI18>$AR$3,AJ18>$AR$4))),(AND(AN18="Tier 3",X18="Yes",AJ18>$AR$5))),1,0))) -> 0 | DD18: =IF(B18="",0,IF(OR(AND(AN18="Tier 1",X18="No",OR(AI18>$AS$3,AJ18>$AS$4)),(AND(AN18="Tier 1",X18="Yes",AJ18>$AS$5)),(AND(AN18="Tier 2",X18="No",OR(AI18>$AT$3,AJ18>$AT$4))),(AND(AN18="Tier 2",X18="Yes",AJ18>$AT$5)),(AND(AN18="Tier 3",X18="No",OR(AI18>$AU$3,AJ18>$AU$4))),(AND(AN18="Tier 3",X18="Yes",AJ18>$AU$5))),1,0)) -> 0 | DE18: =IF((SUM(CF18:CY18)=0),0,W18) -> 0 | DF18: =IF(OR(B18="",DE18>0),0,W18) -> 4800000 | DG18: =IF(B18="",0,IF(COUNTIF(CF18:CY18,1)>0,0,L18-M18)) -> 0 | DH18: =DF18+IF(DE18>0,0,DG18) -> 4800000 | DI18: =IF(B18="","",M18+DG18) -> 4800000 | DJ18: =IF(B18="",0,J18-K18) -> 0 | DK18: =IF(OR(BF18="EUR",BF18="CAD",BF18="GBP",BF18="AUD"),(GB18*(1-V18))+(HH18)+IF(HY18="",0,HY18*(1-U18)),0) -> 0 | DL18: =IF(BF18="EUR",33%,IF(BF18="CAD",38%,IF(BF18="GBP",51%,IF(BF18="AUD",61%,0)))) -> 0 | DM18: =DK18*DL18 -> 0 | DO18: =IF(OR(Y18="Second Lien",Y18="Tier 1 Split Lien",Y18="Tier 2 Split Lien"),DH18,0) -> 0 | DP18: =DO18*DO$6 -> 0 | DQ18: =DH18-DP18 -> 4800000 | DR18: =IF(Y18="Second Lien",DQ18,0) -> 0 | DS18: =DR18*DR$6 -> 0 | DT18: =DQ18-DS18 -> 4800000 | DU18: =IF(BH18="Yes",DT18,0) -> 0 | DV18: =DU18*DU$6 -> 0 | DW18: =DT18-DV18 -> 4800000 | DX18: =IF(OR(BG18="Canada",BG18="United Kingdom",BG18="Australia",BG18="Netherlands Antilles",BG18="Bermuda",BG18="Cayman Islands",BG18="British Virgin Islands",BG18="Channel Islands",BG18="Isle of Man",BG18="Australia",BG18="Netherlands",BG18="Germany",BG18="Sweden",BG18="Switzerland",BG18="Austria",BG18="Belgium",BG18="Denmark",BG18="Finland",BG18="Iceland",BG18="Ireland",BG18="Lichtenstein",BG18="Luxemborg",BG18="Norway"),DW18,0) -> 0 | DY18: =DX18*DX$6 -> 0 | DZ18: =DW18-DY18 -> 4800000 | EA18: =IF(BI18="Yes",DZ18,0) -> 0 | EB18: =EA18*EA$6 -> 0 | EC18: =DZ18-EB18 -> 4800000 | ED18: =IF(OR(Z18="Delayed Draw",Z18="Revolver"),EC18,0) -> 0 | EE18: =ED18*ED$6 -> 0 | EF18: =EC18-EE18 -> 4800000 | EG18: =IF(S18="Yes",EF18,0) -> 0 | EH18: =EG18*EG$6 -> 0 | EI18: =EF18-EH18 -> 4800000 | EJ18: =IF(Q18="Yes",EI18,0) -> 0 | EK18: =EJ18*EJ$6 -> 0 | EL18: =EI18-EK18 -> 4800000 | EM18: =IF(BD18="Semi-Annually",EL18,0) -> 0 | EN18: =EM18*EM$6 -> 0 | EO18: =EL18-EN18 -> 4800000 | EP18: =IF(BK18="Yes",EO18,0) -> 0 | EQ18: =EP18*EP$6 -> 0 | ER18: =EO18-EQ18 -> 4800000 | ES18: =IF(BL18="Yes",ER18,0) -> 0 | ET18: =ES18*ES$6 -> 0 | EU18: =ER18-ET18 -> 4800000 | EV18: =IF(AND(BM18="Yes",OR(BN18="No",AND(BN18="Yes",Inputs!$J$8=Inputs!$J$17+75))),EU18,0) -> 0 | EW18: =EV18*EV$6 -> 0 | EX18: =EU18-EW18 -> 4800000 | EY18: =IF(BW18="Yes",EX18,0) -> 0 | EZ18: =EY18*EY$6 -> 0 | FA18: =EX18-EZ18 -> 4800000 | FB18: =IF(AR18="Yes",FA18,0) -> 0 | FC18: =FB18*FB$6 -> 0 | FD18: =FA18-FC18 -> 4800000 | FE18: =IF(OR(BF18="EUR",BF18="AUD",BF18="CAD",BF18="GBP"),FD18,0) -> 0 | FF18: =FE18*FE$6 -> 0 | FG18: =FD18-FF18 -> 4800000 | FH18: =FG18 -> 4800000 | FI18: =IF(FG18=0,0,VLOOKUP(C18,$GV$10:$GW$406,2,FALSE)*FG18) -> 0 | FJ18: =FG18-FI18 -> 4800000 | FK18: =FJ18 -> 4800000 | FL18: =IF(OR(IC18="",FJ18<0.01),,VLOOKUP(IC18,$GM$10:$GN$406,2,FALSE)*FJ18) -> 0 | FM18: =FJ18-FL18 -> 4800000 | FN18: =FM18 -> 4800000 | FO18: =IF(FM18=0,0,VLOOKUP(C18,$HE$10:$HF$406,2,FALSE)*FM18) -> 0 | FP18: =FM18-FO18 -> 4800000 | FQ18: =IF(SUM(CZ18:DD18)>0,0,IF(AND(AL18>=5000000,AL18<7500000),FP18,0)) -> 0 | FR18: =IF(B18="",0,FQ18*FQ$6*(1-$U18)) -> 0 | FS18: =FP18-FR18 -> 4800000 | FT18: =IF(SUM(CZ18:DD18)>0,0,IF(AL18<15000000,FS18,0)) -> 4800000 | FU18: =IF(B18="",0,FT18*FT$6*(1-$U18)) -> 0 | FV18: =FS18-FU18 -> 4800000 | FW18: =IF(SUM(CZ18:DD18)>0,0,IF(OR(AND(X18="No",AN18="Tier 1",AI18>$AG$3),AND(X18="No",AN18="Tier 2",AI18>$AH$3),AND(X18="No",AN18="Tier 3",AI18>$AI$3)),FV18,0)) -> 0 | FX18: =IF(SUM(CZ18:DD18)>0,0,IF(OR(AND(X18="No",AN18="Tier 1",AJ18>$AG$4),AND(X18="No",AN18="Tier 2",AJ18>$AH$4),AND(X18="No",AN18="Tier 3",AJ18>$AI$4)),FV18,0)) -> 0 | FY18: =IF(SUM(CZ18:DD18)>0,0,IF(OR(AND(X18="Yes",AN18="Tier 1",AJ18>$AG$5),AND(X18="Yes",AN18="Tier 2",AJ18>$AH$5),AND(X18="Yes",AN18="Tier 3",AJ18>$AI$5)),FV18,0)) -> 0 | FZ18: =IF(SUM(FW18:FY18)>0,FV18,0) -> 0 | GA18: =IF(B18="",0,FZ18*FW$6*(1-MIN(90%,T18))) -> 0 | GB18: =FV18-GA18 -> 4800000 | GC18: =IF(AND(N18="No",DJ18=0),GB18,IF(AND(N18="No",DJ18<>0,K18=0),0,IF(AND(N18="No",DJ18<>0,K18>0,J18<>K18),MAX(0,M18-(DI18-GB18)),DH18))) -> 4800000 | GD18: =+GC18*V18 -> 3406225.1 | GE18: =IFERROR(GD18/K18,"") -> 0.70963024 | GF18: =IF(IC18="","",IC18) -> 46 | GG18: {=IF(SUM(IF(IC$9:IC17=IC18,1,0))>0,0,SUMIF($IC$10:$IC$406,IC18,$FJ$10:$FJ$406))} -> 1.0592467e+08 | GH18: =GG18 -> 1.0592467e+08 | GI18: =GI17+1 -> 9 | GJ18: =LARGE($GH$10:$GH$406,GI18) -> 51605989 | GK18: =IF(GI18>GI$6,0,IF(GI18=$GI$2,$GK$2,IF(GI18<4,$GK$3,$GK$4))) -> 1.5289285e+08 | GL18: =MAX(0,GJ18-GK18) -> 0 | GM18: {=IF(GJ18=0,0,LARGE(IF($GG$10:$GG$406=GJ18,$GF$10:$GF$406,0),COUNTIF($GJ$10:$GJ$406,GJ18)-COUNTIF(GJ$9:GJ17,GJ18)))} -> 20 | GN18: =IF(GJ18=0,0,GL18/GJ18) -> 0 | GP18: =IF(C18="","",IF(ISERROR(MATCH(C18,C$10:C17,0)),MAX(GP$10:GP17)+1,INDEX(GP$10:GP17,MATCH(C18,C$10:C17,0)))) -> 8 | GQ18: =IF(COUNTIF($A$10:A18,A18)<=1,SUMIF($A$10:$A$406,A18,$FH$10:$FH$406),0) -> 4800000 | GR18: =GR17+1 -> 9 | GS18: =LARGE($GQ$10:$GQ$406,GR18) -> 26818060 | GT18: =IF(GR18>GR$6,0,IF(GR18<=GR$2,GT$2,IF(AND(GR18<=$GR$3,GR18>$GR$2),GT$3,GT$4))) -> 50964284 | GU18: =MAX(0,GS18-GT18) -> 0 | GV18: {=IF(GS18=0,0,LARGE(IF($GQ$10:$GQ$406=GS18,$GP$10:$GP$406,0),COUNTIF($GS$10:$GS$406,GS18)-COUNTIF(GS$9:GS17,GS18)))} -> 1 | GW18: =IF(GS18=0,0,GU18/GS18) -> 0 | GY18: =IF(C18="","",IF(ISERROR(MATCH(C18,C$10:C17,0)),MAX(GP$10:GP17)+1,INDEX(GP$10:GP17,MATCH(C18,C$10:C17,0)))) -> 8 | GZ18: =IF(COUNTIF($A$10:A18,A18)<=1,SUMIF($A$10:$A$406,A18,$FH$10:$FH$406),0) -> 4800000 | HA18: =HA17+1 -> 9 | HB18: =LARGE($GZ$10:$GZ$406,HA18) -> 26818060 | HC18: - | HD18: =IF(HA18<6,MAX(0,$HD$2/5),0) -> 0 | HE18: {=IF(HB18=0,0,LARGE(IF($GZ$10:$GZ$406=HB18,$GY$10:$GY$406,0),COUNTIF($HB$10:$HB$406,HB18)-COUNTIF(HB$9:HB17,HB18)))} -> 1 | HF18: =IF(HB18=0,0,HD18/HB18) -> 0 | HH18: =DH18-GB18 -> 0 | HI18: 0 | HJ18: =MIN(HI18,DF18) -> 0 | HL18: =IF(COUNTIF($C$10:$C$406,HL17+1),HL17+1,"") -> 9 | HM18: =SUMIF($C$10:$C$406,HL18,$DH$10:$DH$406) -> 4909661.1 | HO18: =MIN(HP18:HT18) -> 4800000 | HP18: =IF(B18="","",$M18) -> 4800000 | HQ18: =IF($N18="Yes",IF(P18>=6,0,MIN($T18*$M18,$U18*$M18)),"") | HR18: =IF(AND(N18="Yes",P18>=6),"",IF($S18="Yes",$R18*$M18,"")) | HS18: =IF($Q18="Yes",MIN($M18,$T18*$M18),"") | HT18: =IF(AND($N18="Yes",$P18>=6),"",IF(OR(CZ18=1,DD18=1,),MIN($T18*$M18,$U18*$M18),IF(OR(DA18=1,DB18=1,DC18=1),IF(AK18>=5000000,MIN($T18*$M18,$IF18*$M18),MIN($T18*$M18,$U18*$M18)),""))) | HU18: =IF(DE18>0,DE18,"") | HV18: =IF(B18="",0,$L18-$M18) -> 0 | HW18: =IF(OR(SUM(HQ18:HU18)>0,P18>=6),"",IF($B18="","",1)) -> 1 | HX18: =IF(AND($HU18<>0,OR(HU18<=MIN(HQ18:HT18),SUM(HQ18:HT18)=0)),$HU18,0) | HY18: =IF(AND($HT18<>0,OR(AND($HT18<>$HU18,$HT18<>$HS18,$HT18<>$HR18,$HT18<>$HQ18,$HT18<MIN($HQ18:$HS18),$HT18<HU18),SUM($HQ18:$HS18)+SUM(HU18)=0),IB18<=0),$HT18,0) -> 0 | HZ18: =IF(AND($HS18<>0,OR(AND($HS18<>$HU18,$HS18<>$HT18,$HS18<>$HR18,$HS18<>$HQ18),$HS18<MIN($HQ18:$HR18),$HS18<MIN($HT18:$HU18),SUM($HQ18:$HR18)+SUM($HT18:$HU18)=0)),$HS18,0) | IA18: =IF(AND($HR18<>0,OR(AND($HR18<>$HU18,HR18<>HT18,HR18<>HS18,HR18<>HQ18,HR18<MIN(HS18:HU18)),SUM(HQ18)+SUM(HS18:HU18)=0)),$HR18,0) | IB18: =IF(AND($HQ18<>0,OR(HQ18<=MIN(HR18:HU18),SUM(HR18:HU18)=0)),$HQ18,0) | IC18: =IF(C18="","",INDEX(Lookups!$E$2:$E$69,MATCH('Loan List'!BE18,Lookups!$F$2:$F$69,0))) -> 46 | ID18: =HV18=DG18 -> TRUE | IF18: =IF(B18="","",IF(AND(Y18="Second Lien",OR(DA18=1,DB18=1,DC18=1)),50%,IF(DA18=1,90%,IF(DB18=1,80%,IF(DC18=1,65%,"No Initial Haircut"))))) -> No Initial Haircut
A19: Amsive Holding Corporation | B19: =IF(D19="","",B18+1) -> 10 | C19: =IF(COUNTIF($A$10:A18,A19)>0,C18,C18+1) -> 9 | D19: Amsive Holding Corporation | E19: Vision Integrated (TL) | G19: 5455179 | H19: 5455179 | I19: =IF(B19="","",VLOOKUP(BF19,Inputs!$A$12:$J$15,10,FALSE)) -> 1 | J19: =IF(B19="","",G19*I19) -> 5455179 | K19: =IF(B19="","",H19*I19) -> 5455179 | L19: =IF(B19="","",IF(COUNTIF($CF19:$CY19,1)>0,0,J19)) -> 5455179 | M19: =IF(B19="","",IF(COUNTIF($CF19:$CY19,1)>0,0,K19)) -> 5455179 | N19: No | O19: N/A | P19: =IF(B19="","",IF(OR(O19="N/A",O19=""),0,YEARFRAC('Borrowing Base'!$J$4,'Loan List'!O19)*12)) -> 0 | Q19: No | R19: 0.99 | S19: =IF(B19="","",IF(R19<95%,"Yes","No")) -> No | T19: 1 | U19: =IF(B19="","",IF(OR(Y19="First Lien",Y19="Split First Lien",Y19="Tier 1 Split Lien",Y19="Tier 2 Split Lien"),50%,30%)) -> 0.5 | V19: =IF(B19="",0,IF(AND(Y19="First Lien",AN19="Tier 1"),IF(AND(X19="Yes",MIN(AH19,$AJ$5)>4.5),(((4.5/MIN(AH19,$AJ$5))*72.5%)+(((MIN(AH19,$AJ$5)-4.5)/MIN(AH19,$AJ$5))*35%)),72.5%),IF(AND(Y19="First Lien",AN19="Tier 2"),IF(AND(X19="Yes",MIN(AH19,$AK$5)>4.5),(((4.5/MIN(AH19,$AK$5))*72.5%)+(((MIN(AH19,$AK$5)-4.5)/MIN(AH19,$AK$5))*35%)),72.5%),IF(AND(X19="Yes",MIN(AH19,$AL$5)>4),(((4/MIN(AH19,$AL$5))*72.5%)+(((MIN(AH19,$AL$5)-4)/MIN(AH19,$AL$5))*35%)),IF(OR(Y19="First Lien",Y19="Split First Lien"),72.5%,IF(Y19="Split Lien", 53%,35%)))))) -> 0.725 | W19: =IF($C19="","",MIN($HP19:$HT19)) -> 4909661.1 | X19: No | Y19: First Lien | Z19: Term | AA19: NR | AB19: NR | AC19: 1.65 | AD19: 0.37822684 | AE19: 1.1738646 | AF19: 0.70128023 | AG19: 3.3763022 | AH19: 4.4444755 | AI19: 4.5545555 | AJ19: 6.9435472 | AK19: 21719323 | AL19: 33751488 | AM19: 45808 | AN19: =IF(C19="","",(IF(AK19>=50000000,"Tier 1",(IF(OR(AK19>=20000000,AND(AK19>5000000,AC19>=1.25,AF19<=0.65)),"Tier 2","Tier 3"))))) -> Tier 2 | AO19: 46183 | AP19: =IF(C19="","",DAYS360(Inputs!$J$8,AO19)/360) -> 0.79444444 | AQ19: =IF(C19="","",AP19) -> 0.79444444 | AR19: No | AS19: 0 | AT19: Yes | AU19: 0.01 | AV19: 0.0575 | AW19: 0.043507 | AX19: =IF(C19="","",MAX(AU19,AW19)) -> 0.043507 | AY19: 0 | AZ19: 0 | BA19: 0 | BB19: =IF(B19="","",IF(AR19="No",AV19-AZ19,"")) -> 0.0575 | BC19: =IF(B19="","",IF(AR19="Yes",AS19-BA19,"")) | BD19: Quarterly | BE19: Media | BF19: USD | BG19: United States | BH19: No | BI19: =IF(B19="","",IF(OR(AND(AZ19>0,BB19>=2.5%,BB19<4%),AND(BA19>0,BC19>=6%,BC19<8%)),"Yes","No")) -> No | BJ19: =IF(B19="","",IF(OR(AND(AZ19>0,BB19<2.5%),AND(BA19>0,BC19<6%)),"Yes","No")) -> No | BK19: No | BL19: No | BM19: Yes | BN19: Yes | BO19: No | BP19: No | BQ19: No | BR19: No | BS19: No | BT19: No | BU19: No | BV19: No | BW19: No | BX19: No | BY19: No | BZ19: No | CA19: No | CB19: Yes | CC19: =IF(B19="","",IF(AT19="No",((BB19+AW19)-$AZ$4),((BB19+AX19)-$AZ$4))*IF(DE19>0,0,M19)) -> 315225.34 | CD19: =IF(B19="","",AY19*(L19-M19)*IF(DE19>0,0,1)) -> 0 | CF19: =IF(AND(B19<>"",R19<=85%),1,0) -> 0 | CG19: =IF(B19="",0,(IF(OR(BF19="USD",BF19="CAD",BF19="GBP",BF19="AUD",BF19="EUR"),0,1))) -> 0 | CH19: =IF(B19="",0,(IF(OR(BG19="United States",BG19="Canada",BG19="United Kingdom",BG19="Australia",BG19="Netherlands Antilles",BG19="Bermuda",BG19="Cayman Islands",BG19="British Virgin Islands",BG19="Channel Islands",BG19="Isle of Man",BG19="Australia",BG19="Netherlands",BG19="Germany",BG19="Sweden",BG19="Switzerland",BG19="Austria",BG19="Belgium",BG19="Denmark",BG19="Finland",BG19="Iceland",BG19="Ireland",BG19="Lichtenstein",BG19="Luxemborg",BG19="Norway"),0,1))) -> 0 | CI19: =IF(BO19="Yes",1,0) -> 0 | CJ19: =IF(BP19="Yes",1,0) -> 0 | CK19: =IF(BQ19="Yes",1,0) -> 0 | CL19: =IF(BR19="Yes",1,0) -> 0 | CM19: =IF(BS19="Yes",1,0) -> 0 | CN19: =IF(BT19="Yes",1,0) -> 0 | CO19: =IF(OR(AND(BJ19="Yes",N19="No"),AND(BJ19="Yes",N19="Yes",P19>=6)),1,0) -> 0 | CP19: =IF(BU19="Yes",1,0) -> 0 | CQ19: =IF(AND(BV19="Yes",BW19="No"),1,0) -> 0 | CR19: =IF(BX19="Yes",1,0) -> 0 | CS19: =IF(AP19="",0,IF(AP19>7,1,0)) -> 0 | CT19: =IF(OR(BD19<>"Monthly",BD19<>"Quarterly",BD19<>"Semi-Annually"),0,1) -> 0 | CU19: =IF(BY19="Yes",1,0) -> 0 | CV19: =IF(BZ19="Yes",1,0) -> 0 | CW19: =IF(CA19="Yes",1,0) -> 0 | CX19: =IF(CB19="No",1,0) -> 0 | CY19: =IF(B19="",0,IF(AK19>=5000000,0,1)) -> 0 | CZ19: =IF(B19="",0,IF(AL19>=5000000,0,1)) -> 0 | DA19: =IF(OR(DB19=1,DC19=1,DD19=1),0,IF(B19="",0,IF(OR(AND(AN19="Tier 1",X19="No",OR(AI19>$AJ$3,AJ19>$AJ$4)),(AND(AN19="Tier 1",X19="Yes",AJ19>$AJ$5)),(AND(AN19="Tier 2",X19="No",OR(AI19>$AK$3,AJ19>$AK$4))),(AND(AN19="Tier 2",X19="Yes",AJ19>$AK$5)),(AND(AN19="Tier 3",X19="No",OR(AI19>$AL$3,AJ19>$AL$4))),(AND(AN19="Tier 3",X19="Yes",AJ19>$AL$5))),1,0))) -> 1 | DB19: =IF(OR(DC19=1,DD19=1),0,IF(B19="",0,IF(OR(AND(AN19="Tier 1",X19="No",OR(AI19>$AM$3,AJ19>$AM$4)),(AND(AN19="Tier 1",X19="Yes",AJ19>$AM$5)),(AND(AN19="Tier 2",X19="No",OR(AI19>$AN$3,AJ19>$AN$4))),(AND(AN19="Tier 2",X19="Yes",AJ19>$AN$5)),(AND(AN19="Tier 3",X19="No",OR(AI19>$AO$3,AJ19>$AO$4))),(AND(AN19="Tier 3",X19="Yes",AJ19>$AO$5))),1,0))) -> 0 | DC19: =IF(DD19=1,0,IF(B19="",0,IF(OR(AND(AN19="Tier 1",X19="No",OR(AI19>$AP$3,AJ19>$AP$4)),(AND(AN19="Tier 1",X19="Yes",AJ19>$AP$5)),(AND(AN19="Tier 2",X19="No",OR(AI19>$AQ$3,AJ19>$AQ$4))),(AND(AN19="Tier 2",X19="Yes",AJ19>$AQ$5)),(AND(AN19="Tier 3",X19="No",OR(AI19>$AR$3,AJ19>$AR$4))),(AND(AN19="Tier 3",X19="Yes",AJ19>$AR$5))),1,0))) -> 0 | DD19: =IF(B19="",0,IF(OR(AND(AN19="Tier 1",X19="No",OR(AI19>$AS$3,AJ19>$AS$4)),(AND(AN19="Tier 1",X19="Yes",AJ19>$AS$5)),(AND(AN19="Tier 2",X19="No",OR(AI19>$AT$3,AJ19>$AT$4))),(AND(AN19="Tier 2",X19="Yes",AJ19>$AT$5)),(AND(AN19="Tier 3",X19="No",OR(AI19>$AU$3,AJ19>$AU$4))),(AND(AN19="Tier 3",X19="Yes",AJ19>$AU$5))),1,0)) -> 0 | DE19: =IF((SUM(CF19:CY19)=0),0,W19) -> 0 | DF19: =IF(OR(B19="",DE19>0),0,W19) -> 4909661.1 | DG19: =IF(B19="",0,IF(COUNTIF(CF19:CY19,1)>0,0,L19-M19)) -> 0 | DH19: =DF19+IF(DE19>0,0,DG19) -> 4909661.1 | DI19: =IF(B19="","",M19+DG19) -> 5455179 | DJ19: =IF(B19="",0,J19-K19) -> 0 | DK19: =IF(OR(BF19="EUR",BF19="CAD",BF19="GBP",BF19="AUD"),(GB19*(1-V19))+(HH19)+IF(HY19="",0,HY19*(1-U19)),0) -> 0 | DL19: =IF(BF19="EUR",33%,IF(BF19="CAD",38%,IF(BF19="GBP",51%,IF(BF19="AUD",61%,0)))) -> 0 | DM19: =DK19*DL19 -> 0 | DO19: =IF(OR(Y19="Second Lien",Y19="Tier 1 Split Lien",Y19="Tier 2 Split Lien"),DH19,0) -> 0 | DP19: =DO19*DO$6 -> 0 | DQ19: =DH19-DP19 -> 4909661.1 | DR19: =IF(Y19="Second Lien",DQ19,0) -> 0 | DS19: =DR19*DR$6 -> 0 | DT19: =DQ19-DS19 -> 4909661.1 | DU19: =IF(BH19="Yes",DT19,0) -> 0 | DV19: =DU19*DU$6 -> 0 | DW19: =DT19-DV19 -> 4909661.1 | DX19: =IF(OR(BG19="Canada",BG19="United Kingdom",BG19="Australia",BG19="Netherlands Antilles",BG19="Bermuda",BG19="Cayman Islands",BG19="British Virgin Islands",BG19="Channel Islands",BG19="Isle of Man",BG19="Australia",BG19="Netherlands",BG19="Germany",BG19="Sweden",BG19="Switzerland",BG19="Austria",BG19="Belgium",BG19="Denmark",BG19="Finland",BG19="Iceland",BG19="Ireland",BG19="Lichtenstein",BG19="Luxemborg",BG19="Norway"),DW19,0) -> 0 | DY19: =DX19*DX$6 -> 0 | DZ19: =DW19-DY19 -> 4909661.1 | EA19: =IF(BI19="Yes",DZ19,0) -> 0 | EB19: =EA19*EA$6 -> 0 | EC19: =DZ19-EB19 -> 4909661.1 | ED19: =IF(OR(Z19="Delayed Draw",Z19="Revolver"),EC19,0) -> 0 | EE19: =ED19*ED$6 -> 0 | EF19: =EC19-EE19 -> 4909661.1 | EG19: =IF(S19="Yes",EF19,0) -> 0 | EH19: =EG19*EG$6 -> 0 | EI19: =EF19-EH19 -> 4909661.1 | EJ19: =IF(Q19="Yes",EI19,0) -> 0 | EK19: =EJ19*EJ$6 -> 0 | EL19: =EI19-EK19 -> 4909661.1 | EM19: =IF(BD19="Semi-Annually",EL19,0) -> 0 | EN19: =EM19*EM$6 -> 0 | EO19: =EL19-EN19 -> 4909661.1 | EP19: =IF(BK19="Yes",EO19,0) -> 0 | EQ19: =EP19*EP$6 -> 0 | ER19: =EO19-EQ19 -> 4909661.1 | ES19: =IF(BL19="Yes",ER19,0) -> 0 | ET19: =ES19*ES$6 -> 0 | EU19: =ER19-ET19 -> 4909661.1 | EV19: =IF(AND(BM19="Yes",OR(BN19="No",AND(BN19="Yes",Inputs!$J$8=Inputs!$J$17+75))),EU19,0) -> 0 | EW19: =EV19*EV$6 -> 0 | EX19: =EU19-EW19 -> 4909661.1 | EY19: =IF(BW19="Yes",EX19,0) -> 0 | EZ19: =EY19*EY$6 -> 0 | FA19: =EX19-EZ19 -> 4909661.1 | FB19: =IF(AR19="Yes",FA19,0) -> 0 | FC19: =FB19*FB$6 -> 0 | FD19: =FA19-FC19 -> 4909661.1 | FE19: =IF(OR(BF19="EUR",BF19="AUD",BF19="CAD",BF19="GBP"),FD19,0) -> 0 | FF19: =FE19*FE$6 -> 0 | FG19: =FD19-FF19 -> 4909661.1 | FH19: =FG19 -> 4909661.1 | FI19: =IF(FG19=0,0,VLOOKUP(C19,$GV$10:$GW$406,2,FALSE)*FG19) -> 0 | FJ19: =FG19-FI19 -> 4909661.1 | FK19: =FJ19 -> 4909661.1 | FL19: =IF(OR(IC19="",FJ19<0.01),,VLOOKUP(IC19,$GM$10:$GN$406,2,FALSE)*FJ19) -> 0 | FM19: =FJ19-FL19 -> 4909661.1 | FN19: =FM19 -> 4909661.1 | FO19: =IF(FM19=0,0,VLOOKUP(C19,$HE$10:$HF$406,2,FALSE)*FM19) -> 0 | FP19: =FM19-FO19 -> 4909661.1 | FQ19: =IF(SUM(CZ19:DD19)>0,0,IF(AND(AL19>=5000000,AL19<7500000),FP19,0)) -> 0 | FR19: =IF(B19="",0,FQ19*FQ$6*(1-$U19)) -> 0 | FS19: =FP19-FR19 -> 4909661.1 | FT19: =IF(SUM(CZ19:DD19)>0,0,IF(AL19<15000000,FS19,0)) -> 0 | FU19: =IF(B19="",0,FT19*FT$6*(1-$U19)) -> 0 | FV19: =FS19-FU19 -> 4909661.1 | FW19: =IF(SUM(CZ19:DD19)>0,0,IF(OR(AND(X19="No",AN19="Tier 1",AI19>$AG$3),AND(X19="No",AN19="Tier 2",AI19>$AH$3),AND(X19="No",AN19="Tier 3",AI19>$AI$3)),FV19,0)) -> 0 | FX19: =IF(SUM(CZ19:DD19)>0,0,IF(OR(AND(X19="No",AN19="Tier 1",AJ19>$AG$4),AND(X19="No",AN19="Tier 2",AJ19>$AH$4),AND(X19="No",AN19="Tier 3",AJ19>$AI$4)),FV19,0)) -> 0 | FY19: =IF(SUM(CZ19:DD19)>0,0,IF(OR(AND(X19="Yes",AN19="Tier 1",AJ19>$AG$5),AND(X19="Yes",AN19="Tier 2",AJ19>$AH$5),AND(X19="Yes",AN19="Tier 3",AJ19>$AI$5)),FV19,0)) -> 0 | FZ19: =IF(SUM(FW19:FY19)>0,FV19,0) -> 0 | GA19: =IF(B19="",0,FZ19*FW$6*(1-MIN(90%,T19))) -> 0 | GB19: =FV19-GA19 -> 4909661.1 | GC19: =IF(AND(N19="No",DJ19=0),GB19,IF(AND(N19="No",DJ19<>0,K19=0),0,IF(AND(N19="No",DJ19<>0,K19>0,J19<>K19),MAX(0,M19-(DI19-GB19)),DH19))) -> 4909661.1 | GD19: =+GC19*V19 -> 3559504.3 | GE19: =IFERROR(GD19/K19,"") -> 0.6525 | GF19: =IF(IC19="","",IC19) -> 46 | GG19: {=IF(SUM(IF(IC$9:IC18=IC19,1,0))>0,0,SUMIF($IC$10:$IC$406,IC19,$FJ$10:$FJ$406))} -> 0 | GH19: =GG19 -> 0 | GI19: =GI18+1 -> 10 | GJ19: =LARGE($GH$10:$GH$406,GI19) -> 50000000 | GK19: =IF(GI19>GI$6,0,IF(GI19=$GI$2,$GK$2,IF(GI19<4,$GK$3,$GK$4))) -> 1.5289285e+08 | GL19: =MAX(0,GJ19-GK19) -> 0 | GM19: {=IF(GJ19=0,0,LARGE(IF($GG$10:$GG$406=GJ19,$GF$10:$GF$406,0),COUNTIF($GJ$10:$GJ$406,GJ19)-COUNTIF(GJ$9:GJ18,GJ19)))} -> 57 | GN19: =IF(GJ19=0,0,GL19/GJ19) -> 0 | GP19: =IF(C19="","",IF(ISERROR(MATCH(C19,C$10:C18,0)),MAX(GP$10:GP18)+1,INDEX(GP$10:GP18,MATCH(C19,C$10:C18,0)))) -> 9 | GQ19: =IF(COUNTIF($A$10:A19,A19)<=1,SUMIF($A$10:$A$406,A19,$FH$10:$FH$406),0) -> 4909661.1 | GR19: =GR18+1 -> 10 | GS19: =LARGE($GQ$10:$GQ$406,GR19) -> 25304386 | GT19: =IF(GR19>GR$6,0,IF(GR19<=GR$2,GT$2,IF(AND(GR19<=$GR$3,GR19>$GR$2),GT$3,GT$4))) -> 50964284 | GU19: =MAX(0,GS19-GT19) -> 0 | GV19: {=IF(GS19=0,0,LARGE(IF($GQ$10:$GQ$406=GS19,$GP$10:$GP$406,0),COUNTIF($GS$10:$GS$406,GS19)-COUNTIF(GS$9:GS18,GS19)))} -> 81 | GW19: =IF(GS19=0,0,GU19/GS19) -> 0 | GY19: =IF(C19="","",IF(ISERROR(MATCH(C19,C$10:C18,0)),MAX(GP$10:GP18)+1,INDEX(GP$10:GP18,MATCH(C19,C$10:C18,0)))) -> 9 | GZ19: =IF(COUNTIF($A$10:A19,A19)<=1,SUMIF($A$10:$A$406,A19,$FH$10:$FH$406),0) -> 4909661.1 | HA19: =HA18+1 -> 10 | HB19: =LARGE($GZ$10:$GZ$406,HA19) -> 25304386 | HC19: - | HD19: =IF(HA19<6,MAX(0,$HD$2/5),0) -> 0 | HE19: {=IF(HB19=0,0,LARGE(IF($GZ$10:$GZ$406=HB19,$GY$10:$GY$406,0),COUNTIF($HB$10:$HB$406,HB19)-COUNTIF(HB$9:HB18,HB19)))} -> 81 | HF19: =IF(HB19=0,0,HD19/HB19) -> 0 | HH19: =DH19-GB19 -> 0 | HI19: 0 | HJ19: =MIN(HI19,DF19) -> 0 | HL19: =IF(COUNTIF($C$10:$C$406,HL18+1),HL18+1,"") -> 10 | HM19: =SUMIF($C$10:$C$406,HL19,$DH$10:$DH$406) -> 15648476 | HO19: =MIN(HP19:HT19) -> 4909661.1 | HP19: =IF(B19="","",$M19) -> 5455179 | HQ19: =IF($N19="Yes",IF(P19>=6,0,MIN($T19*$M19,$U19*$M19)),"") | HR19: =IF(AND(N19="Yes",P19>=6),"",IF($S19="Yes",$R19*$M19,"")) | HS19: =IF($Q19="Yes",MIN($M19,$T19*$M19),"") | HT19: =IF(AND($N19="Yes",$P19>=6),"",IF(OR(CZ19=1,DD19=1,),MIN($T19*$M19,$U19*$M19),IF(OR(DA19=1,DB19=1,DC19=1),IF(AK19>=5000000,MIN($T19*$M19,$IF19*$M19),MIN($T19*$M19,$U19*$M19)),""))) -> 4909661.1 | HU19: =IF(DE19>0,DE19,"") | HV19: =IF(B19="",0,$L19-$M19) -> 0 | HW19: =IF(OR(SUM(HQ19:HU19)>0,P19>=6),"",IF($B19="","",1)) | HX19: =IF(AND($HU19<>0,OR(HU19<=MIN(HQ19:HT19),SUM(HQ19:HT19)=0)),$HU19,0) -> 0 | HY19: =IF(AND($HT19<>0,OR(AND($HT19<>$HU19,$HT19<>$HS19,$HT19<>$HR19,$HT19<>$HQ19,$HT19<MIN($HQ19:$HS19),$HT19<HU19),SUM($HQ19:$HS19)+SUM(HU19)=0),IB19<=0),$HT19,0) -> 4909661.1 | HZ19: =IF(AND($HS19<>0,OR(AND($HS19<>$HU19,$HS19<>$HT19,$HS19<>$HR19,$HS19<>$HQ19),$HS19<MIN($HQ19:$HR19),$HS19<MIN($HT19:$HU19),SUM($HQ19:$HR19)+SUM($HT19:$HU19)=0)),$HS19,0) -> 0 | IA19: =IF(AND($HR19<>0,OR(AND($HR19<>$HU19,HR19<>HT19,HR19<>HS19,HR19<>HQ19,HR19<MIN(HS19:HU19)),SUM(HQ19)+SUM(HS19:HU19)=0)),$HR19,0) -> 0 | IB19: =IF(AND($HQ19<>0,OR(HQ19<=MIN(HR19:HU19),SUM(HR19:HU19)=0)),$HQ19,0) -> 0 | IC19: =IF(C19="","",INDEX(Lookups!$E$2:$E$69,MATCH('Loan List'!BE19,Lookups!$F$2:$F$69,0))) -> 46 | ID19: =HV19=DG19 -> TRUE | IF19: =IF(B19="","",IF(AND(Y19="Second Lien",OR(DA19=1,DB19=1,DC19=1)),50%,IF(DA19=1,90%,IF(DB19=1,80%,IF(DC19=1,65%,"No Initial Haircut"))))) -> 0.9
A20: Beacon Behavioral Support Service, LLC | B20: =IF(D20="","",B19+1) -> 11 | C20: =IF(COUNTIF($A$10:A19,A20)>0,C19,C19+1) -> 10 | D20: Beacon Behavioral Support Service, LLC | E20: Beacon Behavioral (Term Loan) | G20: 17387196 | H20: 17387196 | I20: =IF(B20="","",VLOOKUP(BF20,Inputs!$A$12:$J$15,10,FALSE)) -> 1 | J20: =IF(B20="","",G20*I20) -> 17387196 | K20: =IF(B20="","",H20*I20) -> 17387196 | L20: =IF(B20="","",IF(COUNTIF($CF20:$CY20,1)>0,0,J20)) -> 17387196 | M20: =IF(B20="","",IF(COUNTIF($CF20:$CY20,1)>0,0,K20)) -> 17387196 | N20: No | O20: N/A | P20: =IF(B20="","",IF(OR(O20="N/A",O20=""),0,YEARFRAC('Borrowing Base'!$J$4,'Loan List'!O20)*12)) -> 0 | Q20: No | R20: 0.98881144 | S20: =IF(B20="","",IF(R20<95%,"Yes","No")) -> No | T20: 0.99 | U20: =IF(B20="","",IF(OR(Y20="First Lien",Y20="Split First Lien",Y20="Tier 1 Split Lien",Y20="Tier 2 Split Lien"),50%,30%)) -> 0.5 | V20: =IF(B20="",0,IF(AND(Y20="First Lien",AN20="Tier 1"),IF(AND(X20="Yes",MIN(AH20,$AJ$5)>4.5),(((4.5/MIN(AH20,$AJ$5))*72.5%)+(((MIN(AH20,$AJ$5)-4.5)/MIN(AH20,$AJ$5))*35%)),72.5%),IF(AND(Y20="First Lien",AN20="Tier 2"),IF(AND(X20="Yes",MIN(AH20,$AK$5)>4.5),(((4.5/MIN(AH20,$AK$5))*72.5%)+(((MIN(AH20,$AK$5)-4.5)/MIN(AH20,$AK$5))*35%)),72.5%),IF(AND(X20="Yes",MIN(AH20,$AL$5)>4),(((4/MIN(AH20,$AL$5))*72.5%)+(((MIN(AH20,$AL$5)-4)/MIN(AH20,$AL$5))*35%)),IF(OR(Y20="First Lien",Y20="Split First Lien"),72.5%,IF(Y20="Split Lien", 53%,35%)))))) -> 0.725 | W20: =IF($C20="","",MIN($HP20:$HT20)) -> 15648476 | X20: No | Y20: First Lien | Z20: Term | AA20: NR | AB20: NR | AC20: 1.8043488 | AD20: 1.2453582 | AE20: 1.9044461 | AF20: 0.43180748 | AG20: 3.8076241 | AH20: 3.8076241 | AI20: 5.1840024 | AJ20: 5.1855655 | AK20: 16872358 | AL20: 21286315 | AM20: 45838 | AN20: =IF(C20="","",(IF(AK20>=50000000,"Tier 1",(IF(OR(AK20>=20000000,AND(AK20>5000000,AC20>=1.25,AF20<=0.65)),"Tier 2","Tier 3"))))) -> Tier 2 | AO20: 47290 | AP20: =IF(C20="","",DAYS360(Inputs!$J$8,AO20)/360) -> 3.825 | AQ20: =IF(C20="","",AP20) -> 3.825 | AR20: No | AS20: 0 | AT20: Yes | AU20: 0.01 | AV20: 0.055 | AW20: 0.042956 | AX20: =IF(C20="","",MAX(AU20,AW20)) -> 0.042956 | AY20: 0 | AZ20: 0 | BA20: 0 | BB20: =IF(B20="","",IF(AR20="No",AV20-AZ20,"")) -> 0.055 | BC20: =IF(B20="","",IF(AR20="Yes",AS20-BA20,"")) | BD20: Quarterly | BE20: Health Care Providers & Services | BF20: USD | BG20: United States | BH20: No | BI20: =IF(B20="","",IF(OR(AND(AZ20>0,BB20>=2.5%,BB20<4%),AND(BA20>0,BC20>=6%,BC20<8%)),"Yes","No")) -> No | BJ20: =IF(B20="","",IF(OR(AND(AZ20>0,BB20<2.5%),AND(BA20>0,BC20<6%)),"Yes","No")) -> No | BK20: No | BL20: No | BM20: No | BN20: No | BO20: No | BP20: No | BQ20: No | BR20: No | BS20: No | BT20: No | BU20: No | BV20: No | BW20: No | BX20: No | BY20: No | BZ20: No | CA20: No | CB20: Yes | CC20: =IF(B20="","",IF(AT20="No",((BB20+AW20)-$AZ$4),((BB20+AX20)-$AZ$4))*IF(DE20>0,0,M20)) -> 951663.82 | CD20: =IF(B20="","",AY20*(L20-M20)*IF(DE20>0,0,1)) -> 0 | CF20: =IF(AND(B20<>"",R20<=85%),1,0) -> 0 | CG20: =IF(B20="",0,(IF(OR(BF20="USD",BF20="CAD",BF20="GBP",BF20="AUD",BF20="EUR"),0,1))) -> 0 | CH20: =IF(B20="",0,(IF(OR(BG20="United States",BG20="Canada",BG20="United Kingdom",BG20="Australia",BG20="Netherlands Antilles",BG20="Bermuda",BG20="Cayman Islands",BG20="British Virgin Islands",BG20="Channel Islands",BG20="Isle of Man",BG20="Australia",BG20="Netherlands",BG20="Germany",BG20="Sweden",BG20="Switzerland",BG20="Austria",BG20="Belgium",BG20="Denmark",BG20="Finland",BG20="Iceland",BG20="Ireland",BG20="Lichtenstein",BG20="Luxemborg",BG20="Norway"),0,1))) -> 0 | CI20: =IF(BO20="Yes",1,0) -> 0 | CJ20: =IF(BP20="Yes",1,0) -> 0 | CK20: =IF(BQ20="Yes",1,0) -> 0 | CL20: =IF(BR20="Yes",1,0) -> 0 | CM20: =IF(BS20="Yes",1,0) -> 0 | CN20: =IF(BT20="Yes",1,0) -> 0 | CO20: =IF(OR(AND(BJ20="Yes",N20="No"),AND(BJ20="Yes",N20="Yes",P20>=6)),1,0) -> 0 | CP20: =IF(BU20="Yes",1,0) -> 0 | CQ20: =IF(AND(BV20="Yes",BW20="No"),1,0) -> 0 | CR20: =IF(BX20="Yes",1,0) -> 0 | CS20: =IF(AP20="",0,IF(AP20>7,1,0)) -> 0 | CT20: =IF(OR(BD20<>"Monthly",BD20<>"Quarterly",BD20<>"Semi-Annually"),0,1) -> 0 | CU20: =IF(BY20="Yes",1,0) -> 0 | CV20: =IF(BZ20="Yes",1,0) -> 0 | CW20: =IF(CA20="Yes",1,0) -> 0 | CX20: =IF(CB20="No",1,0) -> 0 | CY20: =IF(B20="",0,IF(AK20>=5000000,0,1)) -> 0 | CZ20: =IF(B20="",0,IF(AL20>=5000000,0,1)) -> 0 | DA20: =IF(OR(DB20=1,DC20=1,DD20=1),0,IF(B20="",0,IF(OR(AND(AN20="Tier 1",X20="No",OR(AI20>$AJ$3,AJ20>$AJ$4)),(AND(AN20="Tier 1",X20="Yes",AJ20>$AJ$5)),(AND(AN20="Tier 2",X20="No",OR(AI20>$AK$3,AJ20>$AK$4))),(AND(AN20="Tier 2",X20="Yes",AJ20>$AK$5)),(AND(AN20="Tier 3",X20="No",OR(AI20>$AL$3,AJ20>$AL$4))),(AND(AN20="Tier 3",X20="Yes",AJ20>$AL$5))),1,0))) -> 1 | DB20: =IF(OR(DC20=1,DD20=1),0,IF(B20="",0,IF(OR(AND(AN20="Tier 1",X20="No",OR(AI20>$AM$3,AJ20>$AM$4)),(AND(AN20="Tier 1",X20="Yes",AJ20>$AM$5)),(AND(AN20="Tier 2",X20="No",OR(AI20>$AN$3,AJ20>$AN$4))),(AND(AN20="Tier 2",X20="Yes",AJ20>$AN$5)),(AND(AN20="Tier 3",X20="No",OR(AI20>$AO$3,AJ20>$AO$4))),(AND(AN20="Tier 3",X20="Yes",AJ20>$AO$5))),1,0))) -> 0 | DC20: =IF(DD20=1,0,IF(B20="",0,IF(OR(AND(AN20="Tier 1",X20="No",OR(AI20>$AP$3,AJ20>$AP$4)),(AND(AN20="Tier 1",X20="Yes",AJ20>$AP$5)),(AND(AN20="Tier 2",X20="No",OR(AI20>$AQ$3,AJ20>$AQ$4))),(AND(AN20="Tier 2",X20="Yes",AJ20>$AQ$5)),(AND(AN20="Tier 3",X20="No",OR(AI20>$AR$3,AJ20>$AR$4))),(AND(AN20="Tier 3",X20="Yes",AJ20>$AR$5))),1,0))) -> 0 | DD20: =IF(B20="",0,IF(OR(AND(AN20="Tier 1",X20="No",OR(AI20>$AS$3,AJ20>$AS$4)),(AND(AN20="Tier 1",X20="Yes",AJ20>$AS$5)),(AND(AN20="Tier 2",X20="No",OR(AI20>$AT$3,AJ20>$AT$4))),(AND(AN20="Tier 2",X20="Yes",AJ20>$AT$5)),(AND(AN20="Tier 3",X20="No",OR(AI20>$AU$3,AJ20>$AU$4))),(AND(AN20="Tier 3",X20="Yes",AJ20>$AU$5))),1,0)) -> 0 | DE20: =IF((SUM(CF20:CY20)=0),0,W20) -> 0 | DF20: =IF(OR(B20="",DE20>0),0,W20) -> 15648476 | DG20: =IF(B20="",0,IF(COUNTIF(CF20:CY20,1)>0,0,L20-M20)) -> 0 | DH20: =DF20+IF(DE20>0,0,DG20) -> 15648476 | DI20: =IF(B20="","",M20+DG20) -> 17387196 | DJ20: =IF(B20="",0,J20-K20) -> 0 | DK20: =IF(OR(BF20="EUR",BF20="CAD",BF20="GBP",BF20="AUD"),(GB20*(1-V20))+(HH20)+IF(HY20="",0,HY20*(1-U20)),0) -> 0 | DL20: =IF(BF20="EUR",33%,IF(BF20="CAD",38%,IF(BF20="GBP",51%,IF(BF20="AUD",61%,0)))) -> 0 | DM20: =DK20*DL20 -> 0 | DO20: =IF(OR(Y20="Second Lien",Y20="Tier 1 Split Lien",Y20="Tier 2 Split Lien"),DH20,0) -> 0 | DP20: =DO20*DO$6 -> 0 | DQ20: =DH20-DP20 -> 15648476 | DR20: =IF(Y20="Second Lien",DQ20,0) -> 0 | DS20: =DR20*DR$6 -> 0 | DT20: =DQ20-DS20 -> 15648476 | DU20: =IF(BH20="Yes",DT20,0) -> 0 | DV20: =DU20*DU$6 -> 0 | DW20: =DT20-DV20 -> 15648476 | DX20: =IF(OR(BG20="Canada",BG20="United Kingdom",BG20="Australia",BG20="Netherlands Antilles",BG20="Bermuda",BG20="Cayman Islands",BG20="British Virgin Islands",BG20="Channel Islands",BG20="Isle of Man",BG20="Australia",BG20="Netherlands",BG20="Germany",BG20="Sweden",BG20="Switzerland",BG20="Austria",BG20="Belgium",BG20="Denmark",BG20="Finland",BG20="Iceland",BG20="Ireland",BG20="Lichtenstein",BG20="Luxemborg",BG20="Norway"),DW20,0) -> 0 | DY20: =DX20*DX$6 -> 0 | DZ20: =DW20-DY20 -> 15648476 | EA20: =IF(BI20="Yes",DZ20,0) -> 0 | EB20: =EA20*EA$6 -> 0 | EC20: =DZ20-EB20 -> 15648476 | ED20: =IF(OR(Z20="Delayed Draw",Z20="Revolver"),EC20,0) -> 0 | EE20: =ED20*ED$6 -> 0 | EF20: =EC20-EE20 -> 15648476 | EG20: =IF(S20="Yes",EF20,0) -> 0 | EH20: =EG20*EG$6 -> 0 | EI20: =EF20-EH20 -> 15648476 | EJ20: =IF(Q20="Yes",EI20,0) -> 0 | EK20: =EJ20*EJ$6 -> 0 | EL20: =EI20-EK20 -> 15648476 | EM20: =IF(BD20="Semi-Annually",EL20,0) -> 0 | EN20: =EM20*EM$6 -> 0 | EO20: =EL20-EN20 -> 15648476 | EP20: =IF(BK20="Yes",EO20,0) -> 0 | EQ20: =EP20*EP$6 -> 0 | ER20: =EO20-EQ20 -> 15648476 | ES20: =IF(BL20="Yes",ER20,0) -> 0 | ET20: =ES20*ES$6 -> 0 | EU20: =ER20-ET20 -> 15648476 | EV20: =IF(AND(BM20="Yes",OR(BN20="No",AND(BN20="Yes",Inputs!$J$8=Inputs!$J$17+75))),EU20,0) -> 0 | EW20: =EV20*EV$6 -> 0 | EX20: =EU20-EW20 -> 15648476 | EY20: =IF(BW20="Yes",EX20,0) -> 0 | EZ20: =EY20*EY$6 -> 0 | FA20: =EX20-EZ20 -> 15648476 | FB20: =IF(AR20="Yes",FA20,0) -> 0 | FC20: =FB20*FB$6 -> 0 | FD20: =FA20-FC20 -> 15648476 | FE20: =IF(OR(BF20="EUR",BF20="AUD",BF20="CAD",BF20="GBP"),FD20,0) -> 0 | FF20: =FE20*FE$6 -> 0 | FG20: =FD20-FF20 -> 15648476 | FH20: =FG20 -> 15648476 | FI20: =IF(FG20=0,0,VLOOKUP(C20,$GV$10:$GW$406,2,FALSE)*FG20) -> 0 | FJ20: =FG20-FI20 -> 15648476 | FK20: =FJ20 -> 15648476 | FL20: =IF(OR(IC20="",FJ20<0.01),,VLOOKUP(IC20,$GM$10:$GN$406,2,FALSE)*FJ20) -> 0 | FM20: =FJ20-FL20 -> 15648476 | FN20: =FM20 -> 15648476 | FO20: =IF(FM20=0,0,VLOOKUP(C20,$HE$10:$HF$406,2,FALSE)*FM20) -> 0 | FP20: =FM20-FO20 -> 15648476 | FQ20: =IF(SUM(CZ20:DD20)>0,0,IF(AND(AL20>=5000000,AL20<7500000),FP20,0)) -> 0 | FR20: =IF(B20="",0,FQ20*FQ$6*(1-$U20)) -> 0 | FS20: =FP20-FR20 -> 15648476 | FT20: =IF(SUM(CZ20:DD20)>0,0,IF(AL20<15000000,FS20,0)) -> 0 | FU20: =IF(B20="",0,FT20*FT$6*(1-$U20)) -> 0 | FV20: =FS20-FU20 -> 15648476 | FW20: =IF(SUM(CZ20:DD20)>0,0,IF(OR(AND(X20="No",AN20="Tier 1",AI20>$AG$3),AND(X20="No",AN20="Tier 2",AI20>$AH$3),AND(X20="No",AN20="Tier 3",AI20>$AI$3)),FV20,0)) -> 0 | FX20: =IF(SUM(CZ20:DD20)>0,0,IF(OR(AND(X20="No",AN20="Tier 1",AJ20>$AG$4),AND(X20="No",AN20="Tier 2",AJ20>$AH$4),AND(X20="No",AN20="Tier 3",AJ20>$AI$4)),FV20,0)) -> 0 | FY20: =IF(SUM(CZ20:DD20)>0,0,IF(OR(AND(X20="Yes",AN20="Tier 1",AJ20>$AG$5),AND(X20="Yes",AN20="Tier 2",AJ20>$AH$5),AND(X20="Yes",AN20="Tier 3",AJ20>$AI$5)),FV20,0)) -> 0 | FZ20: =IF(SUM(FW20:FY20)>0,FV20,0) -> 0 | GA20: =IF(B20="",0,FZ20*FW$6*(1-MIN(90%,T20))) -> 0 | GB20: =FV20-GA20 -> 15648476 | GC20: =IF(AND(N20="No",DJ20=0),GB20,IF(AND(N20="No",DJ20<>0,K20=0),0,IF(AND(N20="No",DJ20<>0,K20>0,J20<>K20),MAX(0,M20-(DI20-GB20)),DH20))) -> 15648476 | GD20: =+GC20*V20 -> 11345145 | GE20: =IFERROR(GD20/K20,"") -> 0.6525 | GF20: =IF(IC20="","",IC20) -> 31 | GG20: {=IF(SUM(IF(IC$9:IC19=IC20,1,0))>0,0,SUMIF($IC$10:$IC$406,IC20,$FJ$10:$FJ$406))} -> 84429923 | GH20: =GG20 -> 84429923 | GI20: =GI19+1 -> 11 | GJ20: =LARGE($GH$10:$GH$406,GI20) -> 48659572 | GK20: =IF(GI20>GI$6,0,IF(GI20=$GI$2,$GK$2,IF(GI20<4,$GK$3,$GK$4))) -> 1.5289285e+08 | GL20: =MAX(0,GJ20-GK20) -> 0 | GM20: {=IF(GJ20=0,0,LARGE(IF($GG$10:$GG$406=GJ20,$GF$10:$GF$406,0),COUNTIF($GJ$10:$GJ$406,GJ20)-COUNTIF(GJ$9:GJ19,GJ20)))} -> 53 | GN20: =IF(GJ20=0,0,GL20/GJ20) -> 0 | GP20: =IF(C20="","",IF(ISERROR(MATCH(C20,C$10:C19,0)),MAX(GP$10:GP19)+1,INDEX(GP$10:GP19,MATCH(C20,C$10:C19,0)))) -> 10 | GQ20: =IF(COUNTIF($A$10:A20,A20)<=1,SUMIF($A$10:$A$406,A20,$FH$10:$FH$406),0) -> 15648476 | GR20: =GR19+1 -> 11 | GS20: =LARGE($GQ$10:$GQ$406,GR20) -> 25111100 | GT20: =IF(GR20>GR$6,0,IF(GR20<=GR$2,GT$2,IF(AND(GR20<=$GR$3,GR20>$GR$2),GT$3,GT$4))) -> 50964284 | GU20: =MAX(0,GS20-GT20) -> 0 | GV20: {=IF(GS20=0,0,LARGE(IF($GQ$10:$GQ$406=GS20,$GP$10:$GP$406,0),COUNTIF($GS$10:$GS$406,GS20)-COUNTIF(GS$9:GS19,GS20)))} -> 44 | GW20: =IF(GS20=0,0,GU20/GS20) -> 0 | GY20: =IF(C20="","",IF(ISERROR(MATCH(C20,C$10:C19,0)),MAX(GP$10:GP19)+1,INDEX(GP$10:GP19,MATCH(C20,C$10:C19,0)))) -> 10 | GZ20: =IF(COUNTIF($A$10:A20,A20)<=1,SUMIF($A$10:$A$406,A20,$FH$10:$FH$406),0) -> 15648476 | HA20: =HA19+1 -> 11 | HB20: =LARGE($GZ$10:$GZ$406,HA20) -> 25111100 | HC20: - | HD20: =IF(HA20<6,MAX(0,$HD$2/5),0) -> 0 | HE20: {=IF(HB20=0,0,LARGE(IF($GZ$10:$GZ$406=HB20,$GY$10:$GY$406,0),COUNTIF($HB$10:$HB$406,HB20)-COUNTIF(HB$9:HB19,HB20)))} -> 44 | HF20: =IF(HB20=0,0,HD20/HB20) -> 0 | HH20: =DH20-GB20 -> 0 | HI20: 0 | HJ20: =MIN(HI20,DF20) -> 0 | HL20: =IF(COUNTIF($C$10:$C$406,HL19+1),HL19+1,"") -> 11 | HM20: =SUMIF($C$10:$C$406,HL20,$DH$10:$DH$406) -> 41568911 | HO20: =MIN(HP20:HT20) -> 15648476 | HP20: =IF(B20="","",$M20) -> 17387196 | HQ20: =IF($N20="Yes",IF(P20>=6,0,MIN($T20*$M20,$U20*$M20)),"") | HR20: =IF(AND(N20="Yes",P20>=6),"",IF($S20="Yes",$R20*$M20,"")) | HS20: =IF($Q20="Yes",MIN($M20,$T20*$M20),"") | HT20: =IF(AND($N20="Yes",$P20>=6),"",IF(OR(CZ20=1,DD20=1,),MIN($T20*$M20,$U20*$M20),IF(OR(DA20=1,DB20=1,DC20=1),IF(AK20>=5000000,MIN($T20*$M20,$IF20*$M20),MIN($T20*$M20,$U20*$M20)),""))) -> 15648476 | HU20: =IF(DE20>0,DE20,"") | HV20: =IF(B20="",0,$L20-$M20) -> 0 | HW20: =IF(OR(SUM(HQ20:HU20)>0,P20>=6),"",IF($B20="","",1)) | HX20: =IF(AND($HU20<>0,OR(HU20<=MIN(HQ20:HT20),SUM(HQ20:HT20)=0)),$HU20,0) -> 0 | HY20: =IF(AND($HT20<>0,OR(AND($HT20<>$HU20,$HT20<>$HS20,$HT20<>$HR20,$HT20<>$HQ20,$HT20<MIN($HQ20:$HS20),$HT20<HU20),SUM($HQ20:$HS20)+SUM(HU20)=0),IB20<=0),$HT20,0) -> 15648476 | HZ20: =IF(AND($HS20<>0,OR(AND($HS20<>$HU20,$HS20<>$HT20,$HS20<>$HR20,$HS20<>$HQ20),$HS20<MIN($HQ20:$HR20),$HS20<MIN($HT20:$HU20),SUM($HQ20:$HR20)+SUM($HT20:$HU20)=0)),$HS20,0) -> 0 | IA20: =IF(AND($HR20<>0,OR(AND($HR20<>$HU20,HR20<>HT20,HR20<>HS20,HR20<>HQ20,HR20<MIN(HS20:HU20)),SUM(HQ20)+SUM(HS20:HU20)=0)),$HR20,0) -> 0 | IB20: =IF(AND($HQ20<>0,OR(HQ20<=MIN(HR20:HU20),SUM(HR20:HU20)=0)),$HQ20,0) -> 0 | IC20: =IF(C20="","",INDEX(Lookups!$E$2:$E$69,MATCH('Loan List'!BE20,Lookups!$F$2:$F$69,0))) -> 31 | ID20: =HV20=DG20 -> TRUE | IF20: =IF(B20="","",IF(AND(Y20="Second Lien",OR(DA20=1,DB20=1,DC20=1)),50%,IF(DA20=1,90%,IF(DB20=1,80%,IF(DC20=1,65%,"No Initial Haircut"))))) -> 0.9
A21: Best Practice Associates, LLC | B21: =IF(D21="","",B20+1) -> 12 | C21: =IF(COUNTIF($A$10:A20,A21)>0,C20,C20+1) -> 11 | D21: Best Practice Associates, LLC | E21: Federal Advisory Partners (First Lien Term Loan) | G21: 41568911 | H21: 41568911 | I21: =IF(B21="","",VLOOKUP(BF21,Inputs!$A$12:$J$15,10,FALSE)) -> 1 | J21: =IF(B21="","",G21*I21) -> 41568911 | K21: =IF(B21="","",H21*I21) -> 41568911 | L21: =IF(B21="","",IF(COUNTIF($CF21:$CY21,1)>0,0,J21)) -> 41568911 | M21: =IF(B21="","",IF(COUNTIF($CF21:$CY21,1)>0,0,K21)) -> 41568911 | N21: No | O21: N/A | P21: =IF(B21="","",IF(OR(O21="N/A",O21=""),0,YEARFRAC('Borrowing Base'!$J$4,'Loan List'!O21)*12)) -> 0 | Q21: No | R21: 0.98503022 | S21: =IF(B21="","",IF(R21<95%,"Yes","No")) -> No | T21: 0.9875 | U21: =IF(B21="","",IF(OR(Y21="First Lien",Y21="Split First Lien",Y21="Tier 1 Split Lien",Y21="Tier 2 Split Lien"),50%,30%)) -> 0.5 | V21: =IF(B21="",0,IF(AND(Y21="First Lien",AN21="Tier 1"),IF(AND(X21="Yes",MIN(AH21,$AJ$5)>4.5),(((4.5/MIN(AH21,$AJ$5))*72.5%)+(((MIN(AH21,$AJ$5)-4.5)/MIN(AH21,$AJ$5))*35%)),72.5%),IF(AND(Y21="First Lien",AN21="Tier 2"),IF(AND(X21="Yes",MIN(AH21,$AK$5)>4.5),(((4.5/MIN(AH21,$AK$5))*72.5%)+(((MIN(AH21,$AK$5)-4.5)/MIN(AH21,$AK$5))*35%)),72.5%),IF(AND(X21="Yes",MIN(AH21,$AL$5)>4),(((4/MIN(AH21,$AL$5))*72.5%)+(((MIN(AH21,$AL$5)-4)/MIN(AH21,$AL$5))*35%)),IF(OR(Y21="First Lien",Y21="Split First Lien"),72.5%,IF(Y21="Split Lien", 53%,35%)))))) -> 0.725 | W21: =IF($C21="","",MIN($HP21:$HT21)) -> 41568911 | X21: No | Y21: First Lien | Z21: Term | AA21: NR | AB21: NR | AC21: 1.2337514 | AD21: 1.7525077 | AE21: 1.97 | AF21: 0.53300119 | AG21: 5.037594 | AH21: 5.3300119 | AI21: 4.7445568 | AJ21: 5.1038799 | AK21: 47275000 | AL21: 67742897 | AM21: 45838 | AN21: =IF(C21="","",(IF(AK21>=50000000,"Tier 1",(IF(OR(AK21>=20000000,AND(AK21>5000000,AC21>=1.25,AF21<=0.65)),"Tier 2","Tier 3"))))) -> Tier 2 | AO21: 47430 | AP21: =IF(C21="","",DAYS360(Inputs!$J$8,AO21)/360) -> 4.2055556 | AQ21: =IF(C21="","",AP21) -> 4.2055556 | AR21: No | AS21: 0 | AT21: Yes | AU21: 0.01 | AV21: 0.0675 | AW21: 0.042956 | AX21: =IF(C21="","",MAX(AU21,AW21)) -> 0.042956 | AY21: 0 | AZ21: 0 | BA21: 0 | BB21: =IF(B21="","",IF(AR21="No",AV21-AZ21,"")) -> 0.0675 | BC21: =IF(B21="","",IF(AR21="Yes",AS21-BA21,"")) | BD21: Quarterly | BE21: Aerospace & Defense | BF21: USD | BG21: United States | BH21: No | BI21: =IF(B21="","",IF(OR(AND(AZ21>0,BB21>=2.5%,BB21<4%),AND(BA21>0,BC21>=6%,BC21<8%)),"Yes","No")) -> No | BJ21: =IF(B21="","",IF(OR(AND(AZ21>0,BB21<2.5%),AND(BA21>0,BC21<6%)),"Yes","No")) -> No | BK21: No | BL21: No | BM21: No | BN21: No | BO21: No | BP21: No | BQ21: No | BR21: No | BS21: No | BT21: No | BU21: No | BV21: No | BW21: No | BX21: No | BY21: No | BZ21: No | CA21: No | CB21: Yes | CC21: =IF(B21="","",IF(AT21="No",((BB21+AW21)-$AZ$4),((BB21+AX21)-$AZ$4))*IF(DE21>0,0,M21)) -> 2794827.5 | CD21: =IF(B21="","",AY21*(L21-M21)*IF(DE21>0,0,1)) -> 0 | CF21: =IF(AND(B21<>"",R21<=85%),1,0) -> 0 | CG21: =IF(B21="",0,(IF(OR(BF21="USD",BF21="CAD",BF21="GBP",BF21="AUD",BF21="EUR"),0,1))) -> 0 | CH21: =IF(B21="",0,(IF(OR(BG21="United States",BG21="Canada",BG21="United Kingdom",BG21="Australia",BG21="Netherlands Antilles",BG21="Bermuda",BG21="Cayman Islands",BG21="British Virgin Islands",BG21="Channel Islands",BG21="Isle of Man",BG21="Australia",BG21="Netherlands",BG21="Germany",BG21="Sweden",BG21="Switzerland",BG21="Austria",BG21="Belgium",BG21="Denmark",BG21="Finland",BG21="Iceland",BG21="Ireland",BG21="Lichtenstein",BG21="Luxemborg",BG21="Norway"),0,1))) -> 0 | CI21: =IF(BO21="Yes",1,0) -> 0 | CJ21: =IF(BP21="Yes",1,0) -> 0 | CK21: =IF(BQ21="Yes",1,0) -> 0 | CL21: =IF(BR21="Yes",1,0) -> 0 | CM21: =IF(BS21="Yes",1,0) -> 0 | CN21: =IF(BT21="Yes",1,0) -> 0 | CO21: =IF(OR(AND(BJ21="Yes",N21="No"),AND(BJ21="Yes",N21="Yes",P21>=6)),1,0) -> 0 | CP21: =IF(BU21="Yes",1,0) -> 0 | CQ21: =IF(AND(BV21="Yes",BW21="No"),1,0) -> 0 | CR21: =IF(BX21="Yes",1,0) -> 0 | CS21: =IF(AP21="",0,IF(AP21>7,1,0)) -> 0 | CT21: =IF(OR(BD21<>"Monthly",BD21<>"Quarterly",BD21<>"Semi-Annually"),0,1) -> 0 | CU21: =IF(BY21="Yes",1,0) -> 0 | CV21: =IF(BZ21="Yes",1,0) -> 0 | CW21: =IF(CA21="Yes",1,0) -> 0 | CX21: =IF(CB21="No",1,0) -> 0 | CY21: =IF(B21="",0,IF(AK21>=5000000,0,1)) -> 0 | CZ21: =IF(B21="",0,IF(AL21>=5000000,0,1)) -> 0 | DA21: =IF(OR(DB21=1,DC21=1,DD21=1),0,IF(B21="",0,IF(OR(AND(AN21="Tier 1",X21="No",OR(AI21>$AJ$3,AJ21>$AJ$4)),(AND(AN21="Tier 1",X21="Yes",AJ21>$AJ$5)),(AND(AN21="Tier 2",X21="No",OR(AI21>$AK$3,AJ21>$AK$4))),(AND(AN21="Tier 2",X21="Yes",AJ21>$AK$5)),(AND(AN21="Tier 3",X21="No",OR(AI21>$AL$3,AJ21>$AL$4))),(AND(AN21="Tier 3",X21="Yes",AJ21>$AL$5))),1,0))) -> 0 | DB21: =IF(OR(DC21=1,DD21=1),0,IF(B21="",0,IF(OR(AND(AN21="Tier 1",X21="No",OR(AI21>$AM$3,AJ21>$AM$4)),(AND(AN21="Tier 1",X21="Yes",AJ21>$AM$5)),(AND(AN21="Tier 2",X21="No",OR(AI21>$AN$3,AJ21>$AN$4))),(AND(AN21="Tier 2",X21="Yes",AJ21>$AN$5)),(AND(AN21="Tier 3",X21="No",OR(AI21>$AO$3,AJ21>$AO$4))),(AND(AN21="Tier 3",X21="Yes",AJ21>$AO$5))),1,0))) -> 0 | DC21: =IF(DD21=1,0,IF(B21="",0,IF(OR(AND(AN21="Tier 1",X21="No",OR(AI21>$AP$3,AJ21>$AP$4)),(AND(AN21="Tier 1",X21="Yes",AJ21>$AP$5)),(AND(AN21="Tier 2",X21="No",OR(AI21>$AQ$3,AJ21>$AQ$4))),(AND(AN21="Tier 2",X21="Yes",AJ21>$AQ$5)),(AND(AN21="Tier 3",X21="No",OR(AI21>$AR$3,AJ21>$AR$4))),(AND(AN21="Tier 3",X21="Yes",AJ21>$AR$5))),1,0))) -> 0 | DD21: =IF(B21="",0,IF(OR(AND(AN21="Tier 1",X21="No",OR(AI21>$AS$3,AJ21>$AS$4)),(AND(AN21="Tier 1",X21="Yes",AJ21>$AS$5)),(AND(AN21="Tier 2",X21="No",OR(AI21>$AT$3,AJ21>$AT$4))),(AND(AN21="Tier 2",X21="Yes",AJ21>$AT$5)),(AND(AN21="Tier 3",X21="No",OR(AI21>$AU$3,AJ21>$AU$4))),(AND(AN21="Tier 3",X21="Yes",AJ21>$AU$5))),1,0)) -> 0 | DE21: =IF((SUM(CF21:CY21)=0),0,W21) -> 0 | DF21: =IF(OR(B21="",DE21>0),0,W21) -> 41568911 | DG21: =IF(B21="",0,IF(COUNTIF(CF21:CY21,1)>0,0,L21-M21)) -> 0 | DH21: =DF21+IF(DE21>0,0,DG21) -> 41568911 | DI21: =IF(B21="","",M21+DG21) -> 41568911 | DJ21: =IF(B21="",0,J21-K21) -> 0 | DK21: =IF(OR(BF21="EUR",BF21="CAD",BF21="GBP",BF21="AUD"),(GB21*(1-V21))+(HH21)+IF(HY21="",0,HY21*(1-U21)),0) -> 0 | DL21: =IF(BF21="EUR",33%,IF(BF21="CAD",38%,IF(BF21="GBP",51%,IF(BF21="AUD",61%,0)))) -> 0 | DM21: =DK21*DL21 -> 0 | DO21: =IF(OR(Y21="Second Lien",Y21="Tier 1 Split Lien",Y21="Tier 2 Split Lien"),DH21,0) -> 0 | DP21: =DO21*DO$6 -> 0 | DQ21: =DH21-DP21 -> 41568911 | DR21: =IF(Y21="Second Lien",DQ21,0) -> 0 | DS21: =DR21*DR$6 -> 0 | DT21: =DQ21-DS21 -> 41568911 | DU21: =IF(BH21="Yes",DT21,0) -> 0 | DV21: =DU21*DU$6 -> 0 | DW21: =DT21-DV21 -> 41568911 | DX21: =IF(OR(BG21="Canada",BG21="United Kingdom",BG21="Australia",BG21="Netherlands Antilles",BG21="Bermuda",BG21="Cayman Islands",BG21="British Virgin Islands",BG21="Channel Islands",BG21="Isle of Man",BG21="Australia",BG21="Netherlands",BG21="Germany",BG21="Sweden",BG21="Switzerland",BG21="Austria",BG21="Belgium",BG21="Denmark",BG21="Finland",BG21="Iceland",BG21="Ireland",BG21="Lichtenstein",BG21="Luxemborg",BG21="Norway"),DW21,0) -> 0 | DY21: =DX21*DX$6 -> 0 | DZ21: =DW21-DY21 -> 41568911 | EA21: =IF(BI21="Yes",DZ21,0) -> 0 | EB21: =EA21*EA$6 -> 0 | EC21: =DZ21-EB21 -> 41568911 | ED21: =IF(OR(Z21="Delayed Draw",Z21="Revolver"),EC21,0) -> 0 | EE21: =ED21*ED$6 -> 0 | EF21: =EC21-EE21 -> 41568911 | EG21: =IF(S21="Yes",EF21,0) -> 0 | EH21: =EG21*EG$6 -> 0 | EI21: =EF21-EH21 -> 41568911 | EJ21: =IF(Q21="Yes",EI21,0) -> 0 | EK21: =EJ21*EJ$6 -> 0 | EL21: =EI21-EK21 -> 41568911 | EM21: =IF(BD21="Semi-Annually",EL21,0) -> 0 | EN21: =EM21*EM$6 -> 0 | EO21: =EL21-EN21 -> 41568911 | EP21: =IF(BK21="Yes",EO21,0) -> 0 | EQ21: =EP21*EP$6 -> 0 | ER21: =EO21-EQ21 -> 41568911 | ES21: =IF(BL21="Yes",ER21,0) -> 0 | ET21: =ES21*ES$6 -> 0 | EU21: =ER21-ET21 -> 41568911 | EV21: =IF(AND(BM21="Yes",OR(BN21="No",AND(BN21="Yes",Inputs!$J$8=Inputs!$J$17+75))),EU21,0) -> 0 | EW21: =EV21*EV$6 -> 0 | EX21: =EU21-EW21 -> 41568911 | EY21: =IF(BW21="Yes",EX21,0) -> 0 | EZ21: =EY21*EY$6 -> 0 | FA21: =EX21-EZ21 -> 41568911 | FB21: =IF(AR21="Yes",FA21,0) -> 0 | FC21: =FB21*FB$6 -> 0 | FD21: =FA21-FC21 -> 41568911 | FE21: =IF(OR(BF21="EUR",BF21="AUD",BF21="CAD",BF21="GBP"),FD21,0) -> 0 | FF21: =FE21*FE$6 -> 0 | FG21: =FD21-FF21 -> 41568911 | FH21: =FG21 -> 41568911 | FI21: =IF(FG21=0,0,VLOOKUP(C21,$GV$10:$GW$406,2,FALSE)*FG21) -> 0 | FJ21: =FG21-FI21 -> 41568911 | FK21: =FJ21 -> 41568911 | FL21: =IF(OR(IC21="",FJ21<0.01),,VLOOKUP(IC21,$GM$10:$GN$406,2,FALSE)*FJ21) -> 0 | FM21: =FJ21-FL21 -> 41568911 | FN21: =FM21 -> 41568911 | FO21: =IF(FM21=0,0,VLOOKUP(C21,$HE$10:$HF$406,2,FALSE)*FM21) -> 0 | FP21: =FM21-FO21 -> 41568911 | FQ21: =IF(SUM(CZ21:DD21)>0,0,IF(AND(AL21>=5000000,AL21<7500000),FP21,0)) -> 0 | FR21: =IF(B21="",0,FQ21*FQ$6*(1-$U21)) -> 0 | FS21: =FP21-FR21 -> 41568911 | FT21: =IF(SUM(CZ21:DD21)>0,0,IF(AL21<15000000,FS21,0)) -> 0 | FU21: =IF(B21="",0,FT21*FT$6*(1-$U21)) -> 0 | FV21: =FS21-FU21 -> 41568911 | FW21: =IF(SUM(CZ21:DD21)>0,0,IF(OR(AND(X21="No",AN21="Tier 1",AI21>$AG$3),AND(X21="No",AN21="Tier 2",AI21>$AH$3),AND(X21="No",AN21="Tier 3",AI21>$AI$3)),FV21,0)) -> 41568911 | FX21: =IF(SUM(CZ21:DD21)>0,0,IF(OR(AND(X21="No",AN21="Tier 1",AJ21>$AG$4),AND(X21="No",AN21="Tier 2",AJ21>$AH$4),AND(X21="No",AN21="Tier 3",AJ21>$AI$4)),FV21,0)) -> 0 | FY21: =IF(SUM(CZ21:DD21)>0,0,IF(OR(AND(X21="Yes",AN21="Tier 1",AJ21>$AG$5),AND(X21="Yes",AN21="Tier 2",AJ21>$AH$5),AND(X21="Yes",AN21="Tier 3",AJ21>$AI$5)),FV21,0)) -> 0 | FZ21: =IF(SUM(FW21:FY21)>0,FV21,0) -> 41568911 | GA21: =IF(B21="",0,FZ21*FW$6*(1-MIN(90%,T21))) -> 186247.21 | GB21: =FV21-GA21 -> 41382664 | GC21: =IF(AND(N21="No",DJ21=0),GB21,IF(AND(N21="No",DJ21<>0,K21=0),0,IF(AND(N21="No",DJ21<>0,K21>0,J21<>K21),MAX(0,M21-(DI21-GB21)),DH21))) -> 41382664 | GD21: =+GC21*V21 -> 30002431 | GE21: =IFERROR(GD21/K21,"") -> 0.72175168 | GF21: =IF(IC21="","",IC21) -> 1 | GG21: {=IF(SUM(IF(IC$9:IC20=IC21,1,0))>0,0,SUMIF($IC$10:$IC$406,IC21,$FJ$10:$FJ$406))} -> 0 | GH21: =GG21 -> 0 | GI21: =GI20+1 -> 12 | GJ21: =LARGE($GH$10:$GH$406,GI21) -> 46330726 | GK21: =IF(GI21>GI$6,0,IF(GI21=$GI$2,$GK$2,IF(GI21<4,$GK$3,$GK$4))) -> 1.5289285e+08 | GL21: =MAX(0,GJ21-GK21) -> 0 | GM21: {=IF(GJ21=0,0,LARGE(IF($GG$10:$GG$406=GJ21,$GF$10:$GF$406,0),COUNTIF($GJ$10:$GJ$406,GJ21)-COUNTIF(GJ$9:GJ20,GJ21)))} -> 14 | GN21: =IF(GJ21=0,0,GL21/GJ21) -> 0 | GP21: =IF(C21="","",IF(ISERROR(MATCH(C21,C$10:C20,0)),MAX(GP$10:GP20)+1,INDEX(GP$10:GP20,MATCH(C21,C$10:C20,0)))) -> 11 | GQ21: =IF(COUNTIF($A$10:A21,A21)<=1,SUMIF($A$10:$A$406,A21,$FH$10:$FH$406),0) -> 41568911 | GR21: =GR20+1 -> 12 | GS21: =LARGE($GQ$10:$GQ$406,GR21) -> 25000000 | GT21: =IF(GR21>GR$6,0,IF(GR21<=GR$2,GT$2,IF(AND(GR21<=$GR$3,GR21>$GR$2),GT$3,GT$4))) -> 50964284 | GU21: =MAX(0,GS21-GT21) -> 0 | GV21: {=IF(GS21=0,0,LARGE(IF($GQ$10:$GQ$406=GS21,$GP$10:$GP$406,0),COUNTIF($GS$10:$GS$406,GS21)-COUNTIF(GS$9:GS20,GS21)))} -> 31 | GW21: =IF(GS21=0,0,GU21/GS21) -> 0 | GY21: =IF(C21="","",IF(ISERROR(MATCH(C21,C$10:C20,0)),MAX(GP$10:GP20)+1,INDEX(GP$10:GP20,MATCH(C21,C$10:C20,0)))) -> 11 | GZ21: =IF(COUNTIF($A$10:A21,A21)<=1,SUMIF($A$10:$A$406,A21,$FH$10:$FH$406),0) -> 41568911 | HA21: =HA20+1 -> 12 | HB21: =LARGE($GZ$10:$GZ$406,HA21) -> 25000000 | HC21: - | HD21: =IF(HA21<6,MAX(0,$HD$2/5),0) -> 0 | HE21: {=IF(HB21=0,0,LARGE(IF($GZ$10:$GZ$406=HB21,$GY$10:$GY$406,0),COUNTIF($HB$10:$HB$406,HB21)-COUNTIF(HB$9:HB20,HB21)))} -> 31 | HF21: =IF(HB21=0,0,HD21/HB21) -> 0 | HH21: =DH21-GB21 -> 186247.21 | HI21: 0 | HJ21: =MIN(HI21,DF21) -> 0 | HL21: =IF(COUNTIF($C$10:$C$406,HL20+1),HL20+1,"") -> 12 | HM21: =SUMIF($C$10:$C$406,HL21,$DH$10:$DH$406) -> 15545911 | HO21: =MIN(HP21:HT21) -> 41568911 | HP21: =IF(B21="","",$M21) -> 41568911 | HQ21: =IF($N21="Yes",IF(P21>=6,0,MIN($T21*$M21,$U21*$M21)),"") | HR21: =IF(AND(N21="Yes",P21>=6),"",IF($S21="Yes",$R21*$M21,"")) | HS21: =IF($Q21="Yes",MIN($M21,$T21*$M21),"") | HT21: =IF(AND($N21="Yes",$P21>=6),"",IF(OR(CZ21=1,DD21=1,),MIN($T21*$M21,$U21*$M21),IF(OR(DA21=1,DB21=1,DC21=1),IF(AK21>=5000000,MIN($T21*$M21,$IF21*$M21),MIN($T21*$M21,$U21*$M21)),""))) | HU21: =IF(DE21>0,DE21,"") | HV21: =IF(B21="",0,$L21-$M21) -> 0 | HW21: =IF(OR(SUM(HQ21:HU21)>0,P21>=6),"",IF($B21="","",1)) -> 1 | HX21: =IF(AND($HU21<>0,OR(HU21<=MIN(HQ21:HT21),SUM(HQ21:HT21)=0)),$HU21,0) | HY21: =IF(AND($HT21<>0,OR(AND($HT21<>$HU21,$HT21<>$HS21,$HT21<>$HR21,$HT21<>$HQ21,$HT21<MIN($HQ21:$HS21),$HT21<HU21),SUM($HQ21:$HS21)+SUM(HU21)=0),IB21<=0),$HT21,0) -> 0 | HZ21: =IF(AND($HS21<>0,OR(AND($HS21<>$HU21,$HS21<>$HT21,$HS21<>$HR21,$HS21<>$HQ21),$HS21<MIN($HQ21:$HR21),$HS21<MIN($HT21:$HU21),SUM($HQ21:$HR21)+SUM($HT21:$HU21)=0)),$HS21,0) | IA21: =IF(AND($HR21<>0,OR(AND($HR21<>$HU21,HR21<>HT21,HR21<>HS21,HR21<>HQ21,HR21<MIN(HS21:HU21)),SUM(HQ21)+SUM(HS21:HU21)=0)),$HR21,0) | IB21: =IF(AND($HQ21<>0,OR(HQ21<=MIN(HR21:HU21),SUM(HR21:HU21)=0)),$HQ21,0) | IC21: =IF(C21="","",INDEX(Lookups!$E$2:$E$69,MATCH('Loan List'!BE21,Lookups!$F$2:$F$69,0))) -> 1 | ID21: =HV21=DG21 -> TRUE | IF21: =IF(B21="","",IF(AND(Y21="Second Lien",OR(DA21=1,DB21=1,DC21=1)),50%,IF(DA21=1,90%,IF(DB21=1,80%,IF(DC21=1,65%,"No Initial Haircut"))))) -> No Initial Haircut
A22: Big Top Holdings, LLC | B22: =IF(D22="","",B21+1) -> 13 | C22: =IF(COUNTIF($A$10:A21,A22)>0,C21,C21+1) -> 12 | D22: Big Top Holdings, LLC | E22: Big Top Manufacturing (Term Loan) | G22: 10088880 | H22: 10088880 | I22: =IF(B22="","",VLOOKUP(BF22,Inputs!$A$12:$J$15,10,FALSE)) -> 1 | J22: =IF(B22="","",G22*I22) -> 10088880 | K22: =IF(B22="","",H22*I22) -> 10088880 | L22: =IF(B22="","",IF(COUNTIF($CF22:$CY22,1)>0,0,J22)) -> 10088880 | M22: =IF(B22="","",IF(COUNTIF($CF22:$CY22,1)>0,0,K22)) -> 10088880 | N22: No | O22: N/A | P22: =IF(B22="","",IF(OR(O22="N/A",O22=""),0,YEARFRAC('Borrowing Base'!$J$4,'Loan List'!O22)*12)) -> 0 | Q22: No | R22: 0.98257459 | S22: =IF(B22="","",IF(R22<95%,"Yes","No")) -> No | T22: 1 | U22: =IF(B22="","",IF(OR(Y22="First Lien",Y22="Split First Lien",Y22="Tier 1 Split Lien",Y22="Tier 2 Split Lien"),50%,30%)) -> 0.5 | V22: =IF(B22="",0,IF(AND(Y22="First Lien",AN22="Tier 1"),IF(AND(X22="Yes",MIN(AH22,$AJ$5)>4.5),(((4.5/MIN(AH22,$AJ$5))*72.5%)+(((MIN(AH22,$AJ$5)-4.5)/MIN(AH22,$AJ$5))*35%)),72.5%),IF(AND(Y22="First Lien",AN22="Tier 2"),IF(AND(X22="Yes",MIN(AH22,$AK$5)>4.5),(((4.5/MIN(AH22,$AK$5))*72.5%)+(((MIN(AH22,$AK$5)-4.5)/MIN(AH22,$AK$5))*35%)),72.5%),IF(AND(X22="Yes",MIN(AH22,$AL$5)>4),(((4/MIN(AH22,$AL$5))*72.5%)+(((MIN(AH22,$AL$5)-4)/MIN(AH22,$AL$5))*35%)),IF(OR(Y22="First Lien",Y22="Split First Lien"),72.5%,IF(Y22="Split Lien", 53%,35%)))))) -> 0.725 | W22: =IF($C22="","",MIN($HP22:$HT22)) -> 10088880 | X22: No | Y22: First Lien | Z22: Term | AA22: NR | AB22: NR | AC22: 1.58 | AD22: 1.2410284 | AE22: 2.3146382 | AF22: 0.48189321 | AG22: 3.7538419 | AH22: 3.7538419 | AI22: 3.3434574 | AJ22: 3.3434574 | AK22: 32800000 | AL22: 35032000 | AM22: 45838 | AN22: =IF(C22="","",(IF(AK22>=50000000,"Tier 1",(IF(OR(AK22>=20000000,AND(AK22>5000000,AC22>=1.25,AF22<=0.65)),"Tier 2","Tier 3"))))) -> Tier 2 | AO22: 47543 | AP22: =IF(C22="","",DAYS360(Inputs!$J$8,AO22)/360) -> 4.5194444 | AQ22: =IF(C22="","",AP22) -> 4.5194444 | AR22: No | AS22: 0 | AT22: Yes | AU22: 0.01 | AV22: 0.055 | AW22: 0.042956 | AX22: =IF(C22="","",MAX(AU22,AW22)) -> 0.042956 | AY22: 0 | AZ22: 0 | BA22: 0 | BB22: =IF(B22="","",IF(AR22="No",AV22-AZ22,"")) -> 0.055 | BC22: =IF(B22="","",IF(AR22="Yes",AS22-BA22,"")) | BD22: Quarterly | BE22: Construction & Engineering | BF22: USD | BG22: United States | BH22: No | BI22: =IF(B22="","",IF(OR(AND(AZ22>0,BB22>=2.5%,BB22<4%),AND(BA22>0,BC22>=6%,BC22<8%)),"Yes","No")) -> No | BJ22: =IF(B22="","",IF(OR(AND(AZ22>0,BB22<2.5%),AND(BA22>0,BC22<6%)),"Yes","No")) -> No | BK22: No | BL22: No | BM22: No | BN22: No | BO22: No | BP22: No | BQ22: No | BR22: No | BS22: No | BT22: No | BU22: No | BV22: No | BW22: No | BX22: No | BY22: No | BZ22: No | CA22: No | CB22: Yes | CC22: =IF(B22="","",IF(AT22="No",((BB22+AW22)-$AZ$4),((BB22+AX22)-$AZ$4))*IF(DE22>0,0,M22)) -> 552200.75 | CD22: =IF(B22="","",AY22*(L22-M22)*IF(DE22>0,0,1)) -> 0 | CF22: =IF(AND(B22<>"",R22<=85%),1,0) -> 0 | CG22: =IF(B22="",0,(IF(OR(BF22="USD",BF22="CAD",BF22="GBP",BF22="AUD",BF22="EUR"),0,1))) -> 0 | CH22: =IF(B22="",0,(IF(OR(BG22="United States",BG22="Canada",BG22="United Kingdom",BG22="Australia",BG22="Netherlands Antilles",BG22="Bermuda",BG22="Cayman Islands",BG22="British Virgin Islands",BG22="Channel Islands",BG22="Isle of Man",BG22="Australia",BG22="Netherlands",BG22="Germany",BG22="Sweden",BG22="Switzerland",BG22="Austria",BG22="Belgium",BG22="Denmark",BG22="Finland",BG22="Iceland",BG22="Ireland",BG22="Lichtenstein",BG22="Luxemborg",BG22="Norway"),0,1))) -> 0 | CI22: =IF(BO22="Yes",1,0) -> 0 | CJ22: =IF(BP22="Yes",1,0) -> 0 | CK22: =IF(BQ22="Yes",1,0) -> 0 | CL22: =IF(BR22="Yes",1,0) -> 0 | CM22: =IF(BS22="Yes",1,0) -> 0 | CN22: =IF(BT22="Yes",1,0) -> 0 | CO22: =IF(OR(AND(BJ22="Yes",N22="No"),AND(BJ22="Yes",N22="Yes",P22>=6)),1,0) -> 0 | CP22: =IF(BU22="Yes",1,0) -> 0 | CQ22: =IF(AND(BV22="Yes",BW22="No"),1,0) -> 0 | CR22: =IF(BX22="Yes",1,0) -> 0 | CS22: =IF(AP22="",0,IF(AP22>7,1,0)) -> 0 | CT22: =IF(OR(BD22<>"Monthly",BD22<>"Quarterly",BD22<>"Semi-Annually"),0,1) -> 0 | CU22: =IF(BY22="Yes",1,0) -> 0 | CV22: =IF(BZ22="Yes",1,0) -> 0 | CW22: =IF(CA22="Yes",1,0) -> 0 | CX22: =IF(CB22="No",1,0) -> 0 | CY22: =IF(B22="",0,IF(AK22>=5000000,0,1)) -> 0 | CZ22: =IF(B22="",0,IF(AL22>=5000000,0,1)) -> 0 | DA22: =IF(OR(DB22=1,DC22=1,DD22=1),0,IF(B22="",0,IF(OR(AND(AN22="Tier 1",X22="No",OR(AI22>$AJ$3,AJ22>$AJ$4)),(AND(AN22="Tier 1",X22="Yes",AJ22>$AJ$5)),(AND(AN22="Tier 2",X22="No",OR(AI22>$AK$3,AJ22>$AK$4))),(AND(AN22="Tier 2",X22="Yes",AJ22>$AK$5)),(AND(AN22="Tier 3",X22="No",OR(AI22>$AL$3,AJ22>$AL$4))),(AND(AN22="Tier 3",X22="Yes",AJ22>$AL$5))),1,0))) -> 0 | DB22: =IF(OR(DC22=1,DD22=1),0,IF(B22="",0,IF(OR(AND(AN22="Tier 1",X22="No",OR(AI22>$AM$3,AJ22>$AM$4)),(AND(AN22="Tier 1",X22="Yes",AJ22>$AM$5)),(AND(AN22="Tier 2",X22="No",OR(AI22>$AN$3,AJ22>$AN$4))),(AND(AN22="Tier 2",X22="Yes",AJ22>$AN$5)),(AND(AN22="Tier 3",X22="No",OR(AI22>$AO$3,AJ22>$AO$4))),(AND(AN22="Tier 3",X22="Yes",AJ22>$AO$5))),1,0))) -> 0 | DC22: =IF(DD22=1,0,IF(B22="",0,IF(OR(AND(AN22="Tier 1",X22="No",OR(AI22>$AP$3,AJ22>$AP$4)),(AND(AN22="Tier 1",X22="Yes",AJ22>$AP$5)),(AND(AN22="Tier 2",X22="No",OR(AI22>$AQ$3,AJ22>$AQ$4))),(AND(AN22="Tier 2",X22="Yes",AJ22>$AQ$5)),(AND(AN22="Tier 3",X22="No",OR(AI22>$AR$3,AJ22>$AR$4))),(AND(AN22="Tier 3",X22="Yes",AJ22>$AR$5))),1,0))) -> 0 | DD22: =IF(B22="",0,IF(OR(AND(AN22="Tier 1",X22="No",OR(AI22>$AS$3,AJ22>$AS$4)),(AND(AN22="Tier 1",X22="Yes",AJ22>$AS$5)),(AND(AN22="Tier 2",X22="No",OR(AI22>$AT$3,AJ22>$AT$4))),(AND(AN22="Tier 2",X22="Yes",AJ22>$AT$5)),(AND(AN22="Tier 3",X22="No",OR(AI22>$AU$3,AJ22>$AU$4))),(AND(AN22="Tier 3",X22="Yes",AJ22>$AU$5))),1,0)) -> 0 | DE22: =IF((SUM(CF22:CY22)=0),0,W22) -> 0 | DF22: =IF(OR(B22="",DE22>0),0,W22) -> 10088880 | DG22: =IF(B22="",0,IF(COUNTIF(CF22:CY22,1)>0,0,L22-M22)) -> 0 | DH22: =DF22+IF(DE22>0,0,DG22) -> 10088880 | DI22: =IF(B22="","",M22+DG22) -> 10088880 | DJ22: =IF(B22="",0,J22-K22) -> 0 | DK22: =IF(OR(BF22="EUR",BF22="CAD",BF22="GBP",BF22="AUD"),(GB22*(1-V22))+(HH22)+IF(HY22="",0,HY22*(1-U22)),0) -> 0 | DL22: =IF(BF22="EUR",33%,IF(BF22="CAD",38%,IF(BF22="GBP",51%,IF(BF22="AUD",61%,0)))) -> 0 | DM22: =DK22*DL22 -> 0 | DO22: =IF(OR(Y22="Second Lien",Y22="Tier 1 Split Lien",Y22="Tier 2 Split Lien"),DH22,0) -> 0 | DP22: =DO22*DO$6 -> 0 | DQ22: =DH22-DP22 -> 10088880 | DR22: =IF(Y22="Second Lien",DQ22,0) -> 0 | DS22: =DR22*DR$6 -> 0 | DT22: =DQ22-DS22 -> 10088880 | DU22: =IF(BH22="Yes",DT22,0) -> 0 | DV22: =DU22*DU$6 -> 0 | DW22: =DT22-DV22 -> 10088880 | DX22: =IF(OR(BG22="Canada",BG22="United Kingdom",BG22="Australia",BG22="Netherlands Antilles",BG22="Bermuda",BG22="Cayman Islands",BG22="British Virgin Islands",BG22="Channel Islands",BG22="Isle of Man",BG22="Australia",BG22="Netherlands",BG22="Germany",BG22="Sweden",BG22="Switzerland",BG22="Austria",BG22="Belgium",BG22="Denmark",BG22="Finland",BG22="Iceland",BG22="Ireland",BG22="Lichtenstein",BG22="Luxemborg",BG22="Norway"),DW22,0) -> 0 | DY22: =DX22*DX$6 -> 0 | DZ22: =DW22-DY22 -> 10088880 | EA22: =IF(BI22="Yes",DZ22,0) -> 0 | EB22: =EA22*EA$6 -> 0 | EC22: =DZ22-EB22 -> 10088880 | ED22: =IF(OR(Z22="Delayed Draw",Z22="Revolver"),EC22,0) -> 0 | EE22: =ED22*ED$6 -> 0 | EF22: =EC22-EE22 -> 10088880 | EG22: =IF(S22="Yes",EF22,0) -> 0 | EH22: =EG22*EG$6 -> 0 | EI22: =EF22-EH22 -> 10088880 | EJ22: =IF(Q22="Yes",EI22,0) -> 0 | EK22: =EJ22*EJ$6 -> 0 | EL22: =EI22-EK22 -> 10088880 | EM22: =IF(BD22="Semi-Annually",EL22,0) -> 0 | EN22: =EM22*EM$6 -> 0 | EO22: =EL22-EN22 -> 10088880 | EP22: =IF(BK22="Yes",EO22,0) -> 0 | EQ22: =EP22*EP$6 -> 0 | ER22: =EO22-EQ22 -> 10088880 | ES22: =IF(BL22="Yes",ER22,0) -> 0 | ET22: =ES22*ES$6 -> 0 | EU22: =ER22-ET22 -> 10088880 | EV22: =IF(AND(BM22="Yes",OR(BN22="No",AND(BN22="Yes",Inputs!$J$8=Inputs!$J$17+75))),EU22,0) -> 0 | EW22: =EV22*EV$6 -> 0 | EX22: =EU22-EW22 -> 10088880 | EY22: =IF(BW22="Yes",EX22,0) -> 0 | EZ22: =EY22*EY$6 -> 0 | FA22: =EX22-EZ22 -> 10088880 | FB22: =IF(AR22="Yes",FA22,0) -> 0 | FC22: =FB22*FB$6 -> 0 | FD22: =FA22-FC22 -> 10088880 | FE22: =IF(OR(BF22="EUR",BF22="AUD",BF22="CAD",BF22="GBP"),FD22,0) -> 0 | FF22: =FE22*FE$6 -> 0 | FG22: =FD22-FF22 -> 10088880 | FH22: =FG22 -> 10088880 | FI22: =IF(FG22=0,0,VLOOKUP(C22,$GV$10:$GW$406,2,FALSE)*FG22) -> 0 | FJ22: =FG22-FI22 -> 10088880 | FK22: =FJ22 -> 10088880 | FL22: =IF(OR(IC22="",FJ22<0.01),,VLOOKUP(IC22,$GM$10:$GN$406,2,FALSE)*FJ22) -> 0 | FM22: =FJ22-FL22 -> 10088880 | FN22: =FM22 -> 10088880 | FO22: =IF(FM22=0,0,VLOOKUP(C22,$HE$10:$HF$406,2,FALSE)*FM22) -> 0 | FP22: =FM22-FO22 -> 10088880 | FQ22: =IF(SUM(CZ22:DD22)>0,0,IF(AND(AL22>=5000000,AL22<7500000),FP22,0)) -> 0 | FR22: =IF(B22="",0,FQ22*FQ$6*(1-$U22)) -> 0 | FS22: =FP22-FR22 -> 10088880 | FT22: =IF(SUM(CZ22:DD22)>0,0,IF(AL22<15000000,FS22,0)) -> 0 | FU22: =IF(B22="",0,FT22*FT$6*(1-$U22)) -> 0 | FV22: =FS22-FU22 -> 10088880 | FW22: =IF(SUM(CZ22:DD22)>0,0,IF(OR(AND(X22="No",AN22="Tier 1",AI22>$AG$3),AND(X22="No",AN22="Tier 2",AI22>$AH$3),AND(X22="No",AN22="Tier 3",AI22>$AI$3)),FV22,0)) -> 0 | FX22: =IF(SUM(CZ22:DD22)>0,0,IF(OR(AND(X22="No",AN22="Tier 1",AJ22>$AG$4),AND(X22="No",AN22="Tier 2",AJ22>$AH$4),AND(X22="No",AN22="Tier 3",AJ22>$AI$4)),FV22,0)) -> 0 | FY22: =IF(SUM(CZ22:DD22)>0,0,IF(OR(AND(X22="Yes",AN22="Tier 1",AJ22>$AG$5),AND(X22="Yes",AN22="Tier 2",AJ22>$AH$5),AND(X22="Yes",AN22="Tier 3",AJ22>$AI$5)),FV22,0)) -> 0 | FZ22: =IF(SUM(FW22:FY22)>0,FV22,0) -> 0 | GA22: =IF(B22="",0,FZ22*FW$6*(1-MIN(90%,T22))) -> 0 | GB22: =FV22-GA22 -> 10088880 | GC22: =IF(AND(N22="No",DJ22=0),GB22,IF(AND(N22="No",DJ22<>0,K22=0),0,IF(AND(N22="No",DJ22<>0,K22>0,J22<>K22),MAX(0,M22-(DI22-GB22)),DH22))) -> 10088880 | GD22: =+GC22*V22 -> 7314438.3 | GE22: =IFERROR(GD22/K22,"") -> 0.725 | GF22: =IF(IC22="","",IC22) -> 14 | GG22: {=IF(SUM(IF(IC$9:IC21=IC22,1,0))>0,0,SUMIF($IC$10:$IC$406,IC22,$FJ$10:$FJ$406))} -> 46330726 | GH22: =GG22 -> 46330726 | GI22: =GI21+1 -> 13 | GJ22: =LARGE($GH$10:$GH$406,GI22) -> 25111100 | GK22: =IF(GI22>GI$6,0,IF(GI22=$GI$2,$GK$2,IF(GI22<4,$GK$3,$GK$4))) -> 1.5289285e+08 | GL22: =MAX(0,GJ22-GK22) -> 0 | GM22: {=IF(GJ22=0,0,LARGE(IF($GG$10:$GG$406=GJ22,$GF$10:$GF$406,0),COUNTIF($GJ$10:$GJ$406,GJ22)-COUNTIF(GJ$9:GJ21,GJ22)))} -> 5 | GN22: =IF(GJ22=0,0,GL22/GJ22) -> 0 | GP22: =IF(C22="","",IF(ISERROR(MATCH(C22,C$10:C21,0)),MAX(GP$10:GP21)+1,INDEX(GP$10:GP21,MATCH(C22,C$10:C21,0)))) -> 12 | GQ22: =IF(COUNTIF($A$10:A22,A22)<=1,SUMIF($A$10:$A$406,A22,$FH$10:$FH$406),0) -> 15545911 | GR22: =GR21+1 -> 13 | GS22: =LARGE($GQ$10:$GQ$406,GR22) -> 20000000 | GT22: =IF(GR22>GR$6,0,IF(GR22<=GR$2,GT$2,IF(AND(GR22<=$GR$3,GR22>$GR$2),GT$3,GT$4))) -> 50964284 | GU22: =MAX(0,GS22-GT22) -> 0 | GV22: {=IF(GS22=0,0,LARGE(IF($GQ$10:$GQ$406=GS22,$GP$10:$GP$406,0),COUNTIF($GS$10:$GS$406,GS22)-COUNTIF(GS$9:GS21,GS22)))} -> 32 | GW22: =IF(GS22=0,0,GU22/GS22) -> 0 | GY22: =IF(C22="","",IF(ISERROR(MATCH(C22,C$10:C21,0)),MAX(GP$10:GP21)+1,INDEX(GP$10:GP21,MATCH(C22,C$10:C21,0)))) -> 12 | GZ22: =IF(COUNTIF($A$10:A22,A22)<=1,SUMIF($A$10:$A$406,A22,$FH$10:$FH$406),0) -> 15545911 | HA22: =HA21+1 -> 13 | HB22: =LARGE($GZ$10:$GZ$406,HA22) -> 20000000 | HC22: - | HD22: =IF(HA22<6,MAX(0,$HD$2/5),0) -> 0 | HE22: {=IF(HB22=0,0,LARGE(IF($GZ$10:$GZ$406=HB22,$GY$10:$GY$406,0),COUNTIF($HB$10:$HB$406,HB22)-COUNTIF(HB$9:HB21,HB22)))} -> 32 | HF22: =IF(HB22=0,0,HD22/HB22) -> 0 | HH22: =DH22-GB22 -> 0 | HI22: 0 | HJ22: =MIN(HI22,DF22) -> 0 | HL22: =IF(COUNTIF($C$10:$C$406,HL21+1),HL21+1,"") -> 13 | HM22: =SUMIF($C$10:$C$406,HL22,$DH$10:$DH$406) -> 893147.4 | HO22: =MIN(HP22:HT22) -> 10088880 | HP22: =IF(B22="","",$M22) -> 10088880 | HQ22: =IF($N22="Yes",IF(P22>=6,0,MIN($T22*$M22,$U22*$M22)),"") | HR22: =IF(AND(N22="Yes",P22>=6),"",IF($S22="Yes",$R22*$M22,"")) | HS22: =IF($Q22="Yes",MIN($M22,$T22*$M22),"") | HT22: =IF(AND($N22="Yes",$P22>=6),"",IF(OR(CZ22=1,DD22=1,),MIN($T22*$M22,$U22*$M22),IF(OR(DA22=1,DB22=1,DC22=1),IF(AK22>=5000000,MIN($T22*$M22,$IF22*$M22),MIN($T22*$M22,$U22*$M22)),""))) | HU22: =IF(DE22>0,DE22,"") | HV22: =IF(B22="",0,$L22-$M22) -> 0 | HW22: =IF(OR(SUM(HQ22:HU22)>0,P22>=6),"",IF($B22="","",1)) -> 1 | HX22: =IF(AND($HU22<>0,OR(HU22<=MIN(HQ22:HT22),SUM(HQ22:HT22)=0)),$HU22,0) | HY22: =IF(AND($HT22<>0,OR(AND($HT22<>$HU22,$HT22<>$HS22,$HT22<>$HR22,$HT22<>$HQ22,$HT22<MIN($HQ22:$HS22),$HT22<HU22),SUM($HQ22:$HS22)+SUM(HU22)=0),IB22<=0),$HT22,0) -> 0 | HZ22: =IF(AND($HS22<>0,OR(AND($HS22<>$HU22,$HS22<>$HT22,$HS22<>$HR22,$HS22<>$HQ22),$HS22<MIN($HQ22:$HR22),$HS22<MIN($HT22:$HU22),SUM($HQ22:$HR22)+SUM($HT22:$HU22)=0)),$HS22,0) | IA22: =IF(AND($HR22<>0,OR(AND($HR22<>$HU22,HR22<>HT22,HR22<>HS22,HR22<>HQ22,HR22<MIN(HS22:HU22)),SUM(HQ22)+SUM(HS22:HU22)=0)),$HR22,0) | IB22: =IF(AND($HQ22<>0,OR(HQ22<=MIN(HR22:HU22),SUM(HR22:HU22)=0)),$HQ22,0) | IC22: =IF(C22="","",INDEX(Lookups!$E$2:$E$69,MATCH('Loan List'!BE22,Lookups!$F$2:$F$69,0))) -> 14 | ID22: =HV22=DG22 -> TRUE | IF22: =IF(B22="","",IF(AND(Y22="Second Lien",OR(DA22=1,DB22=1,DC22=1)),50%,IF(DA22=1,90%,IF(DB22=1,80%,IF(DC22=1,65%,"No Initial Haircut"))))) -> No Initial Haircut
